Workbook
Name LISTA_GESTORES: Configuracion!$F$3:$F$190
Name LISTA_PRODUCTOS: Configuracion!$A$2:$A$193

Sheet Configuracion
A1: PRODUCTOS | B1: STOCK INICIAL | C1: PRECIO VENTA | D1: COMISION
A2: BOLSA DE CEMENTO BLANCO | B2: 0 | C2: 2.86 | D2: 100
A3: BATERIA 5120W SACO | B3: 3 | C3: 1100 | D3: 5000
A4: BATERIA SACO 7680W | B4: 3 | C4: 1400 | D4: 5000
A5: BATERIA DE 15360W SACO | B5: 2 | D5: 5000
A6: BATERIA EXTRA 16K SACO | B6: 2 | C6: 1300 | D6: 5000
A7: BASE PARA PANELES GRANDES | B7: 10 | C7: 100 | D7: 1000
A8: BASE PARA PANELES | B8: 0 | C8: 50 | D8: 1000
A9: BASE FIJA PARA TV 32'' - 86'' | B9: 10 | C9: 20 | D9: 500
A10: BASE GIRATORIA | B10: 8 | C10: 25 | D10: 500
A11: BATERIA 16K SACO | B11: 0 | C11: 2500 | D11: 5000
A12: BREKE 63A SENCILLO | B12: 1 | C12: 20
A13: BATERIA MUST 10.25 KW | B13: 1 | C13: 2050 | D13: 5000
A14: BREKE 63A DOBLE TIR | B14: 0
A15: BREKE 32A DOBLE | B15: 0 | D15: 1000
A16: BOCINA BOOM 8 PULGADAS | B16: 0 | C16: 35 | D16: 1000
A17: BOCINA MILEXUS 8 PULGADAS | B17: 0 | C17: 85 | D17: 1000
A18: BOCINA MILEXUS 8 DUAL | B18: 0 | C18: 190 | D18: 3000
A19: BOMBA DE AGUA SILVER POINT 1 HP | B19: 2 | C19: 60 | D19: 1000
A20: BOMBA DE AGUA SILVER POINT 1X1/2 | B20: 0 | C20: 40 | D20: 1000
A21: BICICLETA INFANTIL | B21: 0 | C21: 130 | D21: 2000
A22: BICICLETA | B22: 0 | C22: 180 | D22: 2000
A23: CONECTORES MC4 | B23: 4 | D23: 1000
A24: CAJITA DECODIFICADORA VIVAMAX | B24: 5 | C24: 40 | D24: 1000
A25: CAJA DE DISTRIBUCION DE VIAS 12 VIAS | B25: 3 | D25: 1000
A26: COLCHON PERSONAL | B26: 3 | C26: 160 | D26: 1500
A27: COLCHON EKO | B27: 4 | C27: 180 | D27: 1500
A28: CAJAS DE AZULEJOS 44X44 2.5 M | B28: 2 | C28: 36.41 | D28: 1250
A29: CAFETERA 3 TASAS | B29: 2 | C29: 12 | D29: 500
A30: CAFETERA DE INDUCCION 6 TASAS | B30: 0 | C30: 15 | D30: 500
A31: CAFETERA ELECTRICA RUDENKOV | B31: 0 | C31: 40 | D31: 1000
A32: CALENTADOR 80 L | B32: 0 | C32: 210 | D32: 3000
A33: CALENTADOR 50 L | B33: 6 | C33: 180 | D33: 3000
A34: DISPENSSDOR DE AGUA ROYAL | B34: 0 | C34: 160 | D34: 2000
A35: ESTACION ENERGIA 6000 W | B35: 0 | C35: 760 | D35: 17800
A36: ESTACION ENERGIA PECRON | B36: 0 | C36: 1100 | D36: 5000
A37: ESTACION ENERGIA ECOFLOW DELTA 2 | B37: 1 | C37: 800 | D37: 5000
A38: ESTACION ENERGIA ECOFLOW DELTA 3 | B38: 2 | C38: 820 | D38: 5000
A39: ESTACION MUST 6000 W | B39: 0
A40: ESTACION MUST 2K CON 2.7K | B40: 5 | C40: 1130 | D40: 3000
A41: ESCRITORIO | B41: 2 | C41: 230 | D41: 2000
A42: ESTACION ECOFLOW DELTA 2 1800W | B42: 0 | C42: 800 | D42: 5500
A43: KIT DE INSTALACION | B43: 0 | C43: 120
A44: EXHIBIDOR HORIZONTAL 13P | B44: 0 | C44: 650 | D44: 4000
A45: EXHIBIDOR VERTICAL 12P | B45: 0 | C45: 600 | D45: 4000
A46: EXHIBIDOR MILEXUS 390 L 14PIES | B46: 0 | C46: 630 | D46: 4000
A47: EXHIBIDOR DOBLE MILEXUS 560 LITROS | B47: 0 | C47: 1120 | D47: 5000
A48: EQUIPO DE MUSICA LG | B48: 2 | C48: 180 | D48: 1000
A49: FOGON DE PETROLEO | B49: 5 | C49: 35 | D49: 500
A50: FOGON DE GAS DE CRISTAL | B50: 0 | C50: 45 | D50: 1000
A51: FOGON DE GAS SENCILLO | B51: 0 | C51: 20 | D51: 1000
A52: FOGON DE GAS 2 QUEMADORES | B52: 0 | C52: 40 | D52: 1000
A53: FOGON DE GAS 3 QUEMADORES | B53: 10 | C53: 35 | D53: 1000
A54: FOGON INFRARROJO MILEXUS 1200 W | B54: 3 | C54: 50 | D54: 1000
A55: FOGON INFRARROJO MAF 2000 W | B55: 2 | C55: 45 | D55: 1000
A56: FOGON INFRARROJO ROYAL 1500 W | B56: 10
A57: FOGON INFRARROJO EKO 1500 W | B57: 5 | C57: 50 | D57: 1000
A58: FILTRO DE AGUA | B58: 10 | C58: 50 | D58: 1000
A59: FREIDORA DE AIRE JMD 4 L | B59: 3 | C59: 55 | D59: 1000
A60: FREIDORA DE AIRE MILEXUS NEGRA 5.7L | B60: 0 | C60: 65 | D60: 1000
A61: INVERSOR 3.6K YINGI | B61: 1 | C61: 550 | D61: 5000
A62: INVERSOR DE 10 K SUNPAL | B62: 1
A63: INVERSOR 12K MUST | B63: 1 | C63: 2200 | D63: 5000
A64: INVERSOR MUST 3000 W | B64: 7 | C64: 650 | D64: 15000
A65: INVERSOR 6000W MUST | B65: 2 | C65: 650 | D65: 5000
A66: LAMPARA RECARGABLE DE 50 CM | B66: 4 | C66: 10 | D66: 500
A67: LAMPARA SOLAR 800W | B67: 3 | C67: 130 | D67: 500
A68: LAMPARA SOLAR 1000W | B68: 3 | C68: 140 | D68: 500
A69: LAMPARA DE 100W CON PANEL | B69: 1 | C69: 45 | D69: 500
A70: LAMPARA DE 360 W CON PANEL INTEGRADO | B70: 0 | C70: 125 | D70: 500
A71: LAMPARA DE 300 W CON PANEL INTEGRADO | B71: 1 | C71: 120 | D71: 500
A72: LAMPARA DE 200 W CON PANEL INDEPENDIENTE | B72: 1 | C72: 90 | D72: 500
A73: LAMPARA DE 300 W CON PANEL INDEPENDIENTE | B73: 1 | C73: 95 | D73: 500
A74: LAVADORA SECADORA AUTOMÁTICA MILEXUS 10 KG | B74: 0 | C74: 650 | D74: 3000
... A151: SPLIT 2 T 220V MILEXUS | B151: 1 | C151: 530 | D151: 3000
A152: SUPRESOR AC | B152: 0
A153: SUPRESOR DC | B153: 0 | D153: 3000
A154: SPLIT MILEXUS 1 T 110 VOLT | B154: 0 | C154: 280 | D154: 3000
A155: SPLIT MILEXUS 1 T 220 VOLT | B155: 2 | C155: 260 | D155: 3000
A156: SPLIT 1 T MILEXUS INVERTER | B156: 0 | C156: 300 | D156: 3000
A157: SILLA GIRATORIA | B157: 0 | C157: 100 | D157: 1000
A158: SPLIT 1 T MILEXUS 220 V INVERTER | B158: 0 | C158: 300 | D158: 3000
A159: TV ROYAL 65 | B159: 0 | C159: 425 | D159: 3000
A160: TV HISENSE 55 | B160: 6 | C160: 430 | D160: 3000
A161: TRANSFER 220V | B161: 1 | C161: 70 | D161: 3000
A162: TV 43" HISENSE | B162: 3 | C162: 260 | D162: 3000
A163: TV 43" MILEXUS | B163: 1 | C163: 255 | D163: 3000
A164: TV 50 SANKEY | B164: 3 | C164: 360 | D164: 3000
A165: MAQUINA DE FRIO | B165: 3 | C165: 80 | D165: 1000
... A183: VITRINA SANKEY 8P | B183: 1 | C183: 500 | D183: 4000
A184: RIEL | B184: 19
A185: CONECTOR DE RIEL | B185: 12
A186: EXPANCIONADORES | B186: 200
A187: PLATINAS | B187: 9
A188: SUJETADOR EXTERIOR | B188: 36
A189: GANCHO TIERRA | B189: 9
A190: PATAS TRASERAS AJUSTABLES | B190: 57
A191: PATAS DELANTERA AJUSTABLE | B191: 56
A192: SUJETADOR INTERMEDIO | B192: 38

Sheet lunes
A1: PRODUCTO | B1: STOCK INICIAL | C1: MOVIMIENTO | D1: CANTIDAD | E1: PRECIO VENTA USD | F1: IMPORTE | G1: TIPO DE VENTA O MOV | H1: COMISION CUP | I1: STOCK FINAL | K1: TIPO CAMBIO | L1: Columna1 | O1: CANTIDAD | P1: USD | Q1: OBSERVACION | R1: USD | S1: MN
A2: SISTEMA FELICITY SOLAR 6 K CON 15K | B2: =IFERROR(VLOOKUP(A2, Configuracion!$A:$B, 2, FALSE), 0) -> 1 | C2: VENTA | D2: 1 | E2: =IF(C2="Venta", IFERROR(VLOOKUP(A2, Configuracion!$A:$D, 3, FALSE), 0), 0) -> 3150 | F2: =E2*D2 -> 3150 | G2: GESTOR | H2: =IF(AND(G2="Gestor", A2<>""), VLOOKUP(A2, Configuracion!$A:$D, 4, FALSE), 0)*Tabla15[[#This Row],[CANTIDAD]] -> 8000 | I2: =IF(OR(A2="", D2=""), "", IF(C2="Entrada", B2+D2, IF(OR(C2="Venta", C2="Salida"), B2-D2, B2))) -> 0 | K2: CUP/USD | L2: 540 | N2: VENTA TOTAL | O2: =Tabla15[[#Totals],[IMPORTE]] -> 9440 | P2: =O2 -> 9440
A3: PANELES 615 W | B3: =IFERROR(VLOOKUP(A3, Configuracion!$A:$B, 2, FALSE), 0) -> 87 | C3: VENTA | D3: 18 | E3: =IF(C3="Venta", IFERROR(VLOOKUP(A3, Configuracion!$A:$D, 3, FALSE), 0), 0) -> 180 | F3: =E3*D3 -> 3240 | G3: GESTOR | H3: =IF(AND(G3="Gestor", A3<>""), VLOOKUP(A3, Configuracion!$A:$D, 4, FALSE), 0)*Tabla15[[#This Row],[CANTIDAD]] -> 18000 | I3: =IF(OR(A3="", D3=""), "", IF(C3="Entrada", B3+D3, IF(OR(C3="Venta", C3="Salida"), B3-D3, B3))) -> 69 | K3: MXN/USD | L3: 20 | N3: USD | O3: 4710 | P3: =O3 -> 4710
A4: NEVERA SANKEY 9 P | B4: =IFERROR(VLOOKUP(A4, Configuracion!$A:$B, 2, FALSE), 0) -> 2 | C4: VENTA | D4: 1 | E4: =IF(C4="Venta", IFERROR(VLOOKUP(A4, Configuracion!$A:$D, 3, FALSE), 0), 0) -> 320 | F4: =E4*D4 -> 320 | G4: GESTOR | H4: =IF(AND(G4="Gestor", A4<>""), VLOOKUP(A4, Configuracion!$A:$D, 4, FALSE), 0)*Tabla15[[#This Row],[CANTIDAD]] -> 3000 | I4: =IF(OR(A4="", D4=""), "", IF(C4="Entrada", B4+D4, IF(OR(C4="Venta", C4="Salida"), B4-D4, B4))) -> 1 | N4: ZELLE | O4: 360 | P4: =O4 -> 360
A5: LAVADORA 7 KG MILEXUS SEMI. | B5: =IFERROR(VLOOKUP(A5, Configuracion!$A:$B, 2, FALSE), 0) -> 12 | C5: VENTA | D5: 2 | E5: =IF(C5="Venta", IFERROR(VLOOKUP(A5, Configuracion!$A:$D, 3, FALSE), 0), 0) -> 170 | F5: =E5*D5 -> 340 | G5: GESTOR | H5: =IF(AND(G5="Gestor", A5<>""), VLOOKUP(A5, Configuracion!$A:$D, 4, FALSE), 0)*Tabla15[[#This Row],[CANTIDAD]] -> 6000 | I5: =IF(OR(A5="", D5=""), "", IF(C5="Entrada", B5+D5, IF(OR(C5="Venta", C5="Salida"), B5-D5, B5))) -> 10 | N5: MXN | P5: =O5/L3 -> 0
A6: BATERIA MUST 10.25 KW | B6: =IFERROR(VLOOKUP(A6, Configuracion!$A:$B, 2, FALSE), 0) -> 1 | C6: VENTA | D6: 1 | E6: =IF(C6="Venta", IFERROR(VLOOKUP(A6, Configuracion!$A:$D, 3, FALSE), 0), 0) -> 2050 | F6: =E6*D6 -> 2050 | G6: TIENDA | H6: =IF(AND(G6="Gestor", A6<>""), VLOOKUP(A6, Configuracion!$A:$D, 4, FALSE), 0)*Tabla15[[#This Row],[CANTIDAD]] -> 0 | I6: =IF(OR(A6="", D6=""), "", IF(C6="Entrada", B6+D6, IF(OR(C6="Venta", C6="Salida"), B6-D6, B6))) -> 0 | N6: CUP EFECTIVO | O6: 1252800 | P6: =O6/L2 -> 2320
A7: PANELES 585 W | B7: =IFERROR(VLOOKUP(A7, Configuracion!$A:$B, 2, FALSE), 0) -> 2 | C7: VENTA | D7: 1 | E7: =IF(C7="Venta", IFERROR(VLOOKUP(A7, Configuracion!$A:$D, 3, FALSE), 0), 0) -> 170 | F7: =E7*D7 -> 170 | G7: GESTOR | H7: =IF(AND(G7="Gestor", A7<>""), VLOOKUP(A7, Configuracion!$A:$D, 4, FALSE), 0)*Tabla15[[#This Row],[CANTIDAD]] -> 1000 | I7: =IF(OR(A7="", D7=""), "", IF(C7="Entrada", B7+D7, IF(OR(C7="Venta", C7="Salida"), B7-D7, B7))) -> 1 | N7: CUP TRANSF | P7: =O7/L2 -> 0
A8: PANELES 490 W | B8: =IFERROR(VLOOKUP(A8, Configuracion!$A:$B, 2, FALSE), 0) -> 11 | C8: VENTA | D8: 1 | E8: 170 | F8: =E8*D8 -> 170 | G8: TIENDA | H8: =IF(AND(G8="Gestor", A8<>""), VLOOKUP(A8, Configuracion!$A:$D, 4, FALSE), 0)*Tabla15[[#This Row],[CANTIDAD]] -> 0 | I8: =IF(OR(A8="", D8=""), "", IF(C8="Entrada", B8+D8, IF(OR(C8="Venta", C8="Salida"), B8-D8, B8))) -> 10 | N8: EUROPA | P8: =O8 -> 0
B9: =IFERROR(VLOOKUP(A9, Configuracion!$A:$B, 2, FALSE), 0) -> 0 | D9: 1 | E9: =IF(C9="Venta", IFERROR(VLOOKUP(A9, Configuracion!$A:$D, 3, FALSE), 0), 0) -> 0 | F9: =E9*D9 -> 0 | H9: =IF(AND(G9="Gestor", A9<>""), VLOOKUP(A9, Configuracion!$A:$D, 4, FALSE), 0)*Tabla15[[#This Row],[CANTIDAD]] -> 0 | I9: =IF(OR(A9="", D9=""), "", IF(C9="Entrada", B9+D9, IF(OR(C9="Venta", C9="Salida"), B9-D9, B9))) | N9: TOTAL | P9: =P3+P4+P5+P6+P7+P8 -> 7390
B10: =IFERROR(VLOOKUP(A10, Configuracion!$A:$B, 2, FALSE), 0) -> 0 | E10: =IF(C10="Venta", IFERROR(VLOOKUP(A10, Configuracion!$A:$D, 3, FALSE), 0), 0) -> 0 | F10: =E10*D10 -> 0 | H10: =IF(AND(G10="Gestor", A10<>""), VLOOKUP(A10, Configuracion!$A:$D, 4, FALSE), 0)*Tabla15[[#This Row],[CANTIDAD]] -> 0 | I10: =IF(OR(A10="", D10=""), "", IF(C10="Entrada", B10+D10, IF(OR(C10="Venta", C10="Salida"), B10-D10, B10))) | N10: ENTRADA DINERO | P10: =P12+P11 -> 0
B11: =IFERROR(VLOOKUP(A11, Configuracion!$A:$B, 2, FALSE), 0) -> 0 | E11: =IF(C11="Venta", IFERROR(VLOOKUP(A11, Configuracion!$A:$D, 3, FALSE), 0), 0) -> 0 | F11: =E11*D11 -> 0 | H11: =IF(AND(G11="Gestor", A11<>""), VLOOKUP(A11, Configuracion!$A:$D, 4, FALSE), 0)*Tabla15[[#This Row],[CANTIDAD]] -> 0 | I11: =IF(OR(A11="", D11=""), "", IF(C11="Entrada", B11+D11, IF(OR(C11="Venta", C11="Salida"), B11-D11, B11))) | N11: CUP | P11: =O11/L2 -> 0
B12: =IFERROR(VLOOKUP(A12, Configuracion!$A:$B, 2, FALSE), 0) -> 0 | E12: =IF(C12="Venta", IFERROR(VLOOKUP(A12, Configuracion!$A:$D, 3, FALSE), 0), 0) -> 0 | F12: =E12*D12 -> 0 | H12: =IF(AND(G12="Gestor", A12<>""), VLOOKUP(A12, Configuracion!$A:$D, 4, FALSE), 0)*Tabla15[[#This Row],[CANTIDAD]] -> 0 | I12: =IF(OR(A12="", D12=""), "", IF(C12="Entrada", B12+D12, IF(OR(C12="Venta", C12="Salida"), B12-D12, B12))) | N12: USD | P12: =O12 -> 0
B13: =IFERROR(VLOOKUP(A13, Configuracion!$A:$B, 2, FALSE), 0) -> 0 | E13: =IF(C13="Venta", IFERROR(VLOOKUP(A13, Configuracion!$A:$D, 3, FALSE), 0), 0) -> 0 | F13: =E13*D13 -> 0 | H13: =IF(AND(G13="Gestor", A13<>""), VLOOKUP(A13, Configuracion!$A:$D, 4, FALSE), 0)*Tabla15[[#This Row],[CANTIDAD]] -> 0 | I13: =IF(OR(A13="", D13=""), "", IF(C13="Entrada", B13+D13, IF(OR(C13="Venta", C13="Salida"), B13-D13, B13))) | N13: EXTRACCION | P13: =P15+P14 -> 2050
B14: =IFERROR(VLOOKUP(A14, Configuracion!$A:$B, 2, FALSE), 0) -> 0 | E14: =IF(C14="Venta", IFERROR(VLOOKUP(A14, Configuracion!$A:$D, 3, FALSE), 0), 0) -> 0 | F14: =E14*D14 -> 0 | H14: =IF(AND(G14="Gestor", A14<>""), VLOOKUP(A14, Configuracion!$A:$D, 4, FALSE), 0)*Tabla15[[#This Row],[CANTIDAD]] -> 0 | I14: =IF(OR(A14="", D14=""), "", IF(C14="Entrada", B14+D14, IF(OR(C14="Venta", C14="Salida"), B14-D14, B14))) | N14: CUP | P14: =O14/L2 -> 0
B15: =IFERROR(VLOOKUP(A15, Configuracion!$A:$B, 2, FALSE), 0) -> 0 | E15: =IF(C15="Venta", IFERROR(VLOOKUP(A15, Configuracion!$A:$D, 3, FALSE), 0), 0) -> 0 | F15: =E15*D15 -> 0 | H15: =IF(AND(G15="Gestor", A15<>""), VLOOKUP(A15, Configuracion!$A:$D, 4, FALSE), 0)*Tabla15[[#This Row],[CANTIDAD]] -> 0 | I15: =IF(OR(A15="", D15=""), "", IF(C15="Entrada", B15+D15, IF(OR(C15="Venta", C15="Salida"), B15-D15, B15))) | N15: USD | O15: 2050 | P15: 2050
B16: =IFERROR(VLOOKUP(A16, Configuracion!$A:$B, 2, FALSE), 0) -> 0 | E16: =IF(C16="Venta", IFERROR(VLOOKUP(A16, Configuracion!$A:$D, 3, FALSE), 0), 0) -> 0 | F16: =E16*D16 -> 0 | H16: =IF(AND(G16="Gestor", A16<>""), VLOOKUP(A16, Configuracion!$A:$D, 4, FALSE), 0)*Tabla15[[#This Row],[CANTIDAD]] -> 0 | I16: =IF(OR(A16="", D16=""), "", IF(C16="Entrada", B16+D16, IF(OR(C16="Venta", C16="Salida"), B16-D16, B16))) | N16: TOTAL GENERAL | P16: =P9+P13-P10 -> 9440 | R16: =P2-P16 -> 0 | S16: =R16*L2 -> 0
B17: =IFERROR(VLOOKUP(A17, Configuracion!$A:$B, 2, FALSE), 0) -> 0 | E17: =IF(C17="Venta", IFERROR(VLOOKUP(A17, Configuracion!$A:$D, 3, FALSE), 0), 0) -> 0 | F17: =E17*D17 -> 0 | H17: =IF(AND(G17="Gestor", A17<>""), VLOOKUP(A17, Configuracion!$A:$D, 4, FALSE), 0)*Tabla15[[#This Row],[CANTIDAD]] -> 0 | I17: =IF(OR(A17="", D17=""), "", IF(C17="Entrada", B17+D17, IF(OR(C17="Venta", C17="Salida"), B17-D17, B17)))
B18: =IFERROR(VLOOKUP(A18, Configuracion!$A:$B, 2, FALSE), 0) -> 0 | E18: =IF(C18="Venta", IFERROR(VLOOKUP(A18, Configuracion!$A:$D, 3, FALSE), 0), 0) -> 0 | F18: =E18*D18 -> 0 | H18: =IF(AND(G18="Gestor", A18<>""), VLOOKUP(A18, Configuracion!$A:$D, 4, FALSE), 0)*Tabla15[[#This Row],[CANTIDAD]] -> 0 | I18: =IF(OR(A18="", D18=""), "", IF(C18="Entrada", B18+D18, IF(OR(C18="Venta", C18="Salida"), B18-D18, B18))) | O18: CUP | P18: USD
B19: =IFERROR(VLOOKUP(A19, Configuracion!$A:$B, 2, FALSE), 0) -> 0 | E19: =IF(C19="Venta", IFERROR(VLOOKUP(A19, Configuracion!$A:$D, 3, FALSE), 0), 0) -> 0 | F19: =E19*D19 -> 0 | H19: =IF(AND(G19="Gestor", A19<>""), VLOOKUP(A19, Configuracion!$A:$D, 4, FALSE), 0)*Tabla15[[#This Row],[CANTIDAD]] -> 0 | I19: =IF(OR(A19="", D19=""), "", IF(C19="Entrada", B19+D19, IF(OR(C19="Venta", C19="Salida"), B19-D19, B19))) | N19: FONDO INICIAL | O19: 100000 | P19: 150
B20: =IFERROR(VLOOKUP(A20, Configuracion!$A:$B, 2, FALSE), 0) -> 0 | H20: =IF(AND(G20="Gestor", A20<>""), VLOOKUP(A20, Configuracion!$A:$D, 4, FALSE), 0)*Tabla15[[#This Row],[CANTIDAD]] -> 0 | N20: CAMBIO
B21: =IFERROR(VLOOKUP(A21, Configuracion!$A:$B, 2, FALSE), 0) -> 0 | E21: =IF(C21="Venta", IFERROR(VLOOKUP(A21, Configuracion!$A:$D, 3, FALSE), 0), 0) -> 0 | F21: =E21*D21 -> 0 | H21: =IF(AND(G21="Gestor", A21<>""), VLOOKUP(A21, Configuracion!$A:$D, 4, FALSE), 0)*Tabla15[[#This Row],[CANTIDAD]] -> 0 | I21: =IF(OR(A21="", D21=""), "", IF(C21="Entrada", B21+D21, IF(OR(C21="Venta", C21="Salida"), B21-D21, B21))) | N21: DOMICILIO | O21: 11000
B22: =IFERROR(VLOOKUP(A22, Configuracion!$A:$B, 2, FALSE), 0) -> 0 | E22: =IF(C22="Venta", IFERROR(VLOOKUP(A22, Configuracion!$A:$D, 3, FALSE), 0), 0) -> 0 | F22: =E22*D22 -> 0 | H22: =IF(AND(G22="Gestor", A22<>""), VLOOKUP(A22, Configuracion!$A:$D, 4, FALSE), 0)*Tabla15[[#This Row],[CANTIDAD]] -> 0 | I22: =IF(OR(A22="", D22=""), "", IF(C22="Entrada", B22+D22, IF(OR(C22="Venta", C22="Salida"), B22-D22, B22))) | N22: OTROS GASTOS | O22: 2000 | Q22: CUSTODIO
B23: =IFERROR(VLOOKUP(A23, Configuracion!$A:$B, 2, FALSE), 0) -> 0 | E23: =IF(C23="Venta", IFERROR(VLOOKUP(A23, Configuracion!$A:$D, 3, FALSE), 0), 0) -> 0 | F23: =E23*D23 -> 0 | H23: =IF(AND(G23="Gestor", A23<>""), VLOOKUP(A23, Configuracion!$A:$D, 4, FALSE), 0)*Tabla15[[#This Row],[CANTIDAD]] -> 0 | I23: =IF(OR(A23="", D23=""), "", IF(C23="Entrada", B23+D23, IF(OR(C23="Venta", C23="Salida"), B23-D23, B23))) | N23: COMISIONES | O23: 42000
B24: =IFERROR(VLOOKUP(A24, Configuracion!$A:$B, 2, FALSE), 0) -> 0 | E24: =IF(C24="Venta", IFERROR(VLOOKUP(A24, Configuracion!$A:$D, 3, FALSE), 0), 0) -> 0 | F24: =E24*D24 -> 0 | H24: =IF(AND(G24="Gestor", A24<>""), VLOOKUP(A24, Configuracion!$A:$D, 4, FALSE), 0)*Tabla15[[#This Row],[CANTIDAD]] -> 0 | I24: =IF(OR(A24="", D24=""), "", IF(C24="Entrada", B24+D24, IF(OR(C24="Venta", C24="Salida"), B24-D24, B24))) | N24: FONDO FINAL | O24: =O19-O21-O22-O23-O20 -> 45000 | P24: =P19-P21-P22-P23-P20 -> 150
B25: =IFERROR(VLOOKUP(A25, Configuracion!$A:$B, 2, FALSE), 0) -> 0 | E25: =IF(C25="Venta", IFERROR(VLOOKUP(A25, Configuracion!$A:$D, 3, FALSE), 0), 0) -> 0 | F25: =E25*D25 -> 0 | H25: =IF(AND(G25="Gestor", A25<>""), VLOOKUP(A25, Configuracion!$A:$D, 4, FALSE), 0)*Tabla15[[#This Row],[CANTIDAD]] -> 0 | I25: =IF(OR(A25="", D25=""), "", IF(C25="Entrada", B25+D25, IF(OR(C25="Venta", C25="Salida"), B25-D25, B25)))
B26: =IFERROR(VLOOKUP(A26, Configuracion!$A:$B, 2, FALSE), 0) -> 0 | E26: =IF(C26="Venta", IFERROR(VLOOKUP(A26, Configuracion!$A:$D, 3, FALSE), 0), 0) -> 0 | F26: =E26*D26 -> 0 | H26: =IF(AND(G26="Gestor", A26<>""), VLOOKUP(A26, Configuracion!$A:$D, 4, FALSE), 0)*Tabla15[[#This Row],[CANTIDAD]] -> 0 | I26: =IF(OR(A26="", D26=""), "", IF(C26="Entrada", B26+D26, IF(OR(C26="Venta", C26="Salida"), B26-D26, B26)))
B27: =IFERROR(VLOOKUP(A27, Configuracion!$A:$B, 2, FALSE), 0) -> 0 | E27: =IF(C27="Venta", IFERROR(VLOOKUP(A27, Configuracion!$A:$D, 3, FALSE), 0), 0) -> 0 | F27: =E27*D27 -> 0 | H27: =IF(AND(G27="Gestor", A27<>""), VLOOKUP(A27, Configuracion!$A:$D, 4, FALSE), 0)*Tabla15[[#This Row],[CANTIDAD]] -> 0 | I27: =IF(OR(A27="", D27=""), "", IF(C27="Entrada", B27+D27, IF(OR(C27="Venta", C27="Salida"), B27-D27, B27)))
B28: =IFERROR(VLOOKUP(A28, Configuracion!$A:$B, 2, FALSE), 0) -> 0 | E28: =IF(C28="Venta", IFERROR(VLOOKUP(A28, Configuracion!$A:$D, 3, FALSE), 0), 0) -> 0 | F28: =E28*D28 -> 0 | H28: =IF(AND(G28="Gestor", A28<>""), VLOOKUP(A28, Configuracion!$A:$D, 4, FALSE), 0)*Tabla15[[#This Row],[CANTIDAD]] -> 0 | I28: =IF(OR(A28="", D28=""), "", IF(C28="Entrada", B28+D28, IF(OR(C28="Venta", C28="Salida"), B28-D28, B28)))
B29: =IFERROR(VLOOKUP(A29, Configuracion!$A:$B, 2, FALSE), 0) -> 0 | E29: =IF(C29="Venta", IFERROR(VLOOKUP(A29, Configuracion!$A:$D, 3, FALSE), 0), 0) -> 0 | F29: =E29*D29 -> 0 | H29: =IF(AND(G29="Gestor", A29<>""), VLOOKUP(A29, Configuracion!$A:$D, 4, FALSE), 0)*Tabla15[[#This Row],[CANTIDAD]] -> 0 | I29: =IF(OR(A29="", D29=""), "", IF(C29="Entrada", B29+D29, IF(OR(C29="Venta", C29="Salida"), B29-D29, B29)))
B30: =IFERROR(VLOOKUP(A30, Configuracion!$A:$B, 2, FALSE), 0) -> 0 | E30: =IF(C30="Venta", IFERROR(VLOOKUP(A30, Configuracion!$A:$D, 3, FALSE), 0), 0) -> 0 | F30: =E30*D30 -> 0 | H30: =IF(AND(G30="Gestor", A30<>""), VLOOKUP(A30, Configuracion!$A:$D, 4, FALSE), 0)*Tabla15[[#This Row],[CANTIDAD]] -> 0 | I30: =IF(OR(A30="", D30=""), "", IF(C30="Entrada", B30+D30, IF(OR(C30="Venta", C30="Salida"), B30-D30, B30)))
B31: =IFERROR(VLOOKUP(A31, Configuracion!$A:$B, 2, FALSE), 0) -> 0 | E31: =IF(C31="Venta", IFERROR(VLOOKUP(A31, Configuracion!$A:$D, 3, FALSE), 0), 0) -> 0 | F31: =E31*D31 -> 0 | H31: =IF(AND(G31="Gestor", A31<>""), VLOOKUP(A31, Configuracion!$A:$D, 4, FALSE), 0)*Tabla15[[#This Row],[CANTIDAD]] -> 0 | I31: =IF(OR(A31="", D31=""), "", IF(C31="Entrada", B31+D31, IF(OR(C31="Venta", C31="Salida"), B31-D31, B31)))
B32: =IFERROR(VLOOKUP(A32, Configuracion!$A:$B, 2, FALSE), 0) -> 0 | E32: =IF(C32="Venta", IFERROR(VLOOKUP(A32, Configuracion!$A:$D, 3, FALSE), 0), 0) -> 0 | F32: =E32*D32 -> 0 | H32: =IF(AND(G32="Gestor", A32<>""), VLOOKUP(A32, Configuracion!$A:$D, 4, FALSE), 0)*Tabla15[[#This Row],[CANTIDAD]] -> 0 | I32: =IF(OR(A32="", D32=""), "", IF(C32="Entrada", B32+D32, IF(OR(C32="Venta", C32="Salida"), B32-D32, B32)))
B33: =IFERROR(VLOOKUP(A33, Configuracion!$A:$B, 2, FALSE), 0) -> 0 | E33: =IF(C33="Venta", IFERROR(VLOOKUP(A33, Configuracion!$A:$D, 3, FALSE), 0), 0) -> 0 | F33: =E33*D33 -> 0 | H33: =IF(AND(G33="Gestor", A33<>""), VLOOKUP(A33, Configuracion!$A:$D, 4, FALSE), 0)*Tabla15[[#This Row],[CANTIDAD]] -> 0 | I33: =IF(OR(A33="", D33=""), "", IF(C33="Entrada", B33+D33, IF(OR(C33="Venta", C33="Salida"), B33-D33, B33)))
B34: =IFERROR(VLOOKUP(A34, Configuracion!$A:$B, 2, FALSE), 0) -> 0 | E34: =IF(C34="Venta", IFERROR(VLOOKUP(A34, Configuracion!$A:$D, 3, FALSE), 0), 0) -> 0 | F34: =E34*D34 -> 0 | H34: =IF(AND(G34="Gestor", A34<>""), VLOOKUP(A34, Configuracion!$A:$D, 4, FALSE), 0)*Tabla15[[#This Row],[CANTIDAD]] -> 0 | I34: =IF(OR(A34="", D34=""), "", IF(C34="Entrada", B34+D34, IF(OR(C34="Venta", C34="Salida"), B34-D34, B34)))
B35: =IFERROR(VLOOKUP(A35, Configuracion!$A:$B, 2, FALSE), 0) -> 0 | E35: =IF(C35="Venta", IFERROR(VLOOKUP(A35, Configuracion!$A:$D, 3, FALSE), 0), 0) -> 0 | F35: =E35*D35 -> 0 | H35: =IF(AND(G35="Gestor", A35<>""), VLOOKUP(A35, Configuracion!$A:$D, 4, FALSE), 0)*Tabla15[[#This Row],[CANTIDAD]] -> 0 | I35: =IF(OR(A35="", D35=""), "", IF(C35="Entrada", B35+D35, IF(OR(C35="Venta", C35="Salida"), B35-D35, B35)))
B36: =IFERROR(VLOOKUP(A36, Configuracion!$A:$B, 2, FALSE), 0) -> 0 | E36: =IF(C36="Venta", IFERROR(VLOOKUP(A36, Configuracion!$A:$D, 3, FALSE), 0), 0) -> 0 | F36: =E36*D36 -> 0 | H36: =IF(AND(G36="Gestor", A36<>""), VLOOKUP(A36, Configuracion!$A:$D, 4, FALSE), 0)*Tabla15[[#This Row],[CANTIDAD]] -> 0 | I36: =IF(OR(A36="", D36=""), "", IF(C36="Entrada", B36+D36, IF(OR(C36="Venta", C36="Salida"), B36-D36, B36)))
... B191: =IFERROR(VLOOKUP(A191, Configuracion!$A:$B, 2, FALSE), 0) -> 0 | E191: =IF(C191="Venta", IFERROR(VLOOKUP(A191, Configuracion!$A:$D, 3, FALSE), 0), 0) -> 0 | F191: =E191*D191 -> 0 | H191: =IF(AND(G191="Gestor", A191<>""), VLOOKUP(A191, Configuracion!$A:$D, 4, FALSE), 0)*Tabla15[[#This Row],[CANTIDAD]] -> 0 | I191: =IF(OR(A191="", D191=""), "", IF(C191="Entrada", B191+D191, IF(OR(C191="Venta", C191="Salida"), B191-D191, B191)))
A192: TOTAL | F192: =SUM(F2:F191) -> 9440 | H192: =SUM(H2:H191) -> 36000

Sheet martes
A1: PRODUCTO | B1: STOCK INICIAL | C1: MOVIMIENTO | D1: CANTIDAD | E1: PRECIO VENTA | F1: IMPORTE | G1: TIPO DE VENTA O MOV | H1: COMISION | I1: STOCK FINAL | K1: TIPO CAMBIO | L1: Columna1 | O1: CANTIDAD | P1: USD | Q1: OBSERVACION | R1: USD | S1: MN
A2: BASE PARA PANELES GRANDES | B2: =IFERROR(VLOOKUP(A2,lunes!$A:$I,9,FALSE),VLOOKUP(A2,Configuracion!$A:$B,2,FALSE)) -> 10 | C2: VENTA | D2: 1 | E2: =IF(C2="Venta", IFERROR(VLOOKUP(A2, Configuracion!$A:$D, 3, FALSE), 0), 0) -> 100 | F2: =E2*D2 -> 100 | G2: GESTOR | H2: =IF(AND(G2="Gestor", A2<>""), VLOOKUP(A2, Configuracion!$A:$D, 4, FALSE), 0)*Tabla10[[#This Row],[CANTIDAD]] -> 1000 | I2: =IF(OR(A2="", D2=""), "", IF(C2="Entrada", B2+D2, IF(OR(C2="Venta", C2="Salida"), B2-D2, B2))) -> 9 | K2: CUP/USD | L2: 550 | N2: VENTA TOTAL | O2: =Tabla10[[#Totals],[IMPORTE]] -> 2075 | P2: =O2 -> 2075
A3: RIEL | B3: =IFERROR(VLOOKUP(A3,lunes!$A:$I,9,FALSE),VLOOKUP(A3,Configuracion!$A:$B,2,FALSE)) -> 19 | C3: SALIDA | D3: 2 | E3: =IF(C3="Venta", IFERROR(VLOOKUP(A3, Configuracion!$A:$D, 3, FALSE), 0), 0) -> 0 | F3: =E3*D3 -> 0 | G3: MOV | H3: =IF(AND(G3="Gestor", A3<>""), VLOOKUP(A3, Configuracion!$A:$D, 4, FALSE), 0)*Tabla10[[#This Row],[CANTIDAD]] -> 0 | I3: =IF(OR(A3="", D3=""), "", IF(C3="Entrada", B3+D3, IF(OR(C3="Venta", C3="Salida"), B3-D3, B3))) -> 17 | K3: MXN/USD | L3: 20 | N3: USD | O3: 1990 | P3: =O3 -> 1990
A4: EXPANCIONADORES | B4: =IFERROR(VLOOKUP(A4,lunes!$A:$I,9,FALSE),VLOOKUP(A4,Configuracion!$A:$B,2,FALSE)) -> 200 | C4: SALIDA | D4: 12 | E4: =IF(C4="Venta", IFERROR(VLOOKUP(A4, Configuracion!$A:$D, 3, FALSE), 0), 0) -> 0 | F4: =E4*D4 -> 0 | G4: MOV | H4: =IF(AND(G4="Gestor", A4<>""), VLOOKUP(A4, Configuracion!$A:$D, 4, FALSE), 0)*Tabla10[[#This Row],[CANTIDAD]] -> 0 | I4: =IF(OR(A4="", D4=""), "", IF(C4="Entrada", B4+D4, IF(OR(C4="Venta", C4="Salida"), B4-D4, B4))) -> 188 | N4: ZELLE | P4: =O4 -> 0
A5: PLATINAS | B5: =IFERROR(VLOOKUP(A5,lunes!$A:$I,9,FALSE),VLOOKUP(A5,Configuracion!$A:$B,2,FALSE)) -> 9 | C5: SALIDA | D5: 1 | E5: =IF(C5="Venta", IFERROR(VLOOKUP(A5, Configuracion!$A:$D, 3, FALSE), 0), 0) -> 0 | F5: =E5*D5 -> 0 | G5: MOV | H5: =IF(AND(G5="Gestor", A5<>""), VLOOKUP(A5, Configuracion!$A:$D, 4, FALSE), 0)*Tabla10[[#This Row],[CANTIDAD]] -> 0 | I5: =IF(OR(A5="", D5=""), "", IF(C5="Entrada", B5+D5, IF(OR(C5="Venta", C5="Salida"), B5-D5, B5))) -> 8 | N5: MXN | P5: =O5/L3 -> 0
A6: SUJETADOR EXTERIOR | B6: =IFERROR(VLOOKUP(A6,lunes!$A:$I,9,FALSE),VLOOKUP(A6,Configuracion!$A:$B,2,FALSE)) -> 36 | C6: SALIDA | D6: 4 | E6: =IF(C6="Venta", IFERROR(VLOOKUP(A6, Configuracion!$A:$D, 3, FALSE), 0), 0) -> 0 | F6: =E6*D6 -> 0 | G6: MOV | H6: =IF(AND(G6="Gestor", A6<>""), VLOOKUP(A6, Configuracion!$A:$D, 4, FALSE), 0)*Tabla10[[#This Row],[CANTIDAD]] -> 0 | I6: =IF(OR(A6="", D6=""), "", IF(C6="Entrada", B6+D6, IF(OR(C6="Venta", C6="Salida"), B6-D6, B6))) -> 32 | N6: CUP EFECTIVO | O6: 35750 | P6: =O6/L2 -> 65
A7: GANCHO TIERRA | B7: =IFERROR(VLOOKUP(A7,lunes!$A:$I,9,FALSE),VLOOKUP(A7,Configuracion!$A:$B,2,FALSE)) -> 9 | C7: SALIDA | D7: 1 | E7: =IF(C7="Venta", IFERROR(VLOOKUP(A7, Configuracion!$A:$D, 3, FALSE), 0), 0) -> 0 | F7: =E7*D7 -> 0 | G7: MOV | H7: =IF(AND(G7="Gestor", A7<>""), VLOOKUP(A7, Configuracion!$A:$D, 4, FALSE), 0)*Tabla10[[#This Row],[CANTIDAD]] -> 0 | I7: =IF(OR(A7="", D7=""), "", IF(C7="Entrada", B7+D7, IF(OR(C7="Venta", C7="Salida"), B7-D7, B7))) -> 8 | N7: CUP TRANSF | P7: =O7/L2 -> 0
A8: PATAS TRASERAS AJUSTABLES | B8: =IFERROR(VLOOKUP(A8,lunes!$A:$I,9,FALSE),VLOOKUP(A8,Configuracion!$A:$B,2,FALSE)) -> 57 | C8: SALIDA | D8: 3 | E8: =IF(C8="Venta", IFERROR(VLOOKUP(A8, Configuracion!$A:$D, 3, FALSE), 0), 0) -> 0 | F8: =E8*D8 -> 0 | G8: MOV | H8: =IF(AND(G8="Gestor", A8<>""), VLOOKUP(A8, Configuracion!$A:$D, 4, FALSE), 0)*Tabla10[[#This Row],[CANTIDAD]] -> 0 | I8: =IF(OR(A8="", D8=""), "", IF(C8="Entrada", B8+D8, IF(OR(C8="Venta", C8="Salida"), B8-D8, B8))) -> 54 | N8: EUROPA | P8: =O8 -> 0
A9: PATAS DELANTERA AJUSTABLE | B9: =IFERROR(VLOOKUP(A9,lunes!$A:$I,9,FALSE),VLOOKUP(A9,Configuracion!$A:$B,2,FALSE)) -> 56 | C9: SALIDA | D9: 3 | E9: =IF(C9="Venta", IFERROR(VLOOKUP(A9, Configuracion!$A:$D, 3, FALSE), 0), 0) -> 0 | F9: =E9*D9 -> 0 | G9: MOV | H9: =IF(AND(G9="Gestor", A9<>""), VLOOKUP(A9, Configuracion!$A:$D, 4, FALSE), 0)*Tabla10[[#This Row],[CANTIDAD]] -> 0 | I9: =IF(OR(A9="", D9=""), "", IF(C9="Entrada", B9+D9, IF(OR(C9="Venta", C9="Salida"), B9-D9, B9))) -> 53 | N9: TOTAL | P9: =P3+P4+P5+P6+P7+P8 -> 2055
A10: SUJETADOR INTERMEDIO | B10: =IFERROR(VLOOKUP(A10,lunes!$A:$I,9,FALSE),VLOOKUP(A10,Configuracion!$A:$B,2,FALSE)) -> 38 | C10: SALIDA | D10: 2 | E10: =IF(C10="Venta", IFERROR(VLOOKUP(A10, Configuracion!$A:$D, 3, FALSE), 0), 0) -> 0 | F10: =E10*D10 -> 0 | G10: MOV | H10: =IF(AND(G10="Gestor", A10<>""), VLOOKUP(A10, Configuracion!$A:$D, 4, FALSE), 0)*Tabla10[[#This Row],[CANTIDAD]] -> 0 | I10: =IF(OR(A10="", D10=""), "", IF(C10="Entrada", B10+D10, IF(OR(C10="Venta", C10="Salida"), B10-D10, B10))) -> 36 | N10: ENTRADA DINERO | P10: =P12+P11 -> 0
A11: LAVADORA 7.5 AUTOMA MILEXUS | B11: =IFERROR(VLOOKUP(A11,lunes!$A:$I,9,FALSE),VLOOKUP(A11,Configuracion!$A:$B,2,FALSE)) -> 6 | C11: VENTA | D11: 1 | E11: =IF(C11="Venta", IFERROR(VLOOKUP(A11, Configuracion!$A:$D, 3, FALSE), 0), 0) -> 225 | F11: =E11*D11 -> 225 | G11: GESTOR | H11: =IF(AND(G11="Gestor", A11<>""), VLOOKUP(A11, Configuracion!$A:$D, 4, FALSE), 0)*Tabla10[[#This Row],[CANTIDAD]] -> 3000 | I11: =IF(OR(A11="", D11=""), "", IF(C11="Entrada", B11+D11, IF(OR(C11="Venta", C11="Salida"), B11-D11, B11))) -> 5 | N11: CUP | P11: =O11/L2 -> 0
A12: TV HISENSE 55 | B12: =IFERROR(VLOOKUP(A12,lunes!$A:$I,9,FALSE),VLOOKUP(A12,Configuracion!$A:$B,2,FALSE)) -> 6 | C12: VENTA | D12: 1 | E12: =IF(C12="Venta", IFERROR(VLOOKUP(A12, Configuracion!$A:$D, 3, FALSE), 0), 0) -> 430 | F12: =E12*D12 -> 430 | G12: GESTOR | H12: =IF(AND(G12="Gestor", A12<>""), VLOOKUP(A12, Configuracion!$A:$D, 4, FALSE), 0)*Tabla10[[#This Row],[CANTIDAD]] -> 3000 | I12: =IF(OR(A12="", D12=""), "", IF(C12="Entrada", B12+D12, IF(OR(C12="Venta", C12="Salida"), B12-D12, B12))) -> 5 | N12: USD | P12: =O12 -> 0
A13: CAJITA DECODIFICADORA VIVAMAX | B13: =IFERROR(VLOOKUP(A13,lunes!$A:$I,9,FALSE),VLOOKUP(A13,Configuracion!$A:$B,2,FALSE)) -> 5 | C13: VENTA | D13: 1 | E13: =IF(C13="Venta", IFERROR(VLOOKUP(A13, Configuracion!$A:$D, 3, FALSE), 0), 0) -> 40 | F13: =E13*D13 -> 40 | G13: TIENDA | H13: =IF(AND(G13="Gestor", A13<>""), VLOOKUP(A13, Configuracion!$A:$D, 4, FALSE), 0)*Tabla10[[#This Row],[CANTIDAD]] -> 0 | I13: =IF(OR(A13="", D13=""), "", IF(C13="Entrada", B13+D13, IF(OR(C13="Venta", C13="Salida"), B13-D13, B13))) -> 4 | N13: EXTRACCION | P13: =P15+P14 -> 0
A14: BASE FIJA PARA TV 32'' - 86'' | B14: =IFERROR(VLOOKUP(A14,lunes!$A:$I,9,FALSE),VLOOKUP(A14,Configuracion!$A:$B,2,FALSE)) -> 10 | C14: VENTA | D14: 1 | E14: =IF(C14="Venta", IFERROR(VLOOKUP(A14, Configuracion!$A:$D, 3, FALSE), 0), 0) -> 20 | F14: =E14*D14 -> 20 | G14: TIENDA | H14: =IF(AND(G14="Gestor", A14<>""), VLOOKUP(A14, Configuracion!$A:$D, 4, FALSE), 0)*Tabla10[[#This Row],[CANTIDAD]] -> 0 | I14: =IF(OR(A14="", D14=""), "", IF(C14="Entrada", B14+D14, IF(OR(C14="Venta", C14="Salida"), B14-D14, B14))) -> 9 | N14: CUP | P14: =O14/L2 -> 0
A15: PANELES 615 W | B15: =IFERROR(VLOOKUP(A15,lunes!$A:$I,9,FALSE),VLOOKUP(A15,Configuracion!$A:$B,2,FALSE)) -> 69 | C15: VENTA | D15: 5 | E15: =IF(C15="Venta", IFERROR(VLOOKUP(A15, Configuracion!$A:$D, 3, FALSE), 0), 0) -> 180 | F15: =E15*D15 -> 900 | G15: GESTOR | H15: =IF(AND(G15="Gestor", A15<>""), VLOOKUP(A15, Configuracion!$A:$D, 4, FALSE), 0)*Tabla10[[#This Row],[CANTIDAD]] -> 5000 | I15: =IF(OR(A15="", D15=""), "", IF(C15="Entrada", B15+D15, IF(OR(C15="Venta", C15="Salida"), B15-D15, B15))) -> 64 | N15: USD | P15: =O15 -> 0
H16: =IF(AND(G16="Gestor", A16<>""), VLOOKUP(A16, Configuracion!$A:$D, 4, FALSE), 0)*Tabla10[[#This Row],[CANTIDAD]] -> 0 | N16: REBAJAS X COMBO | O16: 20 | P16: =O16 -> 20
A17: PANELES 490 W | B17: =IFERROR(VLOOKUP(A17,lunes!$A:$I,9,FALSE),VLOOKUP(A17,Configuracion!$A:$B,2,FALSE)) -> 10 | C17: VENTA | D17: 2 | E17: =IF(C17="Venta", IFERROR(VLOOKUP(A17, Configuracion!$A:$D, 3, FALSE), 0), 0) -> 180 | F17: =E17*D17 -> 360 | G17: GESTOR | H17: =IF(AND(G17="Gestor", A17<>""), VLOOKUP(A17, Configuracion!$A:$D, 4, FALSE), 0)*Tabla10[[#This Row],[CANTIDAD]] -> 2000 | I17: =IF(OR(A17="", D17=""), "", IF(C17="Entrada", B17+D17, IF(OR(C17="Venta", C17="Salida"), B17-D17, B17))) -> 8 | N17: TOTAL GENERAL | P17: =P9+P13-P10+P16 -> 2075 | R17: =P2-P17 -> 0 | S17: =R17*L2 -> 0
A18: BATERIA SACO 7680W | B18: =IFERROR(VLOOKUP(A18,lunes!$A:$I,9,FALSE),VLOOKUP(A18,Configuracion!$A:$B,2,FALSE)) -> 3 | C18: SALIDA | D18: 1 | E18: =IF(C18="Venta", IFERROR(VLOOKUP(A18, Configuracion!$A:$D, 3, FALSE), 0), 0) -> 0 | F18: =E18*D18 -> 0 | G18: MOV | H18: =IF(AND(G18="Gestor", A18<>""), VLOOKUP(A18, Configuracion!$A:$D, 4, FALSE), 0)*Tabla10[[#This Row],[CANTIDAD]] -> 0 | I18: =IF(OR(A18="", D18=""), "", IF(C18="Entrada", B18+D18, IF(OR(C18="Venta", C18="Salida"), B18-D18, B18))) -> 2
A19: ESTACION MUST 2K CON 2.7K | B19: =IFERROR(VLOOKUP(A19,lunes!$A:$I,9,FALSE),VLOOKUP(A19,Configuracion!$A:$B,2,FALSE)) -> 5 | C19: SALIDA | D19: 1 | E19: =IF(C19="Venta", IFERROR(VLOOKUP(A19, Configuracion!$A:$D, 3, FALSE), 0), 0) -> 0 | F19: =E19*D19 -> 0 | G19: MOV | H19: =IF(AND(G19="Gestor", A19<>""), VLOOKUP(A19, Configuracion!$A:$D, 4, FALSE), 0)*Tabla10[[#This Row],[CANTIDAD]] -> 0 | I19: =IF(OR(A19="", D19=""), "", IF(C19="Entrada", B19+D19, IF(OR(C19="Venta", C19="Salida"), B19-D19, B19))) -> 4 | N19: DIA | O19: CUP EFECTIVO | P19: TARJETA CUP | R19: USD
A20: BATERIA MUST 10.25 KW | B20: =IFERROR(VLOOKUP(A20,lunes!$A:$I,9,FALSE),VLOOKUP(A20,Configuracion!$A:$B,2,FALSE)) -> 0 | C20: ENTRADA | D20: 1 | E20: =IF(C20="Venta", IFERROR(VLOOKUP(A20, Configuracion!$A:$D, 3, FALSE), 0), 0) -> 0 | F20: =E20*D20 -> 0 | G20: MOV | H20: =IF(AND(G20="Gestor", A20<>""), VLOOKUP(A20, Configuracion!$A:$D, 4, FALSE), 0)*Tabla10[[#This Row],[CANTIDAD]] -> 0 | I20: =IF(OR(A20="", D20=""), "", IF(C20="Entrada", B20+D20, IF(OR(C20="Venta", C20="Salida"), B20-D20, B20))) -> 1 | N20: PROP`TARJETA | P20: LEO | Q20: CARLOS
B21: =IFERROR(VLOOKUP(A21,lunes!$A:$I,9,FALSE),VLOOKUP(A21,Configuracion!$A:$B,2,FALSE)) -> #N/A | E21: =IF(C21="Venta", IFERROR(VLOOKUP(A21, Configuracion!$A:$D, 3, FALSE), 0), 0) -> 0 | F21: =E21*D21 -> 0 | H21: =IF(AND(G21="Gestor", A21<>""), VLOOKUP(A21, Configuracion!$A:$D, 4, FALSE), 0)*Tabla10[[#This Row],[CANTIDAD]] -> 0 | I21: =IF(OR(A21="", D21=""), "", IF(C21="Entrada", B21+D21, IF(OR(C21="Venta", C21="Salida"), B21-D21, B21))) | N21: FONDO INICIAL | O21: 45000 | P21: 12822 | Q21: 72900 | R21: 150
B22: =IFERROR(VLOOKUP(A22,lunes!$A:$I,9,FALSE),VLOOKUP(A22,Configuracion!$A:$B,2,FALSE)) -> #N/A | E22: =IF(C22="Venta", IFERROR(VLOOKUP(A22, Configuracion!$A:$D, 3, FALSE), 0), 0) -> 0 | F22: =E22*D22 -> 0 | H22: =IF(AND(G22="Gestor", A22<>""), VLOOKUP(A22, Configuracion!$A:$D, 4, FALSE), 0)*Tabla10[[#This Row],[CANTIDAD]] -> 0 | I22: =IF(OR(A22="", D22=""), "", IF(C22="Entrada", B22+D22, IF(OR(C22="Venta", C22="Salida"), B22-D22, B22))) | N22: CAMBIO
B23: =IFERROR(VLOOKUP(A23,lunes!$A:$I,9,FALSE),VLOOKUP(A23,Configuracion!$A:$B,2,FALSE)) -> #N/A | E23: =IF(C23="Venta", IFERROR(VLOOKUP(A23, Configuracion!$A:$D, 3, FALSE), 0), 0) -> 0 | F23: =E23*D23 -> 0 | H23: =IF(AND(G23="Gestor", A23<>""), VLOOKUP(A23, Configuracion!$A:$D, 4, FALSE), 0)*Tabla10[[#This Row],[CANTIDAD]] -> 0 | I23: =IF(OR(A23="", D23=""), "", IF(C23="Entrada", B23+D23, IF(OR(C23="Venta", C23="Salida"), B23-D23, B23))) | N23: DOMICILIO | O23: 5000
B24: =IFERROR(VLOOKUP(A24,lunes!$A:$I,9,FALSE),VLOOKUP(A24,Configuracion!$A:$B,2,FALSE)) -> #N/A | E24: =IF(C24="Venta", IFERROR(VLOOKUP(A24, Configuracion!$A:$D, 3, FALSE), 0), 0) -> 0 | F24: =E24*D24 -> 0 | H24: =IF(AND(G24="Gestor", A24<>""), VLOOKUP(A24, Configuracion!$A:$D, 4, FALSE), 0)*Tabla10[[#This Row],[CANTIDAD]] -> 0 | I24: =IF(OR(A24="", D24=""), "", IF(C24="Entrada", B24+D24, IF(OR(C24="Venta", C24="Salida"), B24-D24, B24))) | N24: OTROS GASTOS | O24: 1000 | S24: CUSTODIO
B25: =IFERROR(VLOOKUP(A25,lunes!$A:$I,9,FALSE),VLOOKUP(A25,Configuracion!$A:$B,2,FALSE)) -> #N/A | E25: =IF(C25="Venta", IFERROR(VLOOKUP(A25, Configuracion!$A:$D, 3, FALSE), 0), 0) -> 0 | F25: =E25*D25 -> 0 | H25: =IF(AND(G25="Gestor", A25<>""), VLOOKUP(A25, Configuracion!$A:$D, 4, FALSE), 0)*Tabla10[[#This Row],[CANTIDAD]] -> 0 | I25: =IF(OR(A25="", D25=""), "", IF(C25="Entrada", B25+D25, IF(OR(C25="Venta", C25="Salida"), B25-D25, B25))) | N25: COMISIONES | O25: 27000
B26: =IFERROR(VLOOKUP(A26,lunes!$A:$I,9,FALSE),VLOOKUP(A26,Configuracion!$A:$B,2,FALSE)) -> #N/A | E26: =IF(C26="Venta", IFERROR(VLOOKUP(A26, Configuracion!$A:$D, 3, FALSE), 0), 0) -> 0 | F26: =E26*D26 -> 0 | H26: =IF(AND(G26="Gestor", A26<>""), VLOOKUP(A26, Configuracion!$A:$D, 4, FALSE), 0)*Tabla10[[#This Row],[CANTIDAD]] -> 0 | I26: =IF(OR(A26="", D26=""), "", IF(C26="Entrada", B26+D26, IF(OR(C26="Venta", C26="Salida"), B26-D26, B26))) | N26: FONDO TOTAL | O26: =O21-O22-O23-O24-O25 -> 12000 | P26: =P21-P22-P24-P23-P25 -> 12822 | Q26: =Q21-Q22-Q24-Q23-Q25 -> 72900 | R26: =R21-R22-R24-R23-R25 -> 150
B27: =IFERROR(VLOOKUP(A27,lunes!$A:$I,9,FALSE),VLOOKUP(A27,Configuracion!$A:$B,2,FALSE)) -> #N/A | E27: =IF(C27="Venta", IFERROR(VLOOKUP(A27, Configuracion!$A:$D, 3, FALSE), 0), 0) -> 0 | F27: =E27*D27 -> 0 | H27: =IF(AND(G27="Gestor", A27<>""), VLOOKUP(A27, Configuracion!$A:$D, 4, FALSE), 0)*Tabla10[[#This Row],[CANTIDAD]] -> 0 | I27: =IF(OR(A27="", D27=""), "", IF(C27="Entrada", B27+D27, IF(OR(C27="Venta", C27="Salida"), B27-D27, B27)))
B28: =IFERROR(VLOOKUP(A28,lunes!$A:$I,9,FALSE),VLOOKUP(A28,Configuracion!$A:$B,2,FALSE)) -> #N/A | E28: =IF(C28="Venta", IFERROR(VLOOKUP(A28, Configuracion!$A:$D, 3, FALSE), 0), 0) -> 0 | F28: =E28*D28 -> 0 | H28: =IF(AND(G28="Gestor", A28<>""), VLOOKUP(A28, Configuracion!$A:$D, 4, FALSE), 0)*Tabla10[[#This Row],[CANTIDAD]] -> 0 | I28: =IF(OR(A28="", D28=""), "", IF(C28="Entrada", B28+D28, IF(OR(C28="Venta", C28="Salida"), B28-D28, B28)))
B29: =IFERROR(VLOOKUP(A29,lunes!$A:$I,9,FALSE),VLOOKUP(A29,Configuracion!$A:$B,2,FALSE)) -> #N/A | E29: =IF(C29="Venta", IFERROR(VLOOKUP(A29, Configuracion!$A:$D, 3, FALSE), 0), 0) -> 0 | F29: =E29*D29 -> 0 | H29: =IF(AND(G29="Gestor", A29<>""), VLOOKUP(A29, Configuracion!$A:$D, 4, FALSE), 0)*Tabla10[[#This Row],[CANTIDAD]] -> 0 | I29: =IF(OR(A29="", D29=""), "", IF(C29="Entrada", B29+D29, IF(OR(C29="Venta", C29="Salida"), B29-D29, B29)))
B30: =IFERROR(VLOOKUP(A30,lunes!$A:$I,9,FALSE),VLOOKUP(A30,Configuracion!$A:$B,2,FALSE)) -> #N/A | E30: =IF(C30="Venta", IFERROR(VLOOKUP(A30, Configuracion!$A:$D, 3, FALSE), 0), 0) -> 0 | F30: =E30*D30 -> 0 | H30: =IF(AND(G30="Gestor", A30<>""), VLOOKUP(A30, Configuracion!$A:$D, 4, FALSE), 0)*Tabla10[[#This Row],[CANTIDAD]] -> 0 | I30: =IF(OR(A30="", D30=""), "", IF(C30="Entrada", B30+D30, IF(OR(C30="Venta", C30="Salida"), B30-D30, B30)))
B31: =IFERROR(VLOOKUP(A31,lunes!$A:$I,9,FALSE),VLOOKUP(A31,Configuracion!$A:$B,2,FALSE)) -> #N/A | E31: =IF(C31="Venta", IFERROR(VLOOKUP(A31, Configuracion!$A:$D, 3, FALSE), 0), 0) -> 0 | F31: =E31*D31 -> 0 | H31: =IF(AND(G31="Gestor", A31<>""), VLOOKUP(A31, Configuracion!$A:$D, 4, FALSE), 0)*Tabla10[[#This Row],[CANTIDAD]] -> 0 | I31: =IF(OR(A31="", D31=""), "", IF(C31="Entrada", B31+D31, IF(OR(C31="Venta", C31="Salida"), B31-D31, B31)))
B32: =IFERROR(VLOOKUP(A32,lunes!$A:$I,9,FALSE),VLOOKUP(A32,Configuracion!$A:$B,2,FALSE)) -> #N/A | E32: =IF(C32="Venta", IFERROR(VLOOKUP(A32, Configuracion!$A:$D, 3, FALSE), 0), 0) -> 0 | F32: =E32*D32 -> 0 | H32: =IF(AND(G32="Gestor", A32<>""), VLOOKUP(A32, Configuracion!$A:$D, 4, FALSE), 0)*Tabla10[[#This Row],[CANTIDAD]] -> 0 | I32: =IF(OR(A32="", D32=""), "", IF(C32="Entrada", B32+D32, IF(OR(C32="Venta", C32="Salida"), B32-D32, B32)))
B33: =IFERROR(VLOOKUP(A33,lunes!$A:$I,9,FALSE),VLOOKUP(A33,Configuracion!$A:$B,2,FALSE)) -> #N/A | E33: =IF(C33="Venta", IFERROR(VLOOKUP(A33, Configuracion!$A:$D, 3, FALSE), 0), 0) -> 0 | F33: =E33*D33 -> 0 | H33: =IF(AND(G33="Gestor", A33<>""), VLOOKUP(A33, Configuracion!$A:$D, 4, FALSE), 0)*Tabla10[[#This Row],[CANTIDAD]] -> 0 | I33: =IF(OR(A33="", D33=""), "", IF(C33="Entrada", B33+D33, IF(OR(C33="Venta", C33="Salida"), B33-D33, B33)))
B34: =IFERROR(VLOOKUP(A34,lunes!$A:$I,9,FALSE),VLOOKUP(A34,Configuracion!$A:$B,2,FALSE)) -> #N/A | E34: =IF(C34="Venta", IFERROR(VLOOKUP(A34, Configuracion!$A:$D, 3, FALSE), 0), 0) -> 0 | F34: =E34*D34 -> 0 | H34: =IF(AND(G34="Gestor", A34<>""), VLOOKUP(A34, Configuracion!$A:$D, 4, FALSE), 0)*Tabla10[[#This Row],[CANTIDAD]] -> 0 | I34: =IF(OR(A34="", D34=""), "", IF(C34="Entrada", B34+D34, IF(OR(C34="Venta", C34="Salida"), B34-D34, B34)))
B35: =IFERROR(VLOOKUP(A35,lunes!$A:$I,9,FALSE),VLOOKUP(A35,Configuracion!$A:$B,2,FALSE)) -> #N/A | E35: =IF(C35="Venta", IFERROR(VLOOKUP(A35, Configuracion!$A:$D, 3, FALSE), 0), 0) -> 0 | F35: =E35*D35 -> 0 | H35: =IF(AND(G35="Gestor", A35<>""), VLOOKUP(A35, Configuracion!$A:$D, 4, FALSE), 0)*Tabla10[[#This Row],[CANTIDAD]] -> 0 | I35: =IF(OR(A35="", D35=""), "", IF(C35="Entrada", B35+D35, IF(OR(C35="Venta", C35="Salida"), B35-D35, B35)))
B36: =IFERROR(VLOOKUP(A36,lunes!$A:$I,9,FALSE),VLOOKUP(A36,Configuracion!$A:$B,2,FALSE)) -> #N/A | E36: =IF(C36="Venta", IFERROR(VLOOKUP(A36, Configuracion!$A:$D, 3, FALSE), 0), 0) -> 0 | F36: =E36*D36 -> 0 | H36: =IF(AND(G36="Gestor", A36<>""), VLOOKUP(A36, Configuracion!$A:$D, 4, FALSE), 0)*Tabla10[[#This Row],[CANTIDAD]] -> 0 | I36: =IF(OR(A36="", D36=""), "", IF(C36="Entrada", B36+D36, IF(OR(C36="Venta", C36="Salida"), B36-D36, B36)))
B37: =IFERROR(VLOOKUP(A37,lunes!$A:$I,9,FALSE),VLOOKUP(A37,Configuracion!$A:$B,2,FALSE)) -> #N/A | E37: =IF(C37="Venta", IFERROR(VLOOKUP(A37, Configuracion!$A:$D, 3, FALSE), 0), 0) -> 0 | F37: =E37*D37 -> 0 | H37: =IF(AND(G37="Gestor", A37<>""), VLOOKUP(A37, Configuracion!$A:$D, 4, FALSE), 0)*Tabla10[[#This Row],[CANTIDAD]] -> 0 | I37: =IF(OR(A37="", D37=""), "", IF(C37="Entrada", B37+D37, IF(OR(C37="Venta", C37="Salida"), B37-D37, B37)))
B38: =IFERROR(VLOOKUP(A38,lunes!$A:$I,9,FALSE),VLOOKUP(A38,Configuracion!$A:$B,2,FALSE)) -> #N/A | E38: =IF(C38="Venta", IFERROR(VLOOKUP(A38, Configuracion!$A:$D, 3, FALSE), 0), 0) -> 0 | F38: =E38*D38 -> 0 | H38: =IF(AND(G38="Gestor", A38<>""), VLOOKUP(A38, Configuracion!$A:$D, 4, FALSE), 0)*Tabla10[[#This Row],[CANTIDAD]] -> 0 | I38: =IF(OR(A38="", D38=""), "", IF(C38="Entrada", B38+D38, IF(OR(C38="Venta", C38="Salida"), B38-D38, B38)))
... B190: =IFERROR(VLOOKUP(A190,lunes!$A:$I,9,FALSE),VLOOKUP(A190,Configuracion!$A:$B,2,FALSE)) -> #N/A | E190: =IF(C190="Venta", IFERROR(VLOOKUP(A190, Configuracion!$A:$D, 3, FALSE), 0), 0) -> 0 | F190: =E190*D190 -> 0 | H190: =IF(AND(G190="Gestor", A190<>""), VLOOKUP(A190, Configuracion!$A:$D, 4, FALSE), 0)*Tabla10[[#This Row],[CANTIDAD]] -> 0 | I190: =IF(OR(A190="", D190=""), "", IF(C190="Entrada", B190+D190, IF(OR(C190="Venta", C190="Salida"), B190-D190, B190)))
B191: =IFERROR(VLOOKUP(A191, lunes!$A:$I, 9, FALSE), 0) -> 0 | E191: =IF(C191="Venta", IFERROR(VLOOKUP(A191, Configuracion!$A:$D, 3, FALSE), 0), 0) -> 0 | F191: =E191*D191 -> 0 | H191: =IF(AND(G191="Gestor", A191<>""), VLOOKUP(A191, Configuracion!$A:$D, 4, FALSE), 0)*Tabla10[[#This Row],[CANTIDAD]] -> 0
F192: =SUM(F2:F191) -> 2075 | H192: =SUM(H2:H191) -> 14000

Sheet miercoles
A1: PRODUCTO | B1: STOCK INICIAL | C1: MOVIMIENTO | D1: CANTIDAD | E1: PRECIO VENTA | F1: IMPORTE | G1: TIPO DE VENTA O MOV | H1: COMISION | I1: STOCK FINAL | K1: TIPO CAMBIO | L1: Columna1 | O1: CANTIDAD | P1: USD | Q1: OBSERVACION | R1: USD | S1: MN
B2: =IFERROR(VLOOKUP(A2,martes!$A:$I,9,FALSE),IFERROR(VLOOKUP(A2,lunes!$A:$I,9,FALSE),VLOOKUP(A2,Configuracion!$A:$B,2,FALSE))) -> #N/A | C2: VENTA | D2: 1 | E2: =IF(C2="Venta", IFERROR(VLOOKUP(A2, Configuracion!$A:$D, 3, FALSE), 0), 0) -> 0 | F2: =E2*D2 -> 0 | G2: TIENDA | H2: =IF(AND(G2="Gestor", A2<>""), VLOOKUP(A2, Configuracion!$A:$D, 4, FALSE), 0)*Tabla1021[[#This Row],[CANTIDAD]] -> 0 | I2: =IF(OR(A2="", D2=""), "", IF(C2="Entrada", B2+D2, IF(OR(C2="Venta", C2="Salida"), B2-D2, B2))) | K2: CUP/USD | L2: 540 | N2: VENTA TOTAL | O2: =Tabla15[[#Totals],[IMPORTE]] -> 9440 | P2: =O2 -> 9440
B3: =IFERROR(VLOOKUP(A3,martes!$A:$I,9,FALSE),IFERROR(VLOOKUP(A3,lunes!$A:$I,9,FALSE),VLOOKUP(A3,Configuracion!$A:$B,2,FALSE))) -> #N/A | C3: VENTA | D3: 1 | E3: =IF(C3="Venta", IFERROR(VLOOKUP(A3, Configuracion!$A:$D, 3, FALSE), 0), 0) -> 0 | F3: =E3*D3 -> 0 | G3: GESTOR | H3: =IF(AND(G3="Gestor", A3<>""), VLOOKUP(A3, Configuracion!$A:$D, 4, FALSE), 0)*Tabla1021[[#This Row],[CANTIDAD]] -> 0 | I3: =IF(OR(A3="", D3=""), "", IF(C3="Entrada", B3+D3, IF(OR(C3="Venta", C3="Salida"), B3-D3, B3))) | K3: MXN/USD | L3: 20 | N3: USD | O3: 4710 | P3: =O3 -> 4710
B4: =IFERROR(VLOOKUP(A4,martes!$A:$I,9,FALSE),IFERROR(VLOOKUP(A4,lunes!$A:$I,9,FALSE),VLOOKUP(A4,Configuracion!$A:$B,2,FALSE))) -> #N/A | C4: SALIDA | D4: 2 | E4: =IF(C4="Venta", IFERROR(VLOOKUP(A4, Configuracion!$A:$D, 3, FALSE), 0), 0) -> 0 | F4: =E4*D4 -> 0 | H4: =IF(AND(G4="Gestor", A4<>""), VLOOKUP(A4, Configuracion!$A:$D, 4, FALSE), 0)*Tabla1021[[#This Row],[CANTIDAD]] -> 0 | I4: =IF(OR(A4="", D4=""), "", IF(C4="Entrada", B4+D4, IF(OR(C4="Venta", C4="Salida"), B4-D4, B4))) | N4: ZELLE | O4: 380 | P4: =O4 -> 380
B5: =IFERROR(VLOOKUP(A5,martes!$A:$I,9,FALSE),IFERROR(VLOOKUP(A5,lunes!$A:$I,9,FALSE),VLOOKUP(A5,Configuracion!$A:$B,2,FALSE))) -> #N/A | E5: =IF(C5="Venta", IFERROR(VLOOKUP(A5, Configuracion!$A:$D, 3, FALSE), 0), 0) -> 0 | F5: =E5*D5 -> 0 | H5: =IF(AND(G5="Gestor", A5<>""), VLOOKUP(A5, Configuracion!$A:$D, 4, FALSE), 0)*Tabla1021[[#This Row],[CANTIDAD]] -> 0 | I5: =IF(OR(A5="", D5=""), "", IF(C5="Entrada", B5+D5, IF(OR(C5="Venta", C5="Salida"), B5-D5, B5))) | N5: MXN | P5: =O5/L3 -> 0
B6: =IFERROR(VLOOKUP(A6,martes!$A:$I,9,FALSE),IFERROR(VLOOKUP(A6,lunes!$A:$I,9,FALSE),VLOOKUP(A6,Configuracion!$A:$B,2,FALSE))) -> #N/A | E6: =IF(C6="Venta", IFERROR(VLOOKUP(A6, Configuracion!$A:$D, 3, FALSE), 0), 0) -> 0 | F6: =E6*D6 -> 0 | H6: =IF(AND(G6="Gestor", A6<>""), VLOOKUP(A6, Configuracion!$A:$D, 4, FALSE), 0)*Tabla1021[[#This Row],[CANTIDAD]] -> 0 | I6: =IF(OR(A6="", D6=""), "", IF(C6="Entrada", B6+D6, IF(OR(C6="Venta", C6="Salida"), B6-D6, B6))) | N6: CUP EFECTIVO | O6: 1252800 | P6: =O6/L2 -> 2320
B7: =IFERROR(VLOOKUP(A7,martes!$A:$I,9,FALSE),IFERROR(VLOOKUP(A7,lunes!$A:$I,9,FALSE),VLOOKUP(A7,Configuracion!$A:$B,2,FALSE))) -> #N/A | E7: =IF(C7="Venta", IFERROR(VLOOKUP(A7, Configuracion!$A:$D, 3, FALSE), 0), 0) -> 0 | F7: =E7*D7 -> 0 | H7: =IF(AND(G7="Gestor", A7<>""), VLOOKUP(A7, Configuracion!$A:$D, 4, FALSE), 0)*Tabla1021[[#This Row],[CANTIDAD]] -> 0 | I7: =IF(OR(A7="", D7=""), "", IF(C7="Entrada", B7+D7, IF(OR(C7="Venta", C7="Salida"), B7-D7, B7))) | N7: CUP TRANSF | P7: =O7/L2 -> 0
B8: =IFERROR(VLOOKUP(A8,martes!$A:$I,9,FALSE),IFERROR(VLOOKUP(A8,lunes!$A:$I,9,FALSE),VLOOKUP(A8,Configuracion!$A:$B,2,FALSE))) -> #N/A | E8: =IF(C8="Venta", IFERROR(VLOOKUP(A8, Configuracion!$A:$D, 3, FALSE), 0), 0) -> 0 | F8: =E8*D8 -> 0 | H8: =IF(AND(G8="Gestor", A8<>""), VLOOKUP(A8, Configuracion!$A:$D, 4, FALSE), 0)*Tabla1021[[#This Row],[CANTIDAD]] -> 0 | I8: =IF(OR(A8="", D8=""), "", IF(C8="Entrada", B8+D8, IF(OR(C8="Venta", C8="Salida"), B8-D8, B8))) | N8: EUROPA | P8: =O8 -> 0
B9: =IFERROR(VLOOKUP(A9,martes!$A:$I,9,FALSE),IFERROR(VLOOKUP(A9,lunes!$A:$I,9,FALSE),VLOOKUP(A9,Configuracion!$A:$B,2,FALSE))) -> #N/A | E9: =IF(C9="Venta", IFERROR(VLOOKUP(A9, Configuracion!$A:$D, 3, FALSE), 0), 0) -> 0 | F9: =E9*D9 -> 0 | H9: =IF(AND(G9="Gestor", A9<>""), VLOOKUP(A9, Configuracion!$A:$D, 4, FALSE), 0)*Tabla1021[[#This Row],[CANTIDAD]] -> 0 | I9: =IF(OR(A9="", D9=""), "", IF(C9="Entrada", B9+D9, IF(OR(C9="Venta", C9="Salida"), B9-D9, B9))) | N9: TOTAL | P9: =P3+P4+P5+P6+P7+P8 -> 7410
B10: =IFERROR(VLOOKUP(A10,martes!$A:$I,9,FALSE),IFERROR(VLOOKUP(A10,lunes!$A:$I,9,FALSE),VLOOKUP(A10,Configuracion!$A:$B,2,FALSE))) -> #N/A | E10: =IF(C10="Venta", IFERROR(VLOOKUP(A10, Configuracion!$A:$D, 3, FALSE), 0), 0) -> 0 | F10: =E10*D10 -> 0 | H10: =IF(AND(G10="Gestor", A10<>""), VLOOKUP(A10, Configuracion!$A:$D, 4, FALSE), 0)*Tabla1021[[#This Row],[CANTIDAD]] -> 0 | I10: =IF(OR(A10="", D10=""), "", IF(C10="Entrada", B10+D10, IF(OR(C10="Venta", C10="Salida"), B10-D10, B10))) | N10: ENTRADA DINERO | P10: =P12+P11 -> 20
B11: =IFERROR(VLOOKUP(A11,martes!$A:$I,9,FALSE),IFERROR(VLOOKUP(A11,lunes!$A:$I,9,FALSE),VLOOKUP(A11,Configuracion!$A:$B,2,FALSE))) -> #N/A | E11: =IF(C11="Venta", IFERROR(VLOOKUP(A11, Configuracion!$A:$D, 3, FALSE), 0), 0) -> 0 | F11: =E11*D11 -> 0 | H11: =IF(AND(G11="Gestor", A11<>""), VLOOKUP(A11, Configuracion!$A:$D, 4, FALSE), 0)*Tabla1021[[#This Row],[CANTIDAD]] -> 0 | I11: =IF(OR(A11="", D11=""), "", IF(C11="Entrada", B11+D11, IF(OR(C11="Venta", C11="Salida"), B11-D11, B11))) | N11: CUP | P11: =O11/L2 -> 0
B12: =IFERROR(VLOOKUP(A12,martes!$A:$I,9,FALSE),IFERROR(VLOOKUP(A12,lunes!$A:$I,9,FALSE),VLOOKUP(A12,Configuracion!$A:$B,2,FALSE))) -> #N/A | E12: =IF(C12="Venta", IFERROR(VLOOKUP(A12, Configuracion!$A:$D, 3, FALSE), 0), 0) -> 0 | F12: =E12*D12 -> 0 | H12: =IF(AND(G12="Gestor", A12<>""), VLOOKUP(A12, Configuracion!$A:$D, 4, FALSE), 0)*Tabla1021[[#This Row],[CANTIDAD]] -> 0 | I12: =IF(OR(A12="", D12=""), "", IF(C12="Entrada", B12+D12, IF(OR(C12="Venta", C12="Salida"), B12-D12, B12))) | N12: USD | O12: 20 | P12: =O12 -> 20 | Q12: ZELLE
B13: =IFERROR(VLOOKUP(A13,martes!$A:$I,9,FALSE),IFERROR(VLOOKUP(A13,lunes!$A:$I,9,FALSE),VLOOKUP(A13,Configuracion!$A:$B,2,FALSE))) -> #N/A | E13: =IF(C13="Venta", IFERROR(VLOOKUP(A13, Configuracion!$A:$D, 3, FALSE), 0), 0) -> 0 | F13: =E13*D13 -> 0 | H13: =IF(AND(G13="Gestor", A13<>""), VLOOKUP(A13, Configuracion!$A:$D, 4, FALSE), 0)*Tabla1021[[#This Row],[CANTIDAD]] -> 0 | I13: =IF(OR(A13="", D13=""), "", IF(C13="Entrada", B13+D13, IF(OR(C13="Venta", C13="Salida"), B13-D13, B13))) | N13: EXTRACCION | P13: =P15+P14 -> 2050
B14: =IFERROR(VLOOKUP(A14,martes!$A:$I,9,FALSE),IFERROR(VLOOKUP(A14,lunes!$A:$I,9,FALSE),VLOOKUP(A14,Configuracion!$A:$B,2,FALSE))) -> #N/A | E14: =IF(C14="Venta", IFERROR(VLOOKUP(A14, Configuracion!$A:$D, 3, FALSE), 0), 0) -> 0 | F14: =E14*D14 -> 0 | H14: =IF(AND(G14="Gestor", A14<>""), VLOOKUP(A14, Configuracion!$A:$D, 4, FALSE), 0)*Tabla1021[[#This Row],[CANTIDAD]] -> 0 | I14: =IF(OR(A14="", D14=""), "", IF(C14="Entrada", B14+D14, IF(OR(C14="Venta", C14="Salida"), B14-D14, B14))) | N14: CUP | P14: =O14/L2 -> 0
B15: =IFERROR(VLOOKUP(A15,martes!$A:$I,9,FALSE),IFERROR(VLOOKUP(A15,lunes!$A:$I,9,FALSE),VLOOKUP(A15,Configuracion!$A:$B,2,FALSE))) -> #N/A | E15: =IF(C15="Venta", IFERROR(VLOOKUP(A15, Configuracion!$A:$D, 3, FALSE), 0), 0) -> 0 | F15: =E15*D15 -> 0 | H15: =IF(AND(G15="Gestor", A15<>""), VLOOKUP(A15, Configuracion!$A:$D, 4, FALSE), 0)*Tabla1021[[#This Row],[CANTIDAD]] -> 0 | I15: =IF(OR(A15="", D15=""), "", IF(C15="Entrada", B15+D15, IF(OR(C15="Venta", C15="Salida"), B15-D15, B15))) | N15: USD | O15: 2050 | P15: 2050
B16: =IFERROR(VLOOKUP(A16,martes!$A:$I,9,FALSE),IFERROR(VLOOKUP(A16,lunes!$A:$I,9,FALSE),VLOOKUP(A16,Configuracion!$A:$B,2,FALSE))) -> #N/A | E16: =IF(C16="Venta", IFERROR(VLOOKUP(A16, Configuracion!$A:$D, 3, FALSE), 0), 0) -> 0 | F16: =E16*D16 -> 0 | H16: =IF(AND(G16="Gestor", A16<>""), VLOOKUP(A16, Configuracion!$A:$D, 4, FALSE), 0)*Tabla1021[[#This Row],[CANTIDAD]] -> 0 | I16: =IF(OR(A16="", D16=""), "", IF(C16="Entrada", B16+D16, IF(OR(C16="Venta", C16="Salida"), B16-D16, B16))) | N16: TOTAL GENERAL | P16: =P9+P13-P10 -> 9440 | R16: =P2-P16 -> 0 | S16: =R16*L2 -> 0
B17: =IFERROR(VLOOKUP(A17,martes!$A:$I,9,FALSE),IFERROR(VLOOKUP(A17,lunes!$A:$I,9,FALSE),VLOOKUP(A17,Configuracion!$A:$B,2,FALSE))) -> #N/A | E17: =IF(C17="Venta", IFERROR(VLOOKUP(A17, Configuracion!$A:$D, 3, FALSE), 0), 0) -> 0 | F17: =E17*D17 -> 0 | H17: =IF(AND(G17="Gestor", A17<>""), VLOOKUP(A17, Configuracion!$A:$D, 4, FALSE), 0)*Tabla1021[[#This Row],[CANTIDAD]] -> 0 | I17: =IF(OR(A17="", D17=""), "", IF(C17="Entrada", B17+D17, IF(OR(C17="Venta", C17="Salida"), B17-D17, B17)))
B18: =IFERROR(VLOOKUP(A18,martes!$A:$I,9,FALSE),IFERROR(VLOOKUP(A18,lunes!$A:$I,9,FALSE),VLOOKUP(A18,Configuracion!$A:$B,2,FALSE))) -> #N/A | E18: =IF(C18="Venta", IFERROR(VLOOKUP(A18, Configuracion!$A:$D, 3, FALSE), 0), 0) -> 0 | F18: =E18*D18 -> 0 | H18: =IF(AND(G18="Gestor", A18<>""), VLOOKUP(A18, Configuracion!$A:$D, 4, FALSE), 0)*Tabla1021[[#This Row],[CANTIDAD]] -> 0 | I18: =IF(OR(A18="", D18=""), "", IF(C18="Entrada", B18+D18, IF(OR(C18="Venta", C18="Salida"), B18-D18, B18))) | O18: CUP | P18: USD
B19: =IFERROR(VLOOKUP(A19,martes!$A:$I,9,FALSE),IFERROR(VLOOKUP(A19,lunes!$A:$I,9,FALSE),VLOOKUP(A19,Configuracion!$A:$B,2,FALSE))) -> #N/A | E19: =IF(C19="Venta", IFERROR(VLOOKUP(A19, Configuracion!$A:$D, 3, FALSE), 0), 0) -> 0 | F19: =E19*D19 -> 0 | H19: =IF(AND(G19="Gestor", A19<>""), VLOOKUP(A19, Configuracion!$A:$D, 4, FALSE), 0)*Tabla1021[[#This Row],[CANTIDAD]] -> 0 | I19: =IF(OR(A19="", D19=""), "", IF(C19="Entrada", B19+D19, IF(OR(C19="Venta", C19="Salida"), B19-D19, B19))) | N19: FONDO INICIAL | O19: 100000 | P19: 150
B20: =IFERROR(VLOOKUP(A20,martes!$A:$I,9,FALSE),IFERROR(VLOOKUP(A20,lunes!$A:$I,9,FALSE),VLOOKUP(A20,Configuracion!$A:$B,2,FALSE))) -> #N/A | E20: =IF(C20="Venta", IFERROR(VLOOKUP(A20, Configuracion!$A:$D, 3, FALSE), 0), 0) -> 0 | F20: =E20*D20 -> 0 | H20: =IF(AND(G20="Gestor", A20<>""), VLOOKUP(A20, Configuracion!$A:$D, 4, FALSE), 0)*Tabla1021[[#This Row],[CANTIDAD]] -> 0 | I20: =IF(OR(A20="", D20=""), "", IF(C20="Entrada", B20+D20, IF(OR(C20="Venta", C20="Salida"), B20-D20, B20))) | N20: CAMBIO
B21: =IFERROR(VLOOKUP(A21,martes!$A:$I,9,FALSE),IFERROR(VLOOKUP(A21,lunes!$A:$I,9,FALSE),VLOOKUP(A21,Configuracion!$A:$B,2,FALSE))) -> #N/A | E21: =IF(C21="Venta", IFERROR(VLOOKUP(A21, Configuracion!$A:$D, 3, FALSE), 0), 0) -> 0 | F21: =E21*D21 -> 0 | H21: =IF(AND(G21="Gestor", A21<>""), VLOOKUP(A21, Configuracion!$A:$D, 4, FALSE), 0)*Tabla1021[[#This Row],[CANTIDAD]] -> 0 | I21: =IF(OR(A21="", D21=""), "", IF(C21="Entrada", B21+D21, IF(OR(C21="Venta", C21="Salida"), B21-D21, B21))) | N21: DOMICILIO
B22: =IFERROR(VLOOKUP(A22,martes!$A:$I,9,FALSE),IFERROR(VLOOKUP(A22,lunes!$A:$I,9,FALSE),VLOOKUP(A22,Configuracion!$A:$B,2,FALSE))) -> #N/A | E22: =IF(C22="Venta", IFERROR(VLOOKUP(A22, Configuracion!$A:$D, 3, FALSE), 0), 0) -> 0 | F22: =E22*D22 -> 0 | H22: =IF(AND(G22="Gestor", A22<>""), VLOOKUP(A22, Configuracion!$A:$D, 4, FALSE), 0)*Tabla1021[[#This Row],[CANTIDAD]] -> 0 | I22: =IF(OR(A22="", D22=""), "", IF(C22="Entrada", B22+D22, IF(OR(C22="Venta", C22="Salida"), B22-D22, B22))) | N22: OTROS GASTOS
B23: =IFERROR(VLOOKUP(A23,martes!$A:$I,9,FALSE),IFERROR(VLOOKUP(A23,lunes!$A:$I,9,FALSE),VLOOKUP(A23,Configuracion!$A:$B,2,FALSE))) -> #N/A | E23: =IF(C23="Venta", IFERROR(VLOOKUP(A23, Configuracion!$A:$D, 3, FALSE), 0), 0) -> 0 | F23: =E23*D23 -> 0 | H23: =IF(AND(G23="Gestor", A23<>""), VLOOKUP(A23, Configuracion!$A:$D, 4, FALSE), 0)*Tabla1021[[#This Row],[CANTIDAD]] -> 0 | I23: =IF(OR(A23="", D23=""), "", IF(C23="Entrada", B23+D23, IF(OR(C23="Venta", C23="Salida"), B23-D23, B23))) | N23: COMISIONES
B24: =IFERROR(VLOOKUP(A24,martes!$A:$I,9,FALSE),IFERROR(VLOOKUP(A24,lunes!$A:$I,9,FALSE),VLOOKUP(A24,Configuracion!$A:$B,2,FALSE))) -> #N/A | E24: =IF(C24="Venta", IFERROR(VLOOKUP(A24, Configuracion!$A:$D, 3, FALSE), 0), 0) -> 0 | F24: =E24*D24 -> 0 | H24: =IF(AND(G24="Gestor", A24<>""), VLOOKUP(A24, Configuracion!$A:$D, 4, FALSE), 0)*Tabla1021[[#This Row],[CANTIDAD]] -> 0 | I24: =IF(OR(A24="", D24=""), "", IF(C24="Entrada", B24+D24, IF(OR(C24="Venta", C24="Salida"), B24-D24, B24))) | N24: FONDO FINAL | O24: =O19-O21-O22-O23-O20 -> 100000 | P24: =P19-P21-P22-P23-P20 -> 150
B25: =IFERROR(VLOOKUP(A25,martes!$A:$I,9,FALSE),IFERROR(VLOOKUP(A25,lunes!$A:$I,9,FALSE),VLOOKUP(A25,Configuracion!$A:$B,2,FALSE))) -> #N/A | E25: =IF(C25="Venta", IFERROR(VLOOKUP(A25, Configuracion!$A:$D, 3, FALSE), 0), 0) -> 0 | F25: =E25*D25 -> 0 | H25: =IF(AND(G25="Gestor", A25<>""), VLOOKUP(A25, Configuracion!$A:$D, 4, FALSE), 0)*Tabla1021[[#This Row],[CANTIDAD]] -> 0 | I25: =IF(OR(A25="", D25=""), "", IF(C25="Entrada", B25+D25, IF(OR(C25="Venta", C25="Salida"), B25-D25, B25)))
B26: =IFERROR(VLOOKUP(A26,martes!$A:$I,9,FALSE),IFERROR(VLOOKUP(A26,lunes!$A:$I,9,FALSE),VLOOKUP(A26,Configuracion!$A:$B,2,FALSE))) -> #N/A | E26: =IF(C26="Venta", IFERROR(VLOOKUP(A26, Configuracion!$A:$D, 3, FALSE), 0), 0) -> 0 | F26: =E26*D26 -> 0 | H26: =IF(AND(G26="Gestor", A26<>""), VLOOKUP(A26, Configuracion!$A:$D, 4, FALSE), 0)*Tabla1021[[#This Row],[CANTIDAD]] -> 0 | I26: =IF(OR(A26="", D26=""), "", IF(C26="Entrada", B26+D26, IF(OR(C26="Venta", C26="Salida"), B26-D26, B26)))
B27: =IFERROR(VLOOKUP(A27,martes!$A:$I,9,FALSE),IFERROR(VLOOKUP(A27,lunes!$A:$I,9,FALSE),VLOOKUP(A27,Configuracion!$A:$B,2,FALSE))) -> #N/A | E27: =IF(C27="Venta", IFERROR(VLOOKUP(A27, Configuracion!$A:$D, 3, FALSE), 0), 0) -> 0 | F27: =E27*D27 -> 0 | H27: =IF(AND(G27="Gestor", A27<>""), VLOOKUP(A27, Configuracion!$A:$D, 4, FALSE), 0)*Tabla1021[[#This Row],[CANTIDAD]] -> 0 | I27: =IF(OR(A27="", D27=""), "", IF(C27="Entrada", B27+D27, IF(OR(C27="Venta", C27="Salida"), B27-D27, B27)))
B28: =IFERROR(VLOOKUP(A28,martes!$A:$I,9,FALSE),IFERROR(VLOOKUP(A28,lunes!$A:$I,9,FALSE),VLOOKUP(A28,Configuracion!$A:$B,2,FALSE))) -> #N/A | E28: =IF(C28="Venta", IFERROR(VLOOKUP(A28, Configuracion!$A:$D, 3, FALSE), 0), 0) -> 0 | F28: =E28*D28 -> 0 | H28: =IF(AND(G28="Gestor", A28<>""), VLOOKUP(A28, Configuracion!$A:$D, 4, FALSE), 0)*Tabla1021[[#This Row],[CANTIDAD]] -> 0 | I28: =IF(OR(A28="", D28=""), "", IF(C28="Entrada", B28+D28, IF(OR(C28="Venta", C28="Salida"), B28-D28, B28)))
B29: =IFERROR(VLOOKUP(A29,martes!$A:$I,9,FALSE),IFERROR(VLOOKUP(A29,lunes!$A:$I,9,FALSE),VLOOKUP(A29,Configuracion!$A:$B,2,FALSE))) -> #N/A | E29: =IF(C29="Venta", IFERROR(VLOOKUP(A29, Configuracion!$A:$D, 3, FALSE), 0), 0) -> 0 | F29: =E29*D29 -> 0 | H29: =IF(AND(G29="Gestor", A29<>""), VLOOKUP(A29, Configuracion!$A:$D, 4, FALSE), 0)*Tabla1021[[#This Row],[CANTIDAD]] -> 0 | I29: =IF(OR(A29="", D29=""), "", IF(C29="Entrada", B29+D29, IF(OR(C29="Venta", C29="Salida"), B29-D29, B29)))
B30: =IFERROR(VLOOKUP(A30,martes!$A:$I,9,FALSE),IFERROR(VLOOKUP(A30,lunes!$A:$I,9,FALSE),VLOOKUP(A30,Configuracion!$A:$B,2,FALSE))) -> #N/A | E30: =IF(C30="Venta", IFERROR(VLOOKUP(A30, Configuracion!$A:$D, 3, FALSE), 0), 0) -> 0 | F30: =E30*D30 -> 0 | H30: =IF(AND(G30="Gestor", A30<>""), VLOOKUP(A30, Configuracion!$A:$D, 4, FALSE), 0)*Tabla1021[[#This Row],[CANTIDAD]] -> 0 | I30: =IF(OR(A30="", D30=""), "", IF(C30="Entrada", B30+D30, IF(OR(C30="Venta", C30="Salida"), B30-D30, B30)))
B31: =IFERROR(VLOOKUP(A31,martes!$A:$I,9,FALSE),IFERROR(VLOOKUP(A31,lunes!$A:$I,9,FALSE),VLOOKUP(A31,Configuracion!$A:$B,2,FALSE))) -> #N/A | E31: =IF(C31="Venta", IFERROR(VLOOKUP(A31, Configuracion!$A:$D, 3, FALSE), 0), 0) -> 0 | F31: =E31*D31 -> 0 | H31: =IF(AND(G31="Gestor", A31<>""), VLOOKUP(A31, Configuracion!$A:$D, 4, FALSE), 0)*Tabla1021[[#This Row],[CANTIDAD]] -> 0 | I31: =IF(OR(A31="", D31=""), "", IF(C31="Entrada", B31+D31, IF(OR(C31="Venta", C31="Salida"), B31-D31, B31)))
B32: =IFERROR(VLOOKUP(A32,martes!$A:$I,9,FALSE),IFERROR(VLOOKUP(A32,lunes!$A:$I,9,FALSE),VLOOKUP(A32,Configuracion!$A:$B,2,FALSE))) -> #N/A | E32: =IF(C32="Venta", IFERROR(VLOOKUP(A32, Configuracion!$A:$D, 3, FALSE), 0), 0) -> 0 | F32: =E32*D32 -> 0 | H32: =IF(AND(G32="Gestor", A32<>""), VLOOKUP(A32, Configuracion!$A:$D, 4, FALSE), 0)*Tabla1021[[#This Row],[CANTIDAD]] -> 0 | I32: =IF(OR(A32="", D32=""), "", IF(C32="Entrada", B32+D32, IF(OR(C32="Venta", C32="Salida"), B32-D32, B32)))
B33: =IFERROR(VLOOKUP(A33,martes!$A:$I,9,FALSE),IFERROR(VLOOKUP(A33,lunes!$A:$I,9,FALSE),VLOOKUP(A33,Configuracion!$A:$B,2,FALSE))) -> #N/A | E33: =IF(C33="Venta", IFERROR(VLOOKUP(A33, Configuracion!$A:$D, 3, FALSE), 0), 0) -> 0 | F33: =E33*D33 -> 0 | H33: =IF(AND(G33="Gestor", A33<>""), VLOOKUP(A33, Configuracion!$A:$D, 4, FALSE), 0)*Tabla1021[[#This Row],[CANTIDAD]] -> 0 | I33: =IF(OR(A33="", D33=""), "", IF(C33="Entrada", B33+D33, IF(OR(C33="Venta", C33="Salida"), B33-D33, B33)))
B34: =IFERROR(VLOOKUP(A34,martes!$A:$I,9,FALSE),IFERROR(VLOOKUP(A34,lunes!$A:$I,9,FALSE),VLOOKUP(A34,Configuracion!$A:$B,2,FALSE))) -> #N/A | E34: =IF(C34="Venta", IFERROR(VLOOKUP(A34, Configuracion!$A:$D, 3, FALSE), 0), 0) -> 0 | F34: =E34*D34 -> 0 | H34: =IF(AND(G34="Gestor", A34<>""), VLOOKUP(A34, Configuracion!$A:$D, 4, FALSE), 0)*Tabla1021[[#This Row],[CANTIDAD]] -> 0 | I34: =IF(OR(A34="", D34=""), "", IF(C34="Entrada", B34+D34, IF(OR(C34="Venta", C34="Salida"), B34-D34, B34)))
B35: =IFERROR(VLOOKUP(A35,martes!$A:$I,9,FALSE),IFERROR(VLOOKUP(A35,lunes!$A:$I,9,FALSE),VLOOKUP(A35,Configuracion!$A:$B,2,FALSE))) -> #N/A | E35: =IF(C35="Venta", IFERROR(VLOOKUP(A35, Configuracion!$A:$D, 3, FALSE), 0), 0) -> 0 | F35: =E35*D35 -> 0 | H35: =IF(AND(G35="Gestor", A35<>""), VLOOKUP(A35, Configuracion!$A:$D, 4, FALSE), 0)*Tabla1021[[#This Row],[CANTIDAD]] -> 0 | I35: =IF(OR(A35="", D35=""), "", IF(C35="Entrada", B35+D35, IF(OR(C35="Venta", C35="Salida"), B35-D35, B35)))
B36: =IFERROR(VLOOKUP(A36,martes!$A:$I,9,FALSE),IFERROR(VLOOKUP(A36,lunes!$A:$I,9,FALSE),VLOOKUP(A36,Configuracion!$A:$B,2,FALSE))) -> #N/A | E36: =IF(C36="Venta", IFERROR(VLOOKUP(A36, Configuracion!$A:$D, 3, FALSE), 0), 0) -> 0 | F36: =E36*D36 -> 0 | H36: =IF(AND(G36="Gestor", A36<>""), VLOOKUP(A36, Configuracion!$A:$D, 4, FALSE), 0)*Tabla1021[[#This Row],[CANTIDAD]] -> 0 | I36: =IF(OR(A36="", D36=""), "", IF(C36="Entrada", B36+D36, IF(OR(C36="Venta", C36="Salida"), B36-D36, B36)))
... B189: =IFERROR(VLOOKUP(A189,martes!$A:$I,9,FALSE),IFERROR(VLOOKUP(A189,lunes!$A:$I,9,FALSE),VLOOKUP(A189,Configuracion!$A:$B,2,FALSE))) -> #N/A | E189: =IF(C189="Venta", IFERROR(VLOOKUP(A189, Configuracion!$A:$D, 3, FALSE), 0), 0) -> 0 | F189: =E189*D189 -> 0 | H189: =IF(AND(G189="Gestor", A189<>""), VLOOKUP(A189, Configuracion!$A:$D, 4, FALSE), 0)*Tabla1021[[#This Row],[CANTIDAD]] -> 0 | I189: =IF(OR(A189="", D189=""), "", IF(C189="Entrada", B189+D189, IF(OR(C189="Venta", C189="Salida"), B189-D189, B189)))
B190: =IFERROR(VLOOKUP(A190,martes!$A:$I,9,FALSE),IFERROR(VLOOKUP(A190,lunes!$A:$I,9,FALSE),VLOOKUP(A190,Configuracion!$A:$B,2,FALSE))) -> #N/A | E190: =IF(C190="Venta", IFERROR(VLOOKUP(A190, Configuracion!$A:$D, 3, FALSE), 0), 0) -> 0 | F190: =E190*D190 -> 0 | H190: =IF(AND(G190="Gestor", A190<>""), VLOOKUP(A190, Configuracion!$A:$D, 4, FALSE), 0)*Tabla1021[[#This Row],[CANTIDAD]] -> 0

Sheet jueves
A1: PRODUCTO | B1: STOCK INICIAL | C1: MOVIMIENTO | D1: CANTIDAD | E1: PRECIO VENTA | F1: IMPORTE | G1: TIPO DE VENTA O MOV | H1: COMISION | I1: STOCK FINAL | K1: TIPO CAMBIO | L1: Columna1 | O1: CANTIDAD | P1: USD | Q1: OBSERVACION | R1: USD | S1: MN
B2: =IFERROR(VLOOKUP(A2,miercoles!$A:$I,9,FALSE),IFERROR(VLOOKUP(A2,martes!$A:$I,9,FALSE),IFERROR(VLOOKUP(A2,lunes!$A:$I,9,FALSE),VLOOKUP(A2,Configuracion!$A:$B,2,FALSE)))) -> #N/A | C2: VENTA | D2: 1 | E2: =IF(C2="Venta", IFERROR(VLOOKUP(A2, Configuracion!$A:$D, 3, FALSE), 0), 0) -> 0 | F2: =E2*D2 -> 0 | G2: TIENDA | H2: =IF(AND(G2="Gestor", A2<>""), VLOOKUP(A2, Configuracion!$A:$D, 4, FALSE), 0)*Tabla1023[[#This Row],[CANTIDAD]] -> 0 | I2: =IF(OR(A2="", D2=""), "", IF(C2="Entrada", B2+D2, IF(OR(C2="Venta", C2="Salida"), B2-D2, B2))) | K2: CUP/USD | L2: 540 | N2: VENTA TOTAL | O2: =Tabla15[[#Totals],[IMPORTE]] -> 9440 | P2: =O2 -> 9440
B3: =IFERROR(VLOOKUP(A3,miercoles!$A:$I,9,FALSE),IFERROR(VLOOKUP(A3,martes!$A:$I,9,FALSE),IFERROR(VLOOKUP(A3,lunes!$A:$I,9,FALSE),VLOOKUP(A3,Configuracion!$A:$B,2,FALSE)))) -> #N/A | C3: VENTA | D3: 1 | E3: =IF(C3="Venta", IFERROR(VLOOKUP(A3, Configuracion!$A:$D, 3, FALSE), 0), 0) -> 0 | F3: =E3*D3 -> 0 | G3: GESTOR | H3: =IF(AND(G3="Gestor", A3<>""), VLOOKUP(A3, Configuracion!$A:$D, 4, FALSE), 0)*Tabla1023[[#This Row],[CANTIDAD]] -> 0 | I3: =IF(OR(A3="", D3=""), "", IF(C3="Entrada", B3+D3, IF(OR(C3="Venta", C3="Salida"), B3-D3, B3))) | K3: MXN/USD | L3: 20 | N3: USD | O3: 4710 | P3: =O3 -> 4710
B4: =IFERROR(VLOOKUP(A4,miercoles!$A:$I,9,FALSE),IFERROR(VLOOKUP(A4,martes!$A:$I,9,FALSE),IFERROR(VLOOKUP(A4,lunes!$A:$I,9,FALSE),VLOOKUP(A4,Configuracion!$A:$B,2,FALSE)))) -> #N/A | C4: VENTA | D4: 1 | E4: =IF(C4="Venta", IFERROR(VLOOKUP(A4, Configuracion!$A:$D, 3, FALSE), 0), 0) -> 0 | F4: =E4*D4 -> 0 | H4: =IF(AND(G4="Gestor", A4<>""), VLOOKUP(A4, Configuracion!$A:$D, 4, FALSE), 0)*Tabla1023[[#This Row],[CANTIDAD]] -> 0 | I4: =IF(OR(A4="", D4=""), "", IF(C4="Entrada", B4+D4, IF(OR(C4="Venta", C4="Salida"), B4-D4, B4))) | N4: ZELLE | O4: 380 | P4: =O4 -> 380
B5: =IFERROR(VLOOKUP(A5,miercoles!$A:$I,9,FALSE),IFERROR(VLOOKUP(A5,martes!$A:$I,9,FALSE),IFERROR(VLOOKUP(A5,lunes!$A:$I,9,FALSE),VLOOKUP(A5,Configuracion!$A:$B,2,FALSE)))) -> #N/A | E5: =IF(C5="Venta", IFERROR(VLOOKUP(A5, Configuracion!$A:$D, 3, FALSE), 0), 0) -> 0 | F5: =E5*D5 -> 0 | H5: =IF(AND(G5="Gestor", A5<>""), VLOOKUP(A5, Configuracion!$A:$D, 4, FALSE), 0)*Tabla1023[[#This Row],[CANTIDAD]] -> 0 | I5: =IF(OR(A5="", D5=""), "", IF(C5="Entrada", B5+D5, IF(OR(C5="Venta", C5="Salida"), B5-D5, B5))) | N5: MXN | P5: =O5/L3 -> 0
B6: =IFERROR(VLOOKUP(A6,miercoles!$A:$I,9,FALSE),IFERROR(VLOOKUP(A6,martes!$A:$I,9,FALSE),IFERROR(VLOOKUP(A6,lunes!$A:$I,9,FALSE),VLOOKUP(A6,Configuracion!$A:$B,2,FALSE)))) -> #N/A | E6: =IF(C6="Venta", IFERROR(VLOOKUP(A6, Configuracion!$A:$D, 3, FALSE), 0), 0) -> 0 | F6: =E6*D6 -> 0 | H6: =IF(AND(G6="Gestor", A6<>""), VLOOKUP(A6, Configuracion!$A:$D, 4, FALSE), 0)*Tabla1023[[#This Row],[CANTIDAD]] -> 0 | I6: =IF(OR(A6="", D6=""), "", IF(C6="Entrada", B6+D6, IF(OR(C6="Venta", C6="Salida"), B6-D6, B6))) | N6: CUP EFECTIVO | O6: 1252800 | P6: =O6/L2 -> 2320
B7: =IFERROR(VLOOKUP(A7,miercoles!$A:$I,9,FALSE),IFERROR(VLOOKUP(A7,martes!$A:$I,9,FALSE),IFERROR(VLOOKUP(A7,lunes!$A:$I,9,FALSE),VLOOKUP(A7,Configuracion!$A:$B,2,FALSE)))) -> #N/A | E7: =IF(C7="Venta", IFERROR(VLOOKUP(A7, Configuracion!$A:$D, 3, FALSE), 0), 0) -> 0 | F7: =E7*D7 -> 0 | H7: =IF(AND(G7="Gestor", A7<>""), VLOOKUP(A7, Configuracion!$A:$D, 4, FALSE), 0)*Tabla1023[[#This Row],[CANTIDAD]] -> 0 | I7: =IF(OR(A7="", D7=""), "", IF(C7="Entrada", B7+D7, IF(OR(C7="Venta", C7="Salida"), B7-D7, B7))) | N7: CUP TRANSF | P7: =O7/L2 -> 0
B8: =IFERROR(VLOOKUP(A8,miercoles!$A:$I,9,FALSE),IFERROR(VLOOKUP(A8,martes!$A:$I,9,FALSE),IFERROR(VLOOKUP(A8,lunes!$A:$I,9,FALSE),VLOOKUP(A8,Configuracion!$A:$B,2,FALSE)))) -> #N/A | E8: =IF(C8="Venta", IFERROR(VLOOKUP(A8, Configuracion!$A:$D, 3, FALSE), 0), 0) -> 0 | F8: =E8*D8 -> 0 | H8: =IF(AND(G8="Gestor", A8<>""), VLOOKUP(A8, Configuracion!$A:$D, 4, FALSE), 0)*Tabla1023[[#This Row],[CANTIDAD]] -> 0 | I8: =IF(OR(A8="", D8=""), "", IF(C8="Entrada", B8+D8, IF(OR(C8="Venta", C8="Salida"), B8-D8, B8))) | N8: EUROPA | P8: =O8 -> 0
B9: =IFERROR(VLOOKUP(A9,miercoles!$A:$I,9,FALSE),IFERROR(VLOOKUP(A9,martes!$A:$I,9,FALSE),IFERROR(VLOOKUP(A9,lunes!$A:$I,9,FALSE),VLOOKUP(A9,Configuracion!$A:$B,2,FALSE)))) -> #N/A | E9: =IF(C9="Venta", IFERROR(VLOOKUP(A9, Configuracion!$A:$D, 3, FALSE), 0), 0) -> 0 | F9: =E9*D9 -> 0 | H9: =IF(AND(G9="Gestor", A9<>""), VLOOKUP(A9, Configuracion!$A:$D, 4, FALSE), 0)*Tabla1023[[#This Row],[CANTIDAD]] -> 0 | I9: =IF(OR(A9="", D9=""), "", IF(C9="Entrada", B9+D9, IF(OR(C9="Venta", C9="Salida"), B9-D9, B9))) | N9: TOTAL | P9: =P3+P4+P5+P6+P7+P8 -> 7410
B10: =IFERROR(VLOOKUP(A10,miercoles!$A:$I,9,FALSE),IFERROR(VLOOKUP(A10,martes!$A:$I,9,FALSE),IFERROR(VLOOKUP(A10,lunes!$A:$I,9,FALSE),VLOOKUP(A10,Configuracion!$A:$B,2,FALSE)))) -> #N/A | E10: =IF(C10="Venta", IFERROR(VLOOKUP(A10, Configuracion!$A:$D, 3, FALSE), 0), 0) -> 0 | F10: =E10*D10 -> 0 | H10: =IF(AND(G10="Gestor", A10<>""), VLOOKUP(A10, Configuracion!$A:$D, 4, FALSE), 0)*Tabla1023[[#This Row],[CANTIDAD]] -> 0 | I10: =IF(OR(A10="", D10=""), "", IF(C10="Entrada", B10+D10, IF(OR(C10="Venta", C10="Salida"), B10-D10, B10))) | N10: ENTRADA DINERO | P10: =P12+P11 -> 20
B11: =IFERROR(VLOOKUP(A11,miercoles!$A:$I,9,FALSE),IFERROR(VLOOKUP(A11,martes!$A:$I,9,FALSE),IFERROR(VLOOKUP(A11,lunes!$A:$I,9,FALSE),VLOOKUP(A11,Configuracion!$A:$B,2,FALSE)))) -> #N/A | E11: =IF(C11="Venta", IFERROR(VLOOKUP(A11, Configuracion!$A:$D, 3, FALSE), 0), 0) -> 0 | F11: =E11*D11 -> 0 | H11: =IF(AND(G11="Gestor", A11<>""), VLOOKUP(A11, Configuracion!$A:$D, 4, FALSE), 0)*Tabla1023[[#This Row],[CANTIDAD]] -> 0 | I11: =IF(OR(A11="", D11=""), "", IF(C11="Entrada", B11+D11, IF(OR(C11="Venta", C11="Salida"), B11-D11, B11))) | N11: CUP | P11: =O11/L2 -> 0
B12: =IFERROR(VLOOKUP(A12,miercoles!$A:$I,9,FALSE),IFERROR(VLOOKUP(A12,martes!$A:$I,9,FALSE),IFERROR(VLOOKUP(A12,lunes!$A:$I,9,FALSE),VLOOKUP(A12,Configuracion!$A:$B,2,FALSE)))) -> #N/A | E12: =IF(C12="Venta", IFERROR(VLOOKUP(A12, Configuracion!$A:$D, 3, FALSE), 0), 0) -> 0 | F12: =E12*D12 -> 0 | H12: =IF(AND(G12="Gestor", A12<>""), VLOOKUP(A12, Configuracion!$A:$D, 4, FALSE), 0)*Tabla1023[[#This Row],[CANTIDAD]] -> 0 | I12: =IF(OR(A12="", D12=""), "", IF(C12="Entrada", B12+D12, IF(OR(C12="Venta", C12="Salida"), B12-D12, B12))) | N12: USD | O12: 20 | P12: =O12 -> 20 | Q12: ZELLE
B13: =IFERROR(VLOOKUP(A13,miercoles!$A:$I,9,FALSE),IFERROR(VLOOKUP(A13,martes!$A:$I,9,FALSE),IFERROR(VLOOKUP(A13,lunes!$A:$I,9,FALSE),VLOOKUP(A13,Configuracion!$A:$B,2,FALSE)))) -> #N/A | E13: =IF(C13="Venta", IFERROR(VLOOKUP(A13, Configuracion!$A:$D, 3, FALSE), 0), 0) -> 0 | F13: =E13*D13 -> 0 | H13: =IF(AND(G13="Gestor", A13<>""), VLOOKUP(A13, Configuracion!$A:$D, 4, FALSE), 0)*Tabla1023[[#This Row],[CANTIDAD]] -> 0 | I13: =IF(OR(A13="", D13=""), "", IF(C13="Entrada", B13+D13, IF(OR(C13="Venta", C13="Salida"), B13-D13, B13))) | N13: EXTRACCION | P13: =P15+P14 -> 2050
B14: =IFERROR(VLOOKUP(A14,miercoles!$A:$I,9,FALSE),IFERROR(VLOOKUP(A14,martes!$A:$I,9,FALSE),IFERROR(VLOOKUP(A14,lunes!$A:$I,9,FALSE),VLOOKUP(A14,Configuracion!$A:$B,2,FALSE)))) -> #N/A | E14: =IF(C14="Venta", IFERROR(VLOOKUP(A14, Configuracion!$A:$D, 3, FALSE), 0), 0) -> 0 | F14: =E14*D14 -> 0 | H14: =IF(AND(G14="Gestor", A14<>""), VLOOKUP(A14, Configuracion!$A:$D, 4, FALSE), 0)*Tabla1023[[#This Row],[CANTIDAD]] -> 0 | I14: =IF(OR(A14="", D14=""), "", IF(C14="Entrada", B14+D14, IF(OR(C14="Venta", C14="Salida"), B14-D14, B14))) | N14: CUP | P14: =O14/L2 -> 0
B15: =IFERROR(VLOOKUP(A15,miercoles!$A:$I,9,FALSE),IFERROR(VLOOKUP(A15,martes!$A:$I,9,FALSE),IFERROR(VLOOKUP(A15,lunes!$A:$I,9,FALSE),VLOOKUP(A15,Configuracion!$A:$B,2,FALSE)))) -> #N/A | E15: =IF(C15="Venta", IFERROR(VLOOKUP(A15, Configuracion!$A:$D, 3, FALSE), 0), 0) -> 0 | F15: =E15*D15 -> 0 | H15: =IF(AND(G15="Gestor", A15<>""), VLOOKUP(A15, Configuracion!$A:$D, 4, FALSE), 0)*Tabla1023[[#This Row],[CANTIDAD]] -> 0 | I15: =IF(OR(A15="", D15=""), "", IF(C15="Entrada", B15+D15, IF(OR(C15="Venta", C15="Salida"), B15-D15, B15))) | N15: USD | O15: 2050 | P15: 2050
B16: =IFERROR(VLOOKUP(A16,miercoles!$A:$I,9,FALSE),IFERROR(VLOOKUP(A16,martes!$A:$I,9,FALSE),IFERROR(VLOOKUP(A16,lunes!$A:$I,9,FALSE),VLOOKUP(A16,Configuracion!$A:$B,2,FALSE)))) -> #N/A | E16: =IF(C16="Venta", IFERROR(VLOOKUP(A16, Configuracion!$A:$D, 3, FALSE), 0), 0) -> 0 | F16: =E16*D16 -> 0 | H16: =IF(AND(G16="Gestor", A16<>""), VLOOKUP(A16, Configuracion!$A:$D, 4, FALSE), 0)*Tabla1023[[#This Row],[CANTIDAD]] -> 0 | I16: =IF(OR(A16="", D16=""), "", IF(C16="Entrada", B16+D16, IF(OR(C16="Venta", C16="Salida"), B16-D16, B16))) | N16: TOTAL GENERAL | P16: =P9+P13-P10 -> 9440 | R16: =P2-P16 -> 0 | S16: =R16*L2 -> 0
B17: =IFERROR(VLOOKUP(A17,miercoles!$A:$I,9,FALSE),IFERROR(VLOOKUP(A17,martes!$A:$I,9,FALSE),IFERROR(VLOOKUP(A17,lunes!$A:$I,9,FALSE),VLOOKUP(A17,Configuracion!$A:$B,2,FALSE)))) -> #N/A | E17: =IF(C17="Venta", IFERROR(VLOOKUP(A17, Configuracion!$A:$D, 3, FALSE), 0), 0) -> 0 | F17: =E17*D17 -> 0 | H17: =IF(AND(G17="Gestor", A17<>""), VLOOKUP(A17, Configuracion!$A:$D, 4, FALSE), 0)*Tabla1023[[#This Row],[CANTIDAD]] -> 0 | I17: =IF(OR(A17="", D17=""), "", IF(C17="Entrada", B17+D17, IF(OR(C17="Venta", C17="Salida"), B17-D17, B17)))
B18: =IFERROR(VLOOKUP(A18,miercoles!$A:$I,9,FALSE),IFERROR(VLOOKUP(A18,martes!$A:$I,9,FALSE),IFERROR(VLOOKUP(A18,lunes!$A:$I,9,FALSE),VLOOKUP(A18,Configuracion!$A:$B,2,FALSE)))) -> #N/A | E18: =IF(C18="Venta", IFERROR(VLOOKUP(A18, Configuracion!$A:$D, 3, FALSE), 0), 0) -> 0 | F18: =E18*D18 -> 0 | H18: =IF(AND(G18="Gestor", A18<>""), VLOOKUP(A18, Configuracion!$A:$D, 4, FALSE), 0)*Tabla1023[[#This Row],[CANTIDAD]] -> 0 | I18: =IF(OR(A18="", D18=""), "", IF(C18="Entrada", B18+D18, IF(OR(C18="Venta", C18="Salida"), B18-D18, B18))) | O18: CUP | P18: USD
B19: =IFERROR(VLOOKUP(A19,miercoles!$A:$I,9,FALSE),IFERROR(VLOOKUP(A19,martes!$A:$I,9,FALSE),IFERROR(VLOOKUP(A19,lunes!$A:$I,9,FALSE),VLOOKUP(A19,Configuracion!$A:$B,2,FALSE)))) -> #N/A | E19: =IF(C19="Venta", IFERROR(VLOOKUP(A19, Configuracion!$A:$D, 3, FALSE), 0), 0) -> 0 | F19: =E19*D19 -> 0 | H19: =IF(AND(G19="Gestor", A19<>""), VLOOKUP(A19, Configuracion!$A:$D, 4, FALSE), 0)*Tabla1023[[#This Row],[CANTIDAD]] -> 0 | I19: =IF(OR(A19="", D19=""), "", IF(C19="Entrada", B19+D19, IF(OR(C19="Venta", C19="Salida"), B19-D19, B19))) | N19: FONDO INICIAL | O19: 100000 | P19: 150
B20: =IFERROR(VLOOKUP(A20,miercoles!$A:$I,9,FALSE),IFERROR(VLOOKUP(A20,martes!$A:$I,9,FALSE),IFERROR(VLOOKUP(A20,lunes!$A:$I,9,FALSE),VLOOKUP(A20,Configuracion!$A:$B,2,FALSE)))) -> #N/A | E20: =IF(C20="Venta", IFERROR(VLOOKUP(A20, Configuracion!$A:$D, 3, FALSE), 0), 0) -> 0 | F20: =E20*D20 -> 0 | H20: =IF(AND(G20="Gestor", A20<>""), VLOOKUP(A20, Configuracion!$A:$D, 4, FALSE), 0)*Tabla1023[[#This Row],[CANTIDAD]] -> 0 | I20: =IF(OR(A20="", D20=""), "", IF(C20="Entrada", B20+D20, IF(OR(C20="Venta", C20="Salida"), B20-D20, B20))) | N20: CAMBIO
B21: =IFERROR(VLOOKUP(A21,miercoles!$A:$I,9,FALSE),IFERROR(VLOOKUP(A21,martes!$A:$I,9,FALSE),IFERROR(VLOOKUP(A21,lunes!$A:$I,9,FALSE),VLOOKUP(A21,Configuracion!$A:$B,2,FALSE)))) -> #N/A | E21: =IF(C21="Venta", IFERROR(VLOOKUP(A21, Configuracion!$A:$D, 3, FALSE), 0), 0) -> 0 | F21: =E21*D21 -> 0 | H21: =IF(AND(G21="Gestor", A21<>""), VLOOKUP(A21, Configuracion!$A:$D, 4, FALSE), 0)*Tabla1023[[#This Row],[CANTIDAD]] -> 0 | I21: =IF(OR(A21="", D21=""), "", IF(C21="Entrada", B21+D21, IF(OR(C21="Venta", C21="Salida"), B21-D21, B21))) | N21: DOMICILIO
B22: =IFERROR(VLOOKUP(A22,miercoles!$A:$I,9,FALSE),IFERROR(VLOOKUP(A22,martes!$A:$I,9,FALSE),IFERROR(VLOOKUP(A22,lunes!$A:$I,9,FALSE),VLOOKUP(A22,Configuracion!$A:$B,2,FALSE)))) -> #N/A | E22: =IF(C22="Venta", IFERROR(VLOOKUP(A22, Configuracion!$A:$D, 3, FALSE), 0), 0) -> 0 | F22: =E22*D22 -> 0 | H22: =IF(AND(G22="Gestor", A22<>""), VLOOKUP(A22, Configuracion!$A:$D, 4, FALSE), 0)*Tabla1023[[#This Row],[CANTIDAD]] -> 0 | I22: =IF(OR(A22="", D22=""), "", IF(C22="Entrada", B22+D22, IF(OR(C22="Venta", C22="Salida"), B22-D22, B22))) | N22: OTROS GASTOS
B23: =IFERROR(VLOOKUP(A23,miercoles!$A:$I,9,FALSE),IFERROR(VLOOKUP(A23,martes!$A:$I,9,FALSE),IFERROR(VLOOKUP(A23,lunes!$A:$I,9,FALSE),VLOOKUP(A23,Configuracion!$A:$B,2,FALSE)))) -> #N/A | E23: =IF(C23="Venta", IFERROR(VLOOKUP(A23, Configuracion!$A:$D, 3, FALSE), 0), 0) -> 0 | F23: =E23*D23 -> 0 | H23: =IF(AND(G23="Gestor", A23<>""), VLOOKUP(A23, Configuracion!$A:$D, 4, FALSE), 0)*Tabla1023[[#This Row],[CANTIDAD]] -> 0 | I23: =IF(OR(A23="", D23=""), "", IF(C23="Entrada", B23+D23, IF(OR(C23="Venta", C23="Salida"), B23-D23, B23))) | N23: COMISIONES
B24: =IFERROR(VLOOKUP(A24,miercoles!$A:$I,9,FALSE),IFERROR(VLOOKUP(A24,martes!$A:$I,9,FALSE),IFERROR(VLOOKUP(A24,lunes!$A:$I,9,FALSE),VLOOKUP(A24,Configuracion!$A:$B,2,FALSE)))) -> #N/A | E24: =IF(C24="Venta", IFERROR(VLOOKUP(A24, Configuracion!$A:$D, 3, FALSE), 0), 0) -> 0 | F24: =E24*D24 -> 0 | H24: =IF(AND(G24="Gestor", A24<>""), VLOOKUP(A24, Configuracion!$A:$D, 4, FALSE), 0)*Tabla1023[[#This Row],[CANTIDAD]] -> 0 | I24: =IF(OR(A24="", D24=""), "", IF(C24="Entrada", B24+D24, IF(OR(C24="Venta", C24="Salida"), B24-D24, B24))) | N24: FONDO FINAL | O24: =O19-O21-O22-O23-O20 -> 100000 | P24: =P19-P21-P22-P23-P20 -> 150
B25: =IFERROR(VLOOKUP(A25,miercoles!$A:$I,9,FALSE),IFERROR(VLOOKUP(A25,martes!$A:$I,9,FALSE),IFERROR(VLOOKUP(A25,lunes!$A:$I,9,FALSE),VLOOKUP(A25,Configuracion!$A:$B,2,FALSE)))) -> #N/A | E25: =IF(C25="Venta", IFERROR(VLOOKUP(A25, Configuracion!$A:$D, 3, FALSE), 0), 0) -> 0 | F25: =E25*D25 -> 0 | H25: =IF(AND(G25="Gestor", A25<>""), VLOOKUP(A25, Configuracion!$A:$D, 4, FALSE), 0)*Tabla1023[[#This Row],[CANTIDAD]] -> 0 | I25: =IF(OR(A25="", D25=""), "", IF(C25="Entrada", B25+D25, IF(OR(C25="Venta", C25="Salida"), B25-D25, B25)))
B26: =IFERROR(VLOOKUP(A26,miercoles!$A:$I,9,FALSE),IFERROR(VLOOKUP(A26,martes!$A:$I,9,FALSE),IFERROR(VLOOKUP(A26,lunes!$A:$I,9,FALSE),VLOOKUP(A26,Configuracion!$A:$B,2,FALSE)))) -> #N/A | E26: =IF(C26="Venta", IFERROR(VLOOKUP(A26, Configuracion!$A:$D, 3, FALSE), 0), 0) -> 0 | F26: =E26*D26 -> 0 | H26: =IF(AND(G26="Gestor", A26<>""), VLOOKUP(A26, Configuracion!$A:$D, 4, FALSE), 0)*Tabla1023[[#This Row],[CANTIDAD]] -> 0 | I26: =IF(OR(A26="", D26=""), "", IF(C26="Entrada", B26+D26, IF(OR(C26="Venta", C26="Salida"), B26-D26, B26)))
B27: =IFERROR(VLOOKUP(A27,miercoles!$A:$I,9,FALSE),IFERROR(VLOOKUP(A27,martes!$A:$I,9,FALSE),IFERROR(VLOOKUP(A27,lunes!$A:$I,9,FALSE),VLOOKUP(A27,Configuracion!$A:$B,2,FALSE)))) -> #N/A | E27: =IF(C27="Venta", IFERROR(VLOOKUP(A27, Configuracion!$A:$D, 3, FALSE), 0), 0) -> 0 | F27: =E27*D27 -> 0 | H27: =IF(AND(G27="Gestor", A27<>""), VLOOKUP(A27, Configuracion!$A:$D, 4, FALSE), 0)*Tabla1023[[#This Row],[CANTIDAD]] -> 0 | I27: =IF(OR(A27="", D27=""), "", IF(C27="Entrada", B27+D27, IF(OR(C27="Venta", C27="Salida"), B27-D27, B27)))
B28: =IFERROR(VLOOKUP(A28,miercoles!$A:$I,9,FALSE),IFERROR(VLOOKUP(A28,martes!$A:$I,9,FALSE),IFERROR(VLOOKUP(A28,lunes!$A:$I,9,FALSE),VLOOKUP(A28,Configuracion!$A:$B,2,FALSE)))) -> #N/A | E28: =IF(C28="Venta", IFERROR(VLOOKUP(A28, Configuracion!$A:$D, 3, FALSE), 0), 0) -> 0 | F28: =E28*D28 -> 0 | H28: =IF(AND(G28="Gestor", A28<>""), VLOOKUP(A28, Configuracion!$A:$D, 4, FALSE), 0)*Tabla1023[[#This Row],[CANTIDAD]] -> 0 | I28: =IF(OR(A28="", D28=""), "", IF(C28="Entrada", B28+D28, IF(OR(C28="Venta", C28="Salida"), B28-D28, B28)))
B29: =IFERROR(VLOOKUP(A29,miercoles!$A:$I,9,FALSE),IFERROR(VLOOKUP(A29,martes!$A:$I,9,FALSE),IFERROR(VLOOKUP(A29,lunes!$A:$I,9,FALSE),VLOOKUP(A29,Configuracion!$A:$B,2,FALSE)))) -> #N/A | E29: =IF(C29="Venta", IFERROR(VLOOKUP(A29, Configuracion!$A:$D, 3, FALSE), 0), 0) -> 0 | F29: =E29*D29 -> 0 | H29: =IF(AND(G29="Gestor", A29<>""), VLOOKUP(A29, Configuracion!$A:$D, 4, FALSE), 0)*Tabla1023[[#This Row],[CANTIDAD]] -> 0 | I29: =IF(OR(A29="", D29=""), "", IF(C29="Entrada", B29+D29, IF(OR(C29="Venta", C29="Salida"), B29-D29, B29)))
B30: =IFERROR(VLOOKUP(A30,miercoles!$A:$I,9,FALSE),IFERROR(VLOOKUP(A30,martes!$A:$I,9,FALSE),IFERROR(VLOOKUP(A30,lunes!$A:$I,9,FALSE),VLOOKUP(A30,Configuracion!$A:$B,2,FALSE)))) -> #N/A | E30: =IF(C30="Venta", IFERROR(VLOOKUP(A30, Configuracion!$A:$D, 3, FALSE), 0), 0) -> 0 | F30: =E30*D30 -> 0 | H30: =IF(AND(G30="Gestor", A30<>""), VLOOKUP(A30, Configuracion!$A:$D, 4, FALSE), 0)*Tabla1023[[#This Row],[CANTIDAD]] -> 0 | I30: =IF(OR(A30="", D30=""), "", IF(C30="Entrada", B30+D30, IF(OR(C30="Venta", C30="Salida"), B30-D30, B30)))
B31: =IFERROR(VLOOKUP(A31,miercoles!$A:$I,9,FALSE),IFERROR(VLOOKUP(A31,martes!$A:$I,9,FALSE),IFERROR(VLOOKUP(A31,lunes!$A:$I,9,FALSE),VLOOKUP(A31,Configuracion!$A:$B,2,FALSE)))) -> #N/A | E31: =IF(C31="Venta", IFERROR(VLOOKUP(A31, Configuracion!$A:$D, 3, FALSE), 0), 0) -> 0 | F31: =E31*D31 -> 0 | H31: =IF(AND(G31="Gestor", A31<>""), VLOOKUP(A31, Configuracion!$A:$D, 4, FALSE), 0)*Tabla1023[[#This Row],[CANTIDAD]] -> 0 | I31: =IF(OR(A31="", D31=""), "", IF(C31="Entrada", B31+D31, IF(OR(C31="Venta", C31="Salida"), B31-D31, B31)))
B32: =IFERROR(VLOOKUP(A32,miercoles!$A:$I,9,FALSE),IFERROR(VLOOKUP(A32,martes!$A:$I,9,FALSE),IFERROR(VLOOKUP(A32,lunes!$A:$I,9,FALSE),VLOOKUP(A32,Configuracion!$A:$B,2,FALSE)))) -> #N/A | E32: =IF(C32="Venta", IFERROR(VLOOKUP(A32, Configuracion!$A:$D, 3, FALSE), 0), 0) -> 0 | F32: =E32*D32 -> 0 | H32: =IF(AND(G32="Gestor", A32<>""), VLOOKUP(A32, Configuracion!$A:$D, 4, FALSE), 0)*Tabla1023[[#This Row],[CANTIDAD]] -> 0 | I32: =IF(OR(A32="", D32=""), "", IF(C32="Entrada", B32+D32, IF(OR(C32="Venta", C32="Salida"), B32-D32, B32)))
B33: =IFERROR(VLOOKUP(A33,miercoles!$A:$I,9,FALSE),IFERROR(VLOOKUP(A33,martes!$A:$I,9,FALSE),IFERROR(VLOOKUP(A33,lunes!$A:$I,9,FALSE),VLOOKUP(A33,Configuracion!$A:$B,2,FALSE)))) -> #N/A | E33: =IF(C33="Venta", IFERROR(VLOOKUP(A33, Configuracion!$A:$D, 3, FALSE), 0), 0) -> 0 | F33: =E33*D33 -> 0 | H33: =IF(AND(G33="Gestor", A33<>""), VLOOKUP(A33, Configuracion!$A:$D, 4, FALSE), 0)*Tabla1023[[#This Row],[CANTIDAD]] -> 0 | I33: =IF(OR(A33="", D33=""), "", IF(C33="Entrada", B33+D33, IF(OR(C33="Venta", C33="Salida"), B33-D33, B33)))
B34: =IFERROR(VLOOKUP(A34,miercoles!$A:$I,9,FALSE),IFERROR(VLOOKUP(A34,martes!$A:$I,9,FALSE),IFERROR(VLOOKUP(A34,lunes!$A:$I,9,FALSE),VLOOKUP(A34,Configuracion!$A:$B,2,FALSE)))) -> #N/A | E34: =IF(C34="Venta", IFERROR(VLOOKUP(A34, Configuracion!$A:$D, 3, FALSE), 0), 0) -> 0 | F34: =E34*D34 -> 0 | H34: =IF(AND(G34="Gestor", A34<>""), VLOOKUP(A34, Configuracion!$A:$D, 4, FALSE), 0)*Tabla1023[[#This Row],[CANTIDAD]] -> 0 | I34: =IF(OR(A34="", D34=""), "", IF(C34="Entrada", B34+D34, IF(OR(C34="Venta", C34="Salida"), B34-D34, B34)))
B35: =IFERROR(VLOOKUP(A35,miercoles!$A:$I,9,FALSE),IFERROR(VLOOKUP(A35,martes!$A:$I,9,FALSE),IFERROR(VLOOKUP(A35,lunes!$A:$I,9,FALSE),VLOOKUP(A35,Configuracion!$A:$B,2,FALSE)))) -> #N/A | E35: =IF(C35="Venta", IFERROR(VLOOKUP(A35, Configuracion!$A:$D, 3, FALSE), 0), 0) -> 0 | F35: =E35*D35 -> 0 | H35: =IF(AND(G35="Gestor", A35<>""), VLOOKUP(A35, Configuracion!$A:$D, 4, FALSE), 0)*Tabla1023[[#This Row],[CANTIDAD]] -> 0 | I35: =IF(OR(A35="", D35=""), "", IF(C35="Entrada", B35+D35, IF(OR(C35="Venta", C35="Salida"), B35-D35, B35)))
B36: =IFERROR(VLOOKUP(A36,miercoles!$A:$I,9,FALSE),IFERROR(VLOOKUP(A36,martes!$A:$I,9,FALSE),IFERROR(VLOOKUP(A36,lunes!$A:$I,9,FALSE),VLOOKUP(A36,Configuracion!$A:$B,2,FALSE)))) -> #N/A | E36: =IF(C36="Venta", IFERROR(VLOOKUP(A36, Configuracion!$A:$D, 3, FALSE), 0), 0) -> 0 | F36: =E36*D36 -> 0 | H36: =IF(AND(G36="Gestor", A36<>""), VLOOKUP(A36, Configuracion!$A:$D, 4, FALSE), 0)*Tabla1023[[#This Row],[CANTIDAD]] -> 0 | I36: =IF(OR(A36="", D36=""), "", IF(C36="Entrada", B36+D36, IF(OR(C36="Venta", C36="Salida"), B36-D36, B36)))
... B189: =IFERROR(VLOOKUP(A189,miercoles!$A:$I,9,FALSE),IFERROR(VLOOKUP(A189,martes!$A:$I,9,FALSE),IFERROR(VLOOKUP(A189,lunes!$A:$I,9,FALSE),VLOOKUP(A189,Configuracion!$A:$B,2,FALSE)))) -> #N/A | E189: =IF(C189="Venta", IFERROR(VLOOKUP(A189, Configuracion!$A:$D, 3, FALSE), 0), 0) -> 0 | F189: =E189*D189 -> 0 | H189: =IF(AND(G189="Gestor", A189<>""), VLOOKUP(A189, Configuracion!$A:$D, 4, FALSE), 0)*Tabla1023[[#This Row],[CANTIDAD]] -> 0 | I189: =IF(OR(A189="", D189=""), "", IF(C189="Entrada", B189+D189, IF(OR(C189="Venta", C189="Salida"), B189-D189, B189)))
B190: =IFERROR(VLOOKUP(A190,miercoles!$A:$I,9,FALSE),IFERROR(VLOOKUP(A190,martes!$A:$I,9,FALSE),IFERROR(VLOOKUP(A190,lunes!$A:$I,9,FALSE),VLOOKUP(A190,Configuracion!$A:$B,2,FALSE)))) -> #N/A | E190: =IF(C190="Venta", IFERROR(VLOOKUP(A190, Configuracion!$A:$D, 3, FALSE), 0), 0) -> 0 | F190: =E190*D190 -> 0 | H190: =IF(AND(G190="Gestor", A190<>""), VLOOKUP(A190, Configuracion!$A:$D, 4, FALSE), 0)*Tabla1023[[#This Row],[CANTIDAD]] -> 0

Sheet viernes
A1: PRODUCTO | B1: STOCK INICIAL | C1: MOVIMIENTO | D1: CANTIDAD | E1: PRECIO VENTA | F1: IMPORTE | G1: TIPO DE VENTA O MOV | H1: COMISION | I1: STOCK FINAL | K1: TIPO CAMBIO | L1: Columna1 | O1: CANTIDAD | P1: USD | Q1: OBSERVACION | R1: USD | S1: MN
B2: =IFERROR(VLOOKUP(A2,jueves!$A:$I,9,FALSE),IFERROR(VLOOKUP(A2,miercoles!$A:$I,9,FALSE),IFERROR(VLOOKUP(A2,martes!$A:$I,9,FALSE),IFERROR(VLOOKUP(A2,lunes!$A:$I,9,FALSE),VLOOKUP(A2,Configuracion!$A:$B,2,FALSE))))) -> #N/A | C2: VENTA | D2: 1 | E2: =IF(C2="Venta", IFERROR(VLOOKUP(A2, Configuracion!$A:$D, 3, FALSE), 0), 0) -> 0 | F2: =E2*D2 -> 0 | G2: TIENDA | H2: =IF(AND(G2="Gestor", A2<>""), VLOOKUP(A2, Configuracion!$A:$D, 4, FALSE), 0)*Tabla1025[[#This Row],[CANTIDAD]] -> 0 | I2: =IF(OR(A2="", D2=""), "", IF(C2="Entrada", B2+D2, IF(OR(C2="Venta", C2="Salida"), B2-D2, B2))) | K2: CUP/USD | L2: 540 | N2: VENTA TOTAL | O2: =Tabla15[[#Totals],[IMPORTE]] -> 9440 | P2: =O2 -> 9440
B3: =IFERROR(VLOOKUP(A3,jueves!$A:$I,9,FALSE),IFERROR(VLOOKUP(A3,miercoles!$A:$I,9,FALSE),IFERROR(VLOOKUP(A3,martes!$A:$I,9,FALSE),IFERROR(VLOOKUP(A3,lunes!$A:$I,9,FALSE),VLOOKUP(A3,Configuracion!$A:$B,2,FALSE))))) -> #N/A | C3: VENTA | D3: 1 | E3: =IF(C3="Venta", IFERROR(VLOOKUP(A3, Configuracion!$A:$D, 3, FALSE), 0), 0) -> 0 | F3: =E3*D3 -> 0 | G3: GESTOR | H3: =IF(AND(G3="Gestor", A3<>""), VLOOKUP(A3, Configuracion!$A:$D, 4, FALSE), 0)*Tabla1025[[#This Row],[CANTIDAD]] -> 0 | I3: =IF(OR(A3="", D3=""), "", IF(C3="Entrada", B3+D3, IF(OR(C3="Venta", C3="Salida"), B3-D3, B3))) | K3: MXN/USD | L3: 20 | N3: USD | O3: 4710 | P3: =O3 -> 4710
B4: =IFERROR(VLOOKUP(A4,jueves!$A:$I,9,FALSE),IFERROR(VLOOKUP(A4,miercoles!$A:$I,9,FALSE),IFERROR(VLOOKUP(A4,martes!$A:$I,9,FALSE),IFERROR(VLOOKUP(A4,lunes!$A:$I,9,FALSE),VLOOKUP(A4,Configuracion!$A:$B,2,FALSE))))) -> #N/A | C4: SALIDA | D4: 1 | E4: =IF(C4="Venta", IFERROR(VLOOKUP(A4, Configuracion!$A:$D, 3, FALSE), 0), 0) -> 0 | F4: =E4*D4 -> 0 | G4: MOV | H4: =IF(AND(G4="Gestor", A4<>""), VLOOKUP(A4, Configuracion!$A:$D, 4, FALSE), 0)*Tabla1025[[#This Row],[CANTIDAD]] -> 0 | I4: =IF(OR(A4="", D4=""), "", IF(C4="Entrada", B4+D4, IF(OR(C4="Venta", C4="Salida"), B4-D4, B4))) | N4: ZELLE | O4: 380 | P4: =O4 -> 380
B5: =IFERROR(VLOOKUP(A5,jueves!$A:$I,9,FALSE),IFERROR(VLOOKUP(A5,miercoles!$A:$I,9,FALSE),IFERROR(VLOOKUP(A5,martes!$A:$I,9,FALSE),IFERROR(VLOOKUP(A5,lunes!$A:$I,9,FALSE),VLOOKUP(A5,Configuracion!$A:$B,2,FALSE))))) -> #N/A | E5: =IF(C5="Venta", IFERROR(VLOOKUP(A5, Configuracion!$A:$D, 3, FALSE), 0), 0) -> 0 | F5: =E5*D5 -> 0 | H5: =IF(AND(G5="Gestor", A5<>""), VLOOKUP(A5, Configuracion!$A:$D, 4, FALSE), 0)*Tabla1025[[#This Row],[CANTIDAD]] -> 0 | I5: =IF(OR(A5="", D5=""), "", IF(C5="Entrada", B5+D5, IF(OR(C5="Venta", C5="Salida"), B5-D5, B5))) | N5: MXN | P5: =O5/L3 -> 0
B6: =IFERROR(VLOOKUP(A6,jueves!$A:$I,9,FALSE),IFERROR(VLOOKUP(A6,miercoles!$A:$I,9,FALSE),IFERROR(VLOOKUP(A6,martes!$A:$I,9,FALSE),IFERROR(VLOOKUP(A6,lunes!$A:$I,9,FALSE),VLOOKUP(A6,Configuracion!$A:$B,2,FALSE))))) -> #N/A | E6: =IF(C6="Venta", IFERROR(VLOOKUP(A6, Configuracion!$A:$D, 3, FALSE), 0), 0) -> 0 | F6: =E6*D6 -> 0 | H6: =IF(AND(G6="Gestor", A6<>""), VLOOKUP(A6, Configuracion!$A:$D, 4, FALSE), 0)*Tabla1025[[#This Row],[CANTIDAD]] -> 0 | I6: =IF(OR(A6="", D6=""), "", IF(C6="Entrada", B6+D6, IF(OR(C6="Venta", C6="Salida"), B6-D6, B6))) | N6: CUP EFECTIVO | O6: 1252800 | P6: =O6/L2 -> 2320
B7: =IFERROR(VLOOKUP(A7,jueves!$A:$I,9,FALSE),IFERROR(VLOOKUP(A7,miercoles!$A:$I,9,FALSE),IFERROR(VLOOKUP(A7,martes!$A:$I,9,FALSE),IFERROR(VLOOKUP(A7,lunes!$A:$I,9,FALSE),VLOOKUP(A7,Configuracion!$A:$B,2,FALSE))))) -> #N/A | E7: =IF(C7="Venta", IFERROR(VLOOKUP(A7, Configuracion!$A:$D, 3, FALSE), 0), 0) -> 0 | F7: =E7*D7 -> 0 | H7: =IF(AND(G7="Gestor", A7<>""), VLOOKUP(A7, Configuracion!$A:$D, 4, FALSE), 0)*Tabla1025[[#This Row],[CANTIDAD]] -> 0 | I7: =IF(OR(A7="", D7=""), "", IF(C7="Entrada", B7+D7, IF(OR(C7="Venta", C7="Salida"), B7-D7, B7))) | N7: CUP TRANSF | P7: =O7/L2 -> 0
B8: =IFERROR(VLOOKUP(A8,jueves!$A:$I,9,FALSE),IFERROR(VLOOKUP(A8,miercoles!$A:$I,9,FALSE),IFERROR(VLOOKUP(A8,martes!$A:$I,9,FALSE),IFERROR(VLOOKUP(A8,lunes!$A:$I,9,FALSE),VLOOKUP(A8,Configuracion!$A:$B,2,FALSE))))) -> #N/A | E8: =IF(C8="Venta", IFERROR(VLOOKUP(A8, Configuracion!$A:$D, 3, FALSE), 0), 0) -> 0 | F8: =E8*D8 -> 0 | H8: =IF(AND(G8="Gestor", A8<>""), VLOOKUP(A8, Configuracion!$A:$D, 4, FALSE), 0)*Tabla1025[[#This Row],[CANTIDAD]] -> 0 | I8: =IF(OR(A8="", D8=""), "", IF(C8="Entrada", B8+D8, IF(OR(C8="Venta", C8="Salida"), B8-D8, B8))) | N8: EUROPA | P8: =O8 -> 0
B9: =IFERROR(VLOOKUP(A9,jueves!$A:$I,9,FALSE),IFERROR(VLOOKUP(A9,miercoles!$A:$I,9,FALSE),IFERROR(VLOOKUP(A9,martes!$A:$I,9,FALSE),IFERROR(VLOOKUP(A9,lunes!$A:$I,9,FALSE),VLOOKUP(A9,Configuracion!$A:$B,2,FALSE))))) -> #N/A | E9: =IF(C9="Venta", IFERROR(VLOOKUP(A9, Configuracion!$A:$D, 3, FALSE), 0), 0) -> 0 | F9: =E9*D9 -> 0 | H9: =IF(AND(G9="Gestor", A9<>""), VLOOKUP(A9, Configuracion!$A:$D, 4, FALSE), 0)*Tabla1025[[#This Row],[CANTIDAD]] -> 0 | I9: =IF(OR(A9="", D9=""), "", IF(C9="Entrada", B9+D9, IF(OR(C9="Venta", C9="Salida"), B9-D9, B9))) | N9: TOTAL | P9: =P3+P4+P5+P6+P7+P8 -> 7410
B10: =IFERROR(VLOOKUP(A10,jueves!$A:$I,9,FALSE),IFERROR(VLOOKUP(A10,miercoles!$A:$I,9,FALSE),IFERROR(VLOOKUP(A10,martes!$A:$I,9,FALSE),IFERROR(VLOOKUP(A10,lunes!$A:$I,9,FALSE),VLOOKUP(A10,Configuracion!$A:$B,2,FALSE))))) -> #N/A | E10: =IF(C10="Venta", IFERROR(VLOOKUP(A10, Configuracion!$A:$D, 3, FALSE), 0), 0) -> 0 | F10: =E10*D10 -> 0 | H10: =IF(AND(G10="Gestor", A10<>""), VLOOKUP(A10, Configuracion!$A:$D, 4, FALSE), 0)*Tabla1025[[#This Row],[CANTIDAD]] -> 0 | I10: =IF(OR(A10="", D10=""), "", IF(C10="Entrada", B10+D10, IF(OR(C10="Venta", C10="Salida"), B10-D10, B10))) | N10: ENTRADA DINERO | P10: =P12+P11 -> 20
B11: =IFERROR(VLOOKUP(A11,jueves!$A:$I,9,FALSE),IFERROR(VLOOKUP(A11,miercoles!$A:$I,9,FALSE),IFERROR(VLOOKUP(A11,martes!$A:$I,9,FALSE),IFERROR(VLOOKUP(A11,lunes!$A:$I,9,FALSE),VLOOKUP(A11,Configuracion!$A:$B,2,FALSE))))) -> #N/A | E11: =IF(C11="Venta", IFERROR(VLOOKUP(A11, Configuracion!$A:$D, 3, FALSE), 0), 0) -> 0 | F11: =E11*D11 -> 0 | H11: =IF(AND(G11="Gestor", A11<>""), VLOOKUP(A11, Configuracion!$A:$D, 4, FALSE), 0)*Tabla1025[[#This Row],[CANTIDAD]] -> 0 | I11: =IF(OR(A11="", D11=""), "", IF(C11="Entrada", B11+D11, IF(OR(C11="Venta", C11="Salida"), B11-D11, B11))) | N11: CUP | P11: =O11/L2 -> 0
B12: =IFERROR(VLOOKUP(A12,jueves!$A:$I,9,FALSE),IFERROR(VLOOKUP(A12,miercoles!$A:$I,9,FALSE),IFERROR(VLOOKUP(A12,martes!$A:$I,9,FALSE),IFERROR(VLOOKUP(A12,lunes!$A:$I,9,FALSE),VLOOKUP(A12,Configuracion!$A:$B,2,FALSE))))) -> #N/A | E12: =IF(C12="Venta", IFERROR(VLOOKUP(A12, Configuracion!$A:$D, 3, FALSE), 0), 0) -> 0 | F12: =E12*D12 -> 0 | H12: =IF(AND(G12="Gestor", A12<>""), VLOOKUP(A12, Configuracion!$A:$D, 4, FALSE), 0)*Tabla1025[[#This Row],[CANTIDAD]] -> 0 | I12: =IF(OR(A12="", D12=""), "", IF(C12="Entrada", B12+D12, IF(OR(C12="Venta", C12="Salida"), B12-D12, B12))) | N12: USD | O12: 20 | P12: =O12 -> 20 | Q12: ZELLE
B13: =IFERROR(VLOOKUP(A13,jueves!$A:$I,9,FALSE),IFERROR(VLOOKUP(A13,miercoles!$A:$I,9,FALSE),IFERROR(VLOOKUP(A13,martes!$A:$I,9,FALSE),IFERROR(VLOOKUP(A13,lunes!$A:$I,9,FALSE),VLOOKUP(A13,Configuracion!$A:$B,2,FALSE))))) -> #N/A | E13: =IF(C13="Venta", IFERROR(VLOOKUP(A13, Configuracion!$A:$D, 3, FALSE), 0), 0) -> 0 | F13: =E13*D13 -> 0 | H13: =IF(AND(G13="Gestor", A13<>""), VLOOKUP(A13, Configuracion!$A:$D, 4, FALSE), 0)*Tabla1025[[#This Row],[CANTIDAD]] -> 0 | I13: =IF(OR(A13="", D13=""), "", IF(C13="Entrada", B13+D13, IF(OR(C13="Venta", C13="Salida"), B13-D13, B13))) | N13: EXTRACCION | P13: =P15+P14 -> 2050
B14: =IFERROR(VLOOKUP(A14,jueves!$A:$I,9,FALSE),IFERROR(VLOOKUP(A14,miercoles!$A:$I,9,FALSE),IFERROR(VLOOKUP(A14,martes!$A:$I,9,FALSE),IFERROR(VLOOKUP(A14,lunes!$A:$I,9,FALSE),VLOOKUP(A14,Configuracion!$A:$B,2,FALSE))))) -> #N/A | E14: =IF(C14="Venta", IFERROR(VLOOKUP(A14, Configuracion!$A:$D, 3, FALSE), 0), 0) -> 0 | F14: =E14*D14 -> 0 | H14: =IF(AND(G14="Gestor", A14<>""), VLOOKUP(A14, Configuracion!$A:$D, 4, FALSE), 0)*Tabla1025[[#This Row],[CANTIDAD]] -> 0 | I14: =IF(OR(A14="", D14=""), "", IF(C14="Entrada", B14+D14, IF(OR(C14="Venta", C14="Salida"), B14-D14, B14))) | N14: CUP | P14: =O14/L2 -> 0
B15: =IFERROR(VLOOKUP(A15,jueves!$A:$I,9,FALSE),IFERROR(VLOOKUP(A15,miercoles!$A:$I,9,FALSE),IFERROR(VLOOKUP(A15,martes!$A:$I,9,FALSE),IFERROR(VLOOKUP(A15,lunes!$A:$I,9,FALSE),VLOOKUP(A15,Configuracion!$A:$B,2,FALSE))))) -> #N/A | E15: =IF(C15="Venta", IFERROR(VLOOKUP(A15, Configuracion!$A:$D, 3, FALSE), 0), 0) -> 0 | F15: =E15*D15 -> 0 | H15: =IF(AND(G15="Gestor", A15<>""), VLOOKUP(A15, Configuracion!$A:$D, 4, FALSE), 0)*Tabla1025[[#This Row],[CANTIDAD]] -> 0 | I15: =IF(OR(A15="", D15=""), "", IF(C15="Entrada", B15+D15, IF(OR(C15="Venta", C15="Salida"), B15-D15, B15))) | N15: USD | O15: 2050 | P15: 2050
B16: =IFERROR(VLOOKUP(A16,jueves!$A:$I,9,FALSE),IFERROR(VLOOKUP(A16,miercoles!$A:$I,9,FALSE),IFERROR(VLOOKUP(A16,martes!$A:$I,9,FALSE),IFERROR(VLOOKUP(A16,lunes!$A:$I,9,FALSE),VLOOKUP(A16,Configuracion!$A:$B,2,FALSE))))) -> #N/A | E16: =IF(C16="Venta", IFERROR(VLOOKUP(A16, Configuracion!$A:$D, 3, FALSE), 0), 0) -> 0 | F16: =E16*D16 -> 0 | H16: =IF(AND(G16="Gestor", A16<>""), VLOOKUP(A16, Configuracion!$A:$D, 4, FALSE), 0)*Tabla1025[[#This Row],[CANTIDAD]] -> 0 | I16: =IF(OR(A16="", D16=""), "", IF(C16="Entrada", B16+D16, IF(OR(C16="Venta", C16="Salida"), B16-D16, B16))) | N16: TOTAL GENERAL | P16: =P9+P13-P10 -> 9440 | R16: =P2-P16 -> 0 | S16: =R16*L2 -> 0
B17: =IFERROR(VLOOKUP(A17,jueves!$A:$I,9,FALSE),IFERROR(VLOOKUP(A17,miercoles!$A:$I,9,FALSE),IFERROR(VLOOKUP(A17,martes!$A:$I,9,FALSE),IFERROR(VLOOKUP(A17,lunes!$A:$I,9,FALSE),VLOOKUP(A17,Configuracion!$A:$B,2,FALSE))))) -> #N/A | E17: =IF(C17="Venta", IFERROR(VLOOKUP(A17, Configuracion!$A:$D, 3, FALSE), 0), 0) -> 0 | F17: =E17*D17 -> 0 | H17: =IF(AND(G17="Gestor", A17<>""), VLOOKUP(A17, Configuracion!$A:$D, 4, FALSE), 0)*Tabla1025[[#This Row],[CANTIDAD]] -> 0 | I17: =IF(OR(A17="", D17=""), "", IF(C17="Entrada", B17+D17, IF(OR(C17="Venta", C17="Salida"), B17-D17, B17)))
B18: =IFERROR(VLOOKUP(A18,jueves!$A:$I,9,FALSE),IFERROR(VLOOKUP(A18,miercoles!$A:$I,9,FALSE),IFERROR(VLOOKUP(A18,martes!$A:$I,9,FALSE),IFERROR(VLOOKUP(A18,lunes!$A:$I,9,FALSE),VLOOKUP(A18,Configuracion!$A:$B,2,FALSE))))) -> #N/A | E18: =IF(C18="Venta", IFERROR(VLOOKUP(A18, Configuracion!$A:$D, 3, FALSE), 0), 0) -> 0 | F18: =E18*D18 -> 0 | H18: =IF(AND(G18="Gestor", A18<>""), VLOOKUP(A18, Configuracion!$A:$D, 4, FALSE), 0)*Tabla1025[[#This Row],[CANTIDAD]] -> 0 | I18: =IF(OR(A18="", D18=""), "", IF(C18="Entrada", B18+D18, IF(OR(C18="Venta", C18="Salida"), B18-D18, B18))) | O18: CUP | P18: USD
B19: =IFERROR(VLOOKUP(A19,jueves!$A:$I,9,FALSE),IFERROR(VLOOKUP(A19,miercoles!$A:$I,9,FALSE),IFERROR(VLOOKUP(A19,martes!$A:$I,9,FALSE),IFERROR(VLOOKUP(A19,lunes!$A:$I,9,FALSE),VLOOKUP(A19,Configuracion!$A:$B,2,FALSE))))) -> #N/A | E19: =IF(C19="Venta", IFERROR(VLOOKUP(A19, Configuracion!$A:$D, 3, FALSE), 0), 0) -> 0 | F19: =E19*D19 -> 0 | H19: =IF(AND(G19="Gestor", A19<>""), VLOOKUP(A19, Configuracion!$A:$D, 4, FALSE), 0)*Tabla1025[[#This Row],[CANTIDAD]] -> 0 | I19: =IF(OR(A19="", D19=""), "", IF(C19="Entrada", B19+D19, IF(OR(C19="Venta", C19="Salida"), B19-D19, B19))) | N19: FONDO INICIAL | O19: 100000 | P19: 150
B20: =IFERROR(VLOOKUP(A20,jueves!$A:$I,9,FALSE),IFERROR(VLOOKUP(A20,miercoles!$A:$I,9,FALSE),IFERROR(VLOOKUP(A20,martes!$A:$I,9,FALSE),IFERROR(VLOOKUP(A20,lunes!$A:$I,9,FALSE),VLOOKUP(A20,Configuracion!$A:$B,2,FALSE))))) -> #N/A | E20: =IF(C20="Venta", IFERROR(VLOOKUP(A20, Configuracion!$A:$D, 3, FALSE), 0), 0) -> 0 | F20: =E20*D20 -> 0 | H20: =IF(AND(G20="Gestor", A20<>""), VLOOKUP(A20, Configuracion!$A:$D, 4, FALSE), 0)*Tabla1025[[#This Row],[CANTIDAD]] -> 0 | I20: =IF(OR(A20="", D20=""), "", IF(C20="Entrada", B20+D20, IF(OR(C20="Venta", C20="Salida"), B20-D20, B20))) | N20: CAMBIO
B21: =IFERROR(VLOOKUP(A21,jueves!$A:$I,9,FALSE),IFERROR(VLOOKUP(A21,miercoles!$A:$I,9,FALSE),IFERROR(VLOOKUP(A21,martes!$A:$I,9,FALSE),IFERROR(VLOOKUP(A21,lunes!$A:$I,9,FALSE),VLOOKUP(A21,Configuracion!$A:$B,2,FALSE))))) -> #N/A | E21: =IF(C21="Venta", IFERROR(VLOOKUP(A21, Configuracion!$A:$D, 3, FALSE), 0), 0) -> 0 | F21: =E21*D21 -> 0 | H21: =IF(AND(G21="Gestor", A21<>""), VLOOKUP(A21, Configuracion!$A:$D, 4, FALSE), 0)*Tabla1025[[#This Row],[CANTIDAD]] -> 0 | I21: =IF(OR(A21="", D21=""), "", IF(C21="Entrada", B21+D21, IF(OR(C21="Venta", C21="Salida"), B21-D21, B21))) | N21: DOMICILIO
B22: =IFERROR(VLOOKUP(A22,jueves!$A:$I,9,FALSE),IFERROR(VLOOKUP(A22,miercoles!$A:$I,9,FALSE),IFERROR(VLOOKUP(A22,martes!$A:$I,9,FALSE),IFERROR(VLOOKUP(A22,lunes!$A:$I,9,FALSE),VLOOKUP(A22,Configuracion!$A:$B,2,FALSE))))) -> #N/A | E22: =IF(C22="Venta", IFERROR(VLOOKUP(A22, Configuracion!$A:$D, 3, FALSE), 0), 0) -> 0 | F22: =E22*D22 -> 0 | H22: =IF(AND(G22="Gestor", A22<>""), VLOOKUP(A22, Configuracion!$A:$D, 4, FALSE), 0)*Tabla1025[[#This Row],[CANTIDAD]] -> 0 | I22: =IF(OR(A22="", D22=""), "", IF(C22="Entrada", B22+D22, IF(OR(C22="Venta", C22="Salida"), B22-D22, B22))) | N22: OTROS GASTOS
B23: =IFERROR(VLOOKUP(A23,jueves!$A:$I,9,FALSE),IFERROR(VLOOKUP(A23,miercoles!$A:$I,9,FALSE),IFERROR(VLOOKUP(A23,martes!$A:$I,9,FALSE),IFERROR(VLOOKUP(A23,lunes!$A:$I,9,FALSE),VLOOKUP(A23,Configuracion!$A:$B,2,FALSE))))) -> #N/A | E23: =IF(C23="Venta", IFERROR(VLOOKUP(A23, Configuracion!$A:$D, 3, FALSE), 0), 0) -> 0 | F23: =E23*D23 -> 0 | H23: =IF(AND(G23="Gestor", A23<>""), VLOOKUP(A23, Configuracion!$A:$D, 4, FALSE), 0)*Tabla1025[[#This Row],[CANTIDAD]] -> 0 | I23: =IF(OR(A23="", D23=""), "", IF(C23="Entrada", B23+D23, IF(OR(C23="Venta", C23="Salida"), B23-D23, B23))) | N23: COMISIONES
B24: =IFERROR(VLOOKUP(A24,jueves!$A:$I,9,FALSE),IFERROR(VLOOKUP(A24,miercoles!$A:$I,9,FALSE),IFERROR(VLOOKUP(A24,martes!$A:$I,9,FALSE),IFERROR(VLOOKUP(A24,lunes!$A:$I,9,FALSE),VLOOKUP(A24,Configuracion!$A:$B,2,FALSE))))) -> #N/A | E24: =IF(C24="Venta", IFERROR(VLOOKUP(A24, Configuracion!$A:$D, 3, FALSE), 0), 0) -> 0 | F24: =E24*D24 -> 0 | H24: =IF(AND(G24="Gestor", A24<>""), VLOOKUP(A24, Configuracion!$A:$D, 4, FALSE), 0)*Tabla1025[[#This Row],[CANTIDAD]] -> 0 | I24: =IF(OR(A24="", D24=""), "", IF(C24="Entrada", B24+D24, IF(OR(C24="Venta", C24="Salida"), B24-D24, B24))) | N24: FONDO FINAL | O24: =O19-O21-O22-O23-O20 -> 100000 | P24: =P19-P21-P22-P23-P20 -> 150
B25: =IFERROR(VLOOKUP(A25,jueves!$A:$I,9,FALSE),IFERROR(VLOOKUP(A25,miercoles!$A:$I,9,FALSE),IFERROR(VLOOKUP(A25,martes!$A:$I,9,FALSE),IFERROR(VLOOKUP(A25,lunes!$A:$I,9,FALSE),VLOOKUP(A25,Configuracion!$A:$B,2,FALSE))))) -> #N/A | E25: =IF(C25="Venta", IFERROR(VLOOKUP(A25, Configuracion!$A:$D, 3, FALSE), 0), 0) -> 0 | F25: =E25*D25 -> 0 | H25: =IF(AND(G25="Gestor", A25<>""), VLOOKUP(A25, Configuracion!$A:$D, 4, FALSE), 0)*Tabla1025[[#This Row],[CANTIDAD]] -> 0 | I25: =IF(OR(A25="", D25=""), "", IF(C25="Entrada", B25+D25, IF(OR(C25="Venta", C25="Salida"), B25-D25, B25)))
B26: =IFERROR(VLOOKUP(A26,jueves!$A:$I,9,FALSE),IFERROR(VLOOKUP(A26,miercoles!$A:$I,9,FALSE),IFERROR(VLOOKUP(A26,martes!$A:$I,9,FALSE),IFERROR(VLOOKUP(A26,lunes!$A:$I,9,FALSE),VLOOKUP(A26,Configuracion!$A:$B,2,FALSE))))) -> #N/A | E26: =IF(C26="Venta", IFERROR(VLOOKUP(A26, Configuracion!$A:$D, 3, FALSE), 0), 0) -> 0 | F26: =E26*D26 -> 0 | H26: =IF(AND(G26="Gestor", A26<>""), VLOOKUP(A26, Configuracion!$A:$D, 4, FALSE), 0)*Tabla1025[[#This Row],[CANTIDAD]] -> 0 | I26: =IF(OR(A26="", D26=""), "", IF(C26="Entrada", B26+D26, IF(OR(C26="Venta", C26="Salida"), B26-D26, B26)))
B27: =IFERROR(VLOOKUP(A27,jueves!$A:$I,9,FALSE),IFERROR(VLOOKUP(A27,miercoles!$A:$I,9,FALSE),IFERROR(VLOOKUP(A27,martes!$A:$I,9,FALSE),IFERROR(VLOOKUP(A27,lunes!$A:$I,9,FALSE),VLOOKUP(A27,Configuracion!$A:$B,2,FALSE))))) -> #N/A | E27: =IF(C27="Venta", IFERROR(VLOOKUP(A27, Configuracion!$A:$D, 3, FALSE), 0), 0) -> 0 | F27: =E27*D27 -> 0 | H27: =IF(AND(G27="Gestor", A27<>""), VLOOKUP(A27, Configuracion!$A:$D, 4, FALSE), 0)*Tabla1025[[#This Row],[CANTIDAD]] -> 0 | I27: =IF(OR(A27="", D27=""), "", IF(C27="Entrada", B27+D27, IF(OR(C27="Venta", C27="Salida"), B27-D27, B27)))
B28: =IFERROR(VLOOKUP(A28,jueves!$A:$I,9,FALSE),IFERROR(VLOOKUP(A28,miercoles!$A:$I,9,FALSE),IFERROR(VLOOKUP(A28,martes!$A:$I,9,FALSE),IFERROR(VLOOKUP(A28,lunes!$A:$I,9,FALSE),VLOOKUP(A28,Configuracion!$A:$B,2,FALSE))))) -> #N/A | E28: =IF(C28="Venta", IFERROR(VLOOKUP(A28, Configuracion!$A:$D, 3, FALSE), 0), 0) -> 0 | F28: =E28*D28 -> 0 | H28: =IF(AND(G28="Gestor", A28<>""), VLOOKUP(A28, Configuracion!$A:$D, 4, FALSE), 0)*Tabla1025[[#This Row],[CANTIDAD]] -> 0 | I28: =IF(OR(A28="", D28=""), "", IF(C28="Entrada", B28+D28, IF(OR(C28="Venta", C28="Salida"), B28-D28, B28)))
B29: =IFERROR(VLOOKUP(A29,jueves!$A:$I,9,FALSE),IFERROR(VLOOKUP(A29,miercoles!$A:$I,9,FALSE),IFERROR(VLOOKUP(A29,martes!$A:$I,9,FALSE),IFERROR(VLOOKUP(A29,lunes!$A:$I,9,FALSE),VLOOKUP(A29,Configuracion!$A:$B,2,FALSE))))) -> #N/A | E29: =IF(C29="Venta", IFERROR(VLOOKUP(A29, Configuracion!$A:$D, 3, FALSE), 0), 0) -> 0 | F29: =E29*D29 -> 0 | H29: =IF(AND(G29="Gestor", A29<>""), VLOOKUP(A29, Configuracion!$A:$D, 4, FALSE), 0)*Tabla1025[[#This Row],[CANTIDAD]] -> 0 | I29: =IF(OR(A29="", D29=""), "", IF(C29="Entrada", B29+D29, IF(OR(C29="Venta", C29="Salida"), B29-D29, B29)))
B30: =IFERROR(VLOOKUP(A30,jueves!$A:$I,9,FALSE),IFERROR(VLOOKUP(A30,miercoles!$A:$I,9,FALSE),IFERROR(VLOOKUP(A30,martes!$A:$I,9,FALSE),IFERROR(VLOOKUP(A30,lunes!$A:$I,9,FALSE),VLOOKUP(A30,Configuracion!$A:$B,2,FALSE))))) -> #N/A | E30: =IF(C30="Venta", IFERROR(VLOOKUP(A30, Configuracion!$A:$D, 3, FALSE), 0), 0) -> 0 | F30: =E30*D30 -> 0 | H30: =IF(AND(G30="Gestor", A30<>""), VLOOKUP(A30, Configuracion!$A:$D, 4, FALSE), 0)*Tabla1025[[#This Row],[CANTIDAD]] -> 0 | I30: =IF(OR(A30="", D30=""), "", IF(C30="Entrada", B30+D30, IF(OR(C30="Venta", C30="Salida"), B30-D30, B30)))
B31: =IFERROR(VLOOKUP(A31,jueves!$A:$I,9,FALSE),IFERROR(VLOOKUP(A31,miercoles!$A:$I,9,FALSE),IFERROR(VLOOKUP(A31,martes!$A:$I,9,FALSE),IFERROR(VLOOKUP(A31,lunes!$A:$I,9,FALSE),VLOOKUP(A31,Configuracion!$A:$B,2,FALSE))))) -> #N/A | E31: =IF(C31="Venta", IFERROR(VLOOKUP(A31, Configuracion!$A:$D, 3, FALSE), 0), 0) -> 0 | F31: =E31*D31 -> 0 | H31: =IF(AND(G31="Gestor", A31<>""), VLOOKUP(A31, Configuracion!$A:$D, 4, FALSE), 0)*Tabla1025[[#This Row],[CANTIDAD]] -> 0 | I31: =IF(OR(A31="", D31=""), "", IF(C31="Entrada", B31+D31, IF(OR(C31="Venta", C31="Salida"), B31-D31, B31)))
B32: =IFERROR(VLOOKUP(A32,jueves!$A:$I,9,FALSE),IFERROR(VLOOKUP(A32,miercoles!$A:$I,9,FALSE),IFERROR(VLOOKUP(A32,martes!$A:$I,9,FALSE),IFERROR(VLOOKUP(A32,lunes!$A:$I,9,FALSE),VLOOKUP(A32,Configuracion!$A:$B,2,FALSE))))) -> #N/A | E32: =IF(C32="Venta", IFERROR(VLOOKUP(A32, Configuracion!$A:$D, 3, FALSE), 0), 0) -> 0 | F32: =E32*D32 -> 0 | H32: =IF(AND(G32="Gestor", A32<>""), VLOOKUP(A32, Configuracion!$A:$D, 4, FALSE), 0)*Tabla1025[[#This Row],[CANTIDAD]] -> 0 | I32: =IF(OR(A32="", D32=""), "", IF(C32="Entrada", B32+D32, IF(OR(C32="Venta", C32="Salida"), B32-D32, B32)))
B33: =IFERROR(VLOOKUP(A33,jueves!$A:$I,9,FALSE),IFERROR(VLOOKUP(A33,miercoles!$A:$I,9,FALSE),IFERROR(VLOOKUP(A33,martes!$A:$I,9,FALSE),IFERROR(VLOOKUP(A33,lunes!$A:$I,9,FALSE),VLOOKUP(A33,Configuracion!$A:$B,2,FALSE))))) -> #N/A | E33: =IF(C33="Venta", IFERROR(VLOOKUP(A33, Configuracion!$A:$D, 3, FALSE), 0), 0) -> 0 | F33: =E33*D33 -> 0 | H33: =IF(AND(G33="Gestor", A33<>""), VLOOKUP(A33, Configuracion!$A:$D, 4, FALSE), 0)*Tabla1025[[#This Row],[CANTIDAD]] -> 0 | I33: =IF(OR(A33="", D33=""), "", IF(C33="Entrada", B33+D33, IF(OR(C33="Venta", C33="Salida"), B33-D33, B33)))
B34: =IFERROR(VLOOKUP(A34,jueves!$A:$I,9,FALSE),IFERROR(VLOOKUP(A34,miercoles!$A:$I,9,FALSE),IFERROR(VLOOKUP(A34,martes!$A:$I,9,FALSE),IFERROR(VLOOKUP(A34,lunes!$A:$I,9,FALSE),VLOOKUP(A34,Configuracion!$A:$B,2,FALSE))))) -> #N/A | E34: =IF(C34="Venta", IFERROR(VLOOKUP(A34, Configuracion!$A:$D, 3, FALSE), 0), 0) -> 0 | F34: =E34*D34 -> 0 | H34: =IF(AND(G34="Gestor", A34<>""), VLOOKUP(A34, Configuracion!$A:$D, 4, FALSE), 0)*Tabla1025[[#This Row],[CANTIDAD]] -> 0 | I34: =IF(OR(A34="", D34=""), "", IF(C34="Entrada", B34+D34, IF(OR(C34="Venta", C34="Salida"), B34-D34, B34)))
B35: =IFERROR(VLOOKUP(A35,jueves!$A:$I,9,FALSE),IFERROR(VLOOKUP(A35,miercoles!$A:$I,9,FALSE),IFERROR(VLOOKUP(A35,martes!$A:$I,9,FALSE),IFERROR(VLOOKUP(A35,lunes!$A:$I,9,FALSE),VLOOKUP(A35,Configuracion!$A:$B,2,FALSE))))) -> #N/A | E35: =IF(C35="Venta", IFERROR(VLOOKUP(A35, Configuracion!$A:$D, 3, FALSE), 0), 0) -> 0 | F35: =E35*D35 -> 0 | H35: =IF(AND(G35="Gestor", A35<>""), VLOOKUP(A35, Configuracion!$A:$D, 4, FALSE), 0)*Tabla1025[[#This Row],[CANTIDAD]] -> 0 | I35: =IF(OR(A35="", D35=""), "", IF(C35="Entrada", B35+D35, IF(OR(C35="Venta", C35="Salida"), B35-D35, B35)))
B36: =IFERROR(VLOOKUP(A36,jueves!$A:$I,9,FALSE),IFERROR(VLOOKUP(A36,miercoles!$A:$I,9,FALSE),IFERROR(VLOOKUP(A36,martes!$A:$I,9,FALSE),IFERROR(VLOOKUP(A36,lunes!$A:$I,9,FALSE),VLOOKUP(A36,Configuracion!$A:$B,2,FALSE))))) -> #N/A | E36: =IF(C36="Venta", IFERROR(VLOOKUP(A36, Configuracion!$A:$D, 3, FALSE), 0), 0) -> 0 | F36: =E36*D36 -> 0 | H36: =IF(AND(G36="Gestor", A36<>""), VLOOKUP(A36, Configuracion!$A:$D, 4, FALSE), 0)*Tabla1025[[#This Row],[CANTIDAD]] -> 0 | I36: =IF(OR(A36="", D36=""), "", IF(C36="Entrada", B36+D36, IF(OR(C36="Venta", C36="Salida"), B36-D36, B36)))
... B189: =IFERROR(VLOOKUP(A189,jueves!$A:$I,9,FALSE),IFERROR(VLOOKUP(A189,miercoles!$A:$I,9,FALSE),IFERROR(VLOOKUP(A189,martes!$A:$I,9,FALSE),IFERROR(VLOOKUP(A189,lunes!$A:$I,9,FALSE),VLOOKUP(A189,Configuracion!$A:$B,2,FALSE))))) -> #N/A | E189: =IF(C189="Venta", IFERROR(VLOOKUP(A189, Configuracion!$A:$D, 3, FALSE), 0), 0) -> 0 | F189: =E189*D189 -> 0 | H189: =IF(AND(G189="Gestor", A189<>""), VLOOKUP(A189, Configuracion!$A:$D, 4, FALSE), 0)*Tabla1025[[#This Row],[CANTIDAD]] -> 0 | I189: =IF(OR(A189="", D189=""), "", IF(C189="Entrada", B189+D189, IF(OR(C189="Venta", C189="Salida"), B189-D189, B189)))
B190: =IFERROR(VLOOKUP(A190,jueves!$A:$I,9,FALSE),IFERROR(VLOOKUP(A190,miercoles!$A:$I,9,FALSE),IFERROR(VLOOKUP(A190,martes!$A:$I,9,FALSE),IFERROR(VLOOKUP(A190,lunes!$A:$I,9,FALSE),VLOOKUP(A190,Configuracion!$A:$B,2,FALSE))))) -> #N/A | E190: =IF(C190="Venta", IFERROR(VLOOKUP(A190, Configuracion!$A:$D, 3, FALSE), 0), 0) -> 0 | F190: =E190*D190 -> 0 | H190: =IF(AND(G190="Gestor", A190<>""), VLOOKUP(A190, Configuracion!$A:$D, 4, FALSE), 0)*Tabla1025[[#This Row],[CANTIDAD]] -> 0

Sheet sabado
A1: PRODUCTO | B1: STOCK INICIAL | C1: MOVIMIENTO | D1: CANTIDAD | E1: PRECIO VENTA | F1: IMPORTE | G1: TIPO DE VENTA O MOV | H1: COMISION | I1: STOCK FINAL | K1: TIPO CAMBIO | L1: Columna1 | O1: CANTIDAD | P1: USD | Q1: OBSERVACION | R1: USD | S1: MN
B2: =IFERROR(VLOOKUP(A2, viernes!$A:$I, 9, FALSE), IFERROR(VLOOKUP(A2, jueves!$A:$I, 9, FALSE), IFERROR(VLOOKUP(A2, miercoles!$A:$I, 9, FALSE), IFERROR(VLOOKUP(A2, martes!$A:$I, 9, FALSE), IFERROR(VLOOKUP(A2, lunes!$A:$I, 9, FALSE), VLOOKUP(A2, Configuracion!$A:$B, 2, FALSE)))))) -> #N/A | C2: VENTA | D2: 1 | E2: =IF(C2="Venta", IFERROR(VLOOKUP(A2, Configuracion!$A:$D, 3, FALSE), 0), 0) -> 0 | F2: =E2*D2 -> 0 | G2: TIENDA | H2: =IF(AND(G2="Gestor", A2<>""), VLOOKUP(A2, Configuracion!$A:$D, 4, FALSE), 0)*Tabla1027[[#This Row],[CANTIDAD]] -> 0 | I2: =IF(OR(A2="", D2=""), "", IF(C2="Entrada", B2+D2, IF(OR(C2="Venta", C2="Salida"), B2-D2, B2))) | K2: CUP/USD | L2: 540 | N2: VENTA TOTAL | O2: =Tabla15[[#Totals],[IMPORTE]] -> 9440 | P2: =O2 -> 9440
B3: =IFERROR(VLOOKUP(A3, viernes!$A:$I, 9, FALSE), IFERROR(VLOOKUP(A3, jueves!$A:$I, 9, FALSE), IFERROR(VLOOKUP(A3, miercoles!$A:$I, 9, FALSE), IFERROR(VLOOKUP(A3, martes!$A:$I, 9, FALSE), IFERROR(VLOOKUP(A3, lunes!$A:$I, 9, FALSE), VLOOKUP(A3, Configuracion!$A:$B, 2, FALSE)))))) -> #N/A | C3: VENTA | D3: 1 | E3: =IF(C3="Venta", IFERROR(VLOOKUP(A3, Configuracion!$A:$D, 3, FALSE), 0), 0) -> 0 | F3: =E3*D3 -> 0 | G3: GESTOR | H3: =IF(AND(G3="Gestor", A3<>""), VLOOKUP(A3, Configuracion!$A:$D, 4, FALSE), 0)*Tabla1027[[#This Row],[CANTIDAD]] -> 0 | I3: =IF(OR(A3="", D3=""), "", IF(C3="Entrada", B3+D3, IF(OR(C3="Venta", C3="Salida"), B3-D3, B3))) | K3: MXN/USD | L3: 20 | N3: USD | O3: 4710 | P3: =O3 -> 4710
B4: =IFERROR(VLOOKUP(A4, viernes!$A:$I, 9, FALSE), IFERROR(VLOOKUP(A4, jueves!$A:$I, 9, FALSE), IFERROR(VLOOKUP(A4, miercoles!$A:$I, 9, FALSE), IFERROR(VLOOKUP(A4, martes!$A:$I, 9, FALSE), IFERROR(VLOOKUP(A4, lunes!$A:$I, 9, FALSE), VLOOKUP(A4, Configuracion!$A:$B, 2, FALSE)))))) -> #N/A | C4: SALIDA | D4: 1 | E4: =IF(C4="Venta", IFERROR(VLOOKUP(A4, Configuracion!$A:$D, 3, FALSE), 0), 0) -> 0 | F4: =E4*D4 -> 0 | G4: MOV | H4: =IF(AND(G4="Gestor", A4<>""), VLOOKUP(A4, Configuracion!$A:$D, 4, FALSE), 0)*Tabla1027[[#This Row],[CANTIDAD]] -> 0 | I4: =IF(OR(A4="", D4=""), "", IF(C4="Entrada", B4+D4, IF(OR(C4="Venta", C4="Salida"), B4-D4, B4))) | N4: ZELLE | O4: 380 | P4: =O4 -> 380
B5: =IFERROR(VLOOKUP(A5, viernes!$A:$I, 9, FALSE), IFERROR(VLOOKUP(A5, jueves!$A:$I, 9, FALSE), IFERROR(VLOOKUP(A5, miercoles!$A:$I, 9, FALSE), IFERROR(VLOOKUP(A5, martes!$A:$I, 9, FALSE), IFERROR(VLOOKUP(A5, lunes!$A:$I, 9, FALSE), VLOOKUP(A5, Configuracion!$A:$B, 2, FALSE)))))) -> #N/A | C5: VENTA | D5: 2 | E5: =IF(C5="Venta", IFERROR(VLOOKUP(A5, Configuracion!$A:$D, 3, FALSE), 0), 0) -> 0 | F5: =E5*D5 -> 0 | G5: GESTOR | H5: =IF(AND(G5="Gestor", A5<>""), VLOOKUP(A5, Configuracion!$A:$D, 4, FALSE), 0)*Tabla1027[[#This Row],[CANTIDAD]] -> 0 | I5: =IF(OR(A5="", D5=""), "", IF(C5="Entrada", B5+D5, IF(OR(C5="Venta", C5="Salida"), B5-D5, B5))) | N5: MXN | P5: =O5/L3 -> 0
B6: =IFERROR(VLOOKUP(A6, viernes!$A:$I, 9, FALSE), IFERROR(VLOOKUP(A6, jueves!$A:$I, 9, FALSE), IFERROR(VLOOKUP(A6, miercoles!$A:$I, 9, FALSE), IFERROR(VLOOKUP(A6, martes!$A:$I, 9, FALSE), IFERROR(VLOOKUP(A6, lunes!$A:$I, 9, FALSE), VLOOKUP(A6, Configuracion!$A:$B, 2, FALSE)))))) -> #N/A | E6: =IF(C6="Venta", IFERROR(VLOOKUP(A6, Configuracion!$A:$D, 3, FALSE), 0), 0) -> 0 | F6: =E6*D6 -> 0 | H6: =IF(AND(G6="Gestor", A6<>""), VLOOKUP(A6, Configuracion!$A:$D, 4, FALSE), 0)*Tabla1027[[#This Row],[CANTIDAD]] -> 0 | I6: =IF(OR(A6="", D6=""), "", IF(C6="Entrada", B6+D6, IF(OR(C6="Venta", C6="Salida"), B6-D6, B6))) | N6: CUP EFECTIVO | O6: 1252800 | P6: =O6/L2 -> 2320
B7: =IFERROR(VLOOKUP(A7, viernes!$A:$I, 9, FALSE), IFERROR(VLOOKUP(A7, jueves!$A:$I, 9, FALSE), IFERROR(VLOOKUP(A7, miercoles!$A:$I, 9, FALSE), IFERROR(VLOOKUP(A7, martes!$A:$I, 9, FALSE), IFERROR(VLOOKUP(A7, lunes!$A:$I, 9, FALSE), VLOOKUP(A7, Configuracion!$A:$B, 2, FALSE)))))) -> #N/A | E7: =IF(C7="Venta", IFERROR(VLOOKUP(A7, Configuracion!$A:$D, 3, FALSE), 0), 0) -> 0 | F7: =E7*D7 -> 0 | H7: =IF(AND(G7="Gestor", A7<>""), VLOOKUP(A7, Configuracion!$A:$D, 4, FALSE), 0)*Tabla1027[[#This Row],[CANTIDAD]] -> 0 | I7: =IF(OR(A7="", D7=""), "", IF(C7="Entrada", B7+D7, IF(OR(C7="Venta", C7="Salida"), B7-D7, B7))) | N7: CUP TRANSF | P7: =O7/L2 -> 0
B8: =IFERROR(VLOOKUP(A8, viernes!$A:$I, 9, FALSE), IFERROR(VLOOKUP(A8, jueves!$A:$I, 9, FALSE), IFERROR(VLOOKUP(A8, miercoles!$A:$I, 9, FALSE), IFERROR(VLOOKUP(A8, martes!$A:$I, 9, FALSE), IFERROR(VLOOKUP(A8, lunes!$A:$I, 9, FALSE), VLOOKUP(A8, Configuracion!$A:$B, 2, FALSE)))))) -> #N/A | E8: =IF(C8="Venta", IFERROR(VLOOKUP(A8, Configuracion!$A:$D, 3, FALSE), 0), 0) -> 0 | F8: =E8*D8 -> 0 | H8: =IF(AND(G8="Gestor", A8<>""), VLOOKUP(A8, Configuracion!$A:$D, 4, FALSE), 0)*Tabla1027[[#This Row],[CANTIDAD]] -> 0 | I8: =IF(OR(A8="", D8=""), "", IF(C8="Entrada", B8+D8, IF(OR(C8="Venta", C8="Salida"), B8-D8, B8))) | N8: EUROPA | P8: =O8 -> 0
B9: =IFERROR(VLOOKUP(A9, viernes!$A:$I, 9, FALSE), IFERROR(VLOOKUP(A9, jueves!$A:$I, 9, FALSE), IFERROR(VLOOKUP(A9, miercoles!$A:$I, 9, FALSE), IFERROR(VLOOKUP(A9, martes!$A:$I, 9, FALSE), IFERROR(VLOOKUP(A9, lunes!$A:$I, 9, FALSE), VLOOKUP(A9, Configuracion!$A:$B, 2, FALSE)))))) -> #N/A | E9: =IF(C9="Venta", IFERROR(VLOOKUP(A9, Configuracion!$A:$D, 3, FALSE), 0), 0) -> 0 | F9: =E9*D9 -> 0 | H9: =IF(AND(G9="Gestor", A9<>""), VLOOKUP(A9, Configuracion!$A:$D, 4, FALSE), 0)*Tabla1027[[#This Row],[CANTIDAD]] -> 0 | I9: =IF(OR(A9="", D9=""), "", IF(C9="Entrada", B9+D9, IF(OR(C9="Venta", C9="Salida"), B9-D9, B9))) | N9: TOTAL | P9: =P3+P4+P5+P6+P7+P8 -> 7410
B10: =IFERROR(VLOOKUP(A10, viernes!$A:$I, 9, FALSE), IFERROR(VLOOKUP(A10, jueves!$A:$I, 9, FALSE), IFERROR(VLOOKUP(A10, miercoles!$A:$I, 9, FALSE), IFERROR(VLOOKUP(A10, martes!$A:$I, 9, FALSE), IFERROR(VLOOKUP(A10, lunes!$A:$I, 9, FALSE), VLOOKUP(A10, Configuracion!$A:$B, 2, FALSE)))))) -> #N/A | E10: =IF(C10="Venta", IFERROR(VLOOKUP(A10, Configuracion!$A:$D, 3, FALSE), 0), 0) -> 0 | F10: =E10*D10 -> 0 | H10: =IF(AND(G10="Gestor", A10<>""), VLOOKUP(A10, Configuracion!$A:$D, 4, FALSE), 0)*Tabla1027[[#This Row],[CANTIDAD]] -> 0 | I10: =IF(OR(A10="", D10=""), "", IF(C10="Entrada", B10+D10, IF(OR(C10="Venta", C10="Salida"), B10-D10, B10))) | N10: ENTRADA DINERO | P10: =P12+P11 -> 20
B11: =IFERROR(VLOOKUP(A11, viernes!$A:$I, 9, FALSE), IFERROR(VLOOKUP(A11, jueves!$A:$I, 9, FALSE), IFERROR(VLOOKUP(A11, miercoles!$A:$I, 9, FALSE), IFERROR(VLOOKUP(A11, martes!$A:$I, 9, FALSE), IFERROR(VLOOKUP(A11, lunes!$A:$I, 9, FALSE), VLOOKUP(A11, Configuracion!$A:$B, 2, FALSE)))))) -> #N/A | E11: =IF(C11="Venta", IFERROR(VLOOKUP(A11, Configuracion!$A:$D, 3, FALSE), 0), 0) -> 0 | F11: =E11*D11 -> 0 | H11: =IF(AND(G11="Gestor", A11<>""), VLOOKUP(A11, Configuracion!$A:$D, 4, FALSE), 0)*Tabla1027[[#This Row],[CANTIDAD]] -> 0 | I11: =IF(OR(A11="", D11=""), "", IF(C11="Entrada", B11+D11, IF(OR(C11="Venta", C11="Salida"), B11-D11, B11))) | N11: CUP | P11: =O11/L2 -> 0
B12: =IFERROR(VLOOKUP(A12, viernes!$A:$I, 9, FALSE), IFERROR(VLOOKUP(A12, jueves!$A:$I, 9, FALSE), IFERROR(VLOOKUP(A12, miercoles!$A:$I, 9, FALSE), IFERROR(VLOOKUP(A12, martes!$A:$I, 9, FALSE), IFERROR(VLOOKUP(A12, lunes!$A:$I, 9, FALSE), VLOOKUP(A12, Configuracion!$A:$B, 2, FALSE)))))) -> #N/A | E12: =IF(C12="Venta", IFERROR(VLOOKUP(A12, Configuracion!$A:$D, 3, FALSE), 0), 0) -> 0 | F12: =E12*D12 -> 0 | H12: =IF(AND(G12="Gestor", A12<>""), VLOOKUP(A12, Configuracion!$A:$D, 4, FALSE), 0)*Tabla1027[[#This Row],[CANTIDAD]] -> 0 | I12: =IF(OR(A12="", D12=""), "", IF(C12="Entrada", B12+D12, IF(OR(C12="Venta", C12="Salida"), B12-D12, B12))) | N12: USD | O12: 20 | P12: =O12 -> 20 | Q12: ZELLE
B13: =IFERROR(VLOOKUP(A13, viernes!$A:$I, 9, FALSE), IFERROR(VLOOKUP(A13, jueves!$A:$I, 9, FALSE), IFERROR(VLOOKUP(A13, miercoles!$A:$I, 9, FALSE), IFERROR(VLOOKUP(A13, martes!$A:$I, 9, FALSE), IFERROR(VLOOKUP(A13, lunes!$A:$I, 9, FALSE), VLOOKUP(A13, Configuracion!$A:$B, 2, FALSE)))))) -> #N/A | E13: =IF(C13="Venta", IFERROR(VLOOKUP(A13, Configuracion!$A:$D, 3, FALSE), 0), 0) -> 0 | F13: =E13*D13 -> 0 | H13: =IF(AND(G13="Gestor", A13<>""), VLOOKUP(A13, Configuracion!$A:$D, 4, FALSE), 0)*Tabla1027[[#This Row],[CANTIDAD]] -> 0 | I13: =IF(OR(A13="", D13=""), "", IF(C13="Entrada", B13+D13, IF(OR(C13="Venta", C13="Salida"), B13-D13, B13))) | N13: EXTRACCION | P13: =P15+P14 -> 2050
B14: =IFERROR(VLOOKUP(A14, viernes!$A:$I, 9, FALSE), IFERROR(VLOOKUP(A14, jueves!$A:$I, 9, FALSE), IFERROR(VLOOKUP(A14, miercoles!$A:$I, 9, FALSE), IFERROR(VLOOKUP(A14, martes!$A:$I, 9, FALSE), IFERROR(VLOOKUP(A14, lunes!$A:$I, 9, FALSE), VLOOKUP(A14, Configuracion!$A:$B, 2, FALSE)))))) -> #N/A | E14: =IF(C14="Venta", IFERROR(VLOOKUP(A14, Configuracion!$A:$D, 3, FALSE), 0), 0) -> 0 | F14: =E14*D14 -> 0 | H14: =IF(AND(G14="Gestor", A14<>""), VLOOKUP(A14, Configuracion!$A:$D, 4, FALSE), 0)*Tabla1027[[#This Row],[CANTIDAD]] -> 0 | I14: =IF(OR(A14="", D14=""), "", IF(C14="Entrada", B14+D14, IF(OR(C14="Venta", C14="Salida"), B14-D14, B14))) | N14: CUP | P14: =O14/L2 -> 0
B15: =IFERROR(VLOOKUP(A15, viernes!$A:$I, 9, FALSE), IFERROR(VLOOKUP(A15, jueves!$A:$I, 9, FALSE), IFERROR(VLOOKUP(A15, miercoles!$A:$I, 9, FALSE), IFERROR(VLOOKUP(A15, martes!$A:$I, 9, FALSE), IFERROR(VLOOKUP(A15, lunes!$A:$I, 9, FALSE), VLOOKUP(A15, Configuracion!$A:$B, 2, FALSE)))))) -> #N/A | E15: =IF(C15="Venta", IFERROR(VLOOKUP(A15, Configuracion!$A:$D, 3, FALSE), 0), 0) -> 0 | F15: =E15*D15 -> 0 | H15: =IF(AND(G15="Gestor", A15<>""), VLOOKUP(A15, Configuracion!$A:$D, 4, FALSE), 0)*Tabla1027[[#This Row],[CANTIDAD]] -> 0 | I15: =IF(OR(A15="", D15=""), "", IF(C15="Entrada", B15+D15, IF(OR(C15="Venta", C15="Salida"), B15-D15, B15))) | N15: USD | O15: 2050 | P15: 2050
B16: =IFERROR(VLOOKUP(A16, viernes!$A:$I, 9, FALSE), IFERROR(VLOOKUP(A16, jueves!$A:$I, 9, FALSE), IFERROR(VLOOKUP(A16, miercoles!$A:$I, 9, FALSE), IFERROR(VLOOKUP(A16, martes!$A:$I, 9, FALSE), IFERROR(VLOOKUP(A16, lunes!$A:$I, 9, FALSE), VLOOKUP(A16, Configuracion!$A:$B, 2, FALSE)))))) -> #N/A | E16: =IF(C16="Venta", IFERROR(VLOOKUP(A16, Configuracion!$A:$D, 3, FALSE), 0), 0) -> 0 | F16: =E16*D16 -> 0 | H16: =IF(AND(G16="Gestor", A16<>""), VLOOKUP(A16, Configuracion!$A:$D, 4, FALSE), 0)*Tabla1027[[#This Row],[CANTIDAD]] -> 0 | I16: =IF(OR(A16="", D16=""), "", IF(C16="Entrada", B16+D16, IF(OR(C16="Venta", C16="Salida"), B16-D16, B16))) | N16: TOTAL GENERAL | P16: =P9+P13-P10 -> 9440 | R16: =P2-P16 -> 0 | S16: =R16*L2 -> 0
B17: =IFERROR(VLOOKUP(A17, viernes!$A:$I, 9, FALSE), IFERROR(VLOOKUP(A17, jueves!$A:$I, 9, FALSE), IFERROR(VLOOKUP(A17, miercoles!$A:$I, 9, FALSE), IFERROR(VLOOKUP(A17, martes!$A:$I, 9, FALSE), IFERROR(VLOOKUP(A17, lunes!$A:$I, 9, FALSE), VLOOKUP(A17, Configuracion!$A:$B, 2, FALSE)))))) -> #N/A | E17: =IF(C17="Venta", IFERROR(VLOOKUP(A17, Configuracion!$A:$D, 3, FALSE), 0), 0) -> 0 | F17: =E17*D17 -> 0 | H17: =IF(AND(G17="Gestor", A17<>""), VLOOKUP(A17, Configuracion!$A:$D, 4, FALSE), 0)*Tabla1027[[#This Row],[CANTIDAD]] -> 0 | I17: =IF(OR(A17="", D17=""), "", IF(C17="Entrada", B17+D17, IF(OR(C17="Venta", C17="Salida"), B17-D17, B17)))
B18: =IFERROR(VLOOKUP(A18, viernes!$A:$I, 9, FALSE), IFERROR(VLOOKUP(A18, jueves!$A:$I, 9, FALSE), IFERROR(VLOOKUP(A18, miercoles!$A:$I, 9, FALSE), IFERROR(VLOOKUP(A18, martes!$A:$I, 9, FALSE), IFERROR(VLOOKUP(A18, lunes!$A:$I, 9, FALSE), VLOOKUP(A18, Configuracion!$A:$B, 2, FALSE)))))) -> #N/A | E18: =IF(C18="Venta", IFERROR(VLOOKUP(A18, Configuracion!$A:$D, 3, FALSE), 0), 0) -> 0 | F18: =E18*D18 -> 0 | H18: =IF(AND(G18="Gestor", A18<>""), VLOOKUP(A18, Configuracion!$A:$D, 4, FALSE), 0)*Tabla1027[[#This Row],[CANTIDAD]] -> 0 | I18: =IF(OR(A18="", D18=""), "", IF(C18="Entrada", B18+D18, IF(OR(C18="Venta", C18="Salida"), B18-D18, B18))) | O18: CUP | P18: USD
B19: =IFERROR(VLOOKUP(A19, viernes!$A:$I, 9, FALSE), IFERROR(VLOOKUP(A19, jueves!$A:$I, 9, FALSE), IFERROR(VLOOKUP(A19, miercoles!$A:$I, 9, FALSE), IFERROR(VLOOKUP(A19, martes!$A:$I, 9, FALSE), IFERROR(VLOOKUP(A19, lunes!$A:$I, 9, FALSE), VLOOKUP(A19, Configuracion!$A:$B, 2, FALSE)))))) -> #N/A | E19: =IF(C19="Venta", IFERROR(VLOOKUP(A19, Configuracion!$A:$D, 3, FALSE), 0), 0) -> 0 | F19: =E19*D19 -> 0 | H19: =IF(AND(G19="Gestor", A19<>""), VLOOKUP(A19, Configuracion!$A:$D, 4, FALSE), 0)*Tabla1027[[#This Row],[CANTIDAD]] -> 0 | I19: =IF(OR(A19="", D19=""), "", IF(C19="Entrada", B19+D19, IF(OR(C19="Venta", C19="Salida"), B19-D19, B19))) | N19: FONDO INICIAL | O19: 100000 | P19: 150
B20: =IFERROR(VLOOKUP(A20, viernes!$A:$I, 9, FALSE), IFERROR(VLOOKUP(A20, jueves!$A:$I, 9, FALSE), IFERROR(VLOOKUP(A20, miercoles!$A:$I, 9, FALSE), IFERROR(VLOOKUP(A20, martes!$A:$I, 9, FALSE), IFERROR(VLOOKUP(A20, lunes!$A:$I, 9, FALSE), VLOOKUP(A20, Configuracion!$A:$B, 2, FALSE)))))) -> #N/A | E20: =IF(C20="Venta", IFERROR(VLOOKUP(A20, Configuracion!$A:$D, 3, FALSE), 0), 0) -> 0 | F20: =E20*D20 -> 0 | H20: =IF(AND(G20="Gestor", A20<>""), VLOOKUP(A20, Configuracion!$A:$D, 4, FALSE), 0)*Tabla1027[[#This Row],[CANTIDAD]] -> 0 | I20: =IF(OR(A20="", D20=""), "", IF(C20="Entrada", B20+D20, IF(OR(C20="Venta", C20="Salida"), B20-D20, B20))) | N20: CAMBIO
B21: =IFERROR(VLOOKUP(A21, viernes!$A:$I, 9, FALSE), IFERROR(VLOOKUP(A21, jueves!$A:$I, 9, FALSE), IFERROR(VLOOKUP(A21, miercoles!$A:$I, 9, FALSE), IFERROR(VLOOKUP(A21, martes!$A:$I, 9, FALSE), IFERROR(VLOOKUP(A21, lunes!$A:$I, 9, FALSE), VLOOKUP(A21, Configuracion!$A:$B, 2, FALSE)))))) -> #N/A | E21: =IF(C21="Venta", IFERROR(VLOOKUP(A21, Configuracion!$A:$D, 3, FALSE), 0), 0) -> 0 | F21: =E21*D21 -> 0 | H21: =IF(AND(G21="Gestor", A21<>""), VLOOKUP(A21, Configuracion!$A:$D, 4, FALSE), 0)*Tabla1027[[#This Row],[CANTIDAD]] -> 0 | I21: =IF(OR(A21="", D21=""), "", IF(C21="Entrada", B21+D21, IF(OR(C21="Venta", C21="Salida"), B21-D21, B21))) | N21: DOMICILIO
B22: =IFERROR(VLOOKUP(A22, viernes!$A:$I, 9, FALSE), IFERROR(VLOOKUP(A22, jueves!$A:$I, 9, FALSE), IFERROR(VLOOKUP(A22, miercoles!$A:$I, 9, FALSE), IFERROR(VLOOKUP(A22, martes!$A:$I, 9, FALSE), IFERROR(VLOOKUP(A22, lunes!$A:$I, 9, FALSE), VLOOKUP(A22, Configuracion!$A:$B, 2, FALSE)))))) -> #N/A | E22: =IF(C22="Venta", IFERROR(VLOOKUP(A22, Configuracion!$A:$D, 3, FALSE), 0), 0) -> 0 | F22: =E22*D22 -> 0 | H22: =IF(AND(G22="Gestor", A22<>""), VLOOKUP(A22, Configuracion!$A:$D, 4, FALSE), 0)*Tabla1027[[#This Row],[CANTIDAD]] -> 0 | I22: =IF(OR(A22="", D22=""), "", IF(C22="Entrada", B22+D22, IF(OR(C22="Venta", C22="Salida"), B22-D22, B22))) | N22: OTROS GASTOS
B23: =IFERROR(VLOOKUP(A23, viernes!$A:$I, 9, FALSE), IFERROR(VLOOKUP(A23, jueves!$A:$I, 9, FALSE), IFERROR(VLOOKUP(A23, miercoles!$A:$I, 9, FALSE), IFERROR(VLOOKUP(A23, martes!$A:$I, 9, FALSE), IFERROR(VLOOKUP(A23, lunes!$A:$I, 9, FALSE), VLOOKUP(A23, Configuracion!$A:$B, 2, FALSE)))))) -> #N/A | E23: =IF(C23="Venta", IFERROR(VLOOKUP(A23, Configuracion!$A:$D, 3, FALSE), 0), 0) -> 0 | F23: =E23*D23 -> 0 | H23: =IF(AND(G23="Gestor", A23<>""), VLOOKUP(A23, Configuracion!$A:$D, 4, FALSE), 0)*Tabla1027[[#This Row],[CANTIDAD]] -> 0 | I23: =IF(OR(A23="", D23=""), "", IF(C23="Entrada", B23+D23, IF(OR(C23="Venta", C23="Salida"), B23-D23, B23))) | N23: COMISIONES
B24: =IFERROR(VLOOKUP(A24, viernes!$A:$I, 9, FALSE), IFERROR(VLOOKUP(A24, jueves!$A:$I, 9, FALSE), IFERROR(VLOOKUP(A24, miercoles!$A:$I, 9, FALSE), IFERROR(VLOOKUP(A24, martes!$A:$I, 9, FALSE), IFERROR(VLOOKUP(A24, lunes!$A:$I, 9, FALSE), VLOOKUP(A24, Configuracion!$A:$B, 2, FALSE)))))) -> #N/A | E24: =IF(C24="Venta", IFERROR(VLOOKUP(A24, Configuracion!$A:$D, 3, FALSE), 0), 0) -> 0 | F24: =E24*D24 -> 0 | H24: =IF(AND(G24="Gestor", A24<>""), VLOOKUP(A24, Configuracion!$A:$D, 4, FALSE), 0)*Tabla1027[[#This Row],[CANTIDAD]] -> 0 | I24: =IF(OR(A24="", D24=""), "", IF(C24="Entrada", B24+D24, IF(OR(C24="Venta", C24="Salida"), B24-D24, B24))) | N24: FONDO FINAL | O24: =O19-O21-O22-O23-O20 -> 100000 | P24: =P19-P21-P22-P23-P20 -> 150
B25: =IFERROR(VLOOKUP(A25, viernes!$A:$I, 9, FALSE), IFERROR(VLOOKUP(A25, jueves!$A:$I, 9, FALSE), IFERROR(VLOOKUP(A25, miercoles!$A:$I, 9, FALSE), IFERROR(VLOOKUP(A25, martes!$A:$I, 9, FALSE), IFERROR(VLOOKUP(A25, lunes!$A:$I, 9, FALSE), VLOOKUP(A25, Configuracion!$A:$B, 2, FALSE)))))) -> #N/A | E25: =IF(C25="Venta", IFERROR(VLOOKUP(A25, Configuracion!$A:$D, 3, FALSE), 0), 0) -> 0 | F25: =E25*D25 -> 0 | H25: =IF(AND(G25="Gestor", A25<>""), VLOOKUP(A25, Configuracion!$A:$D, 4, FALSE), 0)*Tabla1027[[#This Row],[CANTIDAD]] -> 0 | I25: =IF(OR(A25="", D25=""), "", IF(C25="Entrada", B25+D25, IF(OR(C25="Venta", C25="Salida"), B25-D25, B25)))
B26: =IFERROR(VLOOKUP(A26, viernes!$A:$I, 9, FALSE), IFERROR(VLOOKUP(A26, jueves!$A:$I, 9, FALSE), IFERROR(VLOOKUP(A26, miercoles!$A:$I, 9, FALSE), IFERROR(VLOOKUP(A26, martes!$A:$I, 9, FALSE), IFERROR(VLOOKUP(A26, lunes!$A:$I, 9, FALSE), VLOOKUP(A26, Configuracion!$A:$B, 2, FALSE)))))) -> #N/A | E26: =IF(C26="Venta", IFERROR(VLOOKUP(A26, Configuracion!$A:$D, 3, FALSE), 0), 0) -> 0 | F26: =E26*D26 -> 0 | H26: =IF(AND(G26="Gestor", A26<>""), VLOOKUP(A26, Configuracion!$A:$D, 4, FALSE), 0)*Tabla1027[[#This Row],[CANTIDAD]] -> 0 | I26: =IF(OR(A26="", D26=""), "", IF(C26="Entrada", B26+D26, IF(OR(C26="Venta", C26="Salida"), B26-D26, B26)))
B27: =IFERROR(VLOOKUP(A27, viernes!$A:$I, 9, FALSE), IFERROR(VLOOKUP(A27, jueves!$A:$I, 9, FALSE), IFERROR(VLOOKUP(A27, miercoles!$A:$I, 9, FALSE), IFERROR(VLOOKUP(A27, martes!$A:$I, 9, FALSE), IFERROR(VLOOKUP(A27, lunes!$A:$I, 9, FALSE), VLOOKUP(A27, Configuracion!$A:$B, 2, FALSE)))))) -> #N/A | E27: =IF(C27="Venta", IFERROR(VLOOKUP(A27, Configuracion!$A:$D, 3, FALSE), 0), 0) -> 0 | F27: =E27*D27 -> 0 | H27: =IF(AND(G27="Gestor", A27<>""), VLOOKUP(A27, Configuracion!$A:$D, 4, FALSE), 0)*Tabla1027[[#This Row],[CANTIDAD]] -> 0 | I27: =IF(OR(A27="", D27=""), "", IF(C27="Entrada", B27+D27, IF(OR(C27="Venta", C27="Salida"), B27-D27, B27)))
B28: =IFERROR(VLOOKUP(A28, viernes!$A:$I, 9, FALSE), IFERROR(VLOOKUP(A28, jueves!$A:$I, 9, FALSE), IFERROR(VLOOKUP(A28, miercoles!$A:$I, 9, FALSE), IFERROR(VLOOKUP(A28, martes!$A:$I, 9, FALSE), IFERROR(VLOOKUP(A28, lunes!$A:$I, 9, FALSE), VLOOKUP(A28, Configuracion!$A:$B, 2, FALSE)))))) -> #N/A | E28: =IF(C28="Venta", IFERROR(VLOOKUP(A28, Configuracion!$A:$D, 3, FALSE), 0), 0) -> 0 | F28: =E28*D28 -> 0 | H28: =IF(AND(G28="Gestor", A28<>""), VLOOKUP(A28, Configuracion!$A:$D, 4, FALSE), 0)*Tabla1027[[#This Row],[CANTIDAD]] -> 0 | I28: =IF(OR(A28="", D28=""), "", IF(C28="Entrada", B28+D28, IF(OR(C28="Venta", C28="Salida"), B28-D28, B28)))
B29: =IFERROR(VLOOKUP(A29, viernes!$A:$I, 9, FALSE), IFERROR(VLOOKUP(A29, jueves!$A:$I, 9, FALSE), IFERROR(VLOOKUP(A29, miercoles!$A:$I, 9, FALSE), IFERROR(VLOOKUP(A29, martes!$A:$I, 9, FALSE), IFERROR(VLOOKUP(A29, lunes!$A:$I, 9, FALSE), VLOOKUP(A29, Configuracion!$A:$B, 2, FALSE)))))) -> #N/A | E29: =IF(C29="Venta", IFERROR(VLOOKUP(A29, Configuracion!$A:$D, 3, FALSE), 0), 0) -> 0 | F29: =E29*D29 -> 0 | H29: =IF(AND(G29="Gestor", A29<>""), VLOOKUP(A29, Configuracion!$A:$D, 4, FALSE), 0)*Tabla1027[[#This Row],[CANTIDAD]] -> 0 | I29: =IF(OR(A29="", D29=""), "", IF(C29="Entrada", B29+D29, IF(OR(C29="Venta", C29="Salida"), B29-D29, B29)))
B30: =IFERROR(VLOOKUP(A30, viernes!$A:$I, 9, FALSE), IFERROR(VLOOKUP(A30, jueves!$A:$I, 9, FALSE), IFERROR(VLOOKUP(A30, miercoles!$A:$I, 9, FALSE), IFERROR(VLOOKUP(A30, martes!$A:$I, 9, FALSE), IFERROR(VLOOKUP(A30, lunes!$A:$I, 9, FALSE), VLOOKUP(A30, Configuracion!$A:$B, 2, FALSE)))))) -> #N/A | E30: =IF(C30="Venta", IFERROR(VLOOKUP(A30, Configuracion!$A:$D, 3, FALSE), 0), 0) -> 0 | F30: =E30*D30 -> 0 | H30: =IF(AND(G30="Gestor", A30<>""), VLOOKUP(A30, Configuracion!$A:$D, 4, FALSE), 0)*Tabla1027[[#This Row],[CANTIDAD]] -> 0 | I30: =IF(OR(A30="", D30=""), "", IF(C30="Entrada", B30+D30, IF(OR(C30="Venta", C30="Salida"), B30-D30, B30)))
B31: =IFERROR(VLOOKUP(A31, viernes!$A:$I, 9, FALSE), IFERROR(VLOOKUP(A31, jueves!$A:$I, 9, FALSE), IFERROR(VLOOKUP(A31, miercoles!$A:$I, 9, FALSE), IFERROR(VLOOKUP(A31, martes!$A:$I, 9, FALSE), IFERROR(VLOOKUP(A31, lunes!$A:$I, 9, FALSE), VLOOKUP(A31, Configuracion!$A:$B, 2, FALSE)))))) -> #N/A | E31: =IF(C31="Venta", IFERROR(VLOOKUP(A31, Configuracion!$A:$D, 3, FALSE), 0), 0) -> 0 | F31: =E31*D31 -> 0 | H31: =IF(AND(G31="Gestor", A31<>""), VLOOKUP(A31, Configuracion!$A:$D, 4, FALSE), 0)*Tabla1027[[#This Row],[CANTIDAD]] -> 0 | I31: =IF(OR(A31="", D31=""), "", IF(C31="Entrada", B31+D31, IF(OR(C31="Venta", C31="Salida"), B31-D31, B31)))
B32: =IFERROR(VLOOKUP(A32, viernes!$A:$I, 9, FALSE), IFERROR(VLOOKUP(A32, jueves!$A:$I, 9, FALSE), IFERROR(VLOOKUP(A32, miercoles!$A:$I, 9, FALSE), IFERROR(VLOOKUP(A32, martes!$A:$I, 9, FALSE), IFERROR(VLOOKUP(A32, lunes!$A:$I, 9, FALSE), VLOOKUP(A32, Configuracion!$A:$B, 2, FALSE)))))) -> #N/A | E32: =IF(C32="Venta", IFERROR(VLOOKUP(A32, Configuracion!$A:$D, 3, FALSE), 0), 0) -> 0 | F32: =E32*D32 -> 0 | H32: =IF(AND(G32="Gestor", A32<>""), VLOOKUP(A32, Configuracion!$A:$D, 4, FALSE), 0)*Tabla1027[[#This Row],[CANTIDAD]] -> 0 | I32: =IF(OR(A32="", D32=""), "", IF(C32="Entrada", B32+D32, IF(OR(C32="Venta", C32="Salida"), B32-D32, B32)))
B33: =IFERROR(VLOOKUP(A33, viernes!$A:$I, 9, FALSE), IFERROR(VLOOKUP(A33, jueves!$A:$I, 9, FALSE), IFERROR(VLOOKUP(A33, miercoles!$A:$I, 9, FALSE), IFERROR(VLOOKUP(A33, martes!$A:$I, 9, FALSE), IFERROR(VLOOKUP(A33, lunes!$A:$I, 9, FALSE), VLOOKUP(A33, Configuracion!$A:$B, 2, FALSE)))))) -> #N/A | E33: =IF(C33="Venta", IFERROR(VLOOKUP(A33, Configuracion!$A:$D, 3, FALSE), 0), 0) -> 0 | F33: =E33*D33 -> 0 | H33: =IF(AND(G33="Gestor", A33<>""), VLOOKUP(A33, Configuracion!$A:$D, 4, FALSE), 0)*Tabla1027[[#This Row],[CANTIDAD]] -> 0 | I33: =IF(OR(A33="", D33=""), "", IF(C33="Entrada", B33+D33, IF(OR(C33="Venta", C33="Salida"), B33-D33, B33)))
B34: =IFERROR(VLOOKUP(A34, viernes!$A:$I, 9, FALSE), IFERROR(VLOOKUP(A34, jueves!$A:$I, 9, FALSE), IFERROR(VLOOKUP(A34, miercoles!$A:$I, 9, FALSE), IFERROR(VLOOKUP(A34, martes!$A:$I, 9, FALSE), IFERROR(VLOOKUP(A34, lunes!$A:$I, 9, FALSE), VLOOKUP(A34, Configuracion!$A:$B, 2, FALSE)))))) -> #N/A | E34: =IF(C34="Venta", IFERROR(VLOOKUP(A34, Configuracion!$A:$D, 3, FALSE), 0), 0) -> 0 | F34: =E34*D34 -> 0 | H34: =IF(AND(G34="Gestor", A34<>""), VLOOKUP(A34, Configuracion!$A:$D, 4, FALSE), 0)*Tabla1027[[#This Row],[CANTIDAD]] -> 0 | I34: =IF(OR(A34="", D34=""), "", IF(C34="Entrada", B34+D34, IF(OR(C34="Venta", C34="Salida"), B34-D34, B34)))
B35: =IFERROR(VLOOKUP(A35, viernes!$A:$I, 9, FALSE), IFERROR(VLOOKUP(A35, jueves!$A:$I, 9, FALSE), IFERROR(VLOOKUP(A35, miercoles!$A:$I, 9, FALSE), IFERROR(VLOOKUP(A35, martes!$A:$I, 9, FALSE), IFERROR(VLOOKUP(A35, lunes!$A:$I, 9, FALSE), VLOOKUP(A35, Configuracion!$A:$B, 2, FALSE)))))) -> #N/A | E35: =IF(C35="Venta", IFERROR(VLOOKUP(A35, Configuracion!$A:$D, 3, FALSE), 0), 0) -> 0 | F35: =E35*D35 -> 0 | H35: =IF(AND(G35="Gestor", A35<>""), VLOOKUP(A35, Configuracion!$A:$D, 4, FALSE), 0)*Tabla1027[[#This Row],[CANTIDAD]] -> 0 | I35: =IF(OR(A35="", D35=""), "", IF(C35="Entrada", B35+D35, IF(OR(C35="Venta", C35="Salida"), B35-D35, B35)))
B36: =IFERROR(VLOOKUP(A36, viernes!$A:$I, 9, FALSE), IFERROR(VLOOKUP(A36, jueves!$A:$I, 9, FALSE), IFERROR(VLOOKUP(A36, miercoles!$A:$I, 9, FALSE), IFERROR(VLOOKUP(A36, martes!$A:$I, 9, FALSE), IFERROR(VLOOKUP(A36, lunes!$A:$I, 9, FALSE), VLOOKUP(A36, Configuracion!$A:$B, 2, FALSE)))))) -> #N/A | E36: =IF(C36="Venta", IFERROR(VLOOKUP(A36, Configuracion!$A:$D, 3, FALSE), 0), 0) -> 0 | F36: =E36*D36 -> 0 | H36: =IF(AND(G36="Gestor", A36<>""), VLOOKUP(A36, Configuracion!$A:$D, 4, FALSE), 0)*Tabla1027[[#This Row],[CANTIDAD]] -> 0 | I36: =IF(OR(A36="", D36=""), "", IF(C36="Entrada", B36+D36, IF(OR(C36="Venta", C36="Salida"), B36-D36, B36)))
... B189: =IFERROR(VLOOKUP(A189, viernes!$A:$I, 9, FALSE), IFERROR(VLOOKUP(A189, jueves!$A:$I, 9, FALSE), IFERROR(VLOOKUP(A189, miercoles!$A:$I, 9, FALSE), IFERROR(VLOOKUP(A189, martes!$A:$I, 9, FALSE), IFERROR(VLOOKUP(A189, lunes!$A:$I, 9, FALSE), VLOOKUP(A189, Configuracion!$A:$B, 2, FALSE)))))) -> #N/A | E189: =IF(C189="Venta", IFERROR(VLOOKUP(A189, Configuracion!$A:$D, 3, FALSE), 0), 0) -> 0 | F189: =E189*D189 -> 0 | H189: =IF(AND(G189="Gestor", A189<>""), VLOOKUP(A189, Configuracion!$A:$D, 4, FALSE), 0)*Tabla1027[[#This Row],[CANTIDAD]] -> 0 | I189: =IF(OR(A189="", D189=""), "", IF(C189="Entrada", B189+D189, IF(OR(C189="Venta", C189="Salida"), B189-D189, B189)))
B190: =IFERROR(VLOOKUP(A190, viernes!$A:$I, 9, FALSE), IFERROR(VLOOKUP(A190, jueves!$A:$I, 9, FALSE), IFERROR(VLOOKUP(A190, miercoles!$A:$I, 9, FALSE), IFERROR(VLOOKUP(A190, martes!$A:$I, 9, FALSE), IFERROR(VLOOKUP(A190, lunes!$A:$I, 9, FALSE), VLOOKUP(A190, Configuracion!$A:$B, 2, FALSE)))))) -> #N/A | E190: =IF(C190="Venta", IFERROR(VLOOKUP(A190, Configuracion!$A:$D, 3, FALSE), 0), 0) -> 0 | F190: =E190*D190 -> 0 | H190: =IF(AND(G190="Gestor", A190<>""), VLOOKUP(A190, Configuracion!$A:$D, 4, FALSE), 0)*Tabla1027[[#This Row],[CANTIDAD]] -> 0

Sheet COMPROBACION
A1: PRODUCTOS | B1: STOCK INICIAL | C1: VENTAS | D1: ENTRADAS | E1: SALIDAS | F1: STOCK CALCULADO | G1: STOCK FINAL | H1: PRECIO VENTA | I1: IMPORTE PRECIO ORIGINAL | J1: IMPORTE REAL | K1: DIFERENCIA DE IMPORTE
A2: =Configuracion!A81 -> LAVADORA 9 KG MILEXUS SEMI | B2: =VLOOKUP(A2, Configuracion!A:B, 2, FALSE) -> 6 | C2: =SUMIFS(lunes!D:D, lunes!A:A, A2, lunes!C:C, "VENTA") + SUMIFS(martes!D:D, martes!A:A, A2, martes!C:C, "VENTA") + SUMIFS(miercoles!D:D, miercoles!A:A, A2, miercoles!C:C, "VENTA") + SUMIFS(jueves!D:D, jueves!A:A, A2, jueves!C:C, "VENTA") + SUMIFS(viernes!D:D, viernes!A:A, A2, viernes!C:C, "VENTA") + SUMIFS(sabado!D:D, sabado!A:A, A2, sabado!C:C, "VENTA") -> 0 | D2: =SUMIFS(lunes!$D:$D, lunes!$A:$A, $A2, lunes!$C:$C, "ENTRADA") + SUMIFS(martes!$D:$D, martes!$A:$A, $A2, martes!$C:$C, "ENTRADA") + SUMIFS(miercoles!$D:$D, miercoles!$A:$A, $A2, miercoles!$C:$C, "ENTRADA") + SUMIFS(jueves!$D:$D, jueves!$A:$A, $A2, jueves!$C:$C, "ENTRADA") + SUMIFS(viernes!$D:$D, viernes!$A:$A, $A2, viernes!$C:$C, "ENTRADA") + SUMIFS(sabado!$D:$D, sabado!$A:$A, $A2, sabado!$C:$C, "ENTRADA") -> 0 | E2: =SUMIFS(lunes!$D:$D, lunes!$A:$A, $A2, lunes!$C:$C, "SALIDA") + SUMIFS(martes!$D:$D, martes!$A:$A, $A2, martes!$C:$C, "SALIDA") + SUMIFS(miercoles!$D:$D, miercoles!$A:$A, $A2, miercoles!$C:$C, "SALIDA") + SUMIFS(jueves!$D:$D, jueves!$A:$A, $A2, jueves!$C:$C, "SALIDA") + SUMIFS(viernes!$D:$D, viernes!$A:$A, $A2, viernes!$C:$C, "SALIDA") + SUMIFS(sabado!$D:$D, sabado!$A:$A, $A2, sabado!$C:$C, "SALIDA") -> 0 | F2: =B2-C2+D2-E2 -> 6 | G2: =IFERROR(VLOOKUP(A2, sabado!A:I, 9, 0), IFERROR(VLOOKUP(A2, viernes!A:I, 9, 0), IFERROR(VLOOKUP(A2, jueves!A:I, 9, 0), IFERROR(VLOOKUP(A2, miercoles!A:I, 9, 0), IFERROR(VLOOKUP(A2, martes!A:I, 9, 0), IFERROR(VLOOKUP(A2, lunes!A:I, 9, 0), B2)))))) -> 6 | H2: =VLOOKUP(A2, Configuracion!A:C, 3, FALSE) -> 235 | I2: =C2*H2 -> 0 | J2: =SUMIFS(lunes!$F:$F, lunes!$A:$A, $A2, lunes!$C:$C, "VENTA") + SUMIFS(martes!$F:$F, martes!$A:$A, $A2, martes!$C:$C, "VENTA") + SUMIFS(miercoles!$F:$F, miercoles!$A:$A, $A2, miercoles!$C:$C, "VENTA") + SUMIFS(jueves!$F:$F, jueves!$A:$A, $A2, jueves!$C:$C, "VENTA") + SUMIFS(viernes!$F:$F, viernes!$A:$A, $A2, viernes!$C:$C, "VENTA") + SUMIFS(sabado!$F:$F, sabado!$A:$A, $A2, sabado!$C:$C, "VENTA") -> 0 | K2: =I2-J2 -> 0
A3: =Configuracion!A17 -> BOCINA MILEXUS 8 PULGADAS | B3: =VLOOKUP(A3, Configuracion!A:B, 2, FALSE) -> 0 | C3: =SUMIFS(lunes!D:D, lunes!A:A, A3, lunes!C:C, "VENTA") + SUMIFS(martes!D:D, martes!A:A, A3, martes!C:C, "VENTA") + SUMIFS(miercoles!D:D, miercoles!A:A, A3, miercoles!C:C, "VENTA") + SUMIFS(jueves!D:D, jueves!A:A, A3, jueves!C:C, "VENTA") + SUMIFS(viernes!D:D, viernes!A:A, A3, viernes!C:C, "VENTA") + SUMIFS(sabado!D:D, sabado!A:A, A3, sabado!C:C, "VENTA") -> 0 | D3: =SUMIFS(lunes!$D:$D, lunes!$A:$A, $A3, lunes!$C:$C, "ENTRADA") + SUMIFS(martes!$D:$D, martes!$A:$A, $A3, martes!$C:$C, "ENTRADA") + SUMIFS(miercoles!$D:$D, miercoles!$A:$A, $A3, miercoles!$C:$C, "ENTRADA") + SUMIFS(jueves!$D:$D, jueves!$A:$A, $A3, jueves!$C:$C, "ENTRADA") + SUMIFS(viernes!$D:$D, viernes!$A:$A, $A3, viernes!$C:$C, "ENTRADA") + SUMIFS(sabado!$D:$D, sabado!$A:$A, $A3, sabado!$C:$C, "ENTRADA") -> 0 | E3: =SUMIFS(lunes!$D:$D, lunes!$A:$A, $A3, lunes!$C:$C, "SALIDA") + SUMIFS(martes!$D:$D, martes!$A:$A, $A3, martes!$C:$C, "SALIDA") + SUMIFS(miercoles!$D:$D, miercoles!$A:$A, $A3, miercoles!$C:$C, "SALIDA") + SUMIFS(jueves!$D:$D, jueves!$A:$A, $A3, jueves!$C:$C, "SALIDA") + SUMIFS(viernes!$D:$D, viernes!$A:$A, $A3, viernes!$C:$C, "SALIDA") + SUMIFS(sabado!$D:$D, sabado!$A:$A, $A3, sabado!$C:$C, "SALIDA") -> 0 | F3: =B3-C3+D3-E3 -> 0 | G3: =IFERROR(VLOOKUP(A3, sabado!A:I, 9, 0), IFERROR(VLOOKUP(A3, viernes!A:I, 9, 0), IFERROR(VLOOKUP(A3, jueves!A:I, 9, 0), IFERROR(VLOOKUP(A3, miercoles!A:I, 9, 0), IFERROR(VLOOKUP(A3, martes!A:I, 9, 0), IFERROR(VLOOKUP(A3, lunes!A:I, 9, 0), B3)))))) -> 0 | H3: =VLOOKUP(A3, Configuracion!A:C, 3, FALSE) -> 85 | I3: =C3*H3 -> 0 | J3: =SUMIFS(lunes!$F:$F, lunes!$A:$A, $A3, lunes!$C:$C, "VENTA") + SUMIFS(martes!$F:$F, martes!$A:$A, $A3, martes!$C:$C, "VENTA") + SUMIFS(miercoles!$F:$F, miercoles!$A:$A, $A3, miercoles!$C:$C, "VENTA") + SUMIFS(jueves!$F:$F, jueves!$A:$A, $A3, jueves!$C:$C, "VENTA") + SUMIFS(viernes!$F:$F, viernes!$A:$A, $A3, viernes!$C:$C, "VENTA") + SUMIFS(sabado!$F:$F, sabado!$A:$A, $A3, sabado!$C:$C, "VENTA") -> 0 | K3: =I3-J3 -> 0
A4: =Configuracion!A2 -> BOLSA DE CEMENTO BLANCO | B4: =VLOOKUP(A4, Configuracion!A:B, 2, FALSE) -> 0 | C4: =SUMIFS(lunes!D:D, lunes!A:A, A4, lunes!C:C, "VENTA") + SUMIFS(martes!D:D, martes!A:A, A4, martes!C:C, "VENTA") + SUMIFS(miercoles!D:D, miercoles!A:A, A4, miercoles!C:C, "VENTA") + SUMIFS(jueves!D:D, jueves!A:A, A4, jueves!C:C, "VENTA") + SUMIFS(viernes!D:D, viernes!A:A, A4, viernes!C:C, "VENTA") + SUMIFS(sabado!D:D, sabado!A:A, A4, sabado!C:C, "VENTA") -> 0 | D4: =SUMIFS(lunes!$D:$D, lunes!$A:$A, $A4, lunes!$C:$C, "ENTRADA") + SUMIFS(martes!$D:$D, martes!$A:$A, $A4, martes!$C:$C, "ENTRADA") + SUMIFS(miercoles!$D:$D, miercoles!$A:$A, $A4, miercoles!$C:$C, "ENTRADA") + SUMIFS(jueves!$D:$D, jueves!$A:$A, $A4, jueves!$C:$C, "ENTRADA") + SUMIFS(viernes!$D:$D, viernes!$A:$A, $A4, viernes!$C:$C, "ENTRADA") + SUMIFS(sabado!$D:$D, sabado!$A:$A, $A4, sabado!$C:$C, "ENTRADA") -> 0 | E4: =SUMIFS(lunes!$D:$D, lunes!$A:$A, $A4, lunes!$C:$C, "SALIDA") + SUMIFS(martes!$D:$D, martes!$A:$A, $A4, martes!$C:$C, "SALIDA") + SUMIFS(miercoles!$D:$D, miercoles!$A:$A, $A4, miercoles!$C:$C, "SALIDA") + SUMIFS(jueves!$D:$D, jueves!$A:$A, $A4, jueves!$C:$C, "SALIDA") + SUMIFS(viernes!$D:$D, viernes!$A:$A, $A4, viernes!$C:$C, "SALIDA") + SUMIFS(sabado!$D:$D, sabado!$A:$A, $A4, sabado!$C:$C, "SALIDA") -> 0 | F4: =B4-C4+D4-E4 -> 0 | G4: =IFERROR(VLOOKUP(A4, sabado!A:I, 9, 0), IFERROR(VLOOKUP(A4, viernes!A:I, 9, 0), IFERROR(VLOOKUP(A4, jueves!A:I, 9, 0), IFERROR(VLOOKUP(A4, miercoles!A:I, 9, 0), IFERROR(VLOOKUP(A4, martes!A:I, 9, 0), IFERROR(VLOOKUP(A4, lunes!A:I, 9, 0), B4)))))) -> 0 | H4: =VLOOKUP(A4, Configuracion!A:C, 3, FALSE) -> 2.86 | I4: =C4*H4 -> 0 | J4: =SUMIFS(lunes!$F:$F, lunes!$A:$A, $A4, lunes!$C:$C, "VENTA") + SUMIFS(martes!$F:$F, martes!$A:$A, $A4, martes!$C:$C, "VENTA") + SUMIFS(miercoles!$F:$F, miercoles!$A:$A, $A4, miercoles!$C:$C, "VENTA") + SUMIFS(jueves!$F:$F, jueves!$A:$A, $A4, jueves!$C:$C, "VENTA") + SUMIFS(viernes!$F:$F, viernes!$A:$A, $A4, viernes!$C:$C, "VENTA") + SUMIFS(sabado!$F:$F, sabado!$A:$A, $A4, sabado!$C:$C, "VENTA") -> 0 | K4: =I4-J4 -> 0 | M4: VENTA TOTAL SEMANAL
A5: =Configuracion!A3 -> BATERIA 5120W SACO | B5: =VLOOKUP(A5, Configuracion!A:B, 2, FALSE) -> 3 | C5: =SUMIFS(lunes!D:D, lunes!A:A, A5, lunes!C:C, "VENTA") + SUMIFS(martes!D:D, martes!A:A, A5, martes!C:C, "VENTA") + SUMIFS(miercoles!D:D, miercoles!A:A, A5, miercoles!C:C, "VENTA") + SUMIFS(jueves!D:D, jueves!A:A, A5, jueves!C:C, "VENTA") + SUMIFS(viernes!D:D, viernes!A:A, A5, viernes!C:C, "VENTA") + SUMIFS(sabado!D:D, sabado!A:A, A5, sabado!C:C, "VENTA") -> 0 | D5: =SUMIFS(lunes!$D:$D, lunes!$A:$A, $A5, lunes!$C:$C, "ENTRADA") + SUMIFS(martes!$D:$D, martes!$A:$A, $A5, martes!$C:$C, "ENTRADA") + SUMIFS(miercoles!$D:$D, miercoles!$A:$A, $A5, miercoles!$C:$C, "ENTRADA") + SUMIFS(jueves!$D:$D, jueves!$A:$A, $A5, jueves!$C:$C, "ENTRADA") + SUMIFS(viernes!$D:$D, viernes!$A:$A, $A5, viernes!$C:$C, "ENTRADA") + SUMIFS(sabado!$D:$D, sabado!$A:$A, $A5, sabado!$C:$C, "ENTRADA") -> 0 | E5: =SUMIFS(lunes!$D:$D, lunes!$A:$A, $A5, lunes!$C:$C, "SALIDA") + SUMIFS(martes!$D:$D, martes!$A:$A, $A5, martes!$C:$C, "SALIDA") + SUMIFS(miercoles!$D:$D, miercoles!$A:$A, $A5, miercoles!$C:$C, "SALIDA") + SUMIFS(jueves!$D:$D, jueves!$A:$A, $A5, jueves!$C:$C, "SALIDA") + SUMIFS(viernes!$D:$D, viernes!$A:$A, $A5, viernes!$C:$C, "SALIDA") + SUMIFS(sabado!$D:$D, sabado!$A:$A, $A5, sabado!$C:$C, "SALIDA") -> 0 | F5: =B5-C5+D5-E5 -> 3 | G5: =IFERROR(VLOOKUP(A5, sabado!A:I, 9, 0), IFERROR(VLOOKUP(A5, viernes!A:I, 9, 0), IFERROR(VLOOKUP(A5, jueves!A:I, 9, 0), IFERROR(VLOOKUP(A5, miercoles!A:I, 9, 0), IFERROR(VLOOKUP(A5, martes!A:I, 9, 0), IFERROR(VLOOKUP(A5, lunes!A:I, 9, 0), B5)))))) -> 3 | H5: =VLOOKUP(A5, Configuracion!A:C, 3, FALSE) -> 1100 | I5: =C5*H5 -> 0 | J5: =SUMIFS(lunes!$F:$F, lunes!$A:$A, $A5, lunes!$C:$C, "VENTA") + SUMIFS(martes!$F:$F, martes!$A:$A, $A5, martes!$C:$C, "VENTA") + SUMIFS(miercoles!$F:$F, miercoles!$A:$A, $A5, miercoles!$C:$C, "VENTA") + SUMIFS(jueves!$F:$F, jueves!$A:$A, $A5, jueves!$C:$C, "VENTA") + SUMIFS(viernes!$F:$F, viernes!$A:$A, $A5, viernes!$C:$C, "VENTA") + SUMIFS(sabado!$F:$F, sabado!$A:$A, $A5, sabado!$C:$C, "VENTA") -> 0 | K5: =I5-J5 -> 0 | M5: =lunes!P2+martes!P2+miercoles!P2+jueves!P2+viernes!P2+sabado!P2 -> 49275
A6: =Configuracion!A4 -> BATERIA SACO 7680W | B6: =VLOOKUP(A6, Configuracion!A:B, 2, FALSE) -> 3 | C6: =SUMIFS(lunes!D:D, lunes!A:A, A6, lunes!C:C, "VENTA") + SUMIFS(martes!D:D, martes!A:A, A6, martes!C:C, "VENTA") + SUMIFS(miercoles!D:D, miercoles!A:A, A6, miercoles!C:C, "VENTA") + SUMIFS(jueves!D:D, jueves!A:A, A6, jueves!C:C, "VENTA") + SUMIFS(viernes!D:D, viernes!A:A, A6, viernes!C:C, "VENTA") + SUMIFS(sabado!D:D, sabado!A:A, A6, sabado!C:C, "VENTA") -> 0 | D6: =SUMIFS(lunes!$D:$D, lunes!$A:$A, $A6, lunes!$C:$C, "ENTRADA") + SUMIFS(martes!$D:$D, martes!$A:$A, $A6, martes!$C:$C, "ENTRADA") + SUMIFS(miercoles!$D:$D, miercoles!$A:$A, $A6, miercoles!$C:$C, "ENTRADA") + SUMIFS(jueves!$D:$D, jueves!$A:$A, $A6, jueves!$C:$C, "ENTRADA") + SUMIFS(viernes!$D:$D, viernes!$A:$A, $A6, viernes!$C:$C, "ENTRADA") + SUMIFS(sabado!$D:$D, sabado!$A:$A, $A6, sabado!$C:$C, "ENTRADA") -> 0 | E6: =SUMIFS(lunes!$D:$D, lunes!$A:$A, $A6, lunes!$C:$C, "SALIDA") + SUMIFS(martes!$D:$D, martes!$A:$A, $A6, martes!$C:$C, "SALIDA") + SUMIFS(miercoles!$D:$D, miercoles!$A:$A, $A6, miercoles!$C:$C, "SALIDA") + SUMIFS(jueves!$D:$D, jueves!$A:$A, $A6, jueves!$C:$C, "SALIDA") + SUMIFS(viernes!$D:$D, viernes!$A:$A, $A6, viernes!$C:$C, "SALIDA") + SUMIFS(sabado!$D:$D, sabado!$A:$A, $A6, sabado!$C:$C, "SALIDA") -> 1 | F6: =B6-C6+D6-E6 -> 2 | G6: =IFERROR(VLOOKUP(A6, sabado!A:I, 9, 0), IFERROR(VLOOKUP(A6, viernes!A:I, 9, 0), IFERROR(VLOOKUP(A6, jueves!A:I, 9, 0), IFERROR(VLOOKUP(A6, miercoles!A:I, 9, 0), IFERROR(VLOOKUP(A6, martes!A:I, 9, 0), IFERROR(VLOOKUP(A6, lunes!A:I, 9, 0), B6)))))) -> 2 | H6: =VLOOKUP(A6, Configuracion!A:C, 3, FALSE) -> 1400 | I6: =C6*H6 -> 0 | J6: =SUMIFS(lunes!$F:$F, lunes!$A:$A, $A6, lunes!$C:$C, "VENTA") + SUMIFS(martes!$F:$F, martes!$A:$A, $A6, martes!$C:$C, "VENTA") + SUMIFS(miercoles!$F:$F, miercoles!$A:$A, $A6, miercoles!$C:$C, "VENTA") + SUMIFS(jueves!$F:$F, jueves!$A:$A, $A6, jueves!$C:$C, "VENTA") + SUMIFS(viernes!$F:$F, viernes!$A:$A, $A6, viernes!$C:$C, "VENTA") + SUMIFS(sabado!$F:$F, sabado!$A:$A, $A6, sabado!$C:$C, "VENTA") -> 0 | K6: =I6-J6 -> 0
A7: =Configuracion!A5 -> BATERIA DE 15360W SACO | B7: =VLOOKUP(A7, Configuracion!A:B, 2, FALSE) -> 2 | C7: =SUMIFS(lunes!D:D, lunes!A:A, A7, lunes!C:C, "VENTA") + SUMIFS(martes!D:D, martes!A:A, A7, martes!C:C, "VENTA") + SUMIFS(miercoles!D:D, miercoles!A:A, A7, miercoles!C:C, "VENTA") + SUMIFS(jueves!D:D, jueves!A:A, A7, jueves!C:C, "VENTA") + SUMIFS(viernes!D:D, viernes!A:A, A7, viernes!C:C, "VENTA") + SUMIFS(sabado!D:D, sabado!A:A, A7, sabado!C:C, "VENTA") -> 0 | D7: =SUMIFS(lunes!$D:$D, lunes!$A:$A, $A7, lunes!$C:$C, "ENTRADA") + SUMIFS(martes!$D:$D, martes!$A:$A, $A7, martes!$C:$C, "ENTRADA") + SUMIFS(miercoles!$D:$D, miercoles!$A:$A, $A7, miercoles!$C:$C, "ENTRADA") + SUMIFS(jueves!$D:$D, jueves!$A:$A, $A7, jueves!$C:$C, "ENTRADA") + SUMIFS(viernes!$D:$D, viernes!$A:$A, $A7, viernes!$C:$C, "ENTRADA") + SUMIFS(sabado!$D:$D, sabado!$A:$A, $A7, sabado!$C:$C, "ENTRADA") -> 0 | E7: =SUMIFS(lunes!$D:$D, lunes!$A:$A, $A7, lunes!$C:$C, "SALIDA") + SUMIFS(martes!$D:$D, martes!$A:$A, $A7, martes!$C:$C, "SALIDA") + SUMIFS(miercoles!$D:$D, miercoles!$A:$A, $A7, miercoles!$C:$C, "SALIDA") + SUMIFS(jueves!$D:$D, jueves!$A:$A, $A7, jueves!$C:$C, "SALIDA") + SUMIFS(viernes!$D:$D, viernes!$A:$A, $A7, viernes!$C:$C, "SALIDA") + SUMIFS(sabado!$D:$D, sabado!$A:$A, $A7, sabado!$C:$C, "SALIDA") -> 0 | F7: =B7-C7+D7-E7 -> 2 | G7: =IFERROR(VLOOKUP(A7, sabado!A:I, 9, 0), IFERROR(VLOOKUP(A7, viernes!A:I, 9, 0), IFERROR(VLOOKUP(A7, jueves!A:I, 9, 0), IFERROR(VLOOKUP(A7, miercoles!A:I, 9, 0), IFERROR(VLOOKUP(A7, martes!A:I, 9, 0), IFERROR(VLOOKUP(A7, lunes!A:I, 9, 0), B7)))))) -> 2 | H7: =VLOOKUP(A7, Configuracion!A:C, 3, FALSE) -> 0 | I7: =C7*H7 -> 0 | J7: =SUMIFS(lunes!$F:$F, lunes!$A:$A, $A7, lunes!$C:$C, "VENTA") + SUMIFS(martes!$F:$F, martes!$A:$A, $A7, martes!$C:$C, "VENTA") + SUMIFS(miercoles!$F:$F, miercoles!$A:$A, $A7, miercoles!$C:$C, "VENTA") + SUMIFS(jueves!$F:$F, jueves!$A:$A, $A7, jueves!$C:$C, "VENTA") + SUMIFS(viernes!$F:$F, viernes!$A:$A, $A7, viernes!$C:$C, "VENTA") + SUMIFS(sabado!$F:$F, sabado!$A:$A, $A7, sabado!$C:$C, "VENTA") -> 0 | K7: =I7-J7 -> 0
A8: =Configuracion!A6 -> BATERIA EXTRA 16K SACO | B8: =VLOOKUP(A8, Configuracion!A:B, 2, FALSE) -> 2 | C8: =SUMIFS(lunes!D:D, lunes!A:A, A8, lunes!C:C, "VENTA") + SUMIFS(martes!D:D, martes!A:A, A8, martes!C:C, "VENTA") + SUMIFS(miercoles!D:D, miercoles!A:A, A8, miercoles!C:C, "VENTA") + SUMIFS(jueves!D:D, jueves!A:A, A8, jueves!C:C, "VENTA") + SUMIFS(viernes!D:D, viernes!A:A, A8, viernes!C:C, "VENTA") + SUMIFS(sabado!D:D, sabado!A:A, A8, sabado!C:C, "VENTA") -> 0 | D8: =SUMIFS(lunes!$D:$D, lunes!$A:$A, $A8, lunes!$C:$C, "ENTRADA") + SUMIFS(martes!$D:$D, martes!$A:$A, $A8, martes!$C:$C, "ENTRADA") + SUMIFS(miercoles!$D:$D, miercoles!$A:$A, $A8, miercoles!$C:$C, "ENTRADA") + SUMIFS(jueves!$D:$D, jueves!$A:$A, $A8, jueves!$C:$C, "ENTRADA") + SUMIFS(viernes!$D:$D, viernes!$A:$A, $A8, viernes!$C:$C, "ENTRADA") + SUMIFS(sabado!$D:$D, sabado!$A:$A, $A8, sabado!$C:$C, "ENTRADA") -> 0 | E8: =SUMIFS(lunes!$D:$D, lunes!$A:$A, $A8, lunes!$C:$C, "SALIDA") + SUMIFS(martes!$D:$D, martes!$A:$A, $A8, martes!$C:$C, "SALIDA") + SUMIFS(miercoles!$D:$D, miercoles!$A:$A, $A8, miercoles!$C:$C, "SALIDA") + SUMIFS(jueves!$D:$D, jueves!$A:$A, $A8, jueves!$C:$C, "SALIDA") + SUMIFS(viernes!$D:$D, viernes!$A:$A, $A8, viernes!$C:$C, "SALIDA") + SUMIFS(sabado!$D:$D, sabado!$A:$A, $A8, sabado!$C:$C, "SALIDA") -> 0 | F8: =B8-C8+D8-E8 -> 2 | G8: =IFERROR(VLOOKUP(A8, sabado!A:I, 9, 0), IFERROR(VLOOKUP(A8, viernes!A:I, 9, 0), IFERROR(VLOOKUP(A8, jueves!A:I, 9, 0), IFERROR(VLOOKUP(A8, miercoles!A:I, 9, 0), IFERROR(VLOOKUP(A8, martes!A:I, 9, 0), IFERROR(VLOOKUP(A8, lunes!A:I, 9, 0), B8)))))) -> 2 | H8: =VLOOKUP(A8, Configuracion!A:C, 3, FALSE) -> 1300 | I8: =C8*H8 -> 0 | J8: =SUMIFS(lunes!$F:$F, lunes!$A:$A, $A8, lunes!$C:$C, "VENTA") + SUMIFS(martes!$F:$F, martes!$A:$A, $A8, martes!$C:$C, "VENTA") + SUMIFS(miercoles!$F:$F, miercoles!$A:$A, $A8, miercoles!$C:$C, "VENTA") + SUMIFS(jueves!$F:$F, jueves!$A:$A, $A8, jueves!$C:$C, "VENTA") + SUMIFS(viernes!$F:$F, viernes!$A:$A, $A8, viernes!$C:$C, "VENTA") + SUMIFS(sabado!$F:$F, sabado!$A:$A, $A8, sabado!$C:$C, "VENTA") -> 0 | K8: =I8-J8 -> 0 | M8: GASTOS SEMANALES
A9: =Configuracion!A7 -> BASE PARA PANELES GRANDES | B9: =VLOOKUP(A9, Configuracion!A:B, 2, FALSE) -> 10 | C9: =SUMIFS(lunes!D:D, lunes!A:A, A9, lunes!C:C, "VENTA") + SUMIFS(martes!D:D, martes!A:A, A9, martes!C:C, "VENTA") + SUMIFS(miercoles!D:D, miercoles!A:A, A9, miercoles!C:C, "VENTA") + SUMIFS(jueves!D:D, jueves!A:A, A9, jueves!C:C, "VENTA") + SUMIFS(viernes!D:D, viernes!A:A, A9, viernes!C:C, "VENTA") + SUMIFS(sabado!D:D, sabado!A:A, A9, sabado!C:C, "VENTA") -> 1 | D9: =SUMIFS(lunes!$D:$D, lunes!$A:$A, $A9, lunes!$C:$C, "ENTRADA") + SUMIFS(martes!$D:$D, martes!$A:$A, $A9, martes!$C:$C, "ENTRADA") + SUMIFS(miercoles!$D:$D, miercoles!$A:$A, $A9, miercoles!$C:$C, "ENTRADA") + SUMIFS(jueves!$D:$D, jueves!$A:$A, $A9, jueves!$C:$C, "ENTRADA") + SUMIFS(viernes!$D:$D, viernes!$A:$A, $A9, viernes!$C:$C, "ENTRADA") + SUMIFS(sabado!$D:$D, sabado!$A:$A, $A9, sabado!$C:$C, "ENTRADA") -> 0 | E9: =SUMIFS(lunes!$D:$D, lunes!$A:$A, $A9, lunes!$C:$C, "SALIDA") + SUMIFS(martes!$D:$D, martes!$A:$A, $A9, martes!$C:$C, "SALIDA") + SUMIFS(miercoles!$D:$D, miercoles!$A:$A, $A9, miercoles!$C:$C, "SALIDA") + SUMIFS(jueves!$D:$D, jueves!$A:$A, $A9, jueves!$C:$C, "SALIDA") + SUMIFS(viernes!$D:$D, viernes!$A:$A, $A9, viernes!$C:$C, "SALIDA") + SUMIFS(sabado!$D:$D, sabado!$A:$A, $A9, sabado!$C:$C, "SALIDA") -> 0 | F9: =B9-C9+D9-E9 -> 9 | G9: =IFERROR(VLOOKUP(A9, sabado!A:I, 9, 0), IFERROR(VLOOKUP(A9, viernes!A:I, 9, 0), IFERROR(VLOOKUP(A9, jueves!A:I, 9, 0), IFERROR(VLOOKUP(A9, miercoles!A:I, 9, 0), IFERROR(VLOOKUP(A9, martes!A:I, 9, 0), IFERROR(VLOOKUP(A9, lunes!A:I, 9, 0), B9)))))) -> 9 | H9: =VLOOKUP(A9, Configuracion!A:C, 3, FALSE) -> 100 | I9: =C9*H9 -> 100 | J9: =SUMIFS(lunes!$F:$F, lunes!$A:$A, $A9, lunes!$C:$C, "VENTA") + SUMIFS(martes!$F:$F, martes!$A:$A, $A9, martes!$C:$C, "VENTA") + SUMIFS(miercoles!$F:$F, miercoles!$A:$A, $A9, miercoles!$C:$C, "VENTA") + SUMIFS(jueves!$F:$F, jueves!$A:$A, $A9, jueves!$C:$C, "VENTA") + SUMIFS(viernes!$F:$F, viernes!$A:$A, $A9, viernes!$C:$C, "VENTA") + SUMIFS(sabado!$F:$F, sabado!$A:$A, $A9, sabado!$C:$C, "VENTA") -> 100 | K9: =I9-J9 -> 0 | M9: =lunes!P22 + martes!P23 + miercoles!P22 + jueves!P22 + viernes!P22 + sabado!P22 -> 0
A10: =Configuracion!A8 -> BASE PARA PANELES | B10: =VLOOKUP(A10, Configuracion!A:B, 2, FALSE) -> 0 | C10: =SUMIFS(lunes!D:D, lunes!A:A, A10, lunes!C:C, "VENTA") + SUMIFS(martes!D:D, martes!A:A, A10, martes!C:C, "VENTA") + SUMIFS(miercoles!D:D, miercoles!A:A, A10, miercoles!C:C, "VENTA") + SUMIFS(jueves!D:D, jueves!A:A, A10, jueves!C:C, "VENTA") + SUMIFS(viernes!D:D, viernes!A:A, A10, viernes!C:C, "VENTA") + SUMIFS(sabado!D:D, sabado!A:A, A10, sabado!C:C, "VENTA") -> 0 | D10: =SUMIFS(lunes!$D:$D, lunes!$A:$A, $A10, lunes!$C:$C, "ENTRADA") + SUMIFS(martes!$D:$D, martes!$A:$A, $A10, martes!$C:$C, "ENTRADA") + SUMIFS(miercoles!$D:$D, miercoles!$A:$A, $A10, miercoles!$C:$C, "ENTRADA") + SUMIFS(jueves!$D:$D, jueves!$A:$A, $A10, jueves!$C:$C, "ENTRADA") + SUMIFS(viernes!$D:$D, viernes!$A:$A, $A10, viernes!$C:$C, "ENTRADA") + SUMIFS(sabado!$D:$D, sabado!$A:$A, $A10, sabado!$C:$C, "ENTRADA") -> 0 | E10: =SUMIFS(lunes!$D:$D, lunes!$A:$A, $A10, lunes!$C:$C, "SALIDA") + SUMIFS(martes!$D:$D, martes!$A:$A, $A10, martes!$C:$C, "SALIDA") + SUMIFS(miercoles!$D:$D, miercoles!$A:$A, $A10, miercoles!$C:$C, "SALIDA") + SUMIFS(jueves!$D:$D, jueves!$A:$A, $A10, jueves!$C:$C, "SALIDA") + SUMIFS(viernes!$D:$D, viernes!$A:$A, $A10, viernes!$C:$C, "SALIDA") + SUMIFS(sabado!$D:$D, sabado!$A:$A, $A10, sabado!$C:$C, "SALIDA") -> 0 | F10: =B10-C10+D10-E10 -> 0 | G10: =IFERROR(VLOOKUP(A10, sabado!A:I, 9, 0), IFERROR(VLOOKUP(A10, viernes!A:I, 9, 0), IFERROR(VLOOKUP(A10, jueves!A:I, 9, 0), IFERROR(VLOOKUP(A10, miercoles!A:I, 9, 0), IFERROR(VLOOKUP(A10, martes!A:I, 9, 0), IFERROR(VLOOKUP(A10, lunes!A:I, 9, 0), B10)))))) -> 0 | H10: =VLOOKUP(A10, Configuracion!A:C, 3, FALSE) -> 50 | I10: =C10*H10 -> 0 | J10: =SUMIFS(lunes!$F:$F, lunes!$A:$A, $A10, lunes!$C:$C, "VENTA") + SUMIFS(martes!$F:$F, martes!$A:$A, $A10, martes!$C:$C, "VENTA") + SUMIFS(miercoles!$F:$F, miercoles!$A:$A, $A10, miercoles!$C:$C, "VENTA") + SUMIFS(jueves!$F:$F, jueves!$A:$A, $A10, jueves!$C:$C, "VENTA") + SUMIFS(viernes!$F:$F, viernes!$A:$A, $A10, viernes!$C:$C, "VENTA") + SUMIFS(sabado!$F:$F, sabado!$A:$A, $A10, sabado!$C:$C, "VENTA") -> 0 | K10: =I10-J10 -> 0
A11: =Configuracion!A9 -> BASE FIJA PARA TV 32'' - 86'' | B11: =VLOOKUP(A11, Configuracion!A:B, 2, FALSE) -> 10 | C11: =SUMIFS(lunes!D:D, lunes!A:A, A11, lunes!C:C, "VENTA") + SUMIFS(martes!D:D, martes!A:A, A11, martes!C:C, "VENTA") + SUMIFS(miercoles!D:D, miercoles!A:A, A11, miercoles!C:C, "VENTA") + SUMIFS(jueves!D:D, jueves!A:A, A11, jueves!C:C, "VENTA") + SUMIFS(viernes!D:D, viernes!A:A, A11, viernes!C:C, "VENTA") + SUMIFS(sabado!D:D, sabado!A:A, A11, sabado!C:C, "VENTA") -> 1 | D11: =SUMIFS(lunes!$D:$D, lunes!$A:$A, $A11, lunes!$C:$C, "ENTRADA") + SUMIFS(martes!$D:$D, martes!$A:$A, $A11, martes!$C:$C, "ENTRADA") + SUMIFS(miercoles!$D:$D, miercoles!$A:$A, $A11, miercoles!$C:$C, "ENTRADA") + SUMIFS(jueves!$D:$D, jueves!$A:$A, $A11, jueves!$C:$C, "ENTRADA") + SUMIFS(viernes!$D:$D, viernes!$A:$A, $A11, viernes!$C:$C, "ENTRADA") + SUMIFS(sabado!$D:$D, sabado!$A:$A, $A11, sabado!$C:$C, "ENTRADA") -> 0 | E11: =SUMIFS(lunes!$D:$D, lunes!$A:$A, $A11, lunes!$C:$C, "SALIDA") + SUMIFS(martes!$D:$D, martes!$A:$A, $A11, martes!$C:$C, "SALIDA") + SUMIFS(miercoles!$D:$D, miercoles!$A:$A, $A11, miercoles!$C:$C, "SALIDA") + SUMIFS(jueves!$D:$D, jueves!$A:$A, $A11, jueves!$C:$C, "SALIDA") + SUMIFS(viernes!$D:$D, viernes!$A:$A, $A11, viernes!$C:$C, "SALIDA") + SUMIFS(sabado!$D:$D, sabado!$A:$A, $A11, sabado!$C:$C, "SALIDA") -> 0 | F11: =B11-C11+D11-E11 -> 9 | G11: =IFERROR(VLOOKUP(A11, sabado!A:I, 9, 0), IFERROR(VLOOKUP(A11, viernes!A:I, 9, 0), IFERROR(VLOOKUP(A11, jueves!A:I, 9, 0), IFERROR(VLOOKUP(A11, miercoles!A:I, 9, 0), IFERROR(VLOOKUP(A11, martes!A:I, 9, 0), IFERROR(VLOOKUP(A11, lunes!A:I, 9, 0), B11)))))) -> 9 | H11: =VLOOKUP(A11, Configuracion!A:C, 3, FALSE) -> 20 | I11: =C11*H11 -> 20 | J11: =SUMIFS(lunes!$F:$F, lunes!$A:$A, $A11, lunes!$C:$C, "VENTA") + SUMIFS(martes!$F:$F, martes!$A:$A, $A11, martes!$C:$C, "VENTA") + SUMIFS(miercoles!$F:$F, miercoles!$A:$A, $A11, miercoles!$C:$C, "VENTA") + SUMIFS(jueves!$F:$F, jueves!$A:$A, $A11, jueves!$C:$C, "VENTA") + SUMIFS(viernes!$F:$F, viernes!$A:$A, $A11, viernes!$C:$C, "VENTA") + SUMIFS(sabado!$F:$F, sabado!$A:$A, $A11, sabado!$C:$C, "VENTA") -> 20 | K11: =I11-J11 -> 0
A12: =Configuracion!A10 -> BASE GIRATORIA | B12: =VLOOKUP(A12, Configuracion!A:B, 2, FALSE) -> 8 | C12: =SUMIFS(lunes!D:D, lunes!A:A, A12, lunes!C:C, "VENTA") + SUMIFS(martes!D:D, martes!A:A, A12, martes!C:C, "VENTA") + SUMIFS(miercoles!D:D, miercoles!A:A, A12, miercoles!C:C, "VENTA") + SUMIFS(jueves!D:D, jueves!A:A, A12, jueves!C:C, "VENTA") + SUMIFS(viernes!D:D, viernes!A:A, A12, viernes!C:C, "VENTA") + SUMIFS(sabado!D:D, sabado!A:A, A12, sabado!C:C, "VENTA") -> 0 | D12: =SUMIFS(lunes!$D:$D, lunes!$A:$A, $A12, lunes!$C:$C, "ENTRADA") + SUMIFS(martes!$D:$D, martes!$A:$A, $A12, martes!$C:$C, "ENTRADA") + SUMIFS(miercoles!$D:$D, miercoles!$A:$A, $A12, miercoles!$C:$C, "ENTRADA") + SUMIFS(jueves!$D:$D, jueves!$A:$A, $A12, jueves!$C:$C, "ENTRADA") + SUMIFS(viernes!$D:$D, viernes!$A:$A, $A12, viernes!$C:$C, "ENTRADA") + SUMIFS(sabado!$D:$D, sabado!$A:$A, $A12, sabado!$C:$C, "ENTRADA") -> 0 | E12: =SUMIFS(lunes!$D:$D, lunes!$A:$A, $A12, lunes!$C:$C, "SALIDA") + SUMIFS(martes!$D:$D, martes!$A:$A, $A12, martes!$C:$C, "SALIDA") + SUMIFS(miercoles!$D:$D, miercoles!$A:$A, $A12, miercoles!$C:$C, "SALIDA") + SUMIFS(jueves!$D:$D, jueves!$A:$A, $A12, jueves!$C:$C, "SALIDA") + SUMIFS(viernes!$D:$D, viernes!$A:$A, $A12, viernes!$C:$C, "SALIDA") + SUMIFS(sabado!$D:$D, sabado!$A:$A, $A12, sabado!$C:$C, "SALIDA") -> 0 | F12: =B12-C12+D12-E12 -> 8 | G12: =IFERROR(VLOOKUP(A12, sabado!A:I, 9, 0), IFERROR(VLOOKUP(A12, viernes!A:I, 9, 0), IFERROR(VLOOKUP(A12, jueves!A:I, 9, 0), IFERROR(VLOOKUP(A12, miercoles!A:I, 9, 0), IFERROR(VLOOKUP(A12, martes!A:I, 9, 0), IFERROR(VLOOKUP(A12, lunes!A:I, 9, 0), B12)))))) -> 8 | H12: =VLOOKUP(A12, Configuracion!A:C, 3, FALSE) -> 25 | I12: =C12*H12 -> 0 | J12: =SUMIFS(lunes!$F:$F, lunes!$A:$A, $A12, lunes!$C:$C, "VENTA") + SUMIFS(martes!$F:$F, martes!$A:$A, $A12, martes!$C:$C, "VENTA") + SUMIFS(miercoles!$F:$F, miercoles!$A:$A, $A12, miercoles!$C:$C, "VENTA") + SUMIFS(jueves!$F:$F, jueves!$A:$A, $A12, jueves!$C:$C, "VENTA") + SUMIFS(viernes!$F:$F, viernes!$A:$A, $A12, viernes!$C:$C, "VENTA") + SUMIFS(sabado!$F:$F, sabado!$A:$A, $A12, sabado!$C:$C, "VENTA") -> 0 | K12: =I12-J12 -> 0 | M12: COMISIONES TOTALES
A13: =Configuracion!A11 -> BATERIA 16K SACO | B13: =VLOOKUP(A13, Configuracion!A:B, 2, FALSE) -> 0 | C13: =SUMIFS(lunes!D:D, lunes!A:A, A13, lunes!C:C, "VENTA") + SUMIFS(martes!D:D, martes!A:A, A13, martes!C:C, "VENTA") + SUMIFS(miercoles!D:D, miercoles!A:A, A13, miercoles!C:C, "VENTA") + SUMIFS(jueves!D:D, jueves!A:A, A13, jueves!C:C, "VENTA") + SUMIFS(viernes!D:D, viernes!A:A, A13, viernes!C:C, "VENTA") + SUMIFS(sabado!D:D, sabado!A:A, A13, sabado!C:C, "VENTA") -> 0 | D13: =SUMIFS(lunes!$D:$D, lunes!$A:$A, $A13, lunes!$C:$C, "ENTRADA") + SUMIFS(martes!$D:$D, martes!$A:$A, $A13, martes!$C:$C, "ENTRADA") + SUMIFS(miercoles!$D:$D, miercoles!$A:$A, $A13, miercoles!$C:$C, "ENTRADA") + SUMIFS(jueves!$D:$D, jueves!$A:$A, $A13, jueves!$C:$C, "ENTRADA") + SUMIFS(viernes!$D:$D, viernes!$A:$A, $A13, viernes!$C:$C, "ENTRADA") + SUMIFS(sabado!$D:$D, sabado!$A:$A, $A13, sabado!$C:$C, "ENTRADA") -> 0 | E13: =SUMIFS(lunes!$D:$D, lunes!$A:$A, $A13, lunes!$C:$C, "SALIDA") + SUMIFS(martes!$D:$D, martes!$A:$A, $A13, martes!$C:$C, "SALIDA") + SUMIFS(miercoles!$D:$D, miercoles!$A:$A, $A13, miercoles!$C:$C, "SALIDA") + SUMIFS(jueves!$D:$D, jueves!$A:$A, $A13, jueves!$C:$C, "SALIDA") + SUMIFS(viernes!$D:$D, viernes!$A:$A, $A13, viernes!$C:$C, "SALIDA") + SUMIFS(sabado!$D:$D, sabado!$A:$A, $A13, sabado!$C:$C, "SALIDA") -> 0 | F13: =B13-C13+D13-E13 -> 0 | G13: =IFERROR(VLOOKUP(A13, sabado!A:I, 9, 0), IFERROR(VLOOKUP(A13, viernes!A:I, 9, 0), IFERROR(VLOOKUP(A13, jueves!A:I, 9, 0), IFERROR(VLOOKUP(A13, miercoles!A:I, 9, 0), IFERROR(VLOOKUP(A13, martes!A:I, 9, 0), IFERROR(VLOOKUP(A13, lunes!A:I, 9, 0), B13)))))) -> 0 | H13: =VLOOKUP(A13, Configuracion!A:C, 3, FALSE) -> 2500 | I13: =C13*H13 -> 0 | J13: =SUMIFS(lunes!$F:$F, lunes!$A:$A, $A13, lunes!$C:$C, "VENTA") + SUMIFS(martes!$F:$F, martes!$A:$A, $A13, martes!$C:$C, "VENTA") + SUMIFS(miercoles!$F:$F, miercoles!$A:$A, $A13, miercoles!$C:$C, "VENTA") + SUMIFS(jueves!$F:$F, jueves!$A:$A, $A13, jueves!$C:$C, "VENTA") + SUMIFS(viernes!$F:$F, viernes!$A:$A, $A13, viernes!$C:$C, "VENTA") + SUMIFS(sabado!$F:$F, sabado!$A:$A, $A13, sabado!$C:$C, "VENTA") -> 0 | K13: =I13-J13 -> 0 | M13: =lunes!O23 + martes!O24 + miercoles!O23 + jueves!O23 + viernes!O23 + sabado!O23 -> 43000
A14: =Configuracion!A12 -> BREKE 63A SENCILLO | B14: =VLOOKUP(A14, Configuracion!A:B, 2, FALSE) -> 1 | C14: =SUMIFS(lunes!D:D, lunes!A:A, A14, lunes!C:C, "VENTA") + SUMIFS(martes!D:D, martes!A:A, A14, martes!C:C, "VENTA") + SUMIFS(miercoles!D:D, miercoles!A:A, A14, miercoles!C:C, "VENTA") + SUMIFS(jueves!D:D, jueves!A:A, A14, jueves!C:C, "VENTA") + SUMIFS(viernes!D:D, viernes!A:A, A14, viernes!C:C, "VENTA") + SUMIFS(sabado!D:D, sabado!A:A, A14, sabado!C:C, "VENTA") -> 0 | D14: =SUMIFS(lunes!$D:$D, lunes!$A:$A, $A14, lunes!$C:$C, "ENTRADA") + SUMIFS(martes!$D:$D, martes!$A:$A, $A14, martes!$C:$C, "ENTRADA") + SUMIFS(miercoles!$D:$D, miercoles!$A:$A, $A14, miercoles!$C:$C, "ENTRADA") + SUMIFS(jueves!$D:$D, jueves!$A:$A, $A14, jueves!$C:$C, "ENTRADA") + SUMIFS(viernes!$D:$D, viernes!$A:$A, $A14, viernes!$C:$C, "ENTRADA") + SUMIFS(sabado!$D:$D, sabado!$A:$A, $A14, sabado!$C:$C, "ENTRADA") -> 0 | E14: =SUMIFS(lunes!$D:$D, lunes!$A:$A, $A14, lunes!$C:$C, "SALIDA") + SUMIFS(martes!$D:$D, martes!$A:$A, $A14, martes!$C:$C, "SALIDA") + SUMIFS(miercoles!$D:$D, miercoles!$A:$A, $A14, miercoles!$C:$C, "SALIDA") + SUMIFS(jueves!$D:$D, jueves!$A:$A, $A14, jueves!$C:$C, "SALIDA") + SUMIFS(viernes!$D:$D, viernes!$A:$A, $A14, viernes!$C:$C, "SALIDA") + SUMIFS(sabado!$D:$D, sabado!$A:$A, $A14, sabado!$C:$C, "SALIDA") -> 0 | F14: =B14-C14+D14-E14 -> 1 | G14: =IFERROR(VLOOKUP(A14, sabado!A:I, 9, 0), IFERROR(VLOOKUP(A14, viernes!A:I, 9, 0), IFERROR(VLOOKUP(A14, jueves!A:I, 9, 0), IFERROR(VLOOKUP(A14, miercoles!A:I, 9, 0), IFERROR(VLOOKUP(A14, martes!A:I, 9, 0), IFERROR(VLOOKUP(A14, lunes!A:I, 9, 0), B14)))))) -> 1 | H14: =VLOOKUP(A14, Configuracion!A:C, 3, FALSE) -> 20 | I14: =C14*H14 -> 0 | J14: =SUMIFS(lunes!$F:$F, lunes!$A:$A, $A14, lunes!$C:$C, "VENTA") + SUMIFS(martes!$F:$F, martes!$A:$A, $A14, martes!$C:$C, "VENTA") + SUMIFS(miercoles!$F:$F, miercoles!$A:$A, $A14, miercoles!$C:$C, "VENTA") + SUMIFS(jueves!$F:$F, jueves!$A:$A, $A14, jueves!$C:$C, "VENTA") + SUMIFS(viernes!$F:$F, viernes!$A:$A, $A14, viernes!$C:$C, "VENTA") + SUMIFS(sabado!$F:$F, sabado!$A:$A, $A14, sabado!$C:$C, "VENTA") -> 0 | K14: =I14-J14 -> 0
A15: =Configuracion!A13 -> BATERIA MUST 10.25 KW | B15: =VLOOKUP(A15, Configuracion!A:B, 2, FALSE) -> 1 | C15: =SUMIFS(lunes!D:D, lunes!A:A, A15, lunes!C:C, "VENTA") + SUMIFS(martes!D:D, martes!A:A, A15, martes!C:C, "VENTA") + SUMIFS(miercoles!D:D, miercoles!A:A, A15, miercoles!C:C, "VENTA") + SUMIFS(jueves!D:D, jueves!A:A, A15, jueves!C:C, "VENTA") + SUMIFS(viernes!D:D, viernes!A:A, A15, viernes!C:C, "VENTA") + SUMIFS(sabado!D:D, sabado!A:A, A15, sabado!C:C, "VENTA") -> 1 | D15: =SUMIFS(lunes!$D:$D, lunes!$A:$A, $A15, lunes!$C:$C, "ENTRADA") + SUMIFS(martes!$D:$D, martes!$A:$A, $A15, martes!$C:$C, "ENTRADA") + SUMIFS(miercoles!$D:$D, miercoles!$A:$A, $A15, miercoles!$C:$C, "ENTRADA") + SUMIFS(jueves!$D:$D, jueves!$A:$A, $A15, jueves!$C:$C, "ENTRADA") + SUMIFS(viernes!$D:$D, viernes!$A:$A, $A15, viernes!$C:$C, "ENTRADA") + SUMIFS(sabado!$D:$D, sabado!$A:$A, $A15, sabado!$C:$C, "ENTRADA") -> 1 | E15: =SUMIFS(lunes!$D:$D, lunes!$A:$A, $A15, lunes!$C:$C, "SALIDA") + SUMIFS(martes!$D:$D, martes!$A:$A, $A15, martes!$C:$C, "SALIDA") + SUMIFS(miercoles!$D:$D, miercoles!$A:$A, $A15, miercoles!$C:$C, "SALIDA") + SUMIFS(jueves!$D:$D, jueves!$A:$A, $A15, jueves!$C:$C, "SALIDA") + SUMIFS(viernes!$D:$D, viernes!$A:$A, $A15, viernes!$C:$C, "SALIDA") + SUMIFS(sabado!$D:$D, sabado!$A:$A, $A15, sabado!$C:$C, "SALIDA") -> 0 | F15: =B15-C15+D15-E15 -> 1 | G15: =IFERROR(VLOOKUP(A15, sabado!A:I, 9, 0), IFERROR(VLOOKUP(A15, viernes!A:I, 9, 0), IFERROR(VLOOKUP(A15, jueves!A:I, 9, 0), IFERROR(VLOOKUP(A15, miercoles!A:I, 9, 0), IFERROR(VLOOKUP(A15, martes!A:I, 9, 0), IFERROR(VLOOKUP(A15, lunes!A:I, 9, 0), B15)))))) -> 1 | H15: =VLOOKUP(A15, Configuracion!A:C, 3, FALSE) -> 2050 | I15: =C15*H15 -> 2050 | J15: =SUMIFS(lunes!$F:$F, lunes!$A:$A, $A15, lunes!$C:$C, "VENTA") + SUMIFS(martes!$F:$F, martes!$A:$A, $A15, martes!$C:$C, "VENTA") + SUMIFS(miercoles!$F:$F, miercoles!$A:$A, $A15, miercoles!$C:$C, "VENTA") + SUMIFS(jueves!$F:$F, jueves!$A:$A, $A15, jueves!$C:$C, "VENTA") + SUMIFS(viernes!$F:$F, viernes!$A:$A, $A15, viernes!$C:$C, "VENTA") + SUMIFS(sabado!$F:$F, sabado!$A:$A, $A15, sabado!$C:$C, "VENTA") -> 2050 | K15: =I15-J15 -> 0
A16: =Configuracion!A14 -> BREKE 63A DOBLE TIR | B16: =VLOOKUP(A16, Configuracion!A:B, 2, FALSE) -> 0 | C16: =SUMIFS(lunes!D:D, lunes!A:A, A16, lunes!C:C, "VENTA") + SUMIFS(martes!D:D, martes!A:A, A16, martes!C:C, "VENTA") + SUMIFS(miercoles!D:D, miercoles!A:A, A16, miercoles!C:C, "VENTA") + SUMIFS(jueves!D:D, jueves!A:A, A16, jueves!C:C, "VENTA") + SUMIFS(viernes!D:D, viernes!A:A, A16, viernes!C:C, "VENTA") + SUMIFS(sabado!D:D, sabado!A:A, A16, sabado!C:C, "VENTA") -> 0 | D16: =SUMIFS(lunes!$D:$D, lunes!$A:$A, $A16, lunes!$C:$C, "ENTRADA") + SUMIFS(martes!$D:$D, martes!$A:$A, $A16, martes!$C:$C, "ENTRADA") + SUMIFS(miercoles!$D:$D, miercoles!$A:$A, $A16, miercoles!$C:$C, "ENTRADA") + SUMIFS(jueves!$D:$D, jueves!$A:$A, $A16, jueves!$C:$C, "ENTRADA") + SUMIFS(viernes!$D:$D, viernes!$A:$A, $A16, viernes!$C:$C, "ENTRADA") + SUMIFS(sabado!$D:$D, sabado!$A:$A, $A16, sabado!$C:$C, "ENTRADA") -> 0 | E16: =SUMIFS(lunes!$D:$D, lunes!$A:$A, $A16, lunes!$C:$C, "SALIDA") + SUMIFS(martes!$D:$D, martes!$A:$A, $A16, martes!$C:$C, "SALIDA") + SUMIFS(miercoles!$D:$D, miercoles!$A:$A, $A16, miercoles!$C:$C, "SALIDA") + SUMIFS(jueves!$D:$D, jueves!$A:$A, $A16, jueves!$C:$C, "SALIDA") + SUMIFS(viernes!$D:$D, viernes!$A:$A, $A16, viernes!$C:$C, "SALIDA") + SUMIFS(sabado!$D:$D, sabado!$A:$A, $A16, sabado!$C:$C, "SALIDA") -> 0 | F16: =B16-C16+D16-E16 -> 0 | G16: =IFERROR(VLOOKUP(A16, sabado!A:I, 9, 0), IFERROR(VLOOKUP(A16, viernes!A:I, 9, 0), IFERROR(VLOOKUP(A16, jueves!A:I, 9, 0), IFERROR(VLOOKUP(A16, miercoles!A:I, 9, 0), IFERROR(VLOOKUP(A16, martes!A:I, 9, 0), IFERROR(VLOOKUP(A16, lunes!A:I, 9, 0), B16)))))) -> 0 | H16: =VLOOKUP(A16, Configuracion!A:C, 3, FALSE) -> 0 | I16: =C16*H16 -> 0 | J16: =SUMIFS(lunes!$F:$F, lunes!$A:$A, $A16, lunes!$C:$C, "VENTA") + SUMIFS(martes!$F:$F, martes!$A:$A, $A16, martes!$C:$C, "VENTA") + SUMIFS(miercoles!$F:$F, miercoles!$A:$A, $A16, miercoles!$C:$C, "VENTA") + SUMIFS(jueves!$F:$F, jueves!$A:$A, $A16, jueves!$C:$C, "VENTA") + SUMIFS(viernes!$F:$F, viernes!$A:$A, $A16, viernes!$C:$C, "VENTA") + SUMIFS(sabado!$F:$F, sabado!$A:$A, $A16, sabado!$C:$C, "VENTA") -> 0 | K16: =I16-J16 -> 0 | M16: DOMICILIO SEMANAL
A17: =Configuracion!A15 -> BREKE 32A DOBLE | B17: =VLOOKUP(A17, Configuracion!A:B, 2, FALSE) -> 0 | C17: =SUMIFS(lunes!D:D, lunes!A:A, A17, lunes!C:C, "VENTA") + SUMIFS(martes!D:D, martes!A:A, A17, martes!C:C, "VENTA") + SUMIFS(miercoles!D:D, miercoles!A:A, A17, miercoles!C:C, "VENTA") + SUMIFS(jueves!D:D, jueves!A:A, A17, jueves!C:C, "VENTA") + SUMIFS(viernes!D:D, viernes!A:A, A17, viernes!C:C, "VENTA") + SUMIFS(sabado!D:D, sabado!A:A, A17, sabado!C:C, "VENTA") -> 0 | D17: =SUMIFS(lunes!$D:$D, lunes!$A:$A, $A17, lunes!$C:$C, "ENTRADA") + SUMIFS(martes!$D:$D, martes!$A:$A, $A17, martes!$C:$C, "ENTRADA") + SUMIFS(miercoles!$D:$D, miercoles!$A:$A, $A17, miercoles!$C:$C, "ENTRADA") + SUMIFS(jueves!$D:$D, jueves!$A:$A, $A17, jueves!$C:$C, "ENTRADA") + SUMIFS(viernes!$D:$D, viernes!$A:$A, $A17, viernes!$C:$C, "ENTRADA") + SUMIFS(sabado!$D:$D, sabado!$A:$A, $A17, sabado!$C:$C, "ENTRADA") -> 0 | E17: =SUMIFS(lunes!$D:$D, lunes!$A:$A, $A17, lunes!$C:$C, "SALIDA") + SUMIFS(martes!$D:$D, martes!$A:$A, $A17, martes!$C:$C, "SALIDA") + SUMIFS(miercoles!$D:$D, miercoles!$A:$A, $A17, miercoles!$C:$C, "SALIDA") + SUMIFS(jueves!$D:$D, jueves!$A:$A, $A17, jueves!$C:$C, "SALIDA") + SUMIFS(viernes!$D:$D, viernes!$A:$A, $A17, viernes!$C:$C, "SALIDA") + SUMIFS(sabado!$D:$D, sabado!$A:$A, $A17, sabado!$C:$C, "SALIDA") -> 0 | F17: =B17-C17+D17-E17 -> 0 | G17: =IFERROR(VLOOKUP(A17, sabado!A:I, 9, 0), IFERROR(VLOOKUP(A17, viernes!A:I, 9, 0), IFERROR(VLOOKUP(A17, jueves!A:I, 9, 0), IFERROR(VLOOKUP(A17, miercoles!A:I, 9, 0), IFERROR(VLOOKUP(A17, martes!A:I, 9, 0), IFERROR(VLOOKUP(A17, lunes!A:I, 9, 0), B17)))))) -> 0 | H17: =VLOOKUP(A17, Configuracion!A:C, 3, FALSE) -> 0 | I17: =C17*H17 -> 0 | J17: =SUMIFS(lunes!$F:$F, lunes!$A:$A, $A17, lunes!$C:$C, "VENTA") + SUMIFS(martes!$F:$F, martes!$A:$A, $A17, martes!$C:$C, "VENTA") + SUMIFS(miercoles!$F:$F, miercoles!$A:$A, $A17, miercoles!$C:$C, "VENTA") + SUMIFS(jueves!$F:$F, jueves!$A:$A, $A17, jueves!$C:$C, "VENTA") + SUMIFS(viernes!$F:$F, viernes!$A:$A, $A17, viernes!$C:$C, "VENTA") + SUMIFS(sabado!$F:$F, sabado!$A:$A, $A17, sabado!$C:$C, "VENTA") -> 0 | K17: =I17-J17 -> 0 | M17: =lunes!O21 + martes!O22 + miercoles!O21 + jueves!O21 + viernes!O21 + sabado!PO21 -> 11000
A18: =Configuracion!A16 -> BOCINA BOOM 8 PULGADAS | B18: =VLOOKUP(A18, Configuracion!A:B, 2, FALSE) -> 0 | C18: =SUMIFS(lunes!D:D, lunes!A:A, A18, lunes!C:C, "VENTA") + SUMIFS(martes!D:D, martes!A:A, A18, martes!C:C, "VENTA") + SUMIFS(miercoles!D:D, miercoles!A:A, A18, miercoles!C:C, "VENTA") + SUMIFS(jueves!D:D, jueves!A:A, A18, jueves!C:C, "VENTA") + SUMIFS(viernes!D:D, viernes!A:A, A18, viernes!C:C, "VENTA") + SUMIFS(sabado!D:D, sabado!A:A, A18, sabado!C:C, "VENTA") -> 0 | D18: =SUMIFS(lunes!$D:$D, lunes!$A:$A, $A18, lunes!$C:$C, "ENTRADA") + SUMIFS(martes!$D:$D, martes!$A:$A, $A18, martes!$C:$C, "ENTRADA") + SUMIFS(miercoles!$D:$D, miercoles!$A:$A, $A18, miercoles!$C:$C, "ENTRADA") + SUMIFS(jueves!$D:$D, jueves!$A:$A, $A18, jueves!$C:$C, "ENTRADA") + SUMIFS(viernes!$D:$D, viernes!$A:$A, $A18, viernes!$C:$C, "ENTRADA") + SUMIFS(sabado!$D:$D, sabado!$A:$A, $A18, sabado!$C:$C, "ENTRADA") -> 0 | E18: =SUMIFS(lunes!$D:$D, lunes!$A:$A, $A18, lunes!$C:$C, "SALIDA") + SUMIFS(martes!$D:$D, martes!$A:$A, $A18, martes!$C:$C, "SALIDA") + SUMIFS(miercoles!$D:$D, miercoles!$A:$A, $A18, miercoles!$C:$C, "SALIDA") + SUMIFS(jueves!$D:$D, jueves!$A:$A, $A18, jueves!$C:$C, "SALIDA") + SUMIFS(viernes!$D:$D, viernes!$A:$A, $A18, viernes!$C:$C, "SALIDA") + SUMIFS(sabado!$D:$D, sabado!$A:$A, $A18, sabado!$C:$C, "SALIDA") -> 0 | F18: =B18-C18+D18-E18 -> 0 | G18: =IFERROR(VLOOKUP(A18, sabado!A:I, 9, 0), IFERROR(VLOOKUP(A18, viernes!A:I, 9, 0), IFERROR(VLOOKUP(A18, jueves!A:I, 9, 0), IFERROR(VLOOKUP(A18, miercoles!A:I, 9, 0), IFERROR(VLOOKUP(A18, martes!A:I, 9, 0), IFERROR(VLOOKUP(A18, lunes!A:I, 9, 0), B18)))))) -> 0 | H18: =VLOOKUP(A18, Configuracion!A:C, 3, FALSE) -> 35 | I18: =C18*H18 -> 0 | J18: =SUMIFS(lunes!$F:$F, lunes!$A:$A, $A18, lunes!$C:$C, "VENTA") + SUMIFS(martes!$F:$F, martes!$A:$A, $A18, martes!$C:$C, "VENTA") + SUMIFS(miercoles!$F:$F, miercoles!$A:$A, $A18, miercoles!$C:$C, "VENTA") + SUMIFS(jueves!$F:$F, jueves!$A:$A, $A18, jueves!$C:$C, "VENTA") + SUMIFS(viernes!$F:$F, viernes!$A:$A, $A18, viernes!$C:$C, "VENTA") + SUMIFS(sabado!$F:$F, sabado!$A:$A, $A18, sabado!$C:$C, "VENTA") -> 0 | K18: =I18-J18 -> 0
A19: =Configuracion!A18 -> BOCINA MILEXUS 8 DUAL | B19: =VLOOKUP(A19, Configuracion!A:B, 2, FALSE) -> 0 | C19: =SUMIFS(lunes!D:D, lunes!A:A, A19, lunes!C:C, "VENTA") + SUMIFS(martes!D:D, martes!A:A, A19, martes!C:C, "VENTA") + SUMIFS(miercoles!D:D, miercoles!A:A, A19, miercoles!C:C, "VENTA") + SUMIFS(jueves!D:D, jueves!A:A, A19, jueves!C:C, "VENTA") + SUMIFS(viernes!D:D, viernes!A:A, A19, viernes!C:C, "VENTA") + SUMIFS(sabado!D:D, sabado!A:A, A19, sabado!C:C, "VENTA") -> 0 | D19: =SUMIFS(lunes!$D:$D, lunes!$A:$A, $A19, lunes!$C:$C, "ENTRADA") + SUMIFS(martes!$D:$D, martes!$A:$A, $A19, martes!$C:$C, "ENTRADA") + SUMIFS(miercoles!$D:$D, miercoles!$A:$A, $A19, miercoles!$C:$C, "ENTRADA") + SUMIFS(jueves!$D:$D, jueves!$A:$A, $A19, jueves!$C:$C, "ENTRADA") + SUMIFS(viernes!$D:$D, viernes!$A:$A, $A19, viernes!$C:$C, "ENTRADA") + SUMIFS(sabado!$D:$D, sabado!$A:$A, $A19, sabado!$C:$C, "ENTRADA") -> 0 | E19: =SUMIFS(lunes!$D:$D, lunes!$A:$A, $A19, lunes!$C:$C, "SALIDA") + SUMIFS(martes!$D:$D, martes!$A:$A, $A19, martes!$C:$C, "SALIDA") + SUMIFS(miercoles!$D:$D, miercoles!$A:$A, $A19, miercoles!$C:$C, "SALIDA") + SUMIFS(jueves!$D:$D, jueves!$A:$A, $A19, jueves!$C:$C, "SALIDA") + SUMIFS(viernes!$D:$D, viernes!$A:$A, $A19, viernes!$C:$C, "SALIDA") + SUMIFS(sabado!$D:$D, sabado!$A:$A, $A19, sabado!$C:$C, "SALIDA") -> 0 | F19: =B19-C19+D19-E19 -> 0 | G19: =IFERROR(VLOOKUP(A19, sabado!A:I, 9, 0), IFERROR(VLOOKUP(A19, viernes!A:I, 9, 0), IFERROR(VLOOKUP(A19, jueves!A:I, 9, 0), IFERROR(VLOOKUP(A19, miercoles!A:I, 9, 0), IFERROR(VLOOKUP(A19, martes!A:I, 9, 0), IFERROR(VLOOKUP(A19, lunes!A:I, 9, 0), B19)))))) -> 0 | H19: =VLOOKUP(A19, Configuracion!A:C, 3, FALSE) -> 190 | I19: =C19*H19 -> 0 | J19: =SUMIFS(lunes!$F:$F, lunes!$A:$A, $A19, lunes!$C:$C, "VENTA") + SUMIFS(martes!$F:$F, martes!$A:$A, $A19, martes!$C:$C, "VENTA") + SUMIFS(miercoles!$F:$F, miercoles!$A:$A, $A19, miercoles!$C:$C, "VENTA") + SUMIFS(jueves!$F:$F, jueves!$A:$A, $A19, jueves!$C:$C, "VENTA") + SUMIFS(viernes!$F:$F, viernes!$A:$A, $A19, viernes!$C:$C, "VENTA") + SUMIFS(sabado!$F:$F, sabado!$A:$A, $A19, sabado!$C:$C, "VENTA") -> 0 | K19: =I19-J19 -> 0
A20: =Configuracion!A19 -> BOMBA DE AGUA SILVER POINT 1 HP | B20: =VLOOKUP(A20, Configuracion!A:B, 2, FALSE) -> 2 | C20: =SUMIFS(lunes!D:D, lunes!A:A, A20, lunes!C:C, "VENTA") + SUMIFS(martes!D:D, martes!A:A, A20, martes!C:C, "VENTA") + SUMIFS(miercoles!D:D, miercoles!A:A, A20, miercoles!C:C, "VENTA") + SUMIFS(jueves!D:D, jueves!A:A, A20, jueves!C:C, "VENTA") + SUMIFS(viernes!D:D, viernes!A:A, A20, viernes!C:C, "VENTA") + SUMIFS(sabado!D:D, sabado!A:A, A20, sabado!C:C, "VENTA") -> 0 | D20: =SUMIFS(lunes!$D:$D, lunes!$A:$A, $A20, lunes!$C:$C, "ENTRADA") + SUMIFS(martes!$D:$D, martes!$A:$A, $A20, martes!$C:$C, "ENTRADA") + SUMIFS(miercoles!$D:$D, miercoles!$A:$A, $A20, miercoles!$C:$C, "ENTRADA") + SUMIFS(jueves!$D:$D, jueves!$A:$A, $A20, jueves!$C:$C, "ENTRADA") + SUMIFS(viernes!$D:$D, viernes!$A:$A, $A20, viernes!$C:$C, "ENTRADA") + SUMIFS(sabado!$D:$D, sabado!$A:$A, $A20, sabado!$C:$C, "ENTRADA") -> 0 | E20: =SUMIFS(lunes!$D:$D, lunes!$A:$A, $A20, lunes!$C:$C, "SALIDA") + SUMIFS(martes!$D:$D, martes!$A:$A, $A20, martes!$C:$C, "SALIDA") + SUMIFS(miercoles!$D:$D, miercoles!$A:$A, $A20, miercoles!$C:$C, "SALIDA") + SUMIFS(jueves!$D:$D, jueves!$A:$A, $A20, jueves!$C:$C, "SALIDA") + SUMIFS(viernes!$D:$D, viernes!$A:$A, $A20, viernes!$C:$C, "SALIDA") + SUMIFS(sabado!$D:$D, sabado!$A:$A, $A20, sabado!$C:$C, "SALIDA") -> 0 | F20: =B20-C20+D20-E20 -> 2 | G20: =IFERROR(VLOOKUP(A20, sabado!A:I, 9, 0), IFERROR(VLOOKUP(A20, viernes!A:I, 9, 0), IFERROR(VLOOKUP(A20, jueves!A:I, 9, 0), IFERROR(VLOOKUP(A20, miercoles!A:I, 9, 0), IFERROR(VLOOKUP(A20, martes!A:I, 9, 0), IFERROR(VLOOKUP(A20, lunes!A:I, 9, 0), B20)))))) -> 2 | H20: =VLOOKUP(A20, Configuracion!A:C, 3, FALSE) -> 60 | I20: =C20*H20 -> 0 | J20: =SUMIFS(lunes!$F:$F, lunes!$A:$A, $A20, lunes!$C:$C, "VENTA") + SUMIFS(martes!$F:$F, martes!$A:$A, $A20, martes!$C:$C, "VENTA") + SUMIFS(miercoles!$F:$F, miercoles!$A:$A, $A20, miercoles!$C:$C, "VENTA") + SUMIFS(jueves!$F:$F, jueves!$A:$A, $A20, jueves!$C:$C, "VENTA") + SUMIFS(viernes!$F:$F, viernes!$A:$A, $A20, viernes!$C:$C, "VENTA") + SUMIFS(sabado!$F:$F, sabado!$A:$A, $A20, sabado!$C:$C, "VENTA") -> 0 | K20: =I20-J20 -> 0
A21: =Configuracion!A20 -> BOMBA DE AGUA SILVER POINT 1X1/2 | B21: =VLOOKUP(A21, Configuracion!A:B, 2, FALSE) -> 0 | C21: =SUMIFS(lunes!D:D, lunes!A:A, A21, lunes!C:C, "VENTA") + SUMIFS(martes!D:D, martes!A:A, A21, martes!C:C, "VENTA") + SUMIFS(miercoles!D:D, miercoles!A:A, A21, miercoles!C:C, "VENTA") + SUMIFS(jueves!D:D, jueves!A:A, A21, jueves!C:C, "VENTA") + SUMIFS(viernes!D:D, viernes!A:A, A21, viernes!C:C, "VENTA") + SUMIFS(sabado!D:D, sabado!A:A, A21, sabado!C:C, "VENTA") -> 0 | D21: =SUMIFS(lunes!$D:$D, lunes!$A:$A, $A21, lunes!$C:$C, "ENTRADA") + SUMIFS(martes!$D:$D, martes!$A:$A, $A21, martes!$C:$C, "ENTRADA") + SUMIFS(miercoles!$D:$D, miercoles!$A:$A, $A21, miercoles!$C:$C, "ENTRADA") + SUMIFS(jueves!$D:$D, jueves!$A:$A, $A21, jueves!$C:$C, "ENTRADA") + SUMIFS(viernes!$D:$D, viernes!$A:$A, $A21, viernes!$C:$C, "ENTRADA") + SUMIFS(sabado!$D:$D, sabado!$A:$A, $A21, sabado!$C:$C, "ENTRADA") -> 0 | E21: =SUMIFS(lunes!$D:$D, lunes!$A:$A, $A21, lunes!$C:$C, "SALIDA") + SUMIFS(martes!$D:$D, martes!$A:$A, $A21, martes!$C:$C, "SALIDA") + SUMIFS(miercoles!$D:$D, miercoles!$A:$A, $A21, miercoles!$C:$C, "SALIDA") + SUMIFS(jueves!$D:$D, jueves!$A:$A, $A21, jueves!$C:$C, "SALIDA") + SUMIFS(viernes!$D:$D, viernes!$A:$A, $A21, viernes!$C:$C, "SALIDA") + SUMIFS(sabado!$D:$D, sabado!$A:$A, $A21, sabado!$C:$C, "SALIDA") -> 0 | F21: =B21-C21+D21-E21 -> 0 | G21: =IFERROR(VLOOKUP(A21, sabado!A:I, 9, 0), IFERROR(VLOOKUP(A21, viernes!A:I, 9, 0), IFERROR(VLOOKUP(A21, jueves!A:I, 9, 0), IFERROR(VLOOKUP(A21, miercoles!A:I, 9, 0), IFERROR(VLOOKUP(A21, martes!A:I, 9, 0), IFERROR(VLOOKUP(A21, lunes!A:I, 9, 0), B21)))))) -> 0 | H21: =VLOOKUP(A21, Configuracion!A:C, 3, FALSE) -> 40 | I21: =C21*H21 -> 0 | J21: =SUMIFS(lunes!$F:$F, lunes!$A:$A, $A21, lunes!$C:$C, "VENTA") + SUMIFS(martes!$F:$F, martes!$A:$A, $A21, martes!$C:$C, "VENTA") + SUMIFS(miercoles!$F:$F, miercoles!$A:$A, $A21, miercoles!$C:$C, "VENTA") + SUMIFS(jueves!$F:$F, jueves!$A:$A, $A21, jueves!$C:$C, "VENTA") + SUMIFS(viernes!$F:$F, viernes!$A:$A, $A21, viernes!$C:$C, "VENTA") + SUMIFS(sabado!$F:$F, sabado!$A:$A, $A21, sabado!$C:$C, "VENTA") -> 0 | K21: =I21-J21 -> 0
A22: =Configuracion!A21 -> BICICLETA INFANTIL | B22: =VLOOKUP(A22, Configuracion!A:B, 2, FALSE) -> 0 | C22: =SUMIFS(lunes!D:D, lunes!A:A, A22, lunes!C:C, "VENTA") + SUMIFS(martes!D:D, martes!A:A, A22, martes!C:C, "VENTA") + SUMIFS(miercoles!D:D, miercoles!A:A, A22, miercoles!C:C, "VENTA") + SUMIFS(jueves!D:D, jueves!A:A, A22, jueves!C:C, "VENTA") + SUMIFS(viernes!D:D, viernes!A:A, A22, viernes!C:C, "VENTA") + SUMIFS(sabado!D:D, sabado!A:A, A22, sabado!C:C, "VENTA") -> 0 | D22: =SUMIFS(lunes!$D:$D, lunes!$A:$A, $A22, lunes!$C:$C, "ENTRADA") + SUMIFS(martes!$D:$D, martes!$A:$A, $A22, martes!$C:$C, "ENTRADA") + SUMIFS(miercoles!$D:$D, miercoles!$A:$A, $A22, miercoles!$C:$C, "ENTRADA") + SUMIFS(jueves!$D:$D, jueves!$A:$A, $A22, jueves!$C:$C, "ENTRADA") + SUMIFS(viernes!$D:$D, viernes!$A:$A, $A22, viernes!$C:$C, "ENTRADA") + SUMIFS(sabado!$D:$D, sabado!$A:$A, $A22, sabado!$C:$C, "ENTRADA") -> 0 | E22: =SUMIFS(lunes!$D:$D, lunes!$A:$A, $A22, lunes!$C:$C, "SALIDA") + SUMIFS(martes!$D:$D, martes!$A:$A, $A22, martes!$C:$C, "SALIDA") + SUMIFS(miercoles!$D:$D, miercoles!$A:$A, $A22, miercoles!$C:$C, "SALIDA") + SUMIFS(jueves!$D:$D, jueves!$A:$A, $A22, jueves!$C:$C, "SALIDA") + SUMIFS(viernes!$D:$D, viernes!$A:$A, $A22, viernes!$C:$C, "SALIDA") + SUMIFS(sabado!$D:$D, sabado!$A:$A, $A22, sabado!$C:$C, "SALIDA") -> 0 | F22: =B22-C22+D22-E22 -> 0 | G22: =IFERROR(VLOOKUP(A22, sabado!A:I, 9, 0), IFERROR(VLOOKUP(A22, viernes!A:I, 9, 0), IFERROR(VLOOKUP(A22, jueves!A:I, 9, 0), IFERROR(VLOOKUP(A22, miercoles!A:I, 9, 0), IFERROR(VLOOKUP(A22, martes!A:I, 9, 0), IFERROR(VLOOKUP(A22, lunes!A:I, 9, 0), B22)))))) -> 0 | H22: =VLOOKUP(A22, Configuracion!A:C, 3, FALSE) -> 130 | I22: =C22*H22 -> 0 | J22: =SUMIFS(lunes!$F:$F, lunes!$A:$A, $A22, lunes!$C:$C, "VENTA") + SUMIFS(martes!$F:$F, martes!$A:$A, $A22, martes!$C:$C, "VENTA") + SUMIFS(miercoles!$F:$F, miercoles!$A:$A, $A22, miercoles!$C:$C, "VENTA") + SUMIFS(jueves!$F:$F, jueves!$A:$A, $A22, jueves!$C:$C, "VENTA") + SUMIFS(viernes!$F:$F, viernes!$A:$A, $A22, viernes!$C:$C, "VENTA") + SUMIFS(sabado!$F:$F, sabado!$A:$A, $A22, sabado!$C:$C, "VENTA") -> 0 | K22: =I22-J22 -> 0
A23: =Configuracion!A22 -> BICICLETA | B23: =VLOOKUP(A23, Configuracion!A:B, 2, FALSE) -> 0 | C23: =SUMIFS(lunes!D:D, lunes!A:A, A23, lunes!C:C, "VENTA") + SUMIFS(martes!D:D, martes!A:A, A23, martes!C:C, "VENTA") + SUMIFS(miercoles!D:D, miercoles!A:A, A23, miercoles!C:C, "VENTA") + SUMIFS(jueves!D:D, jueves!A:A, A23, jueves!C:C, "VENTA") + SUMIFS(viernes!D:D, viernes!A:A, A23, viernes!C:C, "VENTA") + SUMIFS(sabado!D:D, sabado!A:A, A23, sabado!C:C, "VENTA") -> 0 | D23: =SUMIFS(lunes!$D:$D, lunes!$A:$A, $A23, lunes!$C:$C, "ENTRADA") + SUMIFS(martes!$D:$D, martes!$A:$A, $A23, martes!$C:$C, "ENTRADA") + SUMIFS(miercoles!$D:$D, miercoles!$A:$A, $A23, miercoles!$C:$C, "ENTRADA") + SUMIFS(jueves!$D:$D, jueves!$A:$A, $A23, jueves!$C:$C, "ENTRADA") + SUMIFS(viernes!$D:$D, viernes!$A:$A, $A23, viernes!$C:$C, "ENTRADA") + SUMIFS(sabado!$D:$D, sabado!$A:$A, $A23, sabado!$C:$C, "ENTRADA") -> 0 | E23: =SUMIFS(lunes!$D:$D, lunes!$A:$A, $A23, lunes!$C:$C, "SALIDA") + SUMIFS(martes!$D:$D, martes!$A:$A, $A23, martes!$C:$C, "SALIDA") + SUMIFS(miercoles!$D:$D, miercoles!$A:$A, $A23, miercoles!$C:$C, "SALIDA") + SUMIFS(jueves!$D:$D, jueves!$A:$A, $A23, jueves!$C:$C, "SALIDA") + SUMIFS(viernes!$D:$D, viernes!$A:$A, $A23, viernes!$C:$C, "SALIDA") + SUMIFS(sabado!$D:$D, sabado!$A:$A, $A23, sabado!$C:$C, "SALIDA") -> 0 | F23: =B23-C23+D23-E23 -> 0 | G23: =IFERROR(VLOOKUP(A23, sabado!A:I, 9, 0), IFERROR(VLOOKUP(A23, viernes!A:I, 9, 0), IFERROR(VLOOKUP(A23, jueves!A:I, 9, 0), IFERROR(VLOOKUP(A23, miercoles!A:I, 9, 0), IFERROR(VLOOKUP(A23, martes!A:I, 9, 0), IFERROR(VLOOKUP(A23, lunes!A:I, 9, 0), B23)))))) -> 0 | H23: =VLOOKUP(A23, Configuracion!A:C, 3, FALSE) -> 180 | I23: =C23*H23 -> 0 | J23: =SUMIFS(lunes!$F:$F, lunes!$A:$A, $A23, lunes!$C:$C, "VENTA") + SUMIFS(martes!$F:$F, martes!$A:$A, $A23, martes!$C:$C, "VENTA") + SUMIFS(miercoles!$F:$F, miercoles!$A:$A, $A23, miercoles!$C:$C, "VENTA") + SUMIFS(jueves!$F:$F, jueves!$A:$A, $A23, jueves!$C:$C, "VENTA") + SUMIFS(viernes!$F:$F, viernes!$A:$A, $A23, viernes!$C:$C, "VENTA") + SUMIFS(sabado!$F:$F, sabado!$A:$A, $A23, sabado!$C:$C, "VENTA") -> 0 | K23: =I23-J23 -> 0
A24: =Configuracion!A23 -> CONECTORES MC4 | B24: =VLOOKUP(A24, Configuracion!A:B, 2, FALSE) -> 4 | C24: =SUMIFS(lunes!D:D, lunes!A:A, A24, lunes!C:C, "VENTA") + SUMIFS(martes!D:D, martes!A:A, A24, martes!C:C, "VENTA") + SUMIFS(miercoles!D:D, miercoles!A:A, A24, miercoles!C:C, "VENTA") + SUMIFS(jueves!D:D, jueves!A:A, A24, jueves!C:C, "VENTA") + SUMIFS(viernes!D:D, viernes!A:A, A24, viernes!C:C, "VENTA") + SUMIFS(sabado!D:D, sabado!A:A, A24, sabado!C:C, "VENTA") -> 0 | D24: =SUMIFS(lunes!$D:$D, lunes!$A:$A, $A24, lunes!$C:$C, "ENTRADA") + SUMIFS(martes!$D:$D, martes!$A:$A, $A24, martes!$C:$C, "ENTRADA") + SUMIFS(miercoles!$D:$D, miercoles!$A:$A, $A24, miercoles!$C:$C, "ENTRADA") + SUMIFS(jueves!$D:$D, jueves!$A:$A, $A24, jueves!$C:$C, "ENTRADA") + SUMIFS(viernes!$D:$D, viernes!$A:$A, $A24, viernes!$C:$C, "ENTRADA") + SUMIFS(sabado!$D:$D, sabado!$A:$A, $A24, sabado!$C:$C, "ENTRADA") -> 0 | E24: =SUMIFS(lunes!$D:$D, lunes!$A:$A, $A24, lunes!$C:$C, "SALIDA") + SUMIFS(martes!$D:$D, martes!$A:$A, $A24, martes!$C:$C, "SALIDA") + SUMIFS(miercoles!$D:$D, miercoles!$A:$A, $A24, miercoles!$C:$C, "SALIDA") + SUMIFS(jueves!$D:$D, jueves!$A:$A, $A24, jueves!$C:$C, "SALIDA") + SUMIFS(viernes!$D:$D, viernes!$A:$A, $A24, viernes!$C:$C, "SALIDA") + SUMIFS(sabado!$D:$D, sabado!$A:$A, $A24, sabado!$C:$C, "SALIDA") -> 0 | F24: =B24-C24+D24-E24 -> 4 | G24: =IFERROR(VLOOKUP(A24, sabado!A:I, 9, 0), IFERROR(VLOOKUP(A24, viernes!A:I, 9, 0), IFERROR(VLOOKUP(A24, jueves!A:I, 9, 0), IFERROR(VLOOKUP(A24, miercoles!A:I, 9, 0), IFERROR(VLOOKUP(A24, martes!A:I, 9, 0), IFERROR(VLOOKUP(A24, lunes!A:I, 9, 0), B24)))))) -> 4 | H24: =VLOOKUP(A24, Configuracion!A:C, 3, FALSE) -> 0 | I24: =C24*H24 -> 0 | J24: =SUMIFS(lunes!$F:$F, lunes!$A:$A, $A24, lunes!$C:$C, "VENTA") + SUMIFS(martes!$F:$F, martes!$A:$A, $A24, martes!$C:$C, "VENTA") + SUMIFS(miercoles!$F:$F, miercoles!$A:$A, $A24, miercoles!$C:$C, "VENTA") + SUMIFS(jueves!$F:$F, jueves!$A:$A, $A24, jueves!$C:$C, "VENTA") + SUMIFS(viernes!$F:$F, viernes!$A:$A, $A24, viernes!$C:$C, "VENTA") + SUMIFS(sabado!$F:$F, sabado!$A:$A, $A24, sabado!$C:$C, "VENTA") -> 0 | K24: =I24-J24 -> 0
A25: =Configuracion!A24 -> CAJITA DECODIFICADORA VIVAMAX | B25: =VLOOKUP(A25, Configuracion!A:B, 2, FALSE) -> 5 | C25: =SUMIFS(lunes!D:D, lunes!A:A, A25, lunes!C:C, "VENTA") + SUMIFS(martes!D:D, martes!A:A, A25, martes!C:C, "VENTA") + SUMIFS(miercoles!D:D, miercoles!A:A, A25, miercoles!C:C, "VENTA") + SUMIFS(jueves!D:D, jueves!A:A, A25, jueves!C:C, "VENTA") + SUMIFS(viernes!D:D, viernes!A:A, A25, viernes!C:C, "VENTA") + SUMIFS(sabado!D:D, sabado!A:A, A25, sabado!C:C, "VENTA") -> 1 | D25: =SUMIFS(lunes!$D:$D, lunes!$A:$A, $A25, lunes!$C:$C, "ENTRADA") + SUMIFS(martes!$D:$D, martes!$A:$A, $A25, martes!$C:$C, "ENTRADA") + SUMIFS(miercoles!$D:$D, miercoles!$A:$A, $A25, miercoles!$C:$C, "ENTRADA") + SUMIFS(jueves!$D:$D, jueves!$A:$A, $A25, jueves!$C:$C, "ENTRADA") + SUMIFS(viernes!$D:$D, viernes!$A:$A, $A25, viernes!$C:$C, "ENTRADA") + SUMIFS(sabado!$D:$D, sabado!$A:$A, $A25, sabado!$C:$C, "ENTRADA") -> 0 | E25: =SUMIFS(lunes!$D:$D, lunes!$A:$A, $A25, lunes!$C:$C, "SALIDA") + SUMIFS(martes!$D:$D, martes!$A:$A, $A25, martes!$C:$C, "SALIDA") + SUMIFS(miercoles!$D:$D, miercoles!$A:$A, $A25, miercoles!$C:$C, "SALIDA") + SUMIFS(jueves!$D:$D, jueves!$A:$A, $A25, jueves!$C:$C, "SALIDA") + SUMIFS(viernes!$D:$D, viernes!$A:$A, $A25, viernes!$C:$C, "SALIDA") + SUMIFS(sabado!$D:$D, sabado!$A:$A, $A25, sabado!$C:$C, "SALIDA") -> 0 | F25: =B25-C25+D25-E25 -> 4 | G25: =IFERROR(VLOOKUP(A25, sabado!A:I, 9, 0), IFERROR(VLOOKUP(A25, viernes!A:I, 9, 0), IFERROR(VLOOKUP(A25, jueves!A:I, 9, 0), IFERROR(VLOOKUP(A25, miercoles!A:I, 9, 0), IFERROR(VLOOKUP(A25, martes!A:I, 9, 0), IFERROR(VLOOKUP(A25, lunes!A:I, 9, 0), B25)))))) -> 4 | H25: =VLOOKUP(A25, Configuracion!A:C, 3, FALSE) -> 40 | I25: =C25*H25 -> 40 | J25: =SUMIFS(lunes!$F:$F, lunes!$A:$A, $A25, lunes!$C:$C, "VENTA") + SUMIFS(martes!$F:$F, martes!$A:$A, $A25, martes!$C:$C, "VENTA") + SUMIFS(miercoles!$F:$F, miercoles!$A:$A, $A25, miercoles!$C:$C, "VENTA") + SUMIFS(jueves!$F:$F, jueves!$A:$A, $A25, jueves!$C:$C, "VENTA") + SUMIFS(viernes!$F:$F, viernes!$A:$A, $A25, viernes!$C:$C, "VENTA") + SUMIFS(sabado!$F:$F, sabado!$A:$A, $A25, sabado!$C:$C, "VENTA") -> 40 | K25: =I25-J25 -> 0
A26: =Configuracion!A25 -> CAJA DE DISTRIBUCION DE VIAS 12 VIAS | B26: =VLOOKUP(A26, Configuracion!A:B, 2, FALSE) -> 3 | C26: =SUMIFS(lunes!D:D, lunes!A:A, A26, lunes!C:C, "VENTA") + SUMIFS(martes!D:D, martes!A:A, A26, martes!C:C, "VENTA") + SUMIFS(miercoles!D:D, miercoles!A:A, A26, miercoles!C:C, "VENTA") + SUMIFS(jueves!D:D, jueves!A:A, A26, jueves!C:C, "VENTA") + SUMIFS(viernes!D:D, viernes!A:A, A26, viernes!C:C, "VENTA") + SUMIFS(sabado!D:D, sabado!A:A, A26, sabado!C:C, "VENTA") -> 0 | D26: =SUMIFS(lunes!$D:$D, lunes!$A:$A, $A26, lunes!$C:$C, "ENTRADA") + SUMIFS(martes!$D:$D, martes!$A:$A, $A26, martes!$C:$C, "ENTRADA") + SUMIFS(miercoles!$D:$D, miercoles!$A:$A, $A26, miercoles!$C:$C, "ENTRADA") + SUMIFS(jueves!$D:$D, jueves!$A:$A, $A26, jueves!$C:$C, "ENTRADA") + SUMIFS(viernes!$D:$D, viernes!$A:$A, $A26, viernes!$C:$C, "ENTRADA") + SUMIFS(sabado!$D:$D, sabado!$A:$A, $A26, sabado!$C:$C, "ENTRADA") -> 0 | E26: =SUMIFS(lunes!$D:$D, lunes!$A:$A, $A26, lunes!$C:$C, "SALIDA") + SUMIFS(martes!$D:$D, martes!$A:$A, $A26, martes!$C:$C, "SALIDA") + SUMIFS(miercoles!$D:$D, miercoles!$A:$A, $A26, miercoles!$C:$C, "SALIDA") + SUMIFS(jueves!$D:$D, jueves!$A:$A, $A26, jueves!$C:$C, "SALIDA") + SUMIFS(viernes!$D:$D, viernes!$A:$A, $A26, viernes!$C:$C, "SALIDA") + SUMIFS(sabado!$D:$D, sabado!$A:$A, $A26, sabado!$C:$C, "SALIDA") -> 0 | F26: =B26-C26+D26-E26 -> 3 | G26: =IFERROR(VLOOKUP(A26, sabado!A:I, 9, 0), IFERROR(VLOOKUP(A26, viernes!A:I, 9, 0), IFERROR(VLOOKUP(A26, jueves!A:I, 9, 0), IFERROR(VLOOKUP(A26, miercoles!A:I, 9, 0), IFERROR(VLOOKUP(A26, martes!A:I, 9, 0), IFERROR(VLOOKUP(A26, lunes!A:I, 9, 0), B26)))))) -> 3 | H26: =VLOOKUP(A26, Configuracion!A:C, 3, FALSE) -> 0 | I26: =C26*H26 -> 0 | J26: =SUMIFS(lunes!$F:$F, lunes!$A:$A, $A26, lunes!$C:$C, "VENTA") + SUMIFS(martes!$F:$F, martes!$A:$A, $A26, martes!$C:$C, "VENTA") + SUMIFS(miercoles!$F:$F, miercoles!$A:$A, $A26, miercoles!$C:$C, "VENTA") + SUMIFS(jueves!$F:$F, jueves!$A:$A, $A26, jueves!$C:$C, "VENTA") + SUMIFS(viernes!$F:$F, viernes!$A:$A, $A26, viernes!$C:$C, "VENTA") + SUMIFS(sabado!$F:$F, sabado!$A:$A, $A26, sabado!$C:$C, "VENTA") -> 0 | K26: =I26-J26 -> 0
A27: =Configuracion!A26 -> COLCHON PERSONAL | B27: =VLOOKUP(A27, Configuracion!A:B, 2, FALSE) -> 3 | C27: =SUMIFS(lunes!D:D, lunes!A:A, A27, lunes!C:C, "VENTA") + SUMIFS(martes!D:D, martes!A:A, A27, martes!C:C, "VENTA") + SUMIFS(miercoles!D:D, miercoles!A:A, A27, miercoles!C:C, "VENTA") + SUMIFS(jueves!D:D, jueves!A:A, A27, jueves!C:C, "VENTA") + SUMIFS(viernes!D:D, viernes!A:A, A27, viernes!C:C, "VENTA") + SUMIFS(sabado!D:D, sabado!A:A, A27, sabado!C:C, "VENTA") -> 0 | D27: =SUMIFS(lunes!$D:$D, lunes!$A:$A, $A27, lunes!$C:$C, "ENTRADA") + SUMIFS(martes!$D:$D, martes!$A:$A, $A27, martes!$C:$C, "ENTRADA") + SUMIFS(miercoles!$D:$D, miercoles!$A:$A, $A27, miercoles!$C:$C, "ENTRADA") + SUMIFS(jueves!$D:$D, jueves!$A:$A, $A27, jueves!$C:$C, "ENTRADA") + SUMIFS(viernes!$D:$D, viernes!$A:$A, $A27, viernes!$C:$C, "ENTRADA") + SUMIFS(sabado!$D:$D, sabado!$A:$A, $A27, sabado!$C:$C, "ENTRADA") -> 0 | E27: =SUMIFS(lunes!$D:$D, lunes!$A:$A, $A27, lunes!$C:$C, "SALIDA") + SUMIFS(martes!$D:$D, martes!$A:$A, $A27, martes!$C:$C, "SALIDA") + SUMIFS(miercoles!$D:$D, miercoles!$A:$A, $A27, miercoles!$C:$C, "SALIDA") + SUMIFS(jueves!$D:$D, jueves!$A:$A, $A27, jueves!$C:$C, "SALIDA") + SUMIFS(viernes!$D:$D, viernes!$A:$A, $A27, viernes!$C:$C, "SALIDA") + SUMIFS(sabado!$D:$D, sabado!$A:$A, $A27, sabado!$C:$C, "SALIDA") -> 0 | F27: =B27-C27+D27-E27 -> 3 | G27: =IFERROR(VLOOKUP(A27, sabado!A:I, 9, 0), IFERROR(VLOOKUP(A27, viernes!A:I, 9, 0), IFERROR(VLOOKUP(A27, jueves!A:I, 9, 0), IFERROR(VLOOKUP(A27, miercoles!A:I, 9, 0), IFERROR(VLOOKUP(A27, martes!A:I, 9, 0), IFERROR(VLOOKUP(A27, lunes!A:I, 9, 0), B27)))))) -> 3 | H27: =VLOOKUP(A27, Configuracion!A:C, 3, FALSE) -> 160 | I27: =C27*H27 -> 0 | J27: =SUMIFS(lunes!$F:$F, lunes!$A:$A, $A27, lunes!$C:$C, "VENTA") + SUMIFS(martes!$F:$F, martes!$A:$A, $A27, martes!$C:$C, "VENTA") + SUMIFS(miercoles!$F:$F, miercoles!$A:$A, $A27, miercoles!$C:$C, "VENTA") + SUMIFS(jueves!$F:$F, jueves!$A:$A, $A27, jueves!$C:$C, "VENTA") + SUMIFS(viernes!$F:$F, viernes!$A:$A, $A27, viernes!$C:$C, "VENTA") + SUMIFS(sabado!$F:$F, sabado!$A:$A, $A27, sabado!$C:$C, "VENTA") -> 0 | K27: =I27-J27 -> 0
A28: =Configuracion!A27 -> COLCHON EKO | B28: =VLOOKUP(A28, Configuracion!A:B, 2, FALSE) -> 4 | C28: =SUMIFS(lunes!D:D, lunes!A:A, A28, lunes!C:C, "VENTA") + SUMIFS(martes!D:D, martes!A:A, A28, martes!C:C, "VENTA") + SUMIFS(miercoles!D:D, miercoles!A:A, A28, miercoles!C:C, "VENTA") + SUMIFS(jueves!D:D, jueves!A:A, A28, jueves!C:C, "VENTA") + SUMIFS(viernes!D:D, viernes!A:A, A28, viernes!C:C, "VENTA") + SUMIFS(sabado!D:D, sabado!A:A, A28, sabado!C:C, "VENTA") -> 0 | D28: =SUMIFS(lunes!$D:$D, lunes!$A:$A, $A28, lunes!$C:$C, "ENTRADA") + SUMIFS(martes!$D:$D, martes!$A:$A, $A28, martes!$C:$C, "ENTRADA") + SUMIFS(miercoles!$D:$D, miercoles!$A:$A, $A28, miercoles!$C:$C, "ENTRADA") + SUMIFS(jueves!$D:$D, jueves!$A:$A, $A28, jueves!$C:$C, "ENTRADA") + SUMIFS(viernes!$D:$D, viernes!$A:$A, $A28, viernes!$C:$C, "ENTRADA") + SUMIFS(sabado!$D:$D, sabado!$A:$A, $A28, sabado!$C:$C, "ENTRADA") -> 0 | E28: =SUMIFS(lunes!$D:$D, lunes!$A:$A, $A28, lunes!$C:$C, "SALIDA") + SUMIFS(martes!$D:$D, martes!$A:$A, $A28, martes!$C:$C, "SALIDA") + SUMIFS(miercoles!$D:$D, miercoles!$A:$A, $A28, miercoles!$C:$C, "SALIDA") + SUMIFS(jueves!$D:$D, jueves!$A:$A, $A28, jueves!$C:$C, "SALIDA") + SUMIFS(viernes!$D:$D, viernes!$A:$A, $A28, viernes!$C:$C, "SALIDA") + SUMIFS(sabado!$D:$D, sabado!$A:$A, $A28, sabado!$C:$C, "SALIDA") -> 0 | F28: =B28-C28+D28-E28 -> 4 | G28: =IFERROR(VLOOKUP(A28, sabado!A:I, 9, 0), IFERROR(VLOOKUP(A28, viernes!A:I, 9, 0), IFERROR(VLOOKUP(A28, jueves!A:I, 9, 0), IFERROR(VLOOKUP(A28, miercoles!A:I, 9, 0), IFERROR(VLOOKUP(A28, martes!A:I, 9, 0), IFERROR(VLOOKUP(A28, lunes!A:I, 9, 0), B28)))))) -> 4 | H28: =VLOOKUP(A28, Configuracion!A:C, 3, FALSE) -> 180 | I28: =C28*H28 -> 0 | J28: =SUMIFS(lunes!$F:$F, lunes!$A:$A, $A28, lunes!$C:$C, "VENTA") + SUMIFS(martes!$F:$F, martes!$A:$A, $A28, martes!$C:$C, "VENTA") + SUMIFS(miercoles!$F:$F, miercoles!$A:$A, $A28, miercoles!$C:$C, "VENTA") + SUMIFS(jueves!$F:$F, jueves!$A:$A, $A28, jueves!$C:$C, "VENTA") + SUMIFS(viernes!$F:$F, viernes!$A:$A, $A28, viernes!$C:$C, "VENTA") + SUMIFS(sabado!$F:$F, sabado!$A:$A, $A28, sabado!$C:$C, "VENTA") -> 0 | K28: =I28-J28 -> 0
A29: =Configuracion!A28 -> CAJAS DE AZULEJOS 44X44 2.5 M | B29: =VLOOKUP(A29, Configuracion!A:B, 2, FALSE) -> 2 | C29: =SUMIFS(lunes!D:D, lunes!A:A, A29, lunes!C:C, "VENTA") + SUMIFS(martes!D:D, martes!A:A, A29, martes!C:C, "VENTA") + SUMIFS(miercoles!D:D, miercoles!A:A, A29, miercoles!C:C, "VENTA") + SUMIFS(jueves!D:D, jueves!A:A, A29, jueves!C:C, "VENTA") + SUMIFS(viernes!D:D, viernes!A:A, A29, viernes!C:C, "VENTA") + SUMIFS(sabado!D:D, sabado!A:A, A29, sabado!C:C, "VENTA") -> 0 | D29: =SUMIFS(lunes!$D:$D, lunes!$A:$A, $A29, lunes!$C:$C, "ENTRADA") + SUMIFS(martes!$D:$D, martes!$A:$A, $A29, martes!$C:$C, "ENTRADA") + SUMIFS(miercoles!$D:$D, miercoles!$A:$A, $A29, miercoles!$C:$C, "ENTRADA") + SUMIFS(jueves!$D:$D, jueves!$A:$A, $A29, jueves!$C:$C, "ENTRADA") + SUMIFS(viernes!$D:$D, viernes!$A:$A, $A29, viernes!$C:$C, "ENTRADA") + SUMIFS(sabado!$D:$D, sabado!$A:$A, $A29, sabado!$C:$C, "ENTRADA") -> 0 | E29: =SUMIFS(lunes!$D:$D, lunes!$A:$A, $A29, lunes!$C:$C, "SALIDA") + SUMIFS(martes!$D:$D, martes!$A:$A, $A29, martes!$C:$C, "SALIDA") + SUMIFS(miercoles!$D:$D, miercoles!$A:$A, $A29, miercoles!$C:$C, "SALIDA") + SUMIFS(jueves!$D:$D, jueves!$A:$A, $A29, jueves!$C:$C, "SALIDA") + SUMIFS(viernes!$D:$D, viernes!$A:$A, $A29, viernes!$C:$C, "SALIDA") + SUMIFS(sabado!$D:$D, sabado!$A:$A, $A29, sabado!$C:$C, "SALIDA") -> 0 | F29: =B29-C29+D29-E29 -> 2 | G29: =IFERROR(VLOOKUP(A29, sabado!A:I, 9, 0), IFERROR(VLOOKUP(A29, viernes!A:I, 9, 0), IFERROR(VLOOKUP(A29, jueves!A:I, 9, 0), IFERROR(VLOOKUP(A29, miercoles!A:I, 9, 0), IFERROR(VLOOKUP(A29, martes!A:I, 9, 0), IFERROR(VLOOKUP(A29, lunes!A:I, 9, 0), B29)))))) -> 2 | H29: =VLOOKUP(A29, Configuracion!A:C, 3, FALSE) -> 36.41 | I29: =C29*H29 -> 0 | J29: =SUMIFS(lunes!$F:$F, lunes!$A:$A, $A29, lunes!$C:$C, "VENTA") + SUMIFS(martes!$F:$F, martes!$A:$A, $A29, martes!$C:$C, "VENTA") + SUMIFS(miercoles!$F:$F, miercoles!$A:$A, $A29, miercoles!$C:$C, "VENTA") + SUMIFS(jueves!$F:$F, jueves!$A:$A, $A29, jueves!$C:$C, "VENTA") + SUMIFS(viernes!$F:$F, viernes!$A:$A, $A29, viernes!$C:$C, "VENTA") + SUMIFS(sabado!$F:$F, sabado!$A:$A, $A29, sabado!$C:$C, "VENTA") -> 0 | K29: =I29-J29 -> 0
A30: =Configuracion!A29 -> CAFETERA 3 TASAS | B30: =VLOOKUP(A30, Configuracion!A:B, 2, FALSE) -> 2 | C30: =SUMIFS(lunes!D:D, lunes!A:A, A30, lunes!C:C, "VENTA") + SUMIFS(martes!D:D, martes!A:A, A30, martes!C:C, "VENTA") + SUMIFS(miercoles!D:D, miercoles!A:A, A30, miercoles!C:C, "VENTA") + SUMIFS(jueves!D:D, jueves!A:A, A30, jueves!C:C, "VENTA") + SUMIFS(viernes!D:D, viernes!A:A, A30, viernes!C:C, "VENTA") + SUMIFS(sabado!D:D, sabado!A:A, A30, sabado!C:C, "VENTA") -> 0 | D30: =SUMIFS(lunes!$D:$D, lunes!$A:$A, $A30, lunes!$C:$C, "ENTRADA") + SUMIFS(martes!$D:$D, martes!$A:$A, $A30, martes!$C:$C, "ENTRADA") + SUMIFS(miercoles!$D:$D, miercoles!$A:$A, $A30, miercoles!$C:$C, "ENTRADA") + SUMIFS(jueves!$D:$D, jueves!$A:$A, $A30, jueves!$C:$C, "ENTRADA") + SUMIFS(viernes!$D:$D, viernes!$A:$A, $A30, viernes!$C:$C, "ENTRADA") + SUMIFS(sabado!$D:$D, sabado!$A:$A, $A30, sabado!$C:$C, "ENTRADA") -> 0 | E30: =SUMIFS(lunes!$D:$D, lunes!$A:$A, $A30, lunes!$C:$C, "SALIDA") + SUMIFS(martes!$D:$D, martes!$A:$A, $A30, martes!$C:$C, "SALIDA") + SUMIFS(miercoles!$D:$D, miercoles!$A:$A, $A30, miercoles!$C:$C, "SALIDA") + SUMIFS(jueves!$D:$D, jueves!$A:$A, $A30, jueves!$C:$C, "SALIDA") + SUMIFS(viernes!$D:$D, viernes!$A:$A, $A30, viernes!$C:$C, "SALIDA") + SUMIFS(sabado!$D:$D, sabado!$A:$A, $A30, sabado!$C:$C, "SALIDA") -> 0 | F30: =B30-C30+D30-E30 -> 2 | G30: =IFERROR(VLOOKUP(A30, sabado!A:I, 9, 0), IFERROR(VLOOKUP(A30, viernes!A:I, 9, 0), IFERROR(VLOOKUP(A30, jueves!A:I, 9, 0), IFERROR(VLOOKUP(A30, miercoles!A:I, 9, 0), IFERROR(VLOOKUP(A30, martes!A:I, 9, 0), IFERROR(VLOOKUP(A30, lunes!A:I, 9, 0), B30)))))) -> 2 | H30: =VLOOKUP(A30, Configuracion!A:C, 3, FALSE) -> 12 | I30: =C30*H30 -> 0 | J30: =SUMIFS(lunes!$F:$F, lunes!$A:$A, $A30, lunes!$C:$C, "VENTA") + SUMIFS(martes!$F:$F, martes!$A:$A, $A30, martes!$C:$C, "VENTA") + SUMIFS(miercoles!$F:$F, miercoles!$A:$A, $A30, miercoles!$C:$C, "VENTA") + SUMIFS(jueves!$F:$F, jueves!$A:$A, $A30, jueves!$C:$C, "VENTA") + SUMIFS(viernes!$F:$F, viernes!$A:$A, $A30, viernes!$C:$C, "VENTA") + SUMIFS(sabado!$F:$F, sabado!$A:$A, $A30, sabado!$C:$C, "VENTA") -> 0 | K30: =I30-J30 -> 0
... A81: =Configuracion!A80 -> LAVADORA 8.6 KG JMT SEMI | B81: =VLOOKUP(A81, Configuracion!A:B, 2, FALSE) -> 0 | C81: =SUMIFS(lunes!D:D, lunes!A:A, A81, lunes!C:C, "VENTA") + SUMIFS(martes!D:D, martes!A:A, A81, martes!C:C, "VENTA") + SUMIFS(miercoles!D:D, miercoles!A:A, A81, miercoles!C:C, "VENTA") + SUMIFS(jueves!D:D, jueves!A:A, A81, jueves!C:C, "VENTA") + SUMIFS(viernes!D:D, viernes!A:A, A81, viernes!C:C, "VENTA") + SUMIFS(sabado!D:D, sabado!A:A, A81, sabado!C:C, "VENTA") -> 0 | D81: =SUMIFS(lunes!$D:$D, lunes!$A:$A, $A81, lunes!$C:$C, "ENTRADA") + SUMIFS(martes!$D:$D, martes!$A:$A, $A81, martes!$C:$C, "ENTRADA") + SUMIFS(miercoles!$D:$D, miercoles!$A:$A, $A81, miercoles!$C:$C, "ENTRADA") + SUMIFS(jueves!$D:$D, jueves!$A:$A, $A81, jueves!$C:$C, "ENTRADA") + SUMIFS(viernes!$D:$D, viernes!$A:$A, $A81, viernes!$C:$C, "ENTRADA") + SUMIFS(sabado!$D:$D, sabado!$A:$A, $A81, sabado!$C:$C, "ENTRADA") -> 0 | E81: =SUMIFS(lunes!$D:$D, lunes!$A:$A, $A81, lunes!$C:$C, "SALIDA") + SUMIFS(martes!$D:$D, martes!$A:$A, $A81, martes!$C:$C, "SALIDA") + SUMIFS(miercoles!$D:$D, miercoles!$A:$A, $A81, miercoles!$C:$C, "SALIDA") + SUMIFS(jueves!$D:$D, jueves!$A:$A, $A81, jueves!$C:$C, "SALIDA") + SUMIFS(viernes!$D:$D, viernes!$A:$A, $A81, viernes!$C:$C, "SALIDA") + SUMIFS(sabado!$D:$D, sabado!$A:$A, $A81, sabado!$C:$C, "SALIDA") -> 0 | F81: =B81-C81+D81-E81 -> 0 | G81: =IFERROR(VLOOKUP(A81, sabado!A:I, 9, 0), IFERROR(VLOOKUP(A81, viernes!A:I, 9, 0), IFERROR(VLOOKUP(A81, jueves!A:I, 9, 0), IFERROR(VLOOKUP(A81, miercoles!A:I, 9, 0), IFERROR(VLOOKUP(A81, martes!A:I, 9, 0), IFERROR(VLOOKUP(A81, lunes!A:I, 9, 0), B81)))))) -> 0 | H81: =VLOOKUP(A81, Configuracion!A:C, 3, FALSE) -> 180 | I81: =C81*H81 -> 0 | J81: =SUMIFS(lunes!$F:$F, lunes!$A:$A, $A81, lunes!$C:$C, "VENTA") + SUMIFS(martes!$F:$F, martes!$A:$A, $A81, martes!$C:$C, "VENTA") + SUMIFS(miercoles!$F:$F, miercoles!$A:$A, $A81, miercoles!$C:$C, "VENTA") + SUMIFS(jueves!$F:$F, jueves!$A:$A, $A81, jueves!$C:$C, "VENTA") + SUMIFS(viernes!$F:$F, viernes!$A:$A, $A81, viernes!$C:$C, "VENTA") + SUMIFS(sabado!$F:$F, sabado!$A:$A, $A81, sabado!$C:$C, "VENTA") -> 0 | K81: =I81-J81 -> 0
A82: =Configuracion!A82 -> LAVADORA 9 KG SAMSUNG AUTOMATICA | B82: =VLOOKUP(A82, Configuracion!A:B, 2, FALSE) -> 6 | C82: =SUMIFS(lunes!D:D, lunes!A:A, A82, lunes!C:C, "VENTA") + SUMIFS(martes!D:D, martes!A:A, A82, martes!C:C, "VENTA") + SUMIFS(miercoles!D:D, miercoles!A:A, A82, miercoles!C:C, "VENTA") + SUMIFS(jueves!D:D, jueves!A:A, A82, jueves!C:C, "VENTA") + SUMIFS(viernes!D:D, viernes!A:A, A82, viernes!C:C, "VENTA") + SUMIFS(sabado!D:D, sabado!A:A, A82, sabado!C:C, "VENTA") -> 0 | D82: =SUMIFS(lunes!$D:$D, lunes!$A:$A, $A82, lunes!$C:$C, "ENTRADA") + SUMIFS(martes!$D:$D, martes!$A:$A, $A82, martes!$C:$C, "ENTRADA") + SUMIFS(miercoles!$D:$D, miercoles!$A:$A, $A82, miercoles!$C:$C, "ENTRADA") + SUMIFS(jueves!$D:$D, jueves!$A:$A, $A82, jueves!$C:$C, "ENTRADA") + SUMIFS(viernes!$D:$D, viernes!$A:$A, $A82, viernes!$C:$C, "ENTRADA") + SUMIFS(sabado!$D:$D, sabado!$A:$A, $A82, sabado!$C:$C, "ENTRADA") -> 0 | E82: =SUMIFS(lunes!$D:$D, lunes!$A:$A, $A82, lunes!$C:$C, "SALIDA") + SUMIFS(martes!$D:$D, martes!$A:$A, $A82, martes!$C:$C, "SALIDA") + SUMIFS(miercoles!$D:$D, miercoles!$A:$A, $A82, miercoles!$C:$C, "SALIDA") + SUMIFS(jueves!$D:$D, jueves!$A:$A, $A82, jueves!$C:$C, "SALIDA") + SUMIFS(viernes!$D:$D, viernes!$A:$A, $A82, viernes!$C:$C, "SALIDA") + SUMIFS(sabado!$D:$D, sabado!$A:$A, $A82, sabado!$C:$C, "SALIDA") -> 0 | F82: =B82-C82+D82-E82 -> 6 | G82: =IFERROR(VLOOKUP(A82, sabado!A:I, 9, 0), IFERROR(VLOOKUP(A82, viernes!A:I, 9, 0), IFERROR(VLOOKUP(A82, jueves!A:I, 9, 0), IFERROR(VLOOKUP(A82, miercoles!A:I, 9, 0), IFERROR(VLOOKUP(A82, martes!A:I, 9, 0), IFERROR(VLOOKUP(A82, lunes!A:I, 9, 0), B82)))))) -> 6 | H82: =VLOOKUP(A82, Configuracion!A:C, 3, FALSE) -> 190 | I82: =C82*H82 -> 0 | J82: =SUMIFS(lunes!$F:$F, lunes!$A:$A, $A82, lunes!$C:$C, "VENTA") + SUMIFS(martes!$F:$F, martes!$A:$A, $A82, martes!$C:$C, "VENTA") + SUMIFS(miercoles!$F:$F, miercoles!$A:$A, $A82, miercoles!$C:$C, "VENTA") + SUMIFS(jueves!$F:$F, jueves!$A:$A, $A82, jueves!$C:$C, "VENTA") + SUMIFS(viernes!$F:$F, viernes!$A:$A, $A82, viernes!$C:$C, "VENTA") + SUMIFS(sabado!$F:$F, sabado!$A:$A, $A82, sabado!$C:$C, "VENTA") -> 0 | K82: =I82-J82 -> 0
A83: =Configuracion!A83 -> LICUADORA MILEXUS 3000W PLASTICA 2 EN 1 | B83: =VLOOKUP(A83, Configuracion!A:B, 2, FALSE) -> 2 | C83: =SUMIFS(lunes!D:D, lunes!A:A, A83, lunes!C:C, "VENTA") + SUMIFS(martes!D:D, martes!A:A, A83, martes!C:C, "VENTA") + SUMIFS(miercoles!D:D, miercoles!A:A, A83, miercoles!C:C, "VENTA") + SUMIFS(jueves!D:D, jueves!A:A, A83, jueves!C:C, "VENTA") + SUMIFS(viernes!D:D, viernes!A:A, A83, viernes!C:C, "VENTA") + SUMIFS(sabado!D:D, sabado!A:A, A83, sabado!C:C, "VENTA") -> 0 | D83: =SUMIFS(lunes!$D:$D, lunes!$A:$A, $A83, lunes!$C:$C, "ENTRADA") + SUMIFS(martes!$D:$D, martes!$A:$A, $A83, martes!$C:$C, "ENTRADA") + SUMIFS(miercoles!$D:$D, miercoles!$A:$A, $A83, miercoles!$C:$C, "ENTRADA") + SUMIFS(jueves!$D:$D, jueves!$A:$A, $A83, jueves!$C:$C, "ENTRADA") + SUMIFS(viernes!$D:$D, viernes!$A:$A, $A83, viernes!$C:$C, "ENTRADA") + SUMIFS(sabado!$D:$D, sabado!$A:$A, $A83, sabado!$C:$C, "ENTRADA") -> 0 | E83: =SUMIFS(lunes!$D:$D, lunes!$A:$A, $A83, lunes!$C:$C, "SALIDA") + SUMIFS(martes!$D:$D, martes!$A:$A, $A83, martes!$C:$C, "SALIDA") + SUMIFS(miercoles!$D:$D, miercoles!$A:$A, $A83, miercoles!$C:$C, "SALIDA") + SUMIFS(jueves!$D:$D, jueves!$A:$A, $A83, jueves!$C:$C, "SALIDA") + SUMIFS(viernes!$D:$D, viernes!$A:$A, $A83, viernes!$C:$C, "SALIDA") + SUMIFS(sabado!$D:$D, sabado!$A:$A, $A83, sabado!$C:$C, "SALIDA") -> 0 | F83: =B83-C83+D83-E83 -> 2 | G83: =IFERROR(VLOOKUP(A83, sabado!A:I, 9, 0), IFERROR(VLOOKUP(A83, viernes!A:I, 9, 0), IFERROR(VLOOKUP(A83, jueves!A:I, 9, 0), IFERROR(VLOOKUP(A83, miercoles!A:I, 9, 0), IFERROR(VLOOKUP(A83, martes!A:I, 9, 0), IFERROR(VLOOKUP(A83, lunes!A:I, 9, 0), B83)))))) -> 2 | H83: =VLOOKUP(A83, Configuracion!A:C, 3, FALSE) -> 35 | I83: =C83*H83 -> 0 | J83: =SUMIFS(lunes!$F:$F, lunes!$A:$A, $A83, lunes!$C:$C, "VENTA") + SUMIFS(martes!$F:$F, martes!$A:$A, $A83, martes!$C:$C, "VENTA") + SUMIFS(miercoles!$F:$F, miercoles!$A:$A, $A83, miercoles!$C:$C, "VENTA") + SUMIFS(jueves!$F:$F, jueves!$A:$A, $A83, jueves!$C:$C, "VENTA") + SUMIFS(viernes!$F:$F, viernes!$A:$A, $A83, viernes!$C:$C, "VENTA") + SUMIFS(sabado!$F:$F, sabado!$A:$A, $A83, sabado!$C:$C, "VENTA") -> 0 | K83: =I83-J83 -> 0
A84: =Configuracion!A84 -> LICUADORA MILEXUS 400 W CRISTAL | B84: =VLOOKUP(A84, Configuracion!A:B, 2, FALSE) -> 3 | C84: =SUMIFS(lunes!D:D, lunes!A:A, A84, lunes!C:C, "VENTA") + SUMIFS(martes!D:D, martes!A:A, A84, martes!C:C, "VENTA") + SUMIFS(miercoles!D:D, miercoles!A:A, A84, miercoles!C:C, "VENTA") + SUMIFS(jueves!D:D, jueves!A:A, A84, jueves!C:C, "VENTA") + SUMIFS(viernes!D:D, viernes!A:A, A84, viernes!C:C, "VENTA") + SUMIFS(sabado!D:D, sabado!A:A, A84, sabado!C:C, "VENTA") -> 0 | D84: =SUMIFS(lunes!$D:$D, lunes!$A:$A, $A84, lunes!$C:$C, "ENTRADA") + SUMIFS(martes!$D:$D, martes!$A:$A, $A84, martes!$C:$C, "ENTRADA") + SUMIFS(miercoles!$D:$D, miercoles!$A:$A, $A84, miercoles!$C:$C, "ENTRADA") + SUMIFS(jueves!$D:$D, jueves!$A:$A, $A84, jueves!$C:$C, "ENTRADA") + SUMIFS(viernes!$D:$D, viernes!$A:$A, $A84, viernes!$C:$C, "ENTRADA") + SUMIFS(sabado!$D:$D, sabado!$A:$A, $A84, sabado!$C:$C, "ENTRADA") -> 0 | E84: =SUMIFS(lunes!$D:$D, lunes!$A:$A, $A84, lunes!$C:$C, "SALIDA") + SUMIFS(martes!$D:$D, martes!$A:$A, $A84, martes!$C:$C, "SALIDA") + SUMIFS(miercoles!$D:$D, miercoles!$A:$A, $A84, miercoles!$C:$C, "SALIDA") + SUMIFS(jueves!$D:$D, jueves!$A:$A, $A84, jueves!$C:$C, "SALIDA") + SUMIFS(viernes!$D:$D, viernes!$A:$A, $A84, viernes!$C:$C, "SALIDA") + SUMIFS(sabado!$D:$D, sabado!$A:$A, $A84, sabado!$C:$C, "SALIDA") -> 0 | F84: =B84-C84+D84-E84 -> 3 | G84: =IFERROR(VLOOKUP(A84, sabado!A:I, 9, 0), IFERROR(VLOOKUP(A84, viernes!A:I, 9, 0), IFERROR(VLOOKUP(A84, jueves!A:I, 9, 0), IFERROR(VLOOKUP(A84, miercoles!A:I, 9, 0), IFERROR(VLOOKUP(A84, martes!A:I, 9, 0), IFERROR(VLOOKUP(A84, lunes!A:I, 9, 0), B84)))))) -> 3 | H84: =VLOOKUP(A84, Configuracion!A:C, 3, FALSE) -> 40 | I84: =C84*H84 -> 0 | J84: =SUMIFS(lunes!$F:$F, lunes!$A:$A, $A84, lunes!$C:$C, "VENTA") + SUMIFS(martes!$F:$F, martes!$A:$A, $A84, martes!$C:$C, "VENTA") + SUMIFS(miercoles!$F:$F, miercoles!$A:$A, $A84, miercoles!$C:$C, "VENTA") + SUMIFS(jueves!$F:$F, jueves!$A:$A, $A84, jueves!$C:$C, "VENTA") + SUMIFS(viernes!$F:$F, viernes!$A:$A, $A84, viernes!$C:$C, "VENTA") + SUMIFS(sabado!$F:$F, sabado!$A:$A, $A84, sabado!$C:$C, "VENTA") -> 0 | K84: =I84-J84 -> 0
