Workbook
Name HOJASDIASDELMES: {"01";"02";"03";"04";"05";"06";"07";"08";"09";"10";"11";"12";"13";"14";"15";"16";"17";"18";"19";"20";"21";"22";"23";"24";"25";"26";"27";"28";"29";"30";"31"}

Sheet Movimiento de Producto
A1: Columna1 | B1: Columna2 | C1: Columna3 | D1: Columna4 | E1: Columna5 | F1: Columna6 | G1: ESTACION ENERGIA ECOFLOW DELTA 3
A2: Fecha | B2: Saldo al Inicio | C2: Entrada | D2: Rotura | E2: Venta | F2: Existencia
A3: 1 | B3: =VLOOKUP(G$1,'01'!B:J,2,0) -> 3 | C3: =VLOOKUP(G$1,'01'!B:J,3,0) -> 0 | D3: =VLOOKUP(G$1,'01'!B:J,4,0) -> 0 | E3: =VLOOKUP(G$1,'01'!B:J,6,0) -> 0 | F3: =B3+C3-E3 -> 3 | G3: =VLOOKUP(G$1,'01'!B:J,8,0) -> 0
A4: 2 | B4: =F3 -> 3 | C4: =VLOOKUP(G$1,'02'!B:J,3,0) -> 0 | D4: =VLOOKUP(G$1,'02'!B:J,4,0) -> 0 | E4: =VLOOKUP(G$1,'02'!B:J,6,0) -> 0 | F4: =B4+C4-E4 -> 3 | G4: =VLOOKUP(G$1,'02'!B:J,8,0) -> 0
A5: 3 | B5: =F4 -> 3 | C5: =VLOOKUP(G$1,'03'!B:J,3,0) -> 0 | D5: =VLOOKUP(G$1,'03'!B:J,4,0) -> 0 | E5: =VLOOKUP(G$1,'03'!B:J,6,0) -> 0 | F5: =B5+C5-E5 -> 3 | G5: =VLOOKUP(G$1,'03'!B:J,8,0) -> 0
A6: 4 | B6: =F5 -> 3 | C6: =VLOOKUP(G$1,'04'!B:J,3,0) -> 0 | D6: =VLOOKUP(G$1,'04'!B:J,4,0) -> 0 | E6: =VLOOKUP(G$1,'04'!B:J,6,0) -> 0 | F6: =B6+C6-E6 -> 3 | G6: =VLOOKUP(G$1,'04'!B:J,8,0) -> 0
A7: 5 | B7: =F6 -> 3 | C7: =VLOOKUP(G$1,'05'!B:J,3,0) -> 0 | D7: =VLOOKUP(G$1,'05'!B:J,4,0) -> 0 | E7: =VLOOKUP(G$1,'05'!B:J,6,0) -> 0 | F7: =B7+C7-E7 -> 3 | G7: =VLOOKUP(G$1,'05'!B:J,8,0) -> 0
A8: 6 | B8: =F7 -> 3 | C8: =VLOOKUP(G$1,'06'!B:J,3,0) -> 0 | D8: =VLOOKUP(G$1,'06'!B:J,4,0) -> 0 | E8: =VLOOKUP(G$1,'06'!B:J,6,0) -> 0 | F8: =B8+C8-E8 -> 3 | G8: =VLOOKUP(G$1,'06'!B:J,8,0) -> 0
A9: 7 | B9: =F8 -> 3 | C9: =VLOOKUP(G$1,'07'!B:J,3,0) -> 0 | D9: =VLOOKUP(G$1,'07'!B:J,4,0) -> 0 | E9: =VLOOKUP(G$1,'07'!B:J,6,0) -> 0 | F9: =B9+C9-E9 -> 3 | G9: =VLOOKUP(G$1,'07'!B:J,8,0) -> 0
A10: 8 | B10: =F9 -> 3 | C10: =VLOOKUP(G$1,'08'!B:J,3,0) -> 0 | D10: =VLOOKUP(G$1,'08'!B:J,4,0) -> 0 | E10: =VLOOKUP(G$1,'08'!B:J,6,0) -> 0 | F10: =B10+C10-E10 -> 3 | G10: =VLOOKUP(G$1,'08'!B:J,8,0) -> 0
A11: 9 | B11: =F10 -> 3 | C11: =VLOOKUP(G$1,'09'!B:J,3,0) -> 0 | D11: =VLOOKUP(G$1,'09'!B:J,4,0) -> 0 | E11: =VLOOKUP(G$1,'09'!B:J,6,0) -> 0 | F11: =B11+C11-E11 -> 3 | G11: =VLOOKUP(G$1,'09'!B:J,8,0) -> 0
A12: 10 | B12: =F11 -> 3 | C12: =VLOOKUP(G$1,'10'!B:J,3,0) -> 0 | D12: =VLOOKUP(G$1,'10'!B:J,4,0) -> 0 | E12: =VLOOKUP(G$1,'10'!B:J,6,0) -> 0 | F12: =B12+C12-E12 -> 3 | G12: =VLOOKUP(G$1,'10'!B:J,8,0) -> 0
A13: 11 | B13: =F12 -> 3 | C13: =VLOOKUP(G$1,'11'!B:J,3,0) -> 0 | D13: =VLOOKUP(G$1,'11'!B:J,4,0) -> 0 | E13: =VLOOKUP(G$1,'11'!B:J,6,0) -> 0 | F13: =B13+C13-E13 -> 3 | G13: =VLOOKUP(G$1,'11'!B:J,8,0) -> 0
A14: 12 | B14: =F13 -> 3 | C14: =VLOOKUP(G$1,'12'!B:J,3,0) -> 0 | D14: =VLOOKUP(G$1,'12'!B:J,4,0) -> 0 | E14: =VLOOKUP(G$1,'12'!B:J,6,0) -> 0 | F14: =B14+C14-E14 -> 3 | G14: =VLOOKUP(G$1,'12'!B:J,8,0) -> 0
A15: 13 | B15: =F14 -> 3 | C15: =VLOOKUP(G$1,'13'!B:J,3,0) -> 0 | D15: =VLOOKUP(G$1,'13'!B:J,4,0) -> 0 | E15: =VLOOKUP(G$1,'13'!B:J,6,0) -> 0 | F15: =B15+C15-E15 -> 3 | G15: =VLOOKUP(G$1,'13'!B:J,8,0) -> 0
A16: 14 | B16: =F15 -> 3 | C16: =VLOOKUP(G$1,'14'!B:J,3,0) -> 0 | D16: =VLOOKUP(G$1,'14'!B:J,4,0) -> 0 | E16: =VLOOKUP(G$1,'14'!B:J,6,0) -> 0 | F16: =B16+C16-E16 -> 3 | G16: =VLOOKUP(G$1,'14'!B:J,8,0) -> 0
A17: 15 | B17: =F16 -> 3 | C17: =VLOOKUP(G$1,'15'!B:J,3,0) -> 0 | D17: =VLOOKUP(G$1,'15'!B:J,4,0) -> 0 | E17: =VLOOKUP(G$1,'15'!B:J,6,0) -> 0 | F17: =B17+C17-E17 -> 3 | G17: =VLOOKUP(G$1,'15'!B:J,8,0) -> 0
A18: 16 | B18: =F17 -> 3 | C18: =VLOOKUP(G$1,'16'!B:J,3,0) -> 0 | D18: =VLOOKUP(G$1,'16'!B:J,4,0) -> 0 | E18: =VLOOKUP(G$1,'16'!B:J,6,0) -> 0 | F18: =B18+C18-E18 -> 3 | G18: =VLOOKUP(G$1,'16'!B:J,8,0) -> 0
A19: 17 | B19: =F18 -> 3 | C19: =VLOOKUP(G$1,'17'!B:J,3,0) -> 0 | D19: =VLOOKUP(G$1,'17'!B:J,4,0) -> 0 | E19: =VLOOKUP(G$1,'17'!B:J,6,0) -> 0 | F19: =B19+C19-E19 -> 3 | G19: =VLOOKUP(G$1,'17'!B:J,8,0) -> 0
A20: 18 | B20: =F19 -> 3 | C20: =VLOOKUP(G$1,'18'!B:J,3,0) -> 0 | D20: =VLOOKUP(G$1,'18'!B:J,4,0) -> 0 | E20: =VLOOKUP(G$1,'18'!B:J,6,0) -> 0 | F20: =B20+C20-E20 -> 3 | G20: =VLOOKUP(G$1,'18'!B:J,8,0) -> 0
A21: 19 | B21: =F20 -> 3 | C21: =VLOOKUP(G$1,'19'!B:J,3,0) -> 0 | D21: =VLOOKUP(G$1,'19'!B:J,4,0) -> 0 | E21: =VLOOKUP(G$1,'19'!B:J,6,0) -> 0 | F21: =B21+C21-E21 -> 3 | G21: =VLOOKUP(G$1,'19'!B:J,8,0) -> 0
A22: 20 | B22: =F21 -> 3 | C22: =VLOOKUP(G$1,'20'!B:J,3,0) -> 0 | D22: =VLOOKUP(G$1,'20'!B:J,4,0) -> 0 | E22: =VLOOKUP(G$1,'20'!B:J,6,0) -> 0 | F22: =B22+C22-E22 -> 3 | G22: =VLOOKUP(G$1,'20'!B:J,8,0) -> 0
A23: 21 | B23: =F22 -> 3 | C23: =VLOOKUP(G$1,'21'!B:J,3,0) -> 0 | D23: =VLOOKUP(G$1,'21'!B:J,4,0) -> 0 | E23: =VLOOKUP(G$1,'21'!B:J,6,0) -> 0 | F23: =B23+C23-E23 -> 3 | G23: =VLOOKUP(G$1,'21'!B:J,8,0) -> 0
A24: 22 | B24: =F23 -> 3 | C24: =VLOOKUP(G$1,'22'!B:J,3,0) -> 0 | D24: =VLOOKUP(G$1,'22'!B:J,4,0) -> 0 | E24: =VLOOKUP(G$1,'22'!B:J,6,0) -> 0 | F24: =B24+C24-E24 -> 3 | G24: =VLOOKUP(G$1,'22'!B:J,8,0) -> 0
A25: 23 | B25: =F24 -> 3 | C25: =VLOOKUP(G$1,'23'!B:J,3,0) -> 0 | D25: =VLOOKUP(G$1,'23'!B:J,4,0) -> 0 | E25: =VLOOKUP(G$1,'23'!B:J,6,0) -> 0 | F25: =B25+C25-E25 -> 3 | G25: =VLOOKUP(G$1,'23'!B:J,8,0) -> 0
A26: 24 | B26: =F25 -> 3 | C26: =VLOOKUP(G$1,'24'!B:J,3,0) -> 0 | D26: =VLOOKUP(G$1,'24'!B:J,4,0) -> 0 | E26: =VLOOKUP(G$1,'24'!B:J,6,0) -> 0 | F26: =B26+C26-E26 -> 3 | G26: =VLOOKUP(G$1,'24'!B:J,8,0) -> 0
A27: 25 | B27: =F26 -> 3 | C27: =VLOOKUP(G$1,'25'!B:J,3,0) -> 0 | D27: =VLOOKUP(G$1,'25'!B:J,4,0) -> 0 | E27: =VLOOKUP(G$1,'25'!B:J,6,0) -> 0 | F27: =B27+C27-E27 -> 3 | G27: =VLOOKUP(G$1,'25'!B:J,8,0) -> 0
A28: 26 | B28: =F27 -> 3 | C28: =VLOOKUP(G$1,'26'!B:J,3,0) -> 0 | D28: =VLOOKUP(G$1,'26'!B:J,4,0) -> 0 | E28: =VLOOKUP(G$1,'26'!B:J,6,0) -> 0 | F28: =B28+C28-E28 -> 3 | G28: =VLOOKUP(G$1,'26'!B:J,8,0) -> 0
A29: 27 | B29: =F28 -> 3 | C29: =VLOOKUP(G$1,'27'!B:J,3,0) -> 0 | D29: =VLOOKUP(G$1,'27'!B:J,4,0) -> 0 | E29: =VLOOKUP(G$1,'27'!B:J,6,0) -> 0 | F29: =B29+C29-E29 -> 3 | G29: =VLOOKUP(G$1,'27'!B:J,8,0) -> 0
A30: 28 | B30: =F29 -> 3 | C30: =VLOOKUP(G$1,'28'!B:J,3,0) -> 0 | D30: =VLOOKUP(G$1,'28'!B:J,4,0) -> 0 | E30: =VLOOKUP(G$1,'28'!B:J,6,0) -> 0 | F30: =B30+C30-E30 -> 3 | G30: =VLOOKUP(G$1,'28'!B:J,8,0) -> 0
A31: 29 | B31: =F30 -> 3 | C31: =VLOOKUP(G$1,'29'!B:J,3,0) -> 0 | D31: =VLOOKUP(G$1,'29'!B:J,4,0) -> 0 | E31: =VLOOKUP(G$1,'29'!B:J,6,0) -> 0 | F31: =B31+C31-E31 -> 3 | G31: =VLOOKUP(G$1,'29'!B:J,8,0) -> 0
A32: 30 | B32: =F31 -> 3 | C32: =VLOOKUP(G$1,'30'!B:J,3,0) -> 0 | D32: =VLOOKUP(G$1,'30'!B:J,4,0) -> 0 | E32: =VLOOKUP(G$1,'30'!B:J,6,0) -> 0 | F32: =B32+C32-E32 -> 3 | G32: =VLOOKUP(G$1,'30'!B:J,8,0) -> 0
A33: 31 | B33: =F32 -> 3 | C33: =VLOOKUP(G$1,'31'!B:J,3,0) -> 0 | D33: =VLOOKUP(G$1,'31'!B:J,4,0) -> 0 | E33: =VLOOKUP(G$1,'31'!B:J,6,0) -> 0 | F33: =B33+C33-E33 -> 3 | G33: =VLOOKUP(G$1,'31'!B:J,8,0) -> 0
A34: Total | B34: =B3 -> 3 | C34: =SUBTOTAL(109,Tabla1[Columna3]) -> 0 | D34: =SUBTOTAL(109,Tabla1[Columna4]) -> 0 | E34: =SUBTOTAL(109,Tabla1[Columna5]) -> 0 | F34: =F33 -> 3 | G34: =SUBTOTAL(109,Tabla1[ESTACION ENERGIA ECOFLOW DELTA 3]) -> 0

Sheet Estadística
B3: CONTROL DE INVENTARIO | F3: ÁREA: | G3: NOVA | K3: PUNTO DE VENTA: La Ola
B4: A PRECIO DE VENTA | K4: Período: | L4: =TODAY() -> 46296
F5: No, | K5: =SUBTOTAL(9,K9:K399) -> 118
C6: Venta Semana 1 | E6: Venta Semana 2 | G6: Venta Semana 3 | I6: Venta Semana 4 | K6: Venta Prom./Día | M6: Venta Prom./Semana | O6: Venta Estim./Mes
A7: UM | B7: DETALLE | C7: Físico | D7: Importe | E7: Físico | F7: Importe | G7: Físico | H7: Importe | I7: Físico | J7: Importe | K7: Físico | L7: Importe | M7: Físico | N7: Importe | O7: Físico | P7: Importe
A8: A | B8: B | C8: C | D8: D | E8: E | F8: F | G8: G | H8: H | I8: I | J8: J | K8: K | L8: L | M8: K | N8: L | O8: K | P8: L
A9: U | B9: BOLSA DE CEMENTO BLANCO | C9: =SUM(SUMIF(INDIRECT({"01";"02";"03";"04";"05";"06";"07"} & "!B:G"),$B9,INDIRECT({"01";"02";"03";"04";"05";"06";"07"} & "!G:G"))) -> 0 | D9: =SUM(SUMIF(INDIRECT({"01";"02";"03";"04";"05";"06";"07"} & "!B:I"),$B9,INDIRECT({"01";"02";"03";"04";"05";"06";"07"} & "!I:I"))) -> 0 | E9: {=SUM(SUMIF(INDIRECT({"08";"09";"10";"11";"12";"13";"14"} & "!B:G"),$B9,INDIRECT({"08";"09";"10";"11";"12";"13";"14"} & "!G:G")))} -> 0 | F9: {=SUM(SUMIF(INDIRECT({"08";"09";"10";"11";"12";"13";"14"} & "!B:I"),$B9,INDIRECT({"08";"09";"10";"11";"12";"13";"14"} & "!I:I")))} -> 0 | G9: {=SUM(SUMIF(INDIRECT({"15";"16";"17";"18";"19";"20";"21"} & "!B:G"),$B9,INDIRECT({"15";"16";"17";"18";"19";"20";"21"} & "!G:G")))} -> 0 | H9: {=SUM(SUMIF(INDIRECT({"15";"16";"17";"18";"19";"20";"21"} & "!B:I"),$B9,INDIRECT({"15";"16";"17";"18";"19";"20";"21"} & "!I:I")))} -> 0 | I9: {=SUM(SUMIF(INDIRECT({"22";"23";"24";"25";"26";"27";"28";"29";"30";"31"} & "!B:G"),$B9,INDIRECT({"22";"23";"24";"25";"26";"27";"28";"29";"30";"31"} & "!G:G")))} -> 0 | J9: {=SUM(SUMIF(INDIRECT({"22";"23";"24";"25";"26";"27";"28";"29";"30";"31"} & "!B:I"),$B9,INDIRECT({"22";"23";"24";"25";"26";"27";"28";"29";"30";"31"} & "!I:I")))} -> 0 | K9: =ROUND(SUM(C9,E9,G9,I9)/DAY(TODAY()),0) -> 0 | L9: =SUM(D9,F9,H9,J9)/DAY(TODAY()) -> 0 | M9: =K9*7 -> 0 | N9: =L9*7 -> 0 | O9: =ROUND(K9*30,0) -> 0 | P9: =L9*30 -> 0 | S9: =EXACT(B9,Total!B9) -> TRUE | T9: =SUM(D9+F9+H9+J9) -> 0 | W9: BOLSA DE CEMENTO BLANCO
A10: U | B10: SACO DE CEMENTO GRIS P350 | C10: =SUM(SUMIF(INDIRECT({"01";"02";"03";"04";"05";"06";"07"} & "!B:G"),$B10,INDIRECT({"01";"02";"03";"04";"05";"06";"07"} & "!G:G"))) -> 0 | D10: =SUM(SUMIF(INDIRECT({"01";"02";"03";"04";"05";"06";"07"} & "!B:I"),$B10,INDIRECT({"01";"02";"03";"04";"05";"06";"07"} & "!I:I"))) -> 0 | E10: {=SUM(SUMIF(INDIRECT({"08";"09";"10";"11";"12";"13";"14"} & "!B:G"),$B10,INDIRECT({"08";"09";"10";"11";"12";"13";"14"} & "!G:G")))} -> 5 | F10: {=SUM(SUMIF(INDIRECT({"08";"09";"10";"11";"12";"13";"14"} & "!B:I"),$B10,INDIRECT({"08";"09";"10";"11";"12";"13";"14"} & "!I:I")))} -> 150 | G10: {=SUM(SUMIF(INDIRECT({"15";"16";"17";"18";"19";"20";"21"} & "!B:G"),$B10,INDIRECT({"15";"16";"17";"18";"19";"20";"21"} & "!G:G")))} -> 0 | H10: {=SUM(SUMIF(INDIRECT({"15";"16";"17";"18";"19";"20";"21"} & "!B:I"),$B10,INDIRECT({"15";"16";"17";"18";"19";"20";"21"} & "!I:I")))} -> 0 | I10: {=SUM(SUMIF(INDIRECT({"22";"23";"24";"25";"26";"27";"28";"29";"30";"31"} & "!B:G"),$B10,INDIRECT({"22";"23";"24";"25";"26";"27";"28";"29";"30";"31"} & "!G:G")))} -> 0 | J10: {=SUM(SUMIF(INDIRECT({"22";"23";"24";"25";"26";"27";"28";"29";"30";"31"} & "!B:I"),$B10,INDIRECT({"22";"23";"24";"25";"26";"27";"28";"29";"30";"31"} & "!I:I")))} -> 0 | K10: =ROUND(SUM(C10,E10,G10,I10)/DAY(TODAY()),0) -> 5 | L10: =SUM(D10,F10,H10,J10)/DAY(TODAY()) -> 150 | M10: =K10*7 -> 35 | N10: =L10*7 -> 1050 | O10: =ROUND(K10*30,0) -> 150 | P10: =L10*30 -> 4500 | S10: =EXACT(B10,Total!B10) -> TRUE | T10: =SUM(D10+F10+H10+J10) -> 150 | W10: SACO DE CEMENTO GRIS P350
B11: BATERIA 5K MUST | C11: =SUM(SUMIF(INDIRECT({"01";"02";"03";"04";"05";"06";"07"} & "!B:G"),$B11,INDIRECT({"01";"02";"03";"04";"05";"06";"07"} & "!G:G"))) -> 2 | D11: =SUM(SUMIF(INDIRECT({"01";"02";"03";"04";"05";"06";"07"} & "!B:I"),$B11,INDIRECT({"01";"02";"03";"04";"05";"06";"07"} & "!I:I"))) -> 3200 | E11: {=SUM(SUMIF(INDIRECT({"08";"09";"10";"11";"12";"13";"14"} & "!B:G"),$B11,INDIRECT({"08";"09";"10";"11";"12";"13";"14"} & "!G:G")))} -> 0 | F11: {=SUM(SUMIF(INDIRECT({"08";"09";"10";"11";"12";"13";"14"} & "!B:I"),$B11,INDIRECT({"08";"09";"10";"11";"12";"13";"14"} & "!I:I")))} -> 0 | G11: {=SUM(SUMIF(INDIRECT({"15";"16";"17";"18";"19";"20";"21"} & "!B:G"),$B11,INDIRECT({"15";"16";"17";"18";"19";"20";"21"} & "!G:G")))} -> 0 | H11: {=SUM(SUMIF(INDIRECT({"15";"16";"17";"18";"19";"20";"21"} & "!B:I"),$B11,INDIRECT({"15";"16";"17";"18";"19";"20";"21"} & "!I:I")))} -> 0 | I11: {=SUM(SUMIF(INDIRECT({"22";"23";"24";"25";"26";"27";"28";"29";"30";"31"} & "!B:G"),$B11,INDIRECT({"22";"23";"24";"25";"26";"27";"28";"29";"30";"31"} & "!G:G")))} -> 0 | J11: {=SUM(SUMIF(INDIRECT({"22";"23";"24";"25";"26";"27";"28";"29";"30";"31"} & "!B:I"),$B11,INDIRECT({"22";"23";"24";"25";"26";"27";"28";"29";"30";"31"} & "!I:I")))} -> 0 | K11: =ROUND(SUM(C11,E11,G11,I11)/DAY(TODAY()),0) -> 2 | L11: =SUM(D11,F11,H11,J11)/DAY(TODAY()) -> 3200 | M11: =K11*7 -> 14 | N11: =L11*7 -> 22400 | O11: =ROUND(K11*30,0) -> 60 | P11: =L11*30 -> 96000 | S11: =EXACT(B11,Total!B11) -> TRUE | T11: =SUM(D11+F11+H11+J11) -> 3200 | W11: BATERIA 5K MUST
B12: BATERIA HUMSIENK 24V 200AMP | C12: =SUM(SUMIF(INDIRECT({"01";"02";"03";"04";"05";"06";"07"} & "!B:G"),$B12,INDIRECT({"01";"02";"03";"04";"05";"06";"07"} & "!G:G"))) -> 0 | D12: =SUM(SUMIF(INDIRECT({"01";"02";"03";"04";"05";"06";"07"} & "!B:I"),$B12,INDIRECT({"01";"02";"03";"04";"05";"06";"07"} & "!I:I"))) -> 0 | E12: {=SUM(SUMIF(INDIRECT({"08";"09";"10";"11";"12";"13";"14"} & "!B:G"),$B12,INDIRECT({"08";"09";"10";"11";"12";"13";"14"} & "!G:G")))} -> 0 | F12: {=SUM(SUMIF(INDIRECT({"08";"09";"10";"11";"12";"13";"14"} & "!B:I"),$B12,INDIRECT({"08";"09";"10";"11";"12";"13";"14"} & "!I:I")))} -> 0 | G12: {=SUM(SUMIF(INDIRECT({"15";"16";"17";"18";"19";"20";"21"} & "!B:G"),$B12,INDIRECT({"15";"16";"17";"18";"19";"20";"21"} & "!G:G")))} -> 0 | H12: {=SUM(SUMIF(INDIRECT({"15";"16";"17";"18";"19";"20";"21"} & "!B:I"),$B12,INDIRECT({"15";"16";"17";"18";"19";"20";"21"} & "!I:I")))} -> 0 | I12: {=SUM(SUMIF(INDIRECT({"22";"23";"24";"25";"26";"27";"28";"29";"30";"31"} & "!B:G"),$B12,INDIRECT({"22";"23";"24";"25";"26";"27";"28";"29";"30";"31"} & "!G:G")))} -> 0 | J12: {=SUM(SUMIF(INDIRECT({"22";"23";"24";"25";"26";"27";"28";"29";"30";"31"} & "!B:I"),$B12,INDIRECT({"22";"23";"24";"25";"26";"27";"28";"29";"30";"31"} & "!I:I")))} -> 0 | K12: =ROUND(SUM(C12,E12,G12,I12)/DAY(TODAY()),0) -> 0 | L12: =SUM(D12,F12,H12,J12)/DAY(TODAY()) -> 0 | M12: =K12*7 -> 0 | N12: =L12*7 -> 0 | O12: =ROUND(K12*30,0) -> 0 | P12: =L12*30 -> 0 | S12: =EXACT(B12,Total!B12) -> TRUE | T12: =SUM(D12+F12+H12+J12) -> 0 | W12: BATERIA HUMSIENK 24V 200AMP
A13: U | B13: BATERIA DE 12V 100A JMD | C13: =SUM(SUMIF(INDIRECT({"01";"02";"03";"04";"05";"06";"07"} & "!B:G"),$B13,INDIRECT({"01";"02";"03";"04";"05";"06";"07"} & "!G:G"))) -> 0 | D13: =SUM(SUMIF(INDIRECT({"01";"02";"03";"04";"05";"06";"07"} & "!B:I"),$B13,INDIRECT({"01";"02";"03";"04";"05";"06";"07"} & "!I:I"))) -> 0 | E13: {=SUM(SUMIF(INDIRECT({"08";"09";"10";"11";"12";"13";"14"} & "!B:G"),$B13,INDIRECT({"08";"09";"10";"11";"12";"13";"14"} & "!G:G")))} -> 0 | F13: {=SUM(SUMIF(INDIRECT({"08";"09";"10";"11";"12";"13";"14"} & "!B:I"),$B13,INDIRECT({"08";"09";"10";"11";"12";"13";"14"} & "!I:I")))} -> 0 | G13: {=SUM(SUMIF(INDIRECT({"15";"16";"17";"18";"19";"20";"21"} & "!B:G"),$B13,INDIRECT({"15";"16";"17";"18";"19";"20";"21"} & "!G:G")))} -> 0 | H13: {=SUM(SUMIF(INDIRECT({"15";"16";"17";"18";"19";"20";"21"} & "!B:I"),$B13,INDIRECT({"15";"16";"17";"18";"19";"20";"21"} & "!I:I")))} -> 0 | I13: {=SUM(SUMIF(INDIRECT({"22";"23";"24";"25";"26";"27";"28";"29";"30";"31"} & "!B:G"),$B13,INDIRECT({"22";"23";"24";"25";"26";"27";"28";"29";"30";"31"} & "!G:G")))} -> 0 | J13: {=SUM(SUMIF(INDIRECT({"22";"23";"24";"25";"26";"27";"28";"29";"30";"31"} & "!B:I"),$B13,INDIRECT({"22";"23";"24";"25";"26";"27";"28";"29";"30";"31"} & "!I:I")))} -> 0 | K13: =ROUND(SUM(C13,E13,G13,I13)/DAY(TODAY()),0) -> 0 | L13: =SUM(D13,F13,H13,J13)/DAY(TODAY()) -> 0 | M13: =K13*7 -> 0 | N13: =L13*7 -> 0 | O13: =ROUND(K13*30,0) -> 0 | P13: =L13*30 -> 0 | S13: =EXACT(B13,Total!B13) -> TRUE | T13: =SUM(D13+F13+H13+J13) -> 0 | W13: BATERIA DE 12V 100A JMD
B14: BATERIA DE 12V 150A SACO | C14: =SUM(SUMIF(INDIRECT({"01";"02";"03";"04";"05";"06";"07"} & "!B:G"),$B14,INDIRECT({"01";"02";"03";"04";"05";"06";"07"} & "!G:G"))) -> 0 | D14: =SUM(SUMIF(INDIRECT({"01";"02";"03";"04";"05";"06";"07"} & "!B:I"),$B14,INDIRECT({"01";"02";"03";"04";"05";"06";"07"} & "!I:I"))) -> 0 | E14: {=SUM(SUMIF(INDIRECT({"08";"09";"10";"11";"12";"13";"14"} & "!B:G"),$B14,INDIRECT({"08";"09";"10";"11";"12";"13";"14"} & "!G:G")))} -> 0 | F14: {=SUM(SUMIF(INDIRECT({"08";"09";"10";"11";"12";"13";"14"} & "!B:I"),$B14,INDIRECT({"08";"09";"10";"11";"12";"13";"14"} & "!I:I")))} -> 0 | G14: {=SUM(SUMIF(INDIRECT({"15";"16";"17";"18";"19";"20";"21"} & "!B:G"),$B14,INDIRECT({"15";"16";"17";"18";"19";"20";"21"} & "!G:G")))} -> 1 | H14: {=SUM(SUMIF(INDIRECT({"15";"16";"17";"18";"19";"20";"21"} & "!B:I"),$B14,INDIRECT({"15";"16";"17";"18";"19";"20";"21"} & "!I:I")))} -> 500 | I14: {=SUM(SUMIF(INDIRECT({"22";"23";"24";"25";"26";"27";"28";"29";"30";"31"} & "!B:G"),$B14,INDIRECT({"22";"23";"24";"25";"26";"27";"28";"29";"30";"31"} & "!G:G")))} -> 0 | J14: {=SUM(SUMIF(INDIRECT({"22";"23";"24";"25";"26";"27";"28";"29";"30";"31"} & "!B:I"),$B14,INDIRECT({"22";"23";"24";"25";"26";"27";"28";"29";"30";"31"} & "!I:I")))} -> 0 | K14: =ROUND(SUM(C14,E14,G14,I14)/DAY(TODAY()),0) -> 1 | L14: =SUM(D14,F14,H14,J14)/DAY(TODAY()) -> 500 | M14: =K14*7 -> 7 | N14: =L14*7 -> 3500 | O14: =ROUND(K14*30,0) -> 30 | P14: =L14*30 -> 15000 | S14: =EXACT(B14,Total!B14) -> TRUE | T14: =SUM(D14+F14+H14+J14) -> 500 | W14: BATERIA DE 12V 150A SACO
A15: U | B15: BATERIA EXTRA 16K SACO | C15: =SUM(SUMIF(INDIRECT({"01";"02";"03";"04";"05";"06";"07"} & "!B:G"),$B15,INDIRECT({"01";"02";"03";"04";"05";"06";"07"} & "!G:G"))) -> 0 | D15: =SUM(SUMIF(INDIRECT({"01";"02";"03";"04";"05";"06";"07"} & "!B:I"),$B15,INDIRECT({"01";"02";"03";"04";"05";"06";"07"} & "!I:I"))) -> 0 | E15: {=SUM(SUMIF(INDIRECT({"08";"09";"10";"11";"12";"13";"14"} & "!B:G"),$B15,INDIRECT({"08";"09";"10";"11";"12";"13";"14"} & "!G:G")))} -> 0 | F15: {=SUM(SUMIF(INDIRECT({"08";"09";"10";"11";"12";"13";"14"} & "!B:I"),$B15,INDIRECT({"08";"09";"10";"11";"12";"13";"14"} & "!I:I")))} -> 0 | G15: {=SUM(SUMIF(INDIRECT({"15";"16";"17";"18";"19";"20";"21"} & "!B:G"),$B15,INDIRECT({"15";"16";"17";"18";"19";"20";"21"} & "!G:G")))} -> 0 | H15: {=SUM(SUMIF(INDIRECT({"15";"16";"17";"18";"19";"20";"21"} & "!B:I"),$B15,INDIRECT({"15";"16";"17";"18";"19";"20";"21"} & "!I:I")))} -> 0 | I15: {=SUM(SUMIF(INDIRECT({"22";"23";"24";"25";"26";"27";"28";"29";"30";"31"} & "!B:G"),$B15,INDIRECT({"22";"23";"24";"25";"26";"27";"28";"29";"30";"31"} & "!G:G")))} -> 0 | J15: {=SUM(SUMIF(INDIRECT({"22";"23";"24";"25";"26";"27";"28";"29";"30";"31"} & "!B:I"),$B15,INDIRECT({"22";"23";"24";"25";"26";"27";"28";"29";"30";"31"} & "!I:I")))} -> 0 | K15: =ROUND(SUM(C15,E15,G15,I15)/DAY(TODAY()),0) -> 0 | L15: =SUM(D15,F15,H15,J15)/DAY(TODAY()) -> 0 | M15: =K15*7 -> 0 | N15: =L15*7 -> 0 | O15: =ROUND(K15*30,0) -> 0 | P15: =L15*30 -> 0 | S15: =EXACT(B15,Total!B15) -> TRUE | T15: =SUM(D15+F15+H15+J15) -> 0 | W15: BATERIA EXTRA 16K SACO
A16: U | B16: BASE PARA PANELES GRANDES | C16: =SUM(SUMIF(INDIRECT({"01";"02";"03";"04";"05";"06";"07"} & "!B:G"),$B16,INDIRECT({"01";"02";"03";"04";"05";"06";"07"} & "!G:G"))) -> 0 | D16: =SUM(SUMIF(INDIRECT({"01";"02";"03";"04";"05";"06";"07"} & "!B:I"),$B16,INDIRECT({"01";"02";"03";"04";"05";"06";"07"} & "!I:I"))) -> 0 | E16: {=SUM(SUMIF(INDIRECT({"08";"09";"10";"11";"12";"13";"14"} & "!B:G"),$B16,INDIRECT({"08";"09";"10";"11";"12";"13";"14"} & "!G:G")))} -> 0 | F16: {=SUM(SUMIF(INDIRECT({"08";"09";"10";"11";"12";"13";"14"} & "!B:I"),$B16,INDIRECT({"08";"09";"10";"11";"12";"13";"14"} & "!I:I")))} -> 0 | G16: {=SUM(SUMIF(INDIRECT({"15";"16";"17";"18";"19";"20";"21"} & "!B:G"),$B16,INDIRECT({"15";"16";"17";"18";"19";"20";"21"} & "!G:G")))} -> 0 | H16: {=SUM(SUMIF(INDIRECT({"15";"16";"17";"18";"19";"20";"21"} & "!B:I"),$B16,INDIRECT({"15";"16";"17";"18";"19";"20";"21"} & "!I:I")))} -> 0 | I16: {=SUM(SUMIF(INDIRECT({"22";"23";"24";"25";"26";"27";"28";"29";"30";"31"} & "!B:G"),$B16,INDIRECT({"22";"23";"24";"25";"26";"27";"28";"29";"30";"31"} & "!G:G")))} -> 0 | J16: {=SUM(SUMIF(INDIRECT({"22";"23";"24";"25";"26";"27";"28";"29";"30";"31"} & "!B:I"),$B16,INDIRECT({"22";"23";"24";"25";"26";"27";"28";"29";"30";"31"} & "!I:I")))} -> 0 | K16: =ROUND(SUM(C16,E16,G16,I16)/DAY(TODAY()),0) -> 0 | L16: =SUM(D16,F16,H16,J16)/DAY(TODAY()) -> 0 | M16: =K16*7 -> 0 | N16: =L16*7 -> 0 | O16: =ROUND(K16*30,0) -> 0 | P16: =L16*30 -> 0 | S16: =EXACT(B16,Total!B16) -> TRUE | T16: =SUM(D16+F16+H16+J16) -> 0 | W16: BASE PARA PANELES GRANDES
A17: U | B17: BASE PARA PANELES | C17: =SUM(SUMIF(INDIRECT({"01";"02";"03";"04";"05";"06";"07"} & "!B:G"),$B17,INDIRECT({"01";"02";"03";"04";"05";"06";"07"} & "!G:G"))) -> 0 | D17: =SUM(SUMIF(INDIRECT({"01";"02";"03";"04";"05";"06";"07"} & "!B:I"),$B17,INDIRECT({"01";"02";"03";"04";"05";"06";"07"} & "!I:I"))) -> 0 | E17: {=SUM(SUMIF(INDIRECT({"08";"09";"10";"11";"12";"13";"14"} & "!B:G"),$B17,INDIRECT({"08";"09";"10";"11";"12";"13";"14"} & "!G:G")))} -> 0 | F17: {=SUM(SUMIF(INDIRECT({"08";"09";"10";"11";"12";"13";"14"} & "!B:I"),$B17,INDIRECT({"08";"09";"10";"11";"12";"13";"14"} & "!I:I")))} -> 0 | G17: {=SUM(SUMIF(INDIRECT({"15";"16";"17";"18";"19";"20";"21"} & "!B:G"),$B17,INDIRECT({"15";"16";"17";"18";"19";"20";"21"} & "!G:G")))} -> 0 | H17: {=SUM(SUMIF(INDIRECT({"15";"16";"17";"18";"19";"20";"21"} & "!B:I"),$B17,INDIRECT({"15";"16";"17";"18";"19";"20";"21"} & "!I:I")))} -> 0 | I17: {=SUM(SUMIF(INDIRECT({"22";"23";"24";"25";"26";"27";"28";"29";"30";"31"} & "!B:G"),$B17,INDIRECT({"22";"23";"24";"25";"26";"27";"28";"29";"30";"31"} & "!G:G")))} -> 0 | J17: {=SUM(SUMIF(INDIRECT({"22";"23";"24";"25";"26";"27";"28";"29";"30";"31"} & "!B:I"),$B17,INDIRECT({"22";"23";"24";"25";"26";"27";"28";"29";"30";"31"} & "!I:I")))} -> 0 | K17: =ROUND(SUM(C17,E17,G17,I17)/DAY(TODAY()),0) -> 0 | L17: =SUM(D17,F17,H17,J17)/DAY(TODAY()) -> 0 | M17: =K17*7 -> 0 | N17: =L17*7 -> 0 | O17: =ROUND(K17*30,0) -> 0 | P17: =L17*30 -> 0 | S17: =EXACT(B17,Total!B17) -> TRUE | T17: =SUM(D17+F17+H17+J17) -> 0 | W17: BASE PARA PANELES
A18: U | B18: BASE FIJA PARA TV 32'' - 86'' | C18: =SUM(SUMIF(INDIRECT({"01";"02";"03";"04";"05";"06";"07"} & "!B:G"),$B18,INDIRECT({"01";"02";"03";"04";"05";"06";"07"} & "!G:G"))) -> 0 | D18: =SUM(SUMIF(INDIRECT({"01";"02";"03";"04";"05";"06";"07"} & "!B:I"),$B18,INDIRECT({"01";"02";"03";"04";"05";"06";"07"} & "!I:I"))) -> 0 | E18: {=SUM(SUMIF(INDIRECT({"08";"09";"10";"11";"12";"13";"14"} & "!B:G"),$B18,INDIRECT({"08";"09";"10";"11";"12";"13";"14"} & "!G:G")))} -> 1 | F18: {=SUM(SUMIF(INDIRECT({"08";"09";"10";"11";"12";"13";"14"} & "!B:I"),$B18,INDIRECT({"08";"09";"10";"11";"12";"13";"14"} & "!I:I")))} -> 20 | G18: {=SUM(SUMIF(INDIRECT({"15";"16";"17";"18";"19";"20";"21"} & "!B:G"),$B18,INDIRECT({"15";"16";"17";"18";"19";"20";"21"} & "!G:G")))} -> 0 | H18: {=SUM(SUMIF(INDIRECT({"15";"16";"17";"18";"19";"20";"21"} & "!B:I"),$B18,INDIRECT({"15";"16";"17";"18";"19";"20";"21"} & "!I:I")))} -> 0 | I18: {=SUM(SUMIF(INDIRECT({"22";"23";"24";"25";"26";"27";"28";"29";"30";"31"} & "!B:G"),$B18,INDIRECT({"22";"23";"24";"25";"26";"27";"28";"29";"30";"31"} & "!G:G")))} -> 0 | J18: {=SUM(SUMIF(INDIRECT({"22";"23";"24";"25";"26";"27";"28";"29";"30";"31"} & "!B:I"),$B18,INDIRECT({"22";"23";"24";"25";"26";"27";"28";"29";"30";"31"} & "!I:I")))} -> 0 | K18: =ROUND(SUM(C18,E18,G18,I18)/DAY(TODAY()),0) -> 1 | L18: =SUM(D18,F18,H18,J18)/DAY(TODAY()) -> 20 | M18: =K18*7 -> 7 | N18: =L18*7 -> 140 | O18: =ROUND(K18*30,0) -> 30 | P18: =L18*30 -> 600 | S18: =EXACT(B18,Total!B18) -> TRUE | T18: =SUM(D18+F18+H18+J18) -> 20 | W18: BASE FIJA PARA TV 32'' - 86''
A19: U | B19: BASE GIRATORIA | C19: =SUM(SUMIF(INDIRECT({"01";"02";"03";"04";"05";"06";"07"} & "!B:G"),$B19,INDIRECT({"01";"02";"03";"04";"05";"06";"07"} & "!G:G"))) -> 0 | D19: =SUM(SUMIF(INDIRECT({"01";"02";"03";"04";"05";"06";"07"} & "!B:I"),$B19,INDIRECT({"01";"02";"03";"04";"05";"06";"07"} & "!I:I"))) -> 0 | E19: {=SUM(SUMIF(INDIRECT({"08";"09";"10";"11";"12";"13";"14"} & "!B:G"),$B19,INDIRECT({"08";"09";"10";"11";"12";"13";"14"} & "!G:G")))} -> 0 | F19: {=SUM(SUMIF(INDIRECT({"08";"09";"10";"11";"12";"13";"14"} & "!B:I"),$B19,INDIRECT({"08";"09";"10";"11";"12";"13";"14"} & "!I:I")))} -> 0 | G19: {=SUM(SUMIF(INDIRECT({"15";"16";"17";"18";"19";"20";"21"} & "!B:G"),$B19,INDIRECT({"15";"16";"17";"18";"19";"20";"21"} & "!G:G")))} -> 0 | H19: {=SUM(SUMIF(INDIRECT({"15";"16";"17";"18";"19";"20";"21"} & "!B:I"),$B19,INDIRECT({"15";"16";"17";"18";"19";"20";"21"} & "!I:I")))} -> 0 | I19: {=SUM(SUMIF(INDIRECT({"22";"23";"24";"25";"26";"27";"28";"29";"30";"31"} & "!B:G"),$B19,INDIRECT({"22";"23";"24";"25";"26";"27";"28";"29";"30";"31"} & "!G:G")))} -> 0 | J19: {=SUM(SUMIF(INDIRECT({"22";"23";"24";"25";"26";"27";"28";"29";"30";"31"} & "!B:I"),$B19,INDIRECT({"22";"23";"24";"25";"26";"27";"28";"29";"30";"31"} & "!I:I")))} -> 0 | K19: =ROUND(SUM(C19,E19,G19,I19)/DAY(TODAY()),0) -> 0 | L19: =SUM(D19,F19,H19,J19)/DAY(TODAY()) -> 0 | M19: =K19*7 -> 0 | N19: =L19*7 -> 0 | O19: =ROUND(K19*30,0) -> 0 | P19: =L19*30 -> 0 | S19: =EXACT(B19,Total!B19) -> TRUE | T19: =SUM(D19+F19+H19+J19) -> 0 | W19: BASE GIRATORIA
A20: U | B20: BASE PARA SPLIT | C20: =SUM(SUMIF(INDIRECT({"01";"02";"03";"04";"05";"06";"07"} & "!B:G"),$B20,INDIRECT({"01";"02";"03";"04";"05";"06";"07"} & "!G:G"))) -> 0 | D20: =SUM(SUMIF(INDIRECT({"01";"02";"03";"04";"05";"06";"07"} & "!B:I"),$B20,INDIRECT({"01";"02";"03";"04";"05";"06";"07"} & "!I:I"))) -> 0 | E20: {=SUM(SUMIF(INDIRECT({"08";"09";"10";"11";"12";"13";"14"} & "!B:G"),$B20,INDIRECT({"08";"09";"10";"11";"12";"13";"14"} & "!G:G")))} -> 0 | F20: {=SUM(SUMIF(INDIRECT({"08";"09";"10";"11";"12";"13";"14"} & "!B:I"),$B20,INDIRECT({"08";"09";"10";"11";"12";"13";"14"} & "!I:I")))} -> 0 | G20: {=SUM(SUMIF(INDIRECT({"15";"16";"17";"18";"19";"20";"21"} & "!B:G"),$B20,INDIRECT({"15";"16";"17";"18";"19";"20";"21"} & "!G:G")))} -> 0 | H20: {=SUM(SUMIF(INDIRECT({"15";"16";"17";"18";"19";"20";"21"} & "!B:I"),$B20,INDIRECT({"15";"16";"17";"18";"19";"20";"21"} & "!I:I")))} -> 0 | I20: {=SUM(SUMIF(INDIRECT({"22";"23";"24";"25";"26";"27";"28";"29";"30";"31"} & "!B:G"),$B20,INDIRECT({"22";"23";"24";"25";"26";"27";"28";"29";"30";"31"} & "!G:G")))} -> 0 | J20: {=SUM(SUMIF(INDIRECT({"22";"23";"24";"25";"26";"27";"28";"29";"30";"31"} & "!B:I"),$B20,INDIRECT({"22";"23";"24";"25";"26";"27";"28";"29";"30";"31"} & "!I:I")))} -> 0 | K20: =ROUND(SUM(C20,E20,G20,I20)/DAY(TODAY()),0) -> 0 | L20: =SUM(D20,F20,H20,J20)/DAY(TODAY()) -> 0 | M20: =K20*7 -> 0 | N20: =L20*7 -> 0 | O20: =ROUND(K20*30,0) -> 0 | P20: =L20*30 -> 0 | S20: =EXACT(B20,Total!B20) -> TRUE | T20: =SUM(D20+F20+H20+J20) -> 0 | W20: BASE PARA SPLIT
B21: BATERIA 15K MUST | C21: =SUM(SUMIF(INDIRECT({"01";"02";"03";"04";"05";"06";"07"} & "!B:G"),$B21,INDIRECT({"01";"02";"03";"04";"05";"06";"07"} & "!G:G"))) -> 0 | D21: =SUM(SUMIF(INDIRECT({"01";"02";"03";"04";"05";"06";"07"} & "!B:I"),$B21,INDIRECT({"01";"02";"03";"04";"05";"06";"07"} & "!I:I"))) -> 0 | E21: {=SUM(SUMIF(INDIRECT({"08";"09";"10";"11";"12";"13";"14"} & "!B:G"),$B21,INDIRECT({"08";"09";"10";"11";"12";"13";"14"} & "!G:G")))} -> 0 | F21: {=SUM(SUMIF(INDIRECT({"08";"09";"10";"11";"12";"13";"14"} & "!B:I"),$B21,INDIRECT({"08";"09";"10";"11";"12";"13";"14"} & "!I:I")))} -> 0 | G21: {=SUM(SUMIF(INDIRECT({"15";"16";"17";"18";"19";"20";"21"} & "!B:G"),$B21,INDIRECT({"15";"16";"17";"18";"19";"20";"21"} & "!G:G")))} -> 0 | H21: {=SUM(SUMIF(INDIRECT({"15";"16";"17";"18";"19";"20";"21"} & "!B:I"),$B21,INDIRECT({"15";"16";"17";"18";"19";"20";"21"} & "!I:I")))} -> 0 | I21: {=SUM(SUMIF(INDIRECT({"22";"23";"24";"25";"26";"27";"28";"29";"30";"31"} & "!B:G"),$B21,INDIRECT({"22";"23";"24";"25";"26";"27";"28";"29";"30";"31"} & "!G:G")))} -> 1 | J21: {=SUM(SUMIF(INDIRECT({"22";"23";"24";"25";"26";"27";"28";"29";"30";"31"} & "!B:I"),$B21,INDIRECT({"22";"23";"24";"25";"26";"27";"28";"29";"30";"31"} & "!I:I")))} -> 3450 | K21: =ROUND(SUM(C21,E21,G21,I21)/DAY(TODAY()),0) -> 1 | L21: =SUM(D21,F21,H21,J21)/DAY(TODAY()) -> 3450 | M21: =K21*7 -> 7 | N21: =L21*7 -> 24150 | O21: =ROUND(K21*30,0) -> 30 | P21: =L21*30 -> 103500 | S21: =EXACT(B21,Total!B21) -> TRUE | T21: =SUM(D21+F21+H21+J21) -> 3450 | W21: BATERIA 15K MUST
B22: BREKE 63A SENCILLO | C22: =SUM(SUMIF(INDIRECT({"01";"02";"03";"04";"05";"06";"07"} & "!B:G"),$B22,INDIRECT({"01";"02";"03";"04";"05";"06";"07"} & "!G:G"))) -> 0 | D22: =SUM(SUMIF(INDIRECT({"01";"02";"03";"04";"05";"06";"07"} & "!B:I"),$B22,INDIRECT({"01";"02";"03";"04";"05";"06";"07"} & "!I:I"))) -> 0 | E22: {=SUM(SUMIF(INDIRECT({"08";"09";"10";"11";"12";"13";"14"} & "!B:G"),$B22,INDIRECT({"08";"09";"10";"11";"12";"13";"14"} & "!G:G")))} -> 0 | F22: {=SUM(SUMIF(INDIRECT({"08";"09";"10";"11";"12";"13";"14"} & "!B:I"),$B22,INDIRECT({"08";"09";"10";"11";"12";"13";"14"} & "!I:I")))} -> 0 | G22: {=SUM(SUMIF(INDIRECT({"15";"16";"17";"18";"19";"20";"21"} & "!B:G"),$B22,INDIRECT({"15";"16";"17";"18";"19";"20";"21"} & "!G:G")))} -> 0 | H22: {=SUM(SUMIF(INDIRECT({"15";"16";"17";"18";"19";"20";"21"} & "!B:I"),$B22,INDIRECT({"15";"16";"17";"18";"19";"20";"21"} & "!I:I")))} -> 0 | I22: {=SUM(SUMIF(INDIRECT({"22";"23";"24";"25";"26";"27";"28";"29";"30";"31"} & "!B:G"),$B22,INDIRECT({"22";"23";"24";"25";"26";"27";"28";"29";"30";"31"} & "!G:G")))} -> 0 | J22: {=SUM(SUMIF(INDIRECT({"22";"23";"24";"25";"26";"27";"28";"29";"30";"31"} & "!B:I"),$B22,INDIRECT({"22";"23";"24";"25";"26";"27";"28";"29";"30";"31"} & "!I:I")))} -> 0 | K22: =ROUND(SUM(C22,E22,G22,I22)/DAY(TODAY()),0) -> 0 | L22: =SUM(D22,F22,H22,J22)/DAY(TODAY()) -> 0 | M22: =K22*7 -> 0 | N22: =L22*7 -> 0 | O22: =ROUND(K22*30,0) -> 0 | P22: =L22*30 -> 0 | S22: =EXACT(B22,Total!B22) -> TRUE | T22: =SUM(D22+F22+H22+J22) -> 0 | W22: BREKE 63A SENCILLO
A23: U | B23: BATERIA MUST 10.25 KW | C23: =SUM(SUMIF(INDIRECT({"01";"02";"03";"04";"05";"06";"07"} & "!B:G"),$B23,INDIRECT({"01";"02";"03";"04";"05";"06";"07"} & "!G:G"))) -> 1 | D23: =SUM(SUMIF(INDIRECT({"01";"02";"03";"04";"05";"06";"07"} & "!B:I"),$B23,INDIRECT({"01";"02";"03";"04";"05";"06";"07"} & "!I:I"))) -> 2600 | E23: {=SUM(SUMIF(INDIRECT({"08";"09";"10";"11";"12";"13";"14"} & "!B:G"),$B23,INDIRECT({"08";"09";"10";"11";"12";"13";"14"} & "!G:G")))} -> 0 | F23: {=SUM(SUMIF(INDIRECT({"08";"09";"10";"11";"12";"13";"14"} & "!B:I"),$B23,INDIRECT({"08";"09";"10";"11";"12";"13";"14"} & "!I:I")))} -> 0 | G23: {=SUM(SUMIF(INDIRECT({"15";"16";"17";"18";"19";"20";"21"} & "!B:G"),$B23,INDIRECT({"15";"16";"17";"18";"19";"20";"21"} & "!G:G")))} -> 0 | H23: {=SUM(SUMIF(INDIRECT({"15";"16";"17";"18";"19";"20";"21"} & "!B:I"),$B23,INDIRECT({"15";"16";"17";"18";"19";"20";"21"} & "!I:I")))} -> 0 | I23: {=SUM(SUMIF(INDIRECT({"22";"23";"24";"25";"26";"27";"28";"29";"30";"31"} & "!B:G"),$B23,INDIRECT({"22";"23";"24";"25";"26";"27";"28";"29";"30";"31"} & "!G:G")))} -> 0 | J23: {=SUM(SUMIF(INDIRECT({"22";"23";"24";"25";"26";"27";"28";"29";"30";"31"} & "!B:I"),$B23,INDIRECT({"22";"23";"24";"25";"26";"27";"28";"29";"30";"31"} & "!I:I")))} -> 0 | K23: =ROUND(SUM(C23,E23,G23,I23)/DAY(TODAY()),0) -> 1 | L23: =SUM(D23,F23,H23,J23)/DAY(TODAY()) -> 2600 | M23: =K23*7 -> 7 | N23: =L23*7 -> 18200 | O23: =ROUND(K23*30,0) -> 30 | P23: =L23*30 -> 78000 | S23: =EXACT(B23,Total!B23) -> TRUE | T23: =SUM(D23+F23+H23+J23) -> 2600 | W23: BATERIA MUST 10.25 KW
A24: U | B24: BREKE 63A DOBLE TIR | C24: =SUM(SUMIF(INDIRECT({"01";"02";"03";"04";"05";"06";"07"} & "!B:G"),$B24,INDIRECT({"01";"02";"03";"04";"05";"06";"07"} & "!G:G"))) -> 0 | D24: =SUM(SUMIF(INDIRECT({"01";"02";"03";"04";"05";"06";"07"} & "!B:I"),$B24,INDIRECT({"01";"02";"03";"04";"05";"06";"07"} & "!I:I"))) -> 0 | E24: {=SUM(SUMIF(INDIRECT({"08";"09";"10";"11";"12";"13";"14"} & "!B:G"),$B24,INDIRECT({"08";"09";"10";"11";"12";"13";"14"} & "!G:G")))} -> 0 | F24: {=SUM(SUMIF(INDIRECT({"08";"09";"10";"11";"12";"13";"14"} & "!B:I"),$B24,INDIRECT({"08";"09";"10";"11";"12";"13";"14"} & "!I:I")))} -> 0 | G24: {=SUM(SUMIF(INDIRECT({"15";"16";"17";"18";"19";"20";"21"} & "!B:G"),$B24,INDIRECT({"15";"16";"17";"18";"19";"20";"21"} & "!G:G")))} -> 0 | H24: {=SUM(SUMIF(INDIRECT({"15";"16";"17";"18";"19";"20";"21"} & "!B:I"),$B24,INDIRECT({"15";"16";"17";"18";"19";"20";"21"} & "!I:I")))} -> 0 | I24: {=SUM(SUMIF(INDIRECT({"22";"23";"24";"25";"26";"27";"28";"29";"30";"31"} & "!B:G"),$B24,INDIRECT({"22";"23";"24";"25";"26";"27";"28";"29";"30";"31"} & "!G:G")))} -> 0 | J24: {=SUM(SUMIF(INDIRECT({"22";"23";"24";"25";"26";"27";"28";"29";"30";"31"} & "!B:I"),$B24,INDIRECT({"22";"23";"24";"25";"26";"27";"28";"29";"30";"31"} & "!I:I")))} -> 0 | K24: =ROUND(SUM(C24,E24,G24,I24)/DAY(TODAY()),0) -> 0 | L24: =SUM(D24,F24,H24,J24)/DAY(TODAY()) -> 0 | M24: =K24*7 -> 0 | N24: =L24*7 -> 0 | O24: =ROUND(K24*30,0) -> 0 | P24: =L24*30 -> 0 | S24: =EXACT(B24,Total!B24) -> TRUE | T24: =SUM(D24+F24+H24+J24) -> 0 | W24: BREKE 63A DOBLE TIR
A25: U | B25: BREKE 32A DOBLE | C25: =SUM(SUMIF(INDIRECT({"01";"02";"03";"04";"05";"06";"07"} & "!B:G"),$B25,INDIRECT({"01";"02";"03";"04";"05";"06";"07"} & "!G:G"))) -> 0 | D25: =SUM(SUMIF(INDIRECT({"01";"02";"03";"04";"05";"06";"07"} & "!B:I"),$B25,INDIRECT({"01";"02";"03";"04";"05";"06";"07"} & "!I:I"))) -> 0 | E25: {=SUM(SUMIF(INDIRECT({"08";"09";"10";"11";"12";"13";"14"} & "!B:G"),$B25,INDIRECT({"08";"09";"10";"11";"12";"13";"14"} & "!G:G")))} -> 0 | F25: {=SUM(SUMIF(INDIRECT({"08";"09";"10";"11";"12";"13";"14"} & "!B:I"),$B25,INDIRECT({"08";"09";"10";"11";"12";"13";"14"} & "!I:I")))} -> 0 | G25: {=SUM(SUMIF(INDIRECT({"15";"16";"17";"18";"19";"20";"21"} & "!B:G"),$B25,INDIRECT({"15";"16";"17";"18";"19";"20";"21"} & "!G:G")))} -> 0 | H25: {=SUM(SUMIF(INDIRECT({"15";"16";"17";"18";"19";"20";"21"} & "!B:I"),$B25,INDIRECT({"15";"16";"17";"18";"19";"20";"21"} & "!I:I")))} -> 0 | I25: {=SUM(SUMIF(INDIRECT({"22";"23";"24";"25";"26";"27";"28";"29";"30";"31"} & "!B:G"),$B25,INDIRECT({"22";"23";"24";"25";"26";"27";"28";"29";"30";"31"} & "!G:G")))} -> 0 | J25: {=SUM(SUMIF(INDIRECT({"22";"23";"24";"25";"26";"27";"28";"29";"30";"31"} & "!B:I"),$B25,INDIRECT({"22";"23";"24";"25";"26";"27";"28";"29";"30";"31"} & "!I:I")))} -> 0 | K25: =ROUND(SUM(C25,E25,G25,I25)/DAY(TODAY()),0) -> 0 | L25: =SUM(D25,F25,H25,J25)/DAY(TODAY()) -> 0 | M25: =K25*7 -> 0 | N25: =L25*7 -> 0 | O25: =ROUND(K25*30,0) -> 0 | P25: =L25*30 -> 0 | S25: =EXACT(B25,Total!B25) -> TRUE | T25: =SUM(D25+F25+H25+J25) -> 0 | W25: BREKE 32A DOBLE
B26: BOCINA BOOM 8 PULGADAS | C26: =SUM(SUMIF(INDIRECT({"01";"02";"03";"04";"05";"06";"07"} & "!B:G"),$B26,INDIRECT({"01";"02";"03";"04";"05";"06";"07"} & "!G:G"))) -> 0 | D26: =SUM(SUMIF(INDIRECT({"01";"02";"03";"04";"05";"06";"07"} & "!B:I"),$B26,INDIRECT({"01";"02";"03";"04";"05";"06";"07"} & "!I:I"))) -> 0 | E26: {=SUM(SUMIF(INDIRECT({"08";"09";"10";"11";"12";"13";"14"} & "!B:G"),$B26,INDIRECT({"08";"09";"10";"11";"12";"13";"14"} & "!G:G")))} -> 0 | F26: {=SUM(SUMIF(INDIRECT({"08";"09";"10";"11";"12";"13";"14"} & "!B:I"),$B26,INDIRECT({"08";"09";"10";"11";"12";"13";"14"} & "!I:I")))} -> 0 | G26: {=SUM(SUMIF(INDIRECT({"15";"16";"17";"18";"19";"20";"21"} & "!B:G"),$B26,INDIRECT({"15";"16";"17";"18";"19";"20";"21"} & "!G:G")))} -> 0 | H26: {=SUM(SUMIF(INDIRECT({"15";"16";"17";"18";"19";"20";"21"} & "!B:I"),$B26,INDIRECT({"15";"16";"17";"18";"19";"20";"21"} & "!I:I")))} -> 0 | I26: {=SUM(SUMIF(INDIRECT({"22";"23";"24";"25";"26";"27";"28";"29";"30";"31"} & "!B:G"),$B26,INDIRECT({"22";"23";"24";"25";"26";"27";"28";"29";"30";"31"} & "!G:G")))} -> 0 | J26: {=SUM(SUMIF(INDIRECT({"22";"23";"24";"25";"26";"27";"28";"29";"30";"31"} & "!B:I"),$B26,INDIRECT({"22";"23";"24";"25";"26";"27";"28";"29";"30";"31"} & "!I:I")))} -> 0 | K26: =ROUND(SUM(C26,E26,G26,I26)/DAY(TODAY()),0) -> 0 | L26: =SUM(D26,F26,H26,J26)/DAY(TODAY()) -> 0 | M26: =K26*7 -> 0 | N26: =L26*7 -> 0 | O26: =ROUND(K26*30,0) -> 0 | P26: =L26*30 -> 0 | S26: =EXACT(B26,Total!B26) -> TRUE | T26: =SUM(D26+F26+H26+J26) -> 0 | W26: BOCINA BOOM 8 PULGADAS
B27: BOCINA MILEXUS 8 PULGADAS | C27: =SUM(SUMIF(INDIRECT({"01";"02";"03";"04";"05";"06";"07"} & "!B:G"),$B27,INDIRECT({"01";"02";"03";"04";"05";"06";"07"} & "!G:G"))) -> 0 | D27: =SUM(SUMIF(INDIRECT({"01";"02";"03";"04";"05";"06";"07"} & "!B:I"),$B27,INDIRECT({"01";"02";"03";"04";"05";"06";"07"} & "!I:I"))) -> 0 | E27: {=SUM(SUMIF(INDIRECT({"08";"09";"10";"11";"12";"13";"14"} & "!B:G"),$B27,INDIRECT({"08";"09";"10";"11";"12";"13";"14"} & "!G:G")))} -> 0 | F27: {=SUM(SUMIF(INDIRECT({"08";"09";"10";"11";"12";"13";"14"} & "!B:I"),$B27,INDIRECT({"08";"09";"10";"11";"12";"13";"14"} & "!I:I")))} -> 0 | G27: {=SUM(SUMIF(INDIRECT({"15";"16";"17";"18";"19";"20";"21"} & "!B:G"),$B27,INDIRECT({"15";"16";"17";"18";"19";"20";"21"} & "!G:G")))} -> 2 | H27: {=SUM(SUMIF(INDIRECT({"15";"16";"17";"18";"19";"20";"21"} & "!B:I"),$B27,INDIRECT({"15";"16";"17";"18";"19";"20";"21"} & "!I:I")))} -> 360 | I27: {=SUM(SUMIF(INDIRECT({"22";"23";"24";"25";"26";"27";"28";"29";"30";"31"} & "!B:G"),$B27,INDIRECT({"22";"23";"24";"25";"26";"27";"28";"29";"30";"31"} & "!G:G")))} -> 0 | J27: {=SUM(SUMIF(INDIRECT({"22";"23";"24";"25";"26";"27";"28";"29";"30";"31"} & "!B:I"),$B27,INDIRECT({"22";"23";"24";"25";"26";"27";"28";"29";"30";"31"} & "!I:I")))} -> 0 | K27: =ROUND(SUM(C27,E27,G27,I27)/DAY(TODAY()),0) -> 2 | L27: =SUM(D27,F27,H27,J27)/DAY(TODAY()) -> 360 | M27: =K27*7 -> 14 | N27: =L27*7 -> 2520 | O27: =ROUND(K27*30,0) -> 60 | P27: =L27*30 -> 10800 | S27: =EXACT(B27,Total!B27) -> TRUE | T27: =SUM(D27+F27+H27+J27) -> 360 | W27: BOCINA MILEXUS 8 PULGADAS
B28: BOCINA MILEXUS 6 DUAL | C28: =SUM(SUMIF(INDIRECT({"01";"02";"03";"04";"05";"06";"07"} & "!B:G"),$B28,INDIRECT({"01";"02";"03";"04";"05";"06";"07"} & "!G:G"))) -> 0 | D28: =SUM(SUMIF(INDIRECT({"01";"02";"03";"04";"05";"06";"07"} & "!B:I"),$B28,INDIRECT({"01";"02";"03";"04";"05";"06";"07"} & "!I:I"))) -> 0 | E28: {=SUM(SUMIF(INDIRECT({"08";"09";"10";"11";"12";"13";"14"} & "!B:G"),$B28,INDIRECT({"08";"09";"10";"11";"12";"13";"14"} & "!G:G")))} -> 0 | F28: {=SUM(SUMIF(INDIRECT({"08";"09";"10";"11";"12";"13";"14"} & "!B:I"),$B28,INDIRECT({"08";"09";"10";"11";"12";"13";"14"} & "!I:I")))} -> 0 | G28: {=SUM(SUMIF(INDIRECT({"15";"16";"17";"18";"19";"20";"21"} & "!B:G"),$B28,INDIRECT({"15";"16";"17";"18";"19";"20";"21"} & "!G:G")))} -> 0 | H28: {=SUM(SUMIF(INDIRECT({"15";"16";"17";"18";"19";"20";"21"} & "!B:I"),$B28,INDIRECT({"15";"16";"17";"18";"19";"20";"21"} & "!I:I")))} -> 0 | I28: {=SUM(SUMIF(INDIRECT({"22";"23";"24";"25";"26";"27";"28";"29";"30";"31"} & "!B:G"),$B28,INDIRECT({"22";"23";"24";"25";"26";"27";"28";"29";"30";"31"} & "!G:G")))} -> 0 | J28: {=SUM(SUMIF(INDIRECT({"22";"23";"24";"25";"26";"27";"28";"29";"30";"31"} & "!B:I"),$B28,INDIRECT({"22";"23";"24";"25";"26";"27";"28";"29";"30";"31"} & "!I:I")))} -> 0 | K28: =ROUND(SUM(C28,E28,G28,I28)/DAY(TODAY()),0) -> 0 | L28: =SUM(D28,F28,H28,J28)/DAY(TODAY()) -> 0 | M28: =K28*7 -> 0 | N28: =L28*7 -> 0 | O28: =ROUND(K28*30,0) -> 0 | P28: =L28*30 -> 0 | S28: =EXACT(B28,Total!B28) -> TRUE | T28: =SUM(D28+F28+H28+J28) -> 0 | W28: BOCINA MILEXUS 6 DUAL
A29: U | B29: BOMBA DE AGUA SILVER POINT 1 HP | C29: =SUM(SUMIF(INDIRECT({"01";"02";"03";"04";"05";"06";"07"} & "!B:G"),$B29,INDIRECT({"01";"02";"03";"04";"05";"06";"07"} & "!G:G"))) -> 0 | D29: =SUM(SUMIF(INDIRECT({"01";"02";"03";"04";"05";"06";"07"} & "!B:I"),$B29,INDIRECT({"01";"02";"03";"04";"05";"06";"07"} & "!I:I"))) -> 0 | E29: {=SUM(SUMIF(INDIRECT({"08";"09";"10";"11";"12";"13";"14"} & "!B:G"),$B29,INDIRECT({"08";"09";"10";"11";"12";"13";"14"} & "!G:G")))} -> 0 | F29: {=SUM(SUMIF(INDIRECT({"08";"09";"10";"11";"12";"13";"14"} & "!B:I"),$B29,INDIRECT({"08";"09";"10";"11";"12";"13";"14"} & "!I:I")))} -> 0 | G29: {=SUM(SUMIF(INDIRECT({"15";"16";"17";"18";"19";"20";"21"} & "!B:G"),$B29,INDIRECT({"15";"16";"17";"18";"19";"20";"21"} & "!G:G")))} -> 0 | H29: {=SUM(SUMIF(INDIRECT({"15";"16";"17";"18";"19";"20";"21"} & "!B:I"),$B29,INDIRECT({"15";"16";"17";"18";"19";"20";"21"} & "!I:I")))} -> 0 | I29: {=SUM(SUMIF(INDIRECT({"22";"23";"24";"25";"26";"27";"28";"29";"30";"31"} & "!B:G"),$B29,INDIRECT({"22";"23";"24";"25";"26";"27";"28";"29";"30";"31"} & "!G:G")))} -> 0 | J29: {=SUM(SUMIF(INDIRECT({"22";"23";"24";"25";"26";"27";"28";"29";"30";"31"} & "!B:I"),$B29,INDIRECT({"22";"23";"24";"25";"26";"27";"28";"29";"30";"31"} & "!I:I")))} -> 0 | K29: =ROUND(SUM(C29,E29,G29,I29)/DAY(TODAY()),0) -> 0 | L29: =SUM(D29,F29,H29,J29)/DAY(TODAY()) -> 0 | M29: =K29*7 -> 0 | N29: =L29*7 -> 0 | O29: =ROUND(K29*30,0) -> 0 | P29: =L29*30 -> 0 | S29: =EXACT(B29,Total!B29) -> TRUE | T29: =SUM(D29+F29+H29+J29) -> 0 | W29: BOMBA DE AGUA SILVER POINT 1 HP
B30: BOMBA DE AGUA SILVER POINT 1X1/2 | C30: =SUM(SUMIF(INDIRECT({"01";"02";"03";"04";"05";"06";"07"} & "!B:G"),$B30,INDIRECT({"01";"02";"03";"04";"05";"06";"07"} & "!G:G"))) -> 0 | D30: =SUM(SUMIF(INDIRECT({"01";"02";"03";"04";"05";"06";"07"} & "!B:I"),$B30,INDIRECT({"01";"02";"03";"04";"05";"06";"07"} & "!I:I"))) -> 0 | E30: {=SUM(SUMIF(INDIRECT({"08";"09";"10";"11";"12";"13";"14"} & "!B:G"),$B30,INDIRECT({"08";"09";"10";"11";"12";"13";"14"} & "!G:G")))} -> 0 | F30: {=SUM(SUMIF(INDIRECT({"08";"09";"10";"11";"12";"13";"14"} & "!B:I"),$B30,INDIRECT({"08";"09";"10";"11";"12";"13";"14"} & "!I:I")))} -> 0 | G30: {=SUM(SUMIF(INDIRECT({"15";"16";"17";"18";"19";"20";"21"} & "!B:G"),$B30,INDIRECT({"15";"16";"17";"18";"19";"20";"21"} & "!G:G")))} -> 0 | H30: {=SUM(SUMIF(INDIRECT({"15";"16";"17";"18";"19";"20";"21"} & "!B:I"),$B30,INDIRECT({"15";"16";"17";"18";"19";"20";"21"} & "!I:I")))} -> 0 | I30: {=SUM(SUMIF(INDIRECT({"22";"23";"24";"25";"26";"27";"28";"29";"30";"31"} & "!B:G"),$B30,INDIRECT({"22";"23";"24";"25";"26";"27";"28";"29";"30";"31"} & "!G:G")))} -> 1 | J30: {=SUM(SUMIF(INDIRECT({"22";"23";"24";"25";"26";"27";"28";"29";"30";"31"} & "!B:I"),$B30,INDIRECT({"22";"23";"24";"25";"26";"27";"28";"29";"30";"31"} & "!I:I")))} -> 45 | K30: =ROUND(SUM(C30,E30,G30,I30)/DAY(TODAY()),0) -> 1 | L30: =SUM(D30,F30,H30,J30)/DAY(TODAY()) -> 45 | M30: =K30*7 -> 7 | N30: =L30*7 -> 315 | O30: =ROUND(K30*30,0) -> 30 | P30: =L30*30 -> 1350 | S30: =EXACT(B30,Total!B30) -> TRUE | T30: =SUM(D30+F30+H30+J30) -> 45 | W30: BOMBA DE AGUA SILVER POINT 1X1/2
B31: BICICLETA INFANTIL | C31: =SUM(SUMIF(INDIRECT({"01";"02";"03";"04";"05";"06";"07"} & "!B:G"),$B31,INDIRECT({"01";"02";"03";"04";"05";"06";"07"} & "!G:G"))) -> 0 | D31: =SUM(SUMIF(INDIRECT({"01";"02";"03";"04";"05";"06";"07"} & "!B:I"),$B31,INDIRECT({"01";"02";"03";"04";"05";"06";"07"} & "!I:I"))) -> 0 | E31: {=SUM(SUMIF(INDIRECT({"08";"09";"10";"11";"12";"13";"14"} & "!B:G"),$B31,INDIRECT({"08";"09";"10";"11";"12";"13";"14"} & "!G:G")))} -> 0 | F31: {=SUM(SUMIF(INDIRECT({"08";"09";"10";"11";"12";"13";"14"} & "!B:I"),$B31,INDIRECT({"08";"09";"10";"11";"12";"13";"14"} & "!I:I")))} -> 0 | G31: {=SUM(SUMIF(INDIRECT({"15";"16";"17";"18";"19";"20";"21"} & "!B:G"),$B31,INDIRECT({"15";"16";"17";"18";"19";"20";"21"} & "!G:G")))} -> 0 | H31: {=SUM(SUMIF(INDIRECT({"15";"16";"17";"18";"19";"20";"21"} & "!B:I"),$B31,INDIRECT({"15";"16";"17";"18";"19";"20";"21"} & "!I:I")))} -> 0 | I31: {=SUM(SUMIF(INDIRECT({"22";"23";"24";"25";"26";"27";"28";"29";"30";"31"} & "!B:G"),$B31,INDIRECT({"22";"23";"24";"25";"26";"27";"28";"29";"30";"31"} & "!G:G")))} -> 0 | J31: {=SUM(SUMIF(INDIRECT({"22";"23";"24";"25";"26";"27";"28";"29";"30";"31"} & "!B:I"),$B31,INDIRECT({"22";"23";"24";"25";"26";"27";"28";"29";"30";"31"} & "!I:I")))} -> 0 | K31: =ROUND(SUM(C31,E31,G31,I31)/DAY(TODAY()),0) -> 0 | L31: =SUM(D31,F31,H31,J31)/DAY(TODAY()) -> 0 | M31: =K31*7 -> 0 | N31: =L31*7 -> 0 | O31: =ROUND(K31*30,0) -> 0 | P31: =L31*30 -> 0 | S31: =EXACT(B31,Total!B31) -> TRUE | T31: =SUM(D31+F31+H31+J31) -> 0 | W31: BICICLETA INFANTIL
B32: BICICLETA INFANTIL 20 TZ002 | C32: =SUM(SUMIF(INDIRECT({"01";"02";"03";"04";"05";"06";"07"} & "!B:G"),$B32,INDIRECT({"01";"02";"03";"04";"05";"06";"07"} & "!G:G"))) -> 1 | D32: =SUM(SUMIF(INDIRECT({"01";"02";"03";"04";"05";"06";"07"} & "!B:I"),$B32,INDIRECT({"01";"02";"03";"04";"05";"06";"07"} & "!I:I"))) -> 130 | E32: {=SUM(SUMIF(INDIRECT({"08";"09";"10";"11";"12";"13";"14"} & "!B:G"),$B32,INDIRECT({"08";"09";"10";"11";"12";"13";"14"} & "!G:G")))} -> 0 | F32: {=SUM(SUMIF(INDIRECT({"08";"09";"10";"11";"12";"13";"14"} & "!B:I"),$B32,INDIRECT({"08";"09";"10";"11";"12";"13";"14"} & "!I:I")))} -> 0 | G32: {=SUM(SUMIF(INDIRECT({"15";"16";"17";"18";"19";"20";"21"} & "!B:G"),$B32,INDIRECT({"15";"16";"17";"18";"19";"20";"21"} & "!G:G")))} -> 0 | H32: {=SUM(SUMIF(INDIRECT({"15";"16";"17";"18";"19";"20";"21"} & "!B:I"),$B32,INDIRECT({"15";"16";"17";"18";"19";"20";"21"} & "!I:I")))} -> 0 | I32: {=SUM(SUMIF(INDIRECT({"22";"23";"24";"25";"26";"27";"28";"29";"30";"31"} & "!B:G"),$B32,INDIRECT({"22";"23";"24";"25";"26";"27";"28";"29";"30";"31"} & "!G:G")))} -> 0 | J32: {=SUM(SUMIF(INDIRECT({"22";"23";"24";"25";"26";"27";"28";"29";"30";"31"} & "!B:I"),$B32,INDIRECT({"22";"23";"24";"25";"26";"27";"28";"29";"30";"31"} & "!I:I")))} -> 0 | K32: =ROUND(SUM(C32,E32,G32,I32)/DAY(TODAY()),0) -> 1 | L32: =SUM(D32,F32,H32,J32)/DAY(TODAY()) -> 130 | M32: =K32*7 -> 7 | N32: =L32*7 -> 910 | O32: =ROUND(K32*30,0) -> 30 | P32: =L32*30 -> 3900 | S32: =EXACT(B32,Total!B32) -> TRUE | T32: =SUM(D32+F32+H32+J32) -> 130 | W32: BICICLETA INFANTIL 20 TZ002
A33: U | B33: BICICLETA 26 008-5 | C33: =SUM(SUMIF(INDIRECT({"01";"02";"03";"04";"05";"06";"07"} & "!B:G"),$B33,INDIRECT({"01";"02";"03";"04";"05";"06";"07"} & "!G:G"))) -> 0 | D33: =SUM(SUMIF(INDIRECT({"01";"02";"03";"04";"05";"06";"07"} & "!B:I"),$B33,INDIRECT({"01";"02";"03";"04";"05";"06";"07"} & "!I:I"))) -> 0 | E33: {=SUM(SUMIF(INDIRECT({"08";"09";"10";"11";"12";"13";"14"} & "!B:G"),$B33,INDIRECT({"08";"09";"10";"11";"12";"13";"14"} & "!G:G")))} -> 0 | F33: {=SUM(SUMIF(INDIRECT({"08";"09";"10";"11";"12";"13";"14"} & "!B:I"),$B33,INDIRECT({"08";"09";"10";"11";"12";"13";"14"} & "!I:I")))} -> 0 | G33: {=SUM(SUMIF(INDIRECT({"15";"16";"17";"18";"19";"20";"21"} & "!B:G"),$B33,INDIRECT({"15";"16";"17";"18";"19";"20";"21"} & "!G:G")))} -> 0 | H33: {=SUM(SUMIF(INDIRECT({"15";"16";"17";"18";"19";"20";"21"} & "!B:I"),$B33,INDIRECT({"15";"16";"17";"18";"19";"20";"21"} & "!I:I")))} -> 0 | I33: {=SUM(SUMIF(INDIRECT({"22";"23";"24";"25";"26";"27";"28";"29";"30";"31"} & "!B:G"),$B33,INDIRECT({"22";"23";"24";"25";"26";"27";"28";"29";"30";"31"} & "!G:G")))} -> 0 | J33: {=SUM(SUMIF(INDIRECT({"22";"23";"24";"25";"26";"27";"28";"29";"30";"31"} & "!B:I"),$B33,INDIRECT({"22";"23";"24";"25";"26";"27";"28";"29";"30";"31"} & "!I:I")))} -> 0 | K33: =ROUND(SUM(C33,E33,G33,I33)/DAY(TODAY()),0) -> 0 | L33: =SUM(D33,F33,H33,J33)/DAY(TODAY()) -> 0 | M33: =K33*7 -> 0 | N33: =L33*7 -> 0 | O33: =ROUND(K33*30,0) -> 0 | P33: =L33*30 -> 0 | S33: =EXACT(B33,Total!B33) -> TRUE | T33: =SUM(D33+F33+H33+J33) -> 0 | W33: BICICLETA 26 008-5
A34: U | B34: BICICLETA 26 012 | C34: =SUM(SUMIF(INDIRECT({"01";"02";"03";"04";"05";"06";"07"} & "!B:G"),$B34,INDIRECT({"01";"02";"03";"04";"05";"06";"07"} & "!G:G"))) -> 0 | D34: =SUM(SUMIF(INDIRECT({"01";"02";"03";"04";"05";"06";"07"} & "!B:I"),$B34,INDIRECT({"01";"02";"03";"04";"05";"06";"07"} & "!I:I"))) -> 0 | E34: {=SUM(SUMIF(INDIRECT({"08";"09";"10";"11";"12";"13";"14"} & "!B:G"),$B34,INDIRECT({"08";"09";"10";"11";"12";"13";"14"} & "!G:G")))} -> 0 | F34: {=SUM(SUMIF(INDIRECT({"08";"09";"10";"11";"12";"13";"14"} & "!B:I"),$B34,INDIRECT({"08";"09";"10";"11";"12";"13";"14"} & "!I:I")))} -> 0 | G34: {=SUM(SUMIF(INDIRECT({"15";"16";"17";"18";"19";"20";"21"} & "!B:G"),$B34,INDIRECT({"15";"16";"17";"18";"19";"20";"21"} & "!G:G")))} -> 0 | H34: {=SUM(SUMIF(INDIRECT({"15";"16";"17";"18";"19";"20";"21"} & "!B:I"),$B34,INDIRECT({"15";"16";"17";"18";"19";"20";"21"} & "!I:I")))} -> 0 | I34: {=SUM(SUMIF(INDIRECT({"22";"23";"24";"25";"26";"27";"28";"29";"30";"31"} & "!B:G"),$B34,INDIRECT({"22";"23";"24";"25";"26";"27";"28";"29";"30";"31"} & "!G:G")))} -> 0 | J34: {=SUM(SUMIF(INDIRECT({"22";"23";"24";"25";"26";"27";"28";"29";"30";"31"} & "!B:I"),$B34,INDIRECT({"22";"23";"24";"25";"26";"27";"28";"29";"30";"31"} & "!I:I")))} -> 0 | K34: =ROUND(SUM(C34,E34,G34,I34)/DAY(TODAY()),0) -> 0 | L34: =SUM(D34,F34,H34,J34)/DAY(TODAY()) -> 0 | M34: =K34*7 -> 0 | N34: =L34*7 -> 0 | O34: =ROUND(K34*30,0) -> 0 | P34: =L34*30 -> 0 | S34: =EXACT(B34,Total!B34) -> TRUE | T34: =SUM(D34+F34+H34+J34) -> 0 | W34: BICICLETA 26 012
A35: U | B35: BICICLETA 26 003-4 | C35: =SUM(SUMIF(INDIRECT({"01";"02";"03";"04";"05";"06";"07"} & "!B:G"),$B35,INDIRECT({"01";"02";"03";"04";"05";"06";"07"} & "!G:G"))) -> 0 | D35: =SUM(SUMIF(INDIRECT({"01";"02";"03";"04";"05";"06";"07"} & "!B:I"),$B35,INDIRECT({"01";"02";"03";"04";"05";"06";"07"} & "!I:I"))) -> 0 | E35: {=SUM(SUMIF(INDIRECT({"08";"09";"10";"11";"12";"13";"14"} & "!B:G"),$B35,INDIRECT({"08";"09";"10";"11";"12";"13";"14"} & "!G:G")))} -> 1 | F35: {=SUM(SUMIF(INDIRECT({"08";"09";"10";"11";"12";"13";"14"} & "!B:I"),$B35,INDIRECT({"08";"09";"10";"11";"12";"13";"14"} & "!I:I")))} -> 185 | G35: {=SUM(SUMIF(INDIRECT({"15";"16";"17";"18";"19";"20";"21"} & "!B:G"),$B35,INDIRECT({"15";"16";"17";"18";"19";"20";"21"} & "!G:G")))} -> 0 | H35: {=SUM(SUMIF(INDIRECT({"15";"16";"17";"18";"19";"20";"21"} & "!B:I"),$B35,INDIRECT({"15";"16";"17";"18";"19";"20";"21"} & "!I:I")))} -> 0 | I35: {=SUM(SUMIF(INDIRECT({"22";"23";"24";"25";"26";"27";"28";"29";"30";"31"} & "!B:G"),$B35,INDIRECT({"22";"23";"24";"25";"26";"27";"28";"29";"30";"31"} & "!G:G")))} -> 0 | J35: {=SUM(SUMIF(INDIRECT({"22";"23";"24";"25";"26";"27";"28";"29";"30";"31"} & "!B:I"),$B35,INDIRECT({"22";"23";"24";"25";"26";"27";"28";"29";"30";"31"} & "!I:I")))} -> 0 | K35: =ROUND(SUM(C35,E35,G35,I35)/DAY(TODAY()),0) -> 1 | L35: =SUM(D35,F35,H35,J35)/DAY(TODAY()) -> 185 | M35: =K35*7 -> 7 | N35: =L35*7 -> 1295 | O35: =ROUND(K35*30,0) -> 30 | P35: =L35*30 -> 5550 | S35: =EXACT(B35,Total!B35) -> TRUE | T35: =SUM(D35+F35+H35+J35) -> 185 | W35: BICICLETA 26 003-4
A36: U | B36: BICICLETA 16 023 | C36: =SUM(SUMIF(INDIRECT({"01";"02";"03";"04";"05";"06";"07"} & "!B:G"),$B36,INDIRECT({"01";"02";"03";"04";"05";"06";"07"} & "!G:G"))) -> 0 | D36: =SUM(SUMIF(INDIRECT({"01";"02";"03";"04";"05";"06";"07"} & "!B:I"),$B36,INDIRECT({"01";"02";"03";"04";"05";"06";"07"} & "!I:I"))) -> 0 | E36: {=SUM(SUMIF(INDIRECT({"08";"09";"10";"11";"12";"13";"14"} & "!B:G"),$B36,INDIRECT({"08";"09";"10";"11";"12";"13";"14"} & "!G:G")))} -> 0 | F36: {=SUM(SUMIF(INDIRECT({"08";"09";"10";"11";"12";"13";"14"} & "!B:I"),$B36,INDIRECT({"08";"09";"10";"11";"12";"13";"14"} & "!I:I")))} -> 0 | G36: {=SUM(SUMIF(INDIRECT({"15";"16";"17";"18";"19";"20";"21"} & "!B:G"),$B36,INDIRECT({"15";"16";"17";"18";"19";"20";"21"} & "!G:G")))} -> 0 | H36: {=SUM(SUMIF(INDIRECT({"15";"16";"17";"18";"19";"20";"21"} & "!B:I"),$B36,INDIRECT({"15";"16";"17";"18";"19";"20";"21"} & "!I:I")))} -> 0 | I36: {=SUM(SUMIF(INDIRECT({"22";"23";"24";"25";"26";"27";"28";"29";"30";"31"} & "!B:G"),$B36,INDIRECT({"22";"23";"24";"25";"26";"27";"28";"29";"30";"31"} & "!G:G")))} -> 0 | J36: {=SUM(SUMIF(INDIRECT({"22";"23";"24";"25";"26";"27";"28";"29";"30";"31"} & "!B:I"),$B36,INDIRECT({"22";"23";"24";"25";"26";"27";"28";"29";"30";"31"} & "!I:I")))} -> 0 | K36: =ROUND(SUM(C36,E36,G36,I36)/DAY(TODAY()),0) -> 0 | L36: =SUM(D36,F36,H36,J36)/DAY(TODAY()) -> 0 | M36: =K36*7 -> 0 | N36: =L36*7 -> 0 | O36: =ROUND(K36*30,0) -> 0 | P36: =L36*30 -> 0 | S36: =EXACT(B36,Total!B36) -> TRUE | T36: =SUM(D36+F36+H36+J36) -> 0 | W36: BICICLETA 16 023
A37: U | B37: BICICLETA ELECTRICA | C37: =SUM(SUMIF(INDIRECT({"01";"02";"03";"04";"05";"06";"07"} & "!B:G"),$B37,INDIRECT({"01";"02";"03";"04";"05";"06";"07"} & "!G:G"))) -> 0 | D37: =SUM(SUMIF(INDIRECT({"01";"02";"03";"04";"05";"06";"07"} & "!B:I"),$B37,INDIRECT({"01";"02";"03";"04";"05";"06";"07"} & "!I:I"))) -> 0 | E37: {=SUM(SUMIF(INDIRECT({"08";"09";"10";"11";"12";"13";"14"} & "!B:G"),$B37,INDIRECT({"08";"09";"10";"11";"12";"13";"14"} & "!G:G")))} -> 0 | F37: {=SUM(SUMIF(INDIRECT({"08";"09";"10";"11";"12";"13";"14"} & "!B:I"),$B37,INDIRECT({"08";"09";"10";"11";"12";"13";"14"} & "!I:I")))} -> 0 | G37: {=SUM(SUMIF(INDIRECT({"15";"16";"17";"18";"19";"20";"21"} & "!B:G"),$B37,INDIRECT({"15";"16";"17";"18";"19";"20";"21"} & "!G:G")))} -> 0 | H37: {=SUM(SUMIF(INDIRECT({"15";"16";"17";"18";"19";"20";"21"} & "!B:I"),$B37,INDIRECT({"15";"16";"17";"18";"19";"20";"21"} & "!I:I")))} -> 0 | I37: {=SUM(SUMIF(INDIRECT({"22";"23";"24";"25";"26";"27";"28";"29";"30";"31"} & "!B:G"),$B37,INDIRECT({"22";"23";"24";"25";"26";"27";"28";"29";"30";"31"} & "!G:G")))} -> 0 | J37: {=SUM(SUMIF(INDIRECT({"22";"23";"24";"25";"26";"27";"28";"29";"30";"31"} & "!B:I"),$B37,INDIRECT({"22";"23";"24";"25";"26";"27";"28";"29";"30";"31"} & "!I:I")))} -> 0 | K37: =ROUND(SUM(C37,E37,G37,I37)/DAY(TODAY()),0) -> 0 | L37: =SUM(D37,F37,H37,J37)/DAY(TODAY()) -> 0 | M37: =K37*7 -> 0 | N37: =L37*7 -> 0 | O37: =ROUND(K37*30,0) -> 0 | P37: =L37*30 -> 0 | S37: =EXACT(B37,Total!B37) -> TRUE | T37: =SUM(D37+F37+H37+J37) -> 0 | W37: BICICLETA ELECTRICA
B38: CONECTORES MC4 | C38: =SUM(SUMIF(INDIRECT({"01";"02";"03";"04";"05";"06";"07"} & "!B:G"),$B38,INDIRECT({"01";"02";"03";"04";"05";"06";"07"} & "!G:G"))) -> 0 | D38: =SUM(SUMIF(INDIRECT({"01";"02";"03";"04";"05";"06";"07"} & "!B:I"),$B38,INDIRECT({"01";"02";"03";"04";"05";"06";"07"} & "!I:I"))) -> 0 | E38: {=SUM(SUMIF(INDIRECT({"08";"09";"10";"11";"12";"13";"14"} & "!B:G"),$B38,INDIRECT({"08";"09";"10";"11";"12";"13";"14"} & "!G:G")))} -> 0 | F38: {=SUM(SUMIF(INDIRECT({"08";"09";"10";"11";"12";"13";"14"} & "!B:I"),$B38,INDIRECT({"08";"09";"10";"11";"12";"13";"14"} & "!I:I")))} -> 0 | G38: {=SUM(SUMIF(INDIRECT({"15";"16";"17";"18";"19";"20";"21"} & "!B:G"),$B38,INDIRECT({"15";"16";"17";"18";"19";"20";"21"} & "!G:G")))} -> 0 | H38: {=SUM(SUMIF(INDIRECT({"15";"16";"17";"18";"19";"20";"21"} & "!B:I"),$B38,INDIRECT({"15";"16";"17";"18";"19";"20";"21"} & "!I:I")))} -> 0 | I38: {=SUM(SUMIF(INDIRECT({"22";"23";"24";"25";"26";"27";"28";"29";"30";"31"} & "!B:G"),$B38,INDIRECT({"22";"23";"24";"25";"26";"27";"28";"29";"30";"31"} & "!G:G")))} -> 0 | J38: {=SUM(SUMIF(INDIRECT({"22";"23";"24";"25";"26";"27";"28";"29";"30";"31"} & "!B:I"),$B38,INDIRECT({"22";"23";"24";"25";"26";"27";"28";"29";"30";"31"} & "!I:I")))} -> 0 | K38: =ROUND(SUM(C38,E38,G38,I38)/DAY(TODAY()),0) -> 0 | L38: =SUM(D38,F38,H38,J38)/DAY(TODAY()) -> 0 | M38: =K38*7 -> 0 | N38: =L38*7 -> 0 | O38: =ROUND(K38*30,0) -> 0 | P38: =L38*30 -> 0 | S38: =EXACT(B38,Total!B38) -> TRUE | T38: =SUM(D38+F38+H38+J38) -> 0 | W38: CONECTORES MC4
A39: U | B39: CAJITA DECODIFICADORA ATEC | C39: =SUM(SUMIF(INDIRECT({"01";"02";"03";"04";"05";"06";"07"} & "!B:G"),$B39,INDIRECT({"01";"02";"03";"04";"05";"06";"07"} & "!G:G"))) -> 0 | D39: =SUM(SUMIF(INDIRECT({"01";"02";"03";"04";"05";"06";"07"} & "!B:I"),$B39,INDIRECT({"01";"02";"03";"04";"05";"06";"07"} & "!I:I"))) -> 0 | E39: {=SUM(SUMIF(INDIRECT({"08";"09";"10";"11";"12";"13";"14"} & "!B:G"),$B39,INDIRECT({"08";"09";"10";"11";"12";"13";"14"} & "!G:G")))} -> 1 | F39: {=SUM(SUMIF(INDIRECT({"08";"09";"10";"11";"12";"13";"14"} & "!B:I"),$B39,INDIRECT({"08";"09";"10";"11";"12";"13";"14"} & "!I:I")))} -> 15 | G39: {=SUM(SUMIF(INDIRECT({"15";"16";"17";"18";"19";"20";"21"} & "!B:G"),$B39,INDIRECT({"15";"16";"17";"18";"19";"20";"21"} & "!G:G")))} -> 3 | H39: {=SUM(SUMIF(INDIRECT({"15";"16";"17";"18";"19";"20";"21"} & "!B:I"),$B39,INDIRECT({"15";"16";"17";"18";"19";"20";"21"} & "!I:I")))} -> 135 | I39: {=SUM(SUMIF(INDIRECT({"22";"23";"24";"25";"26";"27";"28";"29";"30";"31"} & "!B:G"),$B39,INDIRECT({"22";"23";"24";"25";"26";"27";"28";"29";"30";"31"} & "!G:G")))} -> 0 | J39: {=SUM(SUMIF(INDIRECT({"22";"23";"24";"25";"26";"27";"28";"29";"30";"31"} & "!B:I"),$B39,INDIRECT({"22";"23";"24";"25";"26";"27";"28";"29";"30";"31"} & "!I:I")))} -> 0 | K39: =ROUND(SUM(C39,E39,G39,I39)/DAY(TODAY()),0) -> 4 | L39: =SUM(D39,F39,H39,J39)/DAY(TODAY()) -> 150 | M39: =K39*7 -> 28 | N39: =L39*7 -> 1050 | O39: =ROUND(K39*30,0) -> 120 | P39: =L39*30 -> 4500 | S39: =EXACT(B39,Total!B39) -> TRUE | T39: =SUM(D39+F39+H39+J39) -> 150 | W39: CAJITA DECODIFICADORA ATEC
A40: U | B40: CAJA DE DISTRIBUCION DE 8 VIAS | C40: =SUM(SUMIF(INDIRECT({"01";"02";"03";"04";"05";"06";"07"} & "!B:G"),$B40,INDIRECT({"01";"02";"03";"04";"05";"06";"07"} & "!G:G"))) -> 0 | D40: =SUM(SUMIF(INDIRECT({"01";"02";"03";"04";"05";"06";"07"} & "!B:I"),$B40,INDIRECT({"01";"02";"03";"04";"05";"06";"07"} & "!I:I"))) -> 0 | E40: {=SUM(SUMIF(INDIRECT({"08";"09";"10";"11";"12";"13";"14"} & "!B:G"),$B40,INDIRECT({"08";"09";"10";"11";"12";"13";"14"} & "!G:G")))} -> 0 | F40: {=SUM(SUMIF(INDIRECT({"08";"09";"10";"11";"12";"13";"14"} & "!B:I"),$B40,INDIRECT({"08";"09";"10";"11";"12";"13";"14"} & "!I:I")))} -> 0 | G40: {=SUM(SUMIF(INDIRECT({"15";"16";"17";"18";"19";"20";"21"} & "!B:G"),$B40,INDIRECT({"15";"16";"17";"18";"19";"20";"21"} & "!G:G")))} -> 0 | H40: {=SUM(SUMIF(INDIRECT({"15";"16";"17";"18";"19";"20";"21"} & "!B:I"),$B40,INDIRECT({"15";"16";"17";"18";"19";"20";"21"} & "!I:I")))} -> 0 | I40: {=SUM(SUMIF(INDIRECT({"22";"23";"24";"25";"26";"27";"28";"29";"30";"31"} & "!B:G"),$B40,INDIRECT({"22";"23";"24";"25";"26";"27";"28";"29";"30";"31"} & "!G:G")))} -> 0 | J40: {=SUM(SUMIF(INDIRECT({"22";"23";"24";"25";"26";"27";"28";"29";"30";"31"} & "!B:I"),$B40,INDIRECT({"22";"23";"24";"25";"26";"27";"28";"29";"30";"31"} & "!I:I")))} -> 0 | K40: =ROUND(SUM(C40,E40,G40,I40)/DAY(TODAY()),0) -> 0 | L40: =SUM(D40,F40,H40,J40)/DAY(TODAY()) -> 0 | M40: =K40*7 -> 0 | N40: =L40*7 -> 0 | O40: =ROUND(K40*30,0) -> 0 | P40: =L40*30 -> 0 | S40: =EXACT(B40,Total!B40) -> TRUE | T40: =SUM(D40+F40+H40+J40) -> 0 | W40: CAJA DE DISTRIBUCION DE 8 VIAS
A41: U | B41: CAJA DE DISTRIBUCION DE 12 VIAS | C41: =SUM(SUMIF(INDIRECT({"01";"02";"03";"04";"05";"06";"07"} & "!B:G"),$B41,INDIRECT({"01";"02";"03";"04";"05";"06";"07"} & "!G:G"))) -> 0 | D41: =SUM(SUMIF(INDIRECT({"01";"02";"03";"04";"05";"06";"07"} & "!B:I"),$B41,INDIRECT({"01";"02";"03";"04";"05";"06";"07"} & "!I:I"))) -> 0 | E41: {=SUM(SUMIF(INDIRECT({"08";"09";"10";"11";"12";"13";"14"} & "!B:G"),$B41,INDIRECT({"08";"09";"10";"11";"12";"13";"14"} & "!G:G")))} -> 0 | F41: {=SUM(SUMIF(INDIRECT({"08";"09";"10";"11";"12";"13";"14"} & "!B:I"),$B41,INDIRECT({"08";"09";"10";"11";"12";"13";"14"} & "!I:I")))} -> 0 | G41: {=SUM(SUMIF(INDIRECT({"15";"16";"17";"18";"19";"20";"21"} & "!B:G"),$B41,INDIRECT({"15";"16";"17";"18";"19";"20";"21"} & "!G:G")))} -> 0 | H41: {=SUM(SUMIF(INDIRECT({"15";"16";"17";"18";"19";"20";"21"} & "!B:I"),$B41,INDIRECT({"15";"16";"17";"18";"19";"20";"21"} & "!I:I")))} -> 0 | I41: {=SUM(SUMIF(INDIRECT({"22";"23";"24";"25";"26";"27";"28";"29";"30";"31"} & "!B:G"),$B41,INDIRECT({"22";"23";"24";"25";"26";"27";"28";"29";"30";"31"} & "!G:G")))} -> 0 | J41: {=SUM(SUMIF(INDIRECT({"22";"23";"24";"25";"26";"27";"28";"29";"30";"31"} & "!B:I"),$B41,INDIRECT({"22";"23";"24";"25";"26";"27";"28";"29";"30";"31"} & "!I:I")))} -> 0 | K41: =ROUND(SUM(C41,E41,G41,I41)/DAY(TODAY()),0) -> 0 | L41: =SUM(D41,F41,H41,J41)/DAY(TODAY()) -> 0 | M41: =K41*7 -> 0 | N41: =L41*7 -> 0 | O41: =ROUND(K41*30,0) -> 0 | P41: =L41*30 -> 0 | S41: =EXACT(B41,Total!B41) -> TRUE | T41: =SUM(D41+F41+H41+J41) -> 0 | W41: CAJA DE DISTRIBUCION DE 12 VIAS
B42: CAJA DE HERRAMIENTAS 13PCS | C42: =SUM(SUMIF(INDIRECT({"01";"02";"03";"04";"05";"06";"07"} & "!B:G"),$B42,INDIRECT({"01";"02";"03";"04";"05";"06";"07"} & "!G:G"))) -> 0 | D42: =SUM(SUMIF(INDIRECT({"01";"02";"03";"04";"05";"06";"07"} & "!B:I"),$B42,INDIRECT({"01";"02";"03";"04";"05";"06";"07"} & "!I:I"))) -> 0 | E42: {=SUM(SUMIF(INDIRECT({"08";"09";"10";"11";"12";"13";"14"} & "!B:G"),$B42,INDIRECT({"08";"09";"10";"11";"12";"13";"14"} & "!G:G")))} -> 2 | F42: {=SUM(SUMIF(INDIRECT({"08";"09";"10";"11";"12";"13";"14"} & "!B:I"),$B42,INDIRECT({"08";"09";"10";"11";"12";"13";"14"} & "!I:I")))} -> 40 | G42: {=SUM(SUMIF(INDIRECT({"15";"16";"17";"18";"19";"20";"21"} & "!B:G"),$B42,INDIRECT({"15";"16";"17";"18";"19";"20";"21"} & "!G:G")))} -> 0 | H42: {=SUM(SUMIF(INDIRECT({"15";"16";"17";"18";"19";"20";"21"} & "!B:I"),$B42,INDIRECT({"15";"16";"17";"18";"19";"20";"21"} & "!I:I")))} -> 0 | I42: {=SUM(SUMIF(INDIRECT({"22";"23";"24";"25";"26";"27";"28";"29";"30";"31"} & "!B:G"),$B42,INDIRECT({"22";"23";"24";"25";"26";"27";"28";"29";"30";"31"} & "!G:G")))} -> 0 | J42: {=SUM(SUMIF(INDIRECT({"22";"23";"24";"25";"26";"27";"28";"29";"30";"31"} & "!B:I"),$B42,INDIRECT({"22";"23";"24";"25";"26";"27";"28";"29";"30";"31"} & "!I:I")))} -> 0 | K42: =ROUND(SUM(C42,E42,G42,I42)/DAY(TODAY()),0) -> 2 | L42: =SUM(D42,F42,H42,J42)/DAY(TODAY()) -> 40 | M42: =K42*7 -> 14 | N42: =L42*7 -> 280 | O42: =ROUND(K42*30,0) -> 60 | P42: =L42*30 -> 1200 | S42: =EXACT(B42,Total!B42) -> TRUE | T42: =SUM(D42+F42+H42+J42) -> 40 | W42: CAJA DE HERRAMIENTAS 13PCS
B43: COLCHON PERSONAL | C43: =SUM(SUMIF(INDIRECT({"01";"02";"03";"04";"05";"06";"07"} & "!B:G"),$B43,INDIRECT({"01";"02";"03";"04";"05";"06";"07"} & "!G:G"))) -> 0 | D43: =SUM(SUMIF(INDIRECT({"01";"02";"03";"04";"05";"06";"07"} & "!B:I"),$B43,INDIRECT({"01";"02";"03";"04";"05";"06";"07"} & "!I:I"))) -> 0 | E43: {=SUM(SUMIF(INDIRECT({"08";"09";"10";"11";"12";"13";"14"} & "!B:G"),$B43,INDIRECT({"08";"09";"10";"11";"12";"13";"14"} & "!G:G")))} -> 0 | F43: {=SUM(SUMIF(INDIRECT({"08";"09";"10";"11";"12";"13";"14"} & "!B:I"),$B43,INDIRECT({"08";"09";"10";"11";"12";"13";"14"} & "!I:I")))} -> 0 | G43: {=SUM(SUMIF(INDIRECT({"15";"16";"17";"18";"19";"20";"21"} & "!B:G"),$B43,INDIRECT({"15";"16";"17";"18";"19";"20";"21"} & "!G:G")))} -> 0 | H43: {=SUM(SUMIF(INDIRECT({"15";"16";"17";"18";"19";"20";"21"} & "!B:I"),$B43,INDIRECT({"15";"16";"17";"18";"19";"20";"21"} & "!I:I")))} -> 0 | I43: {=SUM(SUMIF(INDIRECT({"22";"23";"24";"25";"26";"27";"28";"29";"30";"31"} & "!B:G"),$B43,INDIRECT({"22";"23";"24";"25";"26";"27";"28";"29";"30";"31"} & "!G:G")))} -> 0 | J43: {=SUM(SUMIF(INDIRECT({"22";"23";"24";"25";"26";"27";"28";"29";"30";"31"} & "!B:I"),$B43,INDIRECT({"22";"23";"24";"25";"26";"27";"28";"29";"30";"31"} & "!I:I")))} -> 0 | K43: =ROUND(SUM(C43,E43,G43,I43)/DAY(TODAY()),0) -> 0 | L43: =SUM(D43,F43,H43,J43)/DAY(TODAY()) -> 0 | M43: =K43*7 -> 0 | N43: =L43*7 -> 0 | O43: =ROUND(K43*30,0) -> 0 | P43: =L43*30 -> 0 | S43: =EXACT(B43,Total!B43) -> TRUE | T43: =SUM(D43+F43+H43+J43) -> 0 | W43: COLCHON PERSONAL
A44: U | B44: COLCHON EKO | C44: =SUM(SUMIF(INDIRECT({"01";"02";"03";"04";"05";"06";"07"} & "!B:G"),$B44,INDIRECT({"01";"02";"03";"04";"05";"06";"07"} & "!G:G"))) -> 0 | D44: =SUM(SUMIF(INDIRECT({"01";"02";"03";"04";"05";"06";"07"} & "!B:I"),$B44,INDIRECT({"01";"02";"03";"04";"05";"06";"07"} & "!I:I"))) -> 0 | E44: {=SUM(SUMIF(INDIRECT({"08";"09";"10";"11";"12";"13";"14"} & "!B:G"),$B44,INDIRECT({"08";"09";"10";"11";"12";"13";"14"} & "!G:G")))} -> 0 | F44: {=SUM(SUMIF(INDIRECT({"08";"09";"10";"11";"12";"13";"14"} & "!B:I"),$B44,INDIRECT({"08";"09";"10";"11";"12";"13";"14"} & "!I:I")))} -> 0 | G44: {=SUM(SUMIF(INDIRECT({"15";"16";"17";"18";"19";"20";"21"} & "!B:G"),$B44,INDIRECT({"15";"16";"17";"18";"19";"20";"21"} & "!G:G")))} -> 0 | H44: {=SUM(SUMIF(INDIRECT({"15";"16";"17";"18";"19";"20";"21"} & "!B:I"),$B44,INDIRECT({"15";"16";"17";"18";"19";"20";"21"} & "!I:I")))} -> 0 | I44: {=SUM(SUMIF(INDIRECT({"22";"23";"24";"25";"26";"27";"28";"29";"30";"31"} & "!B:G"),$B44,INDIRECT({"22";"23";"24";"25";"26";"27";"28";"29";"30";"31"} & "!G:G")))} -> 1 | J44: {=SUM(SUMIF(INDIRECT({"22";"23";"24";"25";"26";"27";"28";"29";"30";"31"} & "!B:I"),$B44,INDIRECT({"22";"23";"24";"25";"26";"27";"28";"29";"30";"31"} & "!I:I")))} -> 330 | K44: =ROUND(SUM(C44,E44,G44,I44)/DAY(TODAY()),0) -> 1 | L44: =SUM(D44,F44,H44,J44)/DAY(TODAY()) -> 330 | M44: =K44*7 -> 7 | N44: =L44*7 -> 2310 | O44: =ROUND(K44*30,0) -> 30 | P44: =L44*30 -> 9900 | S44: =EXACT(B44,Total!B44) -> TRUE | T44: =SUM(D44+F44+H44+J44) -> 330 | W44: COLCHON EKO
B45: CAJAS DE AZULEJOS 44X44 2.5 M | C45: =SUM(SUMIF(INDIRECT({"01";"02";"03";"04";"05";"06";"07"} & "!B:G"),$B45,INDIRECT({"01";"02";"03";"04";"05";"06";"07"} & "!G:G"))) -> 0 | D45: =SUM(SUMIF(INDIRECT({"01";"02";"03";"04";"05";"06";"07"} & "!B:I"),$B45,INDIRECT({"01";"02";"03";"04";"05";"06";"07"} & "!I:I"))) -> 0 | E45: {=SUM(SUMIF(INDIRECT({"08";"09";"10";"11";"12";"13";"14"} & "!B:G"),$B45,INDIRECT({"08";"09";"10";"11";"12";"13";"14"} & "!G:G")))} -> 0 | F45: {=SUM(SUMIF(INDIRECT({"08";"09";"10";"11";"12";"13";"14"} & "!B:I"),$B45,INDIRECT({"08";"09";"10";"11";"12";"13";"14"} & "!I:I")))} -> 0 | G45: {=SUM(SUMIF(INDIRECT({"15";"16";"17";"18";"19";"20";"21"} & "!B:G"),$B45,INDIRECT({"15";"16";"17";"18";"19";"20";"21"} & "!G:G")))} -> 0 | H45: {=SUM(SUMIF(INDIRECT({"15";"16";"17";"18";"19";"20";"21"} & "!B:I"),$B45,INDIRECT({"15";"16";"17";"18";"19";"20";"21"} & "!I:I")))} -> 0 | I45: {=SUM(SUMIF(INDIRECT({"22";"23";"24";"25";"26";"27";"28";"29";"30";"31"} & "!B:G"),$B45,INDIRECT({"22";"23";"24";"25";"26";"27";"28";"29";"30";"31"} & "!G:G")))} -> 0 | J45: {=SUM(SUMIF(INDIRECT({"22";"23";"24";"25";"26";"27";"28";"29";"30";"31"} & "!B:I"),$B45,INDIRECT({"22";"23";"24";"25";"26";"27";"28";"29";"30";"31"} & "!I:I")))} -> 0 | K45: =ROUND(SUM(C45,E45,G45,I45)/DAY(TODAY()),0) -> 0 | L45: =SUM(D45,F45,H45,J45)/DAY(TODAY()) -> 0 | M45: =K45*7 -> 0 | N45: =L45*7 -> 0 | O45: =ROUND(K45*30,0) -> 0 | P45: =L45*30 -> 0 | S45: =EXACT(B45,Total!B45) -> TRUE | T45: =SUM(D45+F45+H45+J45) -> 0 | W45: CAJAS DE AZULEJOS 44X44 2.5 M
B46: CAFETERA 3 TASAS | C46: =SUM(SUMIF(INDIRECT({"01";"02";"03";"04";"05";"06";"07"} & "!B:G"),$B46,INDIRECT({"01";"02";"03";"04";"05";"06";"07"} & "!G:G"))) -> 0 | D46: =SUM(SUMIF(INDIRECT({"01";"02";"03";"04";"05";"06";"07"} & "!B:I"),$B46,INDIRECT({"01";"02";"03";"04";"05";"06";"07"} & "!I:I"))) -> 0 | E46: {=SUM(SUMIF(INDIRECT({"08";"09";"10";"11";"12";"13";"14"} & "!B:G"),$B46,INDIRECT({"08";"09";"10";"11";"12";"13";"14"} & "!G:G")))} -> 0 | F46: {=SUM(SUMIF(INDIRECT({"08";"09";"10";"11";"12";"13";"14"} & "!B:I"),$B46,INDIRECT({"08";"09";"10";"11";"12";"13";"14"} & "!I:I")))} -> 0 | G46: {=SUM(SUMIF(INDIRECT({"15";"16";"17";"18";"19";"20";"21"} & "!B:G"),$B46,INDIRECT({"15";"16";"17";"18";"19";"20";"21"} & "!G:G")))} -> 0 | H46: {=SUM(SUMIF(INDIRECT({"15";"16";"17";"18";"19";"20";"21"} & "!B:I"),$B46,INDIRECT({"15";"16";"17";"18";"19";"20";"21"} & "!I:I")))} -> 0 | I46: {=SUM(SUMIF(INDIRECT({"22";"23";"24";"25";"26";"27";"28";"29";"30";"31"} & "!B:G"),$B46,INDIRECT({"22";"23";"24";"25";"26";"27";"28";"29";"30";"31"} & "!G:G")))} -> 0 | J46: {=SUM(SUMIF(INDIRECT({"22";"23";"24";"25";"26";"27";"28";"29";"30";"31"} & "!B:I"),$B46,INDIRECT({"22";"23";"24";"25";"26";"27";"28";"29";"30";"31"} & "!I:I")))} -> 0 | K46: =ROUND(SUM(C46,E46,G46,I46)/DAY(TODAY()),0) -> 0 | L46: =SUM(D46,F46,H46,J46)/DAY(TODAY()) -> 0 | M46: =K46*7 -> 0 | N46: =L46*7 -> 0 | O46: =ROUND(K46*30,0) -> 0 | P46: =L46*30 -> 0 | S46: =EXACT(B46,Total!B46) -> TRUE | T46: =SUM(D46+F46+H46+J46) -> 0 | W46: CAFETERA 3 TASAS
A47: U | B47: CAFETERA ELECTRICA ESPRESO 800W | C47: =SUM(SUMIF(INDIRECT({"01";"02";"03";"04";"05";"06";"07"} & "!B:G"),$B47,INDIRECT({"01";"02";"03";"04";"05";"06";"07"} & "!G:G"))) -> 0 | D47: =SUM(SUMIF(INDIRECT({"01";"02";"03";"04";"05";"06";"07"} & "!B:I"),$B47,INDIRECT({"01";"02";"03";"04";"05";"06";"07"} & "!I:I"))) -> 0 | E47: {=SUM(SUMIF(INDIRECT({"08";"09";"10";"11";"12";"13";"14"} & "!B:G"),$B47,INDIRECT({"08";"09";"10";"11";"12";"13";"14"} & "!G:G")))} -> 0 | F47: {=SUM(SUMIF(INDIRECT({"08";"09";"10";"11";"12";"13";"14"} & "!B:I"),$B47,INDIRECT({"08";"09";"10";"11";"12";"13";"14"} & "!I:I")))} -> 0 | G47: {=SUM(SUMIF(INDIRECT({"15";"16";"17";"18";"19";"20";"21"} & "!B:G"),$B47,INDIRECT({"15";"16";"17";"18";"19";"20";"21"} & "!G:G")))} -> 1 | H47: {=SUM(SUMIF(INDIRECT({"15";"16";"17";"18";"19";"20";"21"} & "!B:I"),$B47,INDIRECT({"15";"16";"17";"18";"19";"20";"21"} & "!I:I")))} -> 70 | I47: {=SUM(SUMIF(INDIRECT({"22";"23";"24";"25";"26";"27";"28";"29";"30";"31"} & "!B:G"),$B47,INDIRECT({"22";"23";"24";"25";"26";"27";"28";"29";"30";"31"} & "!G:G")))} -> 0 | J47: {=SUM(SUMIF(INDIRECT({"22";"23";"24";"25";"26";"27";"28";"29";"30";"31"} & "!B:I"),$B47,INDIRECT({"22";"23";"24";"25";"26";"27";"28";"29";"30";"31"} & "!I:I")))} -> 0 | K47: =ROUND(SUM(C47,E47,G47,I47)/DAY(TODAY()),0) -> 1 | L47: =SUM(D47,F47,H47,J47)/DAY(TODAY()) -> 70 | M47: =K47*7 -> 7 | N47: =L47*7 -> 490 | O47: =ROUND(K47*30,0) -> 30 | P47: =L47*30 -> 2100 | S47: =EXACT(B47,Total!B47) -> TRUE | T47: =SUM(D47+F47+H47+J47) -> 70 | W47: CAFETERA ELECTRICA ESPRESO 800W
A48: U | B48: CAFETERA ELECTRICA RUDENKOV | C48: =SUM(SUMIF(INDIRECT({"01";"02";"03";"04";"05";"06";"07"} & "!B:G"),$B48,INDIRECT({"01";"02";"03";"04";"05";"06";"07"} & "!G:G"))) -> 0 | D48: =SUM(SUMIF(INDIRECT({"01";"02";"03";"04";"05";"06";"07"} & "!B:I"),$B48,INDIRECT({"01";"02";"03";"04";"05";"06";"07"} & "!I:I"))) -> 0 | E48: {=SUM(SUMIF(INDIRECT({"08";"09";"10";"11";"12";"13";"14"} & "!B:G"),$B48,INDIRECT({"08";"09";"10";"11";"12";"13";"14"} & "!G:G")))} -> 1 | F48: {=SUM(SUMIF(INDIRECT({"08";"09";"10";"11";"12";"13";"14"} & "!B:I"),$B48,INDIRECT({"08";"09";"10";"11";"12";"13";"14"} & "!I:I")))} -> 40 | G48: {=SUM(SUMIF(INDIRECT({"15";"16";"17";"18";"19";"20";"21"} & "!B:G"),$B48,INDIRECT({"15";"16";"17";"18";"19";"20";"21"} & "!G:G")))} -> 0 | H48: {=SUM(SUMIF(INDIRECT({"15";"16";"17";"18";"19";"20";"21"} & "!B:I"),$B48,INDIRECT({"15";"16";"17";"18";"19";"20";"21"} & "!I:I")))} -> 0 | I48: {=SUM(SUMIF(INDIRECT({"22";"23";"24";"25";"26";"27";"28";"29";"30";"31"} & "!B:G"),$B48,INDIRECT({"22";"23";"24";"25";"26";"27";"28";"29";"30";"31"} & "!G:G")))} -> 0 | J48: {=SUM(SUMIF(INDIRECT({"22";"23";"24";"25";"26";"27";"28";"29";"30";"31"} & "!B:I"),$B48,INDIRECT({"22";"23";"24";"25";"26";"27";"28";"29";"30";"31"} & "!I:I")))} -> 0 | K48: =ROUND(SUM(C48,E48,G48,I48)/DAY(TODAY()),0) -> 1 | L48: =SUM(D48,F48,H48,J48)/DAY(TODAY()) -> 40 | M48: =K48*7 -> 7 | N48: =L48*7 -> 280 | O48: =ROUND(K48*30,0) -> 30 | P48: =L48*30 -> 1200 | S48: =EXACT(B48,Total!B48) -> TRUE | T48: =SUM(D48+F48+H48+J48) -> 40 | W48: CAFETERA ELECTRICA RUDENKOV
B49: CALENTADOR 80 L | C49: =SUM(SUMIF(INDIRECT({"01";"02";"03";"04";"05";"06";"07"} & "!B:G"),$B49,INDIRECT({"01";"02";"03";"04";"05";"06";"07"} & "!G:G"))) -> 0 | D49: =SUM(SUMIF(INDIRECT({"01";"02";"03";"04";"05";"06";"07"} & "!B:I"),$B49,INDIRECT({"01";"02";"03";"04";"05";"06";"07"} & "!I:I"))) -> 0 | E49: {=SUM(SUMIF(INDIRECT({"08";"09";"10";"11";"12";"13";"14"} & "!B:G"),$B49,INDIRECT({"08";"09";"10";"11";"12";"13";"14"} & "!G:G")))} -> 0 | F49: {=SUM(SUMIF(INDIRECT({"08";"09";"10";"11";"12";"13";"14"} & "!B:I"),$B49,INDIRECT({"08";"09";"10";"11";"12";"13";"14"} & "!I:I")))} -> 0 | G49: {=SUM(SUMIF(INDIRECT({"15";"16";"17";"18";"19";"20";"21"} & "!B:G"),$B49,INDIRECT({"15";"16";"17";"18";"19";"20";"21"} & "!G:G")))} -> 0 | H49: {=SUM(SUMIF(INDIRECT({"15";"16";"17";"18";"19";"20";"21"} & "!B:I"),$B49,INDIRECT({"15";"16";"17";"18";"19";"20";"21"} & "!I:I")))} -> 0 | I49: {=SUM(SUMIF(INDIRECT({"22";"23";"24";"25";"26";"27";"28";"29";"30";"31"} & "!B:G"),$B49,INDIRECT({"22";"23";"24";"25";"26";"27";"28";"29";"30";"31"} & "!G:G")))} -> 1 | J49: {=SUM(SUMIF(INDIRECT({"22";"23";"24";"25";"26";"27";"28";"29";"30";"31"} & "!B:I"),$B49,INDIRECT({"22";"23";"24";"25";"26";"27";"28";"29";"30";"31"} & "!I:I")))} -> 200 | K49: =ROUND(SUM(C49,E49,G49,I49)/DAY(TODAY()),0) -> 1 | L49: =SUM(D49,F49,H49,J49)/DAY(TODAY()) -> 200 | M49: =K49*7 -> 7 | N49: =L49*7 -> 1400 | O49: =ROUND(K49*30,0) -> 30 | P49: =L49*30 -> 6000 | S49: =EXACT(B49,Total!B49) -> TRUE | T49: =SUM(D49+F49+H49+J49) -> 200 | W49: CALENTADOR 80 L
B50: CALENTADOR 50 L | C50: =SUM(SUMIF(INDIRECT({"01";"02";"03";"04";"05";"06";"07"} & "!B:G"),$B50,INDIRECT({"01";"02";"03";"04";"05";"06";"07"} & "!G:G"))) -> 0 | D50: =SUM(SUMIF(INDIRECT({"01";"02";"03";"04";"05";"06";"07"} & "!B:I"),$B50,INDIRECT({"01";"02";"03";"04";"05";"06";"07"} & "!I:I"))) -> 0 | E50: {=SUM(SUMIF(INDIRECT({"08";"09";"10";"11";"12";"13";"14"} & "!B:G"),$B50,INDIRECT({"08";"09";"10";"11";"12";"13";"14"} & "!G:G")))} -> 0 | F50: {=SUM(SUMIF(INDIRECT({"08";"09";"10";"11";"12";"13";"14"} & "!B:I"),$B50,INDIRECT({"08";"09";"10";"11";"12";"13";"14"} & "!I:I")))} -> 0 | G50: {=SUM(SUMIF(INDIRECT({"15";"16";"17";"18";"19";"20";"21"} & "!B:G"),$B50,INDIRECT({"15";"16";"17";"18";"19";"20";"21"} & "!G:G")))} -> 0 | H50: {=SUM(SUMIF(INDIRECT({"15";"16";"17";"18";"19";"20";"21"} & "!B:I"),$B50,INDIRECT({"15";"16";"17";"18";"19";"20";"21"} & "!I:I")))} -> 0 | I50: {=SUM(SUMIF(INDIRECT({"22";"23";"24";"25";"26";"27";"28";"29";"30";"31"} & "!B:G"),$B50,INDIRECT({"22";"23";"24";"25";"26";"27";"28";"29";"30";"31"} & "!G:G")))} -> 0 | J50: {=SUM(SUMIF(INDIRECT({"22";"23";"24";"25";"26";"27";"28";"29";"30";"31"} & "!B:I"),$B50,INDIRECT({"22";"23";"24";"25";"26";"27";"28";"29";"30";"31"} & "!I:I")))} -> 0 | K50: =ROUND(SUM(C50,E50,G50,I50)/DAY(TODAY()),0) -> 0 | L50: =SUM(D50,F50,H50,J50)/DAY(TODAY()) -> 0 | M50: =K50*7 -> 0 | N50: =L50*7 -> 0 | O50: =ROUND(K50*30,0) -> 0 | P50: =L50*30 -> 0 | S50: =EXACT(B50,Total!B50) -> TRUE | T50: =SUM(D50+F50+H50+J50) -> 0 | W50: CALENTADOR 50 L
B51: DISPENSSDOR DE AGUA ROYAL | C51: =SUM(SUMIF(INDIRECT({"01";"02";"03";"04";"05";"06";"07"} & "!B:G"),$B51,INDIRECT({"01";"02";"03";"04";"05";"06";"07"} & "!G:G"))) -> 0 | D51: =SUM(SUMIF(INDIRECT({"01";"02";"03";"04";"05";"06";"07"} & "!B:I"),$B51,INDIRECT({"01";"02";"03";"04";"05";"06";"07"} & "!I:I"))) -> 0 | E51: {=SUM(SUMIF(INDIRECT({"08";"09";"10";"11";"12";"13";"14"} & "!B:G"),$B51,INDIRECT({"08";"09";"10";"11";"12";"13";"14"} & "!G:G")))} -> 0 | F51: {=SUM(SUMIF(INDIRECT({"08";"09";"10";"11";"12";"13";"14"} & "!B:I"),$B51,INDIRECT({"08";"09";"10";"11";"12";"13";"14"} & "!I:I")))} -> 0 | G51: {=SUM(SUMIF(INDIRECT({"15";"16";"17";"18";"19";"20";"21"} & "!B:G"),$B51,INDIRECT({"15";"16";"17";"18";"19";"20";"21"} & "!G:G")))} -> 0 | H51: {=SUM(SUMIF(INDIRECT({"15";"16";"17";"18";"19";"20";"21"} & "!B:I"),$B51,INDIRECT({"15";"16";"17";"18";"19";"20";"21"} & "!I:I")))} -> 0 | I51: {=SUM(SUMIF(INDIRECT({"22";"23";"24";"25";"26";"27";"28";"29";"30";"31"} & "!B:G"),$B51,INDIRECT({"22";"23";"24";"25";"26";"27";"28";"29";"30";"31"} & "!G:G")))} -> 0 | J51: {=SUM(SUMIF(INDIRECT({"22";"23";"24";"25";"26";"27";"28";"29";"30";"31"} & "!B:I"),$B51,INDIRECT({"22";"23";"24";"25";"26";"27";"28";"29";"30";"31"} & "!I:I")))} -> 0 | K51: =ROUND(SUM(C51,E51,G51,I51)/DAY(TODAY()),0) -> 0 | L51: =SUM(D51,F51,H51,J51)/DAY(TODAY()) -> 0 | M51: =K51*7 -> 0 | N51: =L51*7 -> 0 | O51: =ROUND(K51*30,0) -> 0 | P51: =L51*30 -> 0 | S51: =EXACT(B51,Total!B51) -> TRUE | T51: =SUM(D51+F51+H51+J51) -> 0 | W51: DISPENSSDOR DE AGUA ROYAL
B52: ESTACION ENERGIA 6000 W | C52: =SUM(SUMIF(INDIRECT({"01";"02";"03";"04";"05";"06";"07"} & "!B:G"),$B52,INDIRECT({"01";"02";"03";"04";"05";"06";"07"} & "!G:G"))) -> 0 | D52: =SUM(SUMIF(INDIRECT({"01";"02";"03";"04";"05";"06";"07"} & "!B:I"),$B52,INDIRECT({"01";"02";"03";"04";"05";"06";"07"} & "!I:I"))) -> 0 | E52: {=SUM(SUMIF(INDIRECT({"08";"09";"10";"11";"12";"13";"14"} & "!B:G"),$B52,INDIRECT({"08";"09";"10";"11";"12";"13";"14"} & "!G:G")))} -> 0 | F52: {=SUM(SUMIF(INDIRECT({"08";"09";"10";"11";"12";"13";"14"} & "!B:I"),$B52,INDIRECT({"08";"09";"10";"11";"12";"13";"14"} & "!I:I")))} -> 0 | G52: {=SUM(SUMIF(INDIRECT({"15";"16";"17";"18";"19";"20";"21"} & "!B:G"),$B52,INDIRECT({"15";"16";"17";"18";"19";"20";"21"} & "!G:G")))} -> 0 | H52: {=SUM(SUMIF(INDIRECT({"15";"16";"17";"18";"19";"20";"21"} & "!B:I"),$B52,INDIRECT({"15";"16";"17";"18";"19";"20";"21"} & "!I:I")))} -> 0 | I52: {=SUM(SUMIF(INDIRECT({"22";"23";"24";"25";"26";"27";"28";"29";"30";"31"} & "!B:G"),$B52,INDIRECT({"22";"23";"24";"25";"26";"27";"28";"29";"30";"31"} & "!G:G")))} -> 0 | J52: {=SUM(SUMIF(INDIRECT({"22";"23";"24";"25";"26";"27";"28";"29";"30";"31"} & "!B:I"),$B52,INDIRECT({"22";"23";"24";"25";"26";"27";"28";"29";"30";"31"} & "!I:I")))} -> 0 | K52: =ROUND(SUM(C52,E52,G52,I52)/DAY(TODAY()),0) -> 0 | L52: =SUM(D52,F52,H52,J52)/DAY(TODAY()) -> 0 | M52: =K52*7 -> 0 | N52: =L52*7 -> 0 | O52: =ROUND(K52*30,0) -> 0 | P52: =L52*30 -> 0 | S52: =EXACT(B52,Total!B52) -> TRUE | T52: =SUM(D52+F52+H52+J52) -> 0 | W52: ESTACION ENERGIA 6000 W
A53: U | B53: ESTACION ENERGIA PECRON | C53: =SUM(SUMIF(INDIRECT({"01";"02";"03";"04";"05";"06";"07"} & "!B:G"),$B53,INDIRECT({"01";"02";"03";"04";"05";"06";"07"} & "!G:G"))) -> 0 | D53: =SUM(SUMIF(INDIRECT({"01";"02";"03";"04";"05";"06";"07"} & "!B:I"),$B53,INDIRECT({"01";"02";"03";"04";"05";"06";"07"} & "!I:I"))) -> 0 | E53: {=SUM(SUMIF(INDIRECT({"08";"09";"10";"11";"12";"13";"14"} & "!B:G"),$B53,INDIRECT({"08";"09";"10";"11";"12";"13";"14"} & "!G:G")))} -> 0 | F53: {=SUM(SUMIF(INDIRECT({"08";"09";"10";"11";"12";"13";"14"} & "!B:I"),$B53,INDIRECT({"08";"09";"10";"11";"12";"13";"14"} & "!I:I")))} -> 0 | G53: {=SUM(SUMIF(INDIRECT({"15";"16";"17";"18";"19";"20";"21"} & "!B:G"),$B53,INDIRECT({"15";"16";"17";"18";"19";"20";"21"} & "!G:G")))} -> 0 | H53: {=SUM(SUMIF(INDIRECT({"15";"16";"17";"18";"19";"20";"21"} & "!B:I"),$B53,INDIRECT({"15";"16";"17";"18";"19";"20";"21"} & "!I:I")))} -> 0 | I53: {=SUM(SUMIF(INDIRECT({"22";"23";"24";"25";"26";"27";"28";"29";"30";"31"} & "!B:G"),$B53,INDIRECT({"22";"23";"24";"25";"26";"27";"28";"29";"30";"31"} & "!G:G")))} -> 0 | J53: {=SUM(SUMIF(INDIRECT({"22";"23";"24";"25";"26";"27";"28";"29";"30";"31"} & "!B:I"),$B53,INDIRECT({"22";"23";"24";"25";"26";"27";"28";"29";"30";"31"} & "!I:I")))} -> 0 | K53: =ROUND(SUM(C53,E53,G53,I53)/DAY(TODAY()),0) -> 0 | L53: =SUM(D53,F53,H53,J53)/DAY(TODAY()) -> 0 | M53: =K53*7 -> 0 | N53: =L53*7 -> 0 | O53: =ROUND(K53*30,0) -> 0 | P53: =L53*30 -> 0 | S53: =EXACT(B53,Total!B53) -> TRUE | T53: =SUM(D53+F53+H53+J53) -> 0 | W53: ESTACION ENERGIA PECRON
A54: U | B54: ESTACION ENERGIA ECOFLOW DELTA 2 | C54: =SUM(SUMIF(INDIRECT({"01";"02";"03";"04";"05";"06";"07"} & "!B:G"),$B54,INDIRECT({"01";"02";"03";"04";"05";"06";"07"} & "!G:G"))) -> 0 | D54: =SUM(SUMIF(INDIRECT({"01";"02";"03";"04";"05";"06";"07"} & "!B:I"),$B54,INDIRECT({"01";"02";"03";"04";"05";"06";"07"} & "!I:I"))) -> 0 | E54: {=SUM(SUMIF(INDIRECT({"08";"09";"10";"11";"12";"13";"14"} & "!B:G"),$B54,INDIRECT({"08";"09";"10";"11";"12";"13";"14"} & "!G:G")))} -> 0 | F54: {=SUM(SUMIF(INDIRECT({"08";"09";"10";"11";"12";"13";"14"} & "!B:I"),$B54,INDIRECT({"08";"09";"10";"11";"12";"13";"14"} & "!I:I")))} -> 0 | G54: {=SUM(SUMIF(INDIRECT({"15";"16";"17";"18";"19";"20";"21"} & "!B:G"),$B54,INDIRECT({"15";"16";"17";"18";"19";"20";"21"} & "!G:G")))} -> 0 | H54: {=SUM(SUMIF(INDIRECT({"15";"16";"17";"18";"19";"20";"21"} & "!B:I"),$B54,INDIRECT({"15";"16";"17";"18";"19";"20";"21"} & "!I:I")))} -> 0 | I54: {=SUM(SUMIF(INDIRECT({"22";"23";"24";"25";"26";"27";"28";"29";"30";"31"} & "!B:G"),$B54,INDIRECT({"22";"23";"24";"25";"26";"27";"28";"29";"30";"31"} & "!G:G")))} -> 0 | J54: {=SUM(SUMIF(INDIRECT({"22";"23";"24";"25";"26";"27";"28";"29";"30";"31"} & "!B:I"),$B54,INDIRECT({"22";"23";"24";"25";"26";"27";"28";"29";"30";"31"} & "!I:I")))} -> 0 | K54: =ROUND(SUM(C54,E54,G54,I54)/DAY(TODAY()),0) -> 0 | L54: =SUM(D54,F54,H54,J54)/DAY(TODAY()) -> 0 | M54: =K54*7 -> 0 | N54: =L54*7 -> 0 | O54: =ROUND(K54*30,0) -> 0 | P54: =L54*30 -> 0 | S54: =EXACT(B54,Total!B54) -> TRUE | T54: =SUM(D54+F54+H54+J54) -> 0 | W54: ESTACION ENERGIA ECOFLOW DELTA 2
A55: U | B55: ESTACION ENERGIA ECOFLOW DELTA 3 | C55: =SUM(SUMIF(INDIRECT({"01";"02";"03";"04";"05";"06";"07"} & "!B:G"),$B55,INDIRECT({"01";"02";"03";"04";"05";"06";"07"} & "!G:G"))) -> 0 | D55: =SUM(SUMIF(INDIRECT({"01";"02";"03";"04";"05";"06";"07"} & "!B:I"),$B55,INDIRECT({"01";"02";"03";"04";"05";"06";"07"} & "!I:I"))) -> 0 | E55: {=SUM(SUMIF(INDIRECT({"08";"09";"10";"11";"12";"13";"14"} & "!B:G"),$B55,INDIRECT({"08";"09";"10";"11";"12";"13";"14"} & "!G:G")))} -> 0 | F55: {=SUM(SUMIF(INDIRECT({"08";"09";"10";"11";"12";"13";"14"} & "!B:I"),$B55,INDIRECT({"08";"09";"10";"11";"12";"13";"14"} & "!I:I")))} -> 0 | G55: {=SUM(SUMIF(INDIRECT({"15";"16";"17";"18";"19";"20";"21"} & "!B:G"),$B55,INDIRECT({"15";"16";"17";"18";"19";"20";"21"} & "!G:G")))} -> 0 | H55: {=SUM(SUMIF(INDIRECT({"15";"16";"17";"18";"19";"20";"21"} & "!B:I"),$B55,INDIRECT({"15";"16";"17";"18";"19";"20";"21"} & "!I:I")))} -> 0 | I55: {=SUM(SUMIF(INDIRECT({"22";"23";"24";"25";"26";"27";"28";"29";"30";"31"} & "!B:G"),$B55,INDIRECT({"22";"23";"24";"25";"26";"27";"28";"29";"30";"31"} & "!G:G")))} -> 0 | J55: {=SUM(SUMIF(INDIRECT({"22";"23";"24";"25";"26";"27";"28";"29";"30";"31"} & "!B:I"),$B55,INDIRECT({"22";"23";"24";"25";"26";"27";"28";"29";"30";"31"} & "!I:I")))} -> 0 | K55: =ROUND(SUM(C55,E55,G55,I55)/DAY(TODAY()),0) -> 0 | L55: =SUM(D55,F55,H55,J55)/DAY(TODAY()) -> 0 | M55: =K55*7 -> 0 | N55: =L55*7 -> 0 | O55: =ROUND(K55*30,0) -> 0 | P55: =L55*30 -> 0 | S55: =EXACT(B55,Total!B55) -> TRUE | T55: =SUM(D55+F55+H55+J55) -> 0 | W55: ESTACION ENERGIA ECOFLOW DELTA 3
A56: U | B56: ESTACION MUST 6000 W | C56: =SUM(SUMIF(INDIRECT({"01";"02";"03";"04";"05";"06";"07"} & "!B:G"),$B56,INDIRECT({"01";"02";"03";"04";"05";"06";"07"} & "!G:G"))) -> 0 | D56: =SUM(SUMIF(INDIRECT({"01";"02";"03";"04";"05";"06";"07"} & "!B:I"),$B56,INDIRECT({"01";"02";"03";"04";"05";"06";"07"} & "!I:I"))) -> 0 | E56: {=SUM(SUMIF(INDIRECT({"08";"09";"10";"11";"12";"13";"14"} & "!B:G"),$B56,INDIRECT({"08";"09";"10";"11";"12";"13";"14"} & "!G:G")))} -> 0 | F56: {=SUM(SUMIF(INDIRECT({"08";"09";"10";"11";"12";"13";"14"} & "!B:I"),$B56,INDIRECT({"08";"09";"10";"11";"12";"13";"14"} & "!I:I")))} -> 0 | G56: {=SUM(SUMIF(INDIRECT({"15";"16";"17";"18";"19";"20";"21"} & "!B:G"),$B56,INDIRECT({"15";"16";"17";"18";"19";"20";"21"} & "!G:G")))} -> 0 | H56: {=SUM(SUMIF(INDIRECT({"15";"16";"17";"18";"19";"20";"21"} & "!B:I"),$B56,INDIRECT({"15";"16";"17";"18";"19";"20";"21"} & "!I:I")))} -> 0 | I56: {=SUM(SUMIF(INDIRECT({"22";"23";"24";"25";"26";"27";"28";"29";"30";"31"} & "!B:G"),$B56,INDIRECT({"22";"23";"24";"25";"26";"27";"28";"29";"30";"31"} & "!G:G")))} -> 0 | J56: {=SUM(SUMIF(INDIRECT({"22";"23";"24";"25";"26";"27";"28";"29";"30";"31"} & "!B:I"),$B56,INDIRECT({"22";"23";"24";"25";"26";"27";"28";"29";"30";"31"} & "!I:I")))} -> 0 | K56: =ROUND(SUM(C56,E56,G56,I56)/DAY(TODAY()),0) -> 0 | L56: =SUM(D56,F56,H56,J56)/DAY(TODAY()) -> 0 | M56: =K56*7 -> 0 | N56: =L56*7 -> 0 | O56: =ROUND(K56*30,0) -> 0 | P56: =L56*30 -> 0 | S56: =EXACT(B56,Total!B56) -> TRUE | T56: =SUM(D56+F56+H56+J56) -> 0 | W56: ESTACION MUST 6000 W
A57: U | B57: ESTACION MUST 2K CON 2.7K | C57: =SUM(SUMIF(INDIRECT({"01";"02";"03";"04";"05";"06";"07"} & "!B:G"),$B57,INDIRECT({"01";"02";"03";"04";"05";"06";"07"} & "!G:G"))) -> 0 | D57: =SUM(SUMIF(INDIRECT({"01";"02";"03";"04";"05";"06";"07"} & "!B:I"),$B57,INDIRECT({"01";"02";"03";"04";"05";"06";"07"} & "!I:I"))) -> 0 | E57: {=SUM(SUMIF(INDIRECT({"08";"09";"10";"11";"12";"13";"14"} & "!B:G"),$B57,INDIRECT({"08";"09";"10";"11";"12";"13";"14"} & "!G:G")))} -> 1 | F57: {=SUM(SUMIF(INDIRECT({"08";"09";"10";"11";"12";"13";"14"} & "!B:I"),$B57,INDIRECT({"08";"09";"10";"11";"12";"13";"14"} & "!I:I")))} -> 1300 | G57: {=SUM(SUMIF(INDIRECT({"15";"16";"17";"18";"19";"20";"21"} & "!B:G"),$B57,INDIRECT({"15";"16";"17";"18";"19";"20";"21"} & "!G:G")))} -> 0 | H57: {=SUM(SUMIF(INDIRECT({"15";"16";"17";"18";"19";"20";"21"} & "!B:I"),$B57,INDIRECT({"15";"16";"17";"18";"19";"20";"21"} & "!I:I")))} -> 0 | I57: {=SUM(SUMIF(INDIRECT({"22";"23";"24";"25";"26";"27";"28";"29";"30";"31"} & "!B:G"),$B57,INDIRECT({"22";"23";"24";"25";"26";"27";"28";"29";"30";"31"} & "!G:G")))} -> 0 | J57: {=SUM(SUMIF(INDIRECT({"22";"23";"24";"25";"26";"27";"28";"29";"30";"31"} & "!B:I"),$B57,INDIRECT({"22";"23";"24";"25";"26";"27";"28";"29";"30";"31"} & "!I:I")))} -> 0 | K57: =ROUND(SUM(C57,E57,G57,I57)/DAY(TODAY()),0) -> 1 | L57: =SUM(D57,F57,H57,J57)/DAY(TODAY()) -> 1300 | M57: =K57*7 -> 7 | N57: =L57*7 -> 9100 | O57: =ROUND(K57*30,0) -> 30 | P57: =L57*30 -> 39000 | S57: =EXACT(B57,Total!B57) -> TRUE | T57: =SUM(D57+F57+H57+J57) -> 1300 | W57: ESTACION MUST 2K CON 2.7K
B58: ESCRITORIO | C58: =SUM(SUMIF(INDIRECT({"01";"02";"03";"04";"05";"06";"07"} & "!B:G"),$B58,INDIRECT({"01";"02";"03";"04";"05";"06";"07"} & "!G:G"))) -> 0 | D58: =SUM(SUMIF(INDIRECT({"01";"02";"03";"04";"05";"06";"07"} & "!B:I"),$B58,INDIRECT({"01";"02";"03";"04";"05";"06";"07"} & "!I:I"))) -> 0 | E58: {=SUM(SUMIF(INDIRECT({"08";"09";"10";"11";"12";"13";"14"} & "!B:G"),$B58,INDIRECT({"08";"09";"10";"11";"12";"13";"14"} & "!G:G")))} -> 0 | F58: {=SUM(SUMIF(INDIRECT({"08";"09";"10";"11";"12";"13";"14"} & "!B:I"),$B58,INDIRECT({"08";"09";"10";"11";"12";"13";"14"} & "!I:I")))} -> 0 | G58: {=SUM(SUMIF(INDIRECT({"15";"16";"17";"18";"19";"20";"21"} & "!B:G"),$B58,INDIRECT({"15";"16";"17";"18";"19";"20";"21"} & "!G:G")))} -> 0 | H58: {=SUM(SUMIF(INDIRECT({"15";"16";"17";"18";"19";"20";"21"} & "!B:I"),$B58,INDIRECT({"15";"16";"17";"18";"19";"20";"21"} & "!I:I")))} -> 0 | I58: {=SUM(SUMIF(INDIRECT({"22";"23";"24";"25";"26";"27";"28";"29";"30";"31"} & "!B:G"),$B58,INDIRECT({"22";"23";"24";"25";"26";"27";"28";"29";"30";"31"} & "!G:G")))} -> 0 | J58: {=SUM(SUMIF(INDIRECT({"22";"23";"24";"25";"26";"27";"28";"29";"30";"31"} & "!B:I"),$B58,INDIRECT({"22";"23";"24";"25";"26";"27";"28";"29";"30";"31"} & "!I:I")))} -> 0 | K58: =ROUND(SUM(C58,E58,G58,I58)/DAY(TODAY()),0) -> 0 | L58: =SUM(D58,F58,H58,J58)/DAY(TODAY()) -> 0 | M58: =K58*7 -> 0 | N58: =L58*7 -> 0 | O58: =ROUND(K58*30,0) -> 0 | P58: =L58*30 -> 0 | S58: =EXACT(B58,Total!B58) -> TRUE | T58: =SUM(D58+F58+H58+J58) -> 0 | W58: ESCRITORIO
A59: U | B59: ESTACION ECOFLOW DELTA 2 1800W | C59: =SUM(SUMIF(INDIRECT({"01";"02";"03";"04";"05";"06";"07"} & "!B:G"),$B59,INDIRECT({"01";"02";"03";"04";"05";"06";"07"} & "!G:G"))) -> 0 | D59: =SUM(SUMIF(INDIRECT({"01";"02";"03";"04";"05";"06";"07"} & "!B:I"),$B59,INDIRECT({"01";"02";"03";"04";"05";"06";"07"} & "!I:I"))) -> 0 | E59: {=SUM(SUMIF(INDIRECT({"08";"09";"10";"11";"12";"13";"14"} & "!B:G"),$B59,INDIRECT({"08";"09";"10";"11";"12";"13";"14"} & "!G:G")))} -> 0 | F59: {=SUM(SUMIF(INDIRECT({"08";"09";"10";"11";"12";"13";"14"} & "!B:I"),$B59,INDIRECT({"08";"09";"10";"11";"12";"13";"14"} & "!I:I")))} -> 0 | G59: {=SUM(SUMIF(INDIRECT({"15";"16";"17";"18";"19";"20";"21"} & "!B:G"),$B59,INDIRECT({"15";"16";"17";"18";"19";"20";"21"} & "!G:G")))} -> 0 | H59: {=SUM(SUMIF(INDIRECT({"15";"16";"17";"18";"19";"20";"21"} & "!B:I"),$B59,INDIRECT({"15";"16";"17";"18";"19";"20";"21"} & "!I:I")))} -> 0 | I59: {=SUM(SUMIF(INDIRECT({"22";"23";"24";"25";"26";"27";"28";"29";"30";"31"} & "!B:G"),$B59,INDIRECT({"22";"23";"24";"25";"26";"27";"28";"29";"30";"31"} & "!G:G")))} -> 0 | J59: {=SUM(SUMIF(INDIRECT({"22";"23";"24";"25";"26";"27";"28";"29";"30";"31"} & "!B:I"),$B59,INDIRECT({"22";"23";"24";"25";"26";"27";"28";"29";"30";"31"} & "!I:I")))} -> 0 | K59: =ROUND(SUM(C59,E59,G59,I59)/DAY(TODAY()),0) -> 0 | L59: =SUM(D59,F59,H59,J59)/DAY(TODAY()) -> 0 | M59: =K59*7 -> 0 | N59: =L59*7 -> 0 | O59: =ROUND(K59*30,0) -> 0 | P59: =L59*30 -> 0 | S59: =EXACT(B59,Total!B59) -> TRUE | T59: =SUM(D59+F59+H59+J59) -> 0 | W59: ESTACION ECOFLOW DELTA 2 1800W
B60: KIT DE INSTALACION | C60: =SUM(SUMIF(INDIRECT({"01";"02";"03";"04";"05";"06";"07"} & "!B:G"),$B60,INDIRECT({"01";"02";"03";"04";"05";"06";"07"} & "!G:G"))) -> 0 | D60: =SUM(SUMIF(INDIRECT({"01";"02";"03";"04";"05";"06";"07"} & "!B:I"),$B60,INDIRECT({"01";"02";"03";"04";"05";"06";"07"} & "!I:I"))) -> 0 | E60: {=SUM(SUMIF(INDIRECT({"08";"09";"10";"11";"12";"13";"14"} & "!B:G"),$B60,INDIRECT({"08";"09";"10";"11";"12";"13";"14"} & "!G:G")))} -> 0 | F60: {=SUM(SUMIF(INDIRECT({"08";"09";"10";"11";"12";"13";"14"} & "!B:I"),$B60,INDIRECT({"08";"09";"10";"11";"12";"13";"14"} & "!I:I")))} -> 0 | G60: {=SUM(SUMIF(INDIRECT({"15";"16";"17";"18";"19";"20";"21"} & "!B:G"),$B60,INDIRECT({"15";"16";"17";"18";"19";"20";"21"} & "!G:G")))} -> 0 | H60: {=SUM(SUMIF(INDIRECT({"15";"16";"17";"18";"19";"20";"21"} & "!B:I"),$B60,INDIRECT({"15";"16";"17";"18";"19";"20";"21"} & "!I:I")))} -> 0 | I60: {=SUM(SUMIF(INDIRECT({"22";"23";"24";"25";"26";"27";"28";"29";"30";"31"} & "!B:G"),$B60,INDIRECT({"22";"23";"24";"25";"26";"27";"28";"29";"30";"31"} & "!G:G")))} -> 0 | J60: {=SUM(SUMIF(INDIRECT({"22";"23";"24";"25";"26";"27";"28";"29";"30";"31"} & "!B:I"),$B60,INDIRECT({"22";"23";"24";"25";"26";"27";"28";"29";"30";"31"} & "!I:I")))} -> 0 | K60: =ROUND(SUM(C60,E60,G60,I60)/DAY(TODAY()),0) -> 0 | L60: =SUM(D60,F60,H60,J60)/DAY(TODAY()) -> 0 | M60: =K60*7 -> 0 | N60: =L60*7 -> 0 | O60: =ROUND(K60*30,0) -> 0 | P60: =L60*30 -> 0 | S60: =EXACT(B60,Total!B60) -> TRUE | T60: =SUM(D60+F60+H60+J60) -> 0 | W60: KIT DE INSTALACION
B61: EXHIBIDOR HORIZONTAL 13P | C61: =SUM(SUMIF(INDIRECT({"01";"02";"03";"04";"05";"06";"07"} & "!B:G"),$B61,INDIRECT({"01";"02";"03";"04";"05";"06";"07"} & "!G:G"))) -> 0 | D61: =SUM(SUMIF(INDIRECT({"01";"02";"03";"04";"05";"06";"07"} & "!B:I"),$B61,INDIRECT({"01";"02";"03";"04";"05";"06";"07"} & "!I:I"))) -> 0 | E61: {=SUM(SUMIF(INDIRECT({"08";"09";"10";"11";"12";"13";"14"} & "!B:G"),$B61,INDIRECT({"08";"09";"10";"11";"12";"13";"14"} & "!G:G")))} -> 0 | F61: {=SUM(SUMIF(INDIRECT({"08";"09";"10";"11";"12";"13";"14"} & "!B:I"),$B61,INDIRECT({"08";"09";"10";"11";"12";"13";"14"} & "!I:I")))} -> 0 | G61: {=SUM(SUMIF(INDIRECT({"15";"16";"17";"18";"19";"20";"21"} & "!B:G"),$B61,INDIRECT({"15";"16";"17";"18";"19";"20";"21"} & "!G:G")))} -> 0 | H61: {=SUM(SUMIF(INDIRECT({"15";"16";"17";"18";"19";"20";"21"} & "!B:I"),$B61,INDIRECT({"15";"16";"17";"18";"19";"20";"21"} & "!I:I")))} -> 0 | I61: {=SUM(SUMIF(INDIRECT({"22";"23";"24";"25";"26";"27";"28";"29";"30";"31"} & "!B:G"),$B61,INDIRECT({"22";"23";"24";"25";"26";"27";"28";"29";"30";"31"} & "!G:G")))} -> 0 | J61: {=SUM(SUMIF(INDIRECT({"22";"23";"24";"25";"26";"27";"28";"29";"30";"31"} & "!B:I"),$B61,INDIRECT({"22";"23";"24";"25";"26";"27";"28";"29";"30";"31"} & "!I:I")))} -> 0 | K61: =ROUND(SUM(C61,E61,G61,I61)/DAY(TODAY()),0) -> 0 | L61: =SUM(D61,F61,H61,J61)/DAY(TODAY()) -> 0 | M61: =K61*7 -> 0 | N61: =L61*7 -> 0 | O61: =ROUND(K61*30,0) -> 0 | P61: =L61*30 -> 0 | S61: =EXACT(B61,Total!B61) -> TRUE | T61: =SUM(D61+F61+H61+J61) -> 0 | W61: EXHIBIDOR HORIZONTAL 13P
B62: EXHIBIDOR VERTICAL SANKEY 8P | C62: =SUM(SUMIF(INDIRECT({"01";"02";"03";"04";"05";"06";"07"} & "!B:G"),$B62,INDIRECT({"01";"02";"03";"04";"05";"06";"07"} & "!G:G"))) -> 0 | D62: =SUM(SUMIF(INDIRECT({"01";"02";"03";"04";"05";"06";"07"} & "!B:I"),$B62,INDIRECT({"01";"02";"03";"04";"05";"06";"07"} & "!I:I"))) -> 0 | E62: {=SUM(SUMIF(INDIRECT({"08";"09";"10";"11";"12";"13";"14"} & "!B:G"),$B62,INDIRECT({"08";"09";"10";"11";"12";"13";"14"} & "!G:G")))} -> 0 | F62: {=SUM(SUMIF(INDIRECT({"08";"09";"10";"11";"12";"13";"14"} & "!B:I"),$B62,INDIRECT({"08";"09";"10";"11";"12";"13";"14"} & "!I:I")))} -> 0 | G62: {=SUM(SUMIF(INDIRECT({"15";"16";"17";"18";"19";"20";"21"} & "!B:G"),$B62,INDIRECT({"15";"16";"17";"18";"19";"20";"21"} & "!G:G")))} -> 0 | H62: {=SUM(SUMIF(INDIRECT({"15";"16";"17";"18";"19";"20";"21"} & "!B:I"),$B62,INDIRECT({"15";"16";"17";"18";"19";"20";"21"} & "!I:I")))} -> 0 | I62: {=SUM(SUMIF(INDIRECT({"22";"23";"24";"25";"26";"27";"28";"29";"30";"31"} & "!B:G"),$B62,INDIRECT({"22";"23";"24";"25";"26";"27";"28";"29";"30";"31"} & "!G:G")))} -> 0 | J62: {=SUM(SUMIF(INDIRECT({"22";"23";"24";"25";"26";"27";"28";"29";"30";"31"} & "!B:I"),$B62,INDIRECT({"22";"23";"24";"25";"26";"27";"28";"29";"30";"31"} & "!I:I")))} -> 0 | K62: =ROUND(SUM(C62,E62,G62,I62)/DAY(TODAY()),0) -> 0 | L62: =SUM(D62,F62,H62,J62)/DAY(TODAY()) -> 0 | M62: =K62*7 -> 0 | N62: =L62*7 -> 0 | O62: =ROUND(K62*30,0) -> 0 | P62: =L62*30 -> 0 | S62: =EXACT(B62,Total!B62) -> TRUE | T62: =SUM(D62+F62+H62+J62) -> 0 | W62: EXHIBIDOR VERTICAL SANKEY 8P
B63: EXHIBIDOR MILEXUS 390 L 14PIES | C63: =SUM(SUMIF(INDIRECT({"01";"02";"03";"04";"05";"06";"07"} & "!B:G"),$B63,INDIRECT({"01";"02";"03";"04";"05";"06";"07"} & "!G:G"))) -> 0 | D63: =SUM(SUMIF(INDIRECT({"01";"02";"03";"04";"05";"06";"07"} & "!B:I"),$B63,INDIRECT({"01";"02";"03";"04";"05";"06";"07"} & "!I:I"))) -> 0 | E63: {=SUM(SUMIF(INDIRECT({"08";"09";"10";"11";"12";"13";"14"} & "!B:G"),$B63,INDIRECT({"08";"09";"10";"11";"12";"13";"14"} & "!G:G")))} -> 0 | F63: {=SUM(SUMIF(INDIRECT({"08";"09";"10";"11";"12";"13";"14"} & "!B:I"),$B63,INDIRECT({"08";"09";"10";"11";"12";"13";"14"} & "!I:I")))} -> 0 | G63: {=SUM(SUMIF(INDIRECT({"15";"16";"17";"18";"19";"20";"21"} & "!B:G"),$B63,INDIRECT({"15";"16";"17";"18";"19";"20";"21"} & "!G:G")))} -> 0 | H63: {=SUM(SUMIF(INDIRECT({"15";"16";"17";"18";"19";"20";"21"} & "!B:I"),$B63,INDIRECT({"15";"16";"17";"18";"19";"20";"21"} & "!I:I")))} -> 0 | I63: {=SUM(SUMIF(INDIRECT({"22";"23";"24";"25";"26";"27";"28";"29";"30";"31"} & "!B:G"),$B63,INDIRECT({"22";"23";"24";"25";"26";"27";"28";"29";"30";"31"} & "!G:G")))} -> 0 | J63: {=SUM(SUMIF(INDIRECT({"22";"23";"24";"25";"26";"27";"28";"29";"30";"31"} & "!B:I"),$B63,INDIRECT({"22";"23";"24";"25";"26";"27";"28";"29";"30";"31"} & "!I:I")))} -> 0 | K63: =ROUND(SUM(C63,E63,G63,I63)/DAY(TODAY()),0) -> 0 | L63: =SUM(D63,F63,H63,J63)/DAY(TODAY()) -> 0 | M63: =K63*7 -> 0 | N63: =L63*7 -> 0 | O63: =ROUND(K63*30,0) -> 0 | P63: =L63*30 -> 0 | S63: =EXACT(B63,Total!B63) -> TRUE | T63: =SUM(D63+F63+H63+J63) -> 0 | W63: EXHIBIDOR MILEXUS 390 L 14PIES
B64: EXHIBIDOR DOBLE MILEXUS 560 LITROS | C64: =SUM(SUMIF(INDIRECT({"01";"02";"03";"04";"05";"06";"07"} & "!B:G"),$B64,INDIRECT({"01";"02";"03";"04";"05";"06";"07"} & "!G:G"))) -> 0 | D64: =SUM(SUMIF(INDIRECT({"01";"02";"03";"04";"05";"06";"07"} & "!B:I"),$B64,INDIRECT({"01";"02";"03";"04";"05";"06";"07"} & "!I:I"))) -> 0 | E64: {=SUM(SUMIF(INDIRECT({"08";"09";"10";"11";"12";"13";"14"} & "!B:G"),$B64,INDIRECT({"08";"09";"10";"11";"12";"13";"14"} & "!G:G")))} -> 0 | F64: {=SUM(SUMIF(INDIRECT({"08";"09";"10";"11";"12";"13";"14"} & "!B:I"),$B64,INDIRECT({"08";"09";"10";"11";"12";"13";"14"} & "!I:I")))} -> 0 | G64: {=SUM(SUMIF(INDIRECT({"15";"16";"17";"18";"19";"20";"21"} & "!B:G"),$B64,INDIRECT({"15";"16";"17";"18";"19";"20";"21"} & "!G:G")))} -> 0 | H64: {=SUM(SUMIF(INDIRECT({"15";"16";"17";"18";"19";"20";"21"} & "!B:I"),$B64,INDIRECT({"15";"16";"17";"18";"19";"20";"21"} & "!I:I")))} -> 0 | I64: {=SUM(SUMIF(INDIRECT({"22";"23";"24";"25";"26";"27";"28";"29";"30";"31"} & "!B:G"),$B64,INDIRECT({"22";"23";"24";"25";"26";"27";"28";"29";"30";"31"} & "!G:G")))} -> 0 | J64: {=SUM(SUMIF(INDIRECT({"22";"23";"24";"25";"26";"27";"28";"29";"30";"31"} & "!B:I"),$B64,INDIRECT({"22";"23";"24";"25";"26";"27";"28";"29";"30";"31"} & "!I:I")))} -> 0 | K64: =ROUND(SUM(C64,E64,G64,I64)/DAY(TODAY()),0) -> 0 | L64: =SUM(D64,F64,H64,J64)/DAY(TODAY()) -> 0 | M64: =K64*7 -> 0 | N64: =L64*7 -> 0 | O64: =ROUND(K64*30,0) -> 0 | P64: =L64*30 -> 0 | S64: =EXACT(B64,Total!B64) -> TRUE | T64: =SUM(D64+F64+H64+J64) -> 0 | W64: EXHIBIDOR DOBLE MILEXUS 560 LITROS
A65: U | B65: ENFRIADOR DE AIRE ALL NOVU | C65: =SUM(SUMIF(INDIRECT({"01";"02";"03";"04";"05";"06";"07"} & "!B:G"),$B65,INDIRECT({"01";"02";"03";"04";"05";"06";"07"} & "!G:G"))) -> 0 | D65: =SUM(SUMIF(INDIRECT({"01";"02";"03";"04";"05";"06";"07"} & "!B:I"),$B65,INDIRECT({"01";"02";"03";"04";"05";"06";"07"} & "!I:I"))) -> 0 | E65: {=SUM(SUMIF(INDIRECT({"08";"09";"10";"11";"12";"13";"14"} & "!B:G"),$B65,INDIRECT({"08";"09";"10";"11";"12";"13";"14"} & "!G:G")))} -> 0 | F65: {=SUM(SUMIF(INDIRECT({"08";"09";"10";"11";"12";"13";"14"} & "!B:I"),$B65,INDIRECT({"08";"09";"10";"11";"12";"13";"14"} & "!I:I")))} -> 0 | G65: {=SUM(SUMIF(INDIRECT({"15";"16";"17";"18";"19";"20";"21"} & "!B:G"),$B65,INDIRECT({"15";"16";"17";"18";"19";"20";"21"} & "!G:G")))} -> 0 | H65: {=SUM(SUMIF(INDIRECT({"15";"16";"17";"18";"19";"20";"21"} & "!B:I"),$B65,INDIRECT({"15";"16";"17";"18";"19";"20";"21"} & "!I:I")))} -> 0 | I65: {=SUM(SUMIF(INDIRECT({"22";"23";"24";"25";"26";"27";"28";"29";"30";"31"} & "!B:G"),$B65,INDIRECT({"22";"23";"24";"25";"26";"27";"28";"29";"30";"31"} & "!G:G")))} -> 0 | J65: {=SUM(SUMIF(INDIRECT({"22";"23";"24";"25";"26";"27";"28";"29";"30";"31"} & "!B:I"),$B65,INDIRECT({"22";"23";"24";"25";"26";"27";"28";"29";"30";"31"} & "!I:I")))} -> 0 | K65: =ROUND(SUM(C65,E65,G65,I65)/DAY(TODAY()),0) -> 0 | L65: =SUM(D65,F65,H65,J65)/DAY(TODAY()) -> 0 | M65: =K65*7 -> 0 | N65: =L65*7 -> 0 | O65: =ROUND(K65*30,0) -> 0 | P65: =L65*30 -> 0 | S65: =EXACT(B65,Total!B65) -> TRUE | T65: =SUM(D65+F65+H65+J65) -> 0 | W65: ENFRIADOR DE AIRE ALL NOVU
A66: U | B66: ENFRIADOR DE AIRE ALL NOVU DOBLE | C66: =SUM(SUMIF(INDIRECT({"01";"02";"03";"04";"05";"06";"07"} & "!B:G"),$B66,INDIRECT({"01";"02";"03";"04";"05";"06";"07"} & "!G:G"))) -> 0 | D66: =SUM(SUMIF(INDIRECT({"01";"02";"03";"04";"05";"06";"07"} & "!B:I"),$B66,INDIRECT({"01";"02";"03";"04";"05";"06";"07"} & "!I:I"))) -> 0 | E66: {=SUM(SUMIF(INDIRECT({"08";"09";"10";"11";"12";"13";"14"} & "!B:G"),$B66,INDIRECT({"08";"09";"10";"11";"12";"13";"14"} & "!G:G")))} -> 0 | F66: {=SUM(SUMIF(INDIRECT({"08";"09";"10";"11";"12";"13";"14"} & "!B:I"),$B66,INDIRECT({"08";"09";"10";"11";"12";"13";"14"} & "!I:I")))} -> 0 | G66: {=SUM(SUMIF(INDIRECT({"15";"16";"17";"18";"19";"20";"21"} & "!B:G"),$B66,INDIRECT({"15";"16";"17";"18";"19";"20";"21"} & "!G:G")))} -> 0 | H66: {=SUM(SUMIF(INDIRECT({"15";"16";"17";"18";"19";"20";"21"} & "!B:I"),$B66,INDIRECT({"15";"16";"17";"18";"19";"20";"21"} & "!I:I")))} -> 0 | I66: {=SUM(SUMIF(INDIRECT({"22";"23";"24";"25";"26";"27";"28";"29";"30";"31"} & "!B:G"),$B66,INDIRECT({"22";"23";"24";"25";"26";"27";"28";"29";"30";"31"} & "!G:G")))} -> 0 | J66: {=SUM(SUMIF(INDIRECT({"22";"23";"24";"25";"26";"27";"28";"29";"30";"31"} & "!B:I"),$B66,INDIRECT({"22";"23";"24";"25";"26";"27";"28";"29";"30";"31"} & "!I:I")))} -> 0 | K66: =ROUND(SUM(C66,E66,G66,I66)/DAY(TODAY()),0) -> 0 | L66: =SUM(D66,F66,H66,J66)/DAY(TODAY()) -> 0 | M66: =K66*7 -> 0 | N66: =L66*7 -> 0 | O66: =ROUND(K66*30,0) -> 0 | P66: =L66*30 -> 0 | S66: =EXACT(B66,Total!B66) -> TRUE | T66: =SUM(D66+F66+H66+J66) -> 0 | W66: ENFRIADOR DE AIRE ALL NOVU DOBLE
A67: U | B67: EQUIPO DE MUSICA LG | C67: =SUM(SUMIF(INDIRECT({"01";"02";"03";"04";"05";"06";"07"} & "!B:G"),$B67,INDIRECT({"01";"02";"03";"04";"05";"06";"07"} & "!G:G"))) -> 0 | D67: =SUM(SUMIF(INDIRECT({"01";"02";"03";"04";"05";"06";"07"} & "!B:I"),$B67,INDIRECT({"01";"02";"03";"04";"05";"06";"07"} & "!I:I"))) -> 0 | E67: {=SUM(SUMIF(INDIRECT({"08";"09";"10";"11";"12";"13";"14"} & "!B:G"),$B67,INDIRECT({"08";"09";"10";"11";"12";"13";"14"} & "!G:G")))} -> 0 | F67: {=SUM(SUMIF(INDIRECT({"08";"09";"10";"11";"12";"13";"14"} & "!B:I"),$B67,INDIRECT({"08";"09";"10";"11";"12";"13";"14"} & "!I:I")))} -> 0 | G67: {=SUM(SUMIF(INDIRECT({"15";"16";"17";"18";"19";"20";"21"} & "!B:G"),$B67,INDIRECT({"15";"16";"17";"18";"19";"20";"21"} & "!G:G")))} -> 0 | H67: {=SUM(SUMIF(INDIRECT({"15";"16";"17";"18";"19";"20";"21"} & "!B:I"),$B67,INDIRECT({"15";"16";"17";"18";"19";"20";"21"} & "!I:I")))} -> 0 | I67: {=SUM(SUMIF(INDIRECT({"22";"23";"24";"25";"26";"27";"28";"29";"30";"31"} & "!B:G"),$B67,INDIRECT({"22";"23";"24";"25";"26";"27";"28";"29";"30";"31"} & "!G:G")))} -> 0 | J67: {=SUM(SUMIF(INDIRECT({"22";"23";"24";"25";"26";"27";"28";"29";"30";"31"} & "!B:I"),$B67,INDIRECT({"22";"23";"24";"25";"26";"27";"28";"29";"30";"31"} & "!I:I")))} -> 0 | K67: =ROUND(SUM(C67,E67,G67,I67)/DAY(TODAY()),0) -> 0 | L67: =SUM(D67,F67,H67,J67)/DAY(TODAY()) -> 0 | M67: =K67*7 -> 0 | N67: =L67*7 -> 0 | O67: =ROUND(K67*30,0) -> 0 | P67: =L67*30 -> 0 | S67: =EXACT(B67,Total!B67) -> TRUE | T67: =SUM(D67+F67+H67+J67) -> 0 | W67: EQUIPO DE MUSICA LG
A68: U | B68: EQUIPO DE MUSICA LG GRANDE | C68: =SUM(SUMIF(INDIRECT({"01";"02";"03";"04";"05";"06";"07"} & "!B:G"),$B68,INDIRECT({"01";"02";"03";"04";"05";"06";"07"} & "!G:G"))) -> 0 | D68: =SUM(SUMIF(INDIRECT({"01";"02";"03";"04";"05";"06";"07"} & "!B:I"),$B68,INDIRECT({"01";"02";"03";"04";"05";"06";"07"} & "!I:I"))) -> 0 | E68: {=SUM(SUMIF(INDIRECT({"08";"09";"10";"11";"12";"13";"14"} & "!B:G"),$B68,INDIRECT({"08";"09";"10";"11";"12";"13";"14"} & "!G:G")))} -> 0 | F68: {=SUM(SUMIF(INDIRECT({"08";"09";"10";"11";"12";"13";"14"} & "!B:I"),$B68,INDIRECT({"08";"09";"10";"11";"12";"13";"14"} & "!I:I")))} -> 0 | G68: {=SUM(SUMIF(INDIRECT({"15";"16";"17";"18";"19";"20";"21"} & "!B:G"),$B68,INDIRECT({"15";"16";"17";"18";"19";"20";"21"} & "!G:G")))} -> 0 | H68: {=SUM(SUMIF(INDIRECT({"15";"16";"17";"18";"19";"20";"21"} & "!B:I"),$B68,INDIRECT({"15";"16";"17";"18";"19";"20";"21"} & "!I:I")))} -> 0 | I68: {=SUM(SUMIF(INDIRECT({"22";"23";"24";"25";"26";"27";"28";"29";"30";"31"} & "!B:G"),$B68,INDIRECT({"22";"23";"24";"25";"26";"27";"28";"29";"30";"31"} & "!G:G")))} -> 0 | J68: {=SUM(SUMIF(INDIRECT({"22";"23";"24";"25";"26";"27";"28";"29";"30";"31"} & "!B:I"),$B68,INDIRECT({"22";"23";"24";"25";"26";"27";"28";"29";"30";"31"} & "!I:I")))} -> 0 | K68: =ROUND(SUM(C68,E68,G68,I68)/DAY(TODAY()),0) -> 0 | L68: =SUM(D68,F68,H68,J68)/DAY(TODAY()) -> 0 | M68: =K68*7 -> 0 | N68: =L68*7 -> 0 | O68: =ROUND(K68*30,0) -> 0 | P68: =L68*30 -> 0 | S68: =EXACT(B68,Total!B68) -> TRUE | T68: =SUM(D68+F68+H68+J68) -> 0 | W68: EQUIPO DE MUSICA LG GRANDE
A69: U | B69: ESCALERA DE 6 ESCALONES | C69: =SUM(SUMIF(INDIRECT({"01";"02";"03";"04";"05";"06";"07"} & "!B:G"),$B69,INDIRECT({"01";"02";"03";"04";"05";"06";"07"} & "!G:G"))) -> 0 | D69: =SUM(SUMIF(INDIRECT({"01";"02";"03";"04";"05";"06";"07"} & "!B:I"),$B69,INDIRECT({"01";"02";"03";"04";"05";"06";"07"} & "!I:I"))) -> 0 | E69: {=SUM(SUMIF(INDIRECT({"08";"09";"10";"11";"12";"13";"14"} & "!B:G"),$B69,INDIRECT({"08";"09";"10";"11";"12";"13";"14"} & "!G:G")))} -> 0 | F69: {=SUM(SUMIF(INDIRECT({"08";"09";"10";"11";"12";"13";"14"} & "!B:I"),$B69,INDIRECT({"08";"09";"10";"11";"12";"13";"14"} & "!I:I")))} -> 0 | G69: {=SUM(SUMIF(INDIRECT({"15";"16";"17";"18";"19";"20";"21"} & "!B:G"),$B69,INDIRECT({"15";"16";"17";"18";"19";"20";"21"} & "!G:G")))} -> 0 | H69: {=SUM(SUMIF(INDIRECT({"15";"16";"17";"18";"19";"20";"21"} & "!B:I"),$B69,INDIRECT({"15";"16";"17";"18";"19";"20";"21"} & "!I:I")))} -> 0 | I69: {=SUM(SUMIF(INDIRECT({"22";"23";"24";"25";"26";"27";"28";"29";"30";"31"} & "!B:G"),$B69,INDIRECT({"22";"23";"24";"25";"26";"27";"28";"29";"30";"31"} & "!G:G")))} -> 0 | J69: {=SUM(SUMIF(INDIRECT({"22";"23";"24";"25";"26";"27";"28";"29";"30";"31"} & "!B:I"),$B69,INDIRECT({"22";"23";"24";"25";"26";"27";"28";"29";"30";"31"} & "!I:I")))} -> 0 | K69: =ROUND(SUM(C69,E69,G69,I69)/DAY(TODAY()),0) -> 0 | L69: =SUM(D69,F69,H69,J69)/DAY(TODAY()) -> 0 | M69: =K69*7 -> 0 | N69: =L69*7 -> 0 | O69: =ROUND(K69*30,0) -> 0 | P69: =L69*30 -> 0 | S69: =EXACT(B69,Total!B69) -> TRUE | T69: =SUM(D69+F69+H69+J69) -> 0 | W69: ESCALERA DE 6 ESCALONES
B70: ESCALERA DE 4 ESCALONES | C70: =SUM(SUMIF(INDIRECT({"01";"02";"03";"04";"05";"06";"07"} & "!B:G"),$B70,INDIRECT({"01";"02";"03";"04";"05";"06";"07"} & "!G:G"))) -> 0 | D70: =SUM(SUMIF(INDIRECT({"01";"02";"03";"04";"05";"06";"07"} & "!B:I"),$B70,INDIRECT({"01";"02";"03";"04";"05";"06";"07"} & "!I:I"))) -> 0 | E70: {=SUM(SUMIF(INDIRECT({"08";"09";"10";"11";"12";"13";"14"} & "!B:G"),$B70,INDIRECT({"08";"09";"10";"11";"12";"13";"14"} & "!G:G")))} -> 0 | F70: {=SUM(SUMIF(INDIRECT({"08";"09";"10";"11";"12";"13";"14"} & "!B:I"),$B70,INDIRECT({"08";"09";"10";"11";"12";"13";"14"} & "!I:I")))} -> 0 | G70: {=SUM(SUMIF(INDIRECT({"15";"16";"17";"18";"19";"20";"21"} & "!B:G"),$B70,INDIRECT({"15";"16";"17";"18";"19";"20";"21"} & "!G:G")))} -> 0 | H70: {=SUM(SUMIF(INDIRECT({"15";"16";"17";"18";"19";"20";"21"} & "!B:I"),$B70,INDIRECT({"15";"16";"17";"18";"19";"20";"21"} & "!I:I")))} -> 0 | I70: {=SUM(SUMIF(INDIRECT({"22";"23";"24";"25";"26";"27";"28";"29";"30";"31"} & "!B:G"),$B70,INDIRECT({"22";"23";"24";"25";"26";"27";"28";"29";"30";"31"} & "!G:G")))} -> 0 | J70: {=SUM(SUMIF(INDIRECT({"22";"23";"24";"25";"26";"27";"28";"29";"30";"31"} & "!B:I"),$B70,INDIRECT({"22";"23";"24";"25";"26";"27";"28";"29";"30";"31"} & "!I:I")))} -> 0 | K70: =ROUND(SUM(C70,E70,G70,I70)/DAY(TODAY()),0) -> 0 | L70: =SUM(D70,F70,H70,J70)/DAY(TODAY()) -> 0 | M70: =K70*7 -> 0 | N70: =L70*7 -> 0 | O70: =ROUND(K70*30,0) -> 0 | P70: =L70*30 -> 0 | S70: =EXACT(B70,Total!B70) -> TRUE | T70: =SUM(D70+F70+H70+J70) -> 0 | W70: ESCALERA DE 4 ESCALONES
A71: U | B71: ESTANTES | C71: =SUM(SUMIF(INDIRECT({"01";"02";"03";"04";"05";"06";"07"} & "!B:G"),$B71,INDIRECT({"01";"02";"03";"04";"05";"06";"07"} & "!G:G"))) -> 0 | D71: =SUM(SUMIF(INDIRECT({"01";"02";"03";"04";"05";"06";"07"} & "!B:I"),$B71,INDIRECT({"01";"02";"03";"04";"05";"06";"07"} & "!I:I"))) -> 0 | E71: {=SUM(SUMIF(INDIRECT({"08";"09";"10";"11";"12";"13";"14"} & "!B:G"),$B71,INDIRECT({"08";"09";"10";"11";"12";"13";"14"} & "!G:G")))} -> 0 | F71: {=SUM(SUMIF(INDIRECT({"08";"09";"10";"11";"12";"13";"14"} & "!B:I"),$B71,INDIRECT({"08";"09";"10";"11";"12";"13";"14"} & "!I:I")))} -> 0 | G71: {=SUM(SUMIF(INDIRECT({"15";"16";"17";"18";"19";"20";"21"} & "!B:G"),$B71,INDIRECT({"15";"16";"17";"18";"19";"20";"21"} & "!G:G")))} -> 0 | H71: {=SUM(SUMIF(INDIRECT({"15";"16";"17";"18";"19";"20";"21"} & "!B:I"),$B71,INDIRECT({"15";"16";"17";"18";"19";"20";"21"} & "!I:I")))} -> 0 | I71: {=SUM(SUMIF(INDIRECT({"22";"23";"24";"25";"26";"27";"28";"29";"30";"31"} & "!B:G"),$B71,INDIRECT({"22";"23";"24";"25";"26";"27";"28";"29";"30";"31"} & "!G:G")))} -> 3 | J71: {=SUM(SUMIF(INDIRECT({"22";"23";"24";"25";"26";"27";"28";"29";"30";"31"} & "!B:I"),$B71,INDIRECT({"22";"23";"24";"25";"26";"27";"28";"29";"30";"31"} & "!I:I")))} -> 375 | K71: =ROUND(SUM(C71,E71,G71,I71)/DAY(TODAY()),0) -> 3 | L71: =SUM(D71,F71,H71,J71)/DAY(TODAY()) -> 375 | M71: =K71*7 -> 21 | N71: =L71*7 -> 2625 | O71: =ROUND(K71*30,0) -> 90 | P71: =L71*30 -> 11250 | S71: =EXACT(B71,Total!B71) -> TRUE | T71: =SUM(D71+F71+H71+J71) -> 375 | W71: ESTANTES
A72: U | B72: FOGON DE PETROLEO | C72: =SUM(SUMIF(INDIRECT({"01";"02";"03";"04";"05";"06";"07"} & "!B:G"),$B72,INDIRECT({"01";"02";"03";"04";"05";"06";"07"} & "!G:G"))) -> 0 | D72: =SUM(SUMIF(INDIRECT({"01";"02";"03";"04";"05";"06";"07"} & "!B:I"),$B72,INDIRECT({"01";"02";"03";"04";"05";"06";"07"} & "!I:I"))) -> 0 | E72: {=SUM(SUMIF(INDIRECT({"08";"09";"10";"11";"12";"13";"14"} & "!B:G"),$B72,INDIRECT({"08";"09";"10";"11";"12";"13";"14"} & "!G:G")))} -> 0 | F72: {=SUM(SUMIF(INDIRECT({"08";"09";"10";"11";"12";"13";"14"} & "!B:I"),$B72,INDIRECT({"08";"09";"10";"11";"12";"13";"14"} & "!I:I")))} -> 0 | G72: {=SUM(SUMIF(INDIRECT({"15";"16";"17";"18";"19";"20";"21"} & "!B:G"),$B72,INDIRECT({"15";"16";"17";"18";"19";"20";"21"} & "!G:G")))} -> 0 | H72: {=SUM(SUMIF(INDIRECT({"15";"16";"17";"18";"19";"20";"21"} & "!B:I"),$B72,INDIRECT({"15";"16";"17";"18";"19";"20";"21"} & "!I:I")))} -> 0 | I72: {=SUM(SUMIF(INDIRECT({"22";"23";"24";"25";"26";"27";"28";"29";"30";"31"} & "!B:G"),$B72,INDIRECT({"22";"23";"24";"25";"26";"27";"28";"29";"30";"31"} & "!G:G")))} -> 0 | J72: {=SUM(SUMIF(INDIRECT({"22";"23";"24";"25";"26";"27";"28";"29";"30";"31"} & "!B:I"),$B72,INDIRECT({"22";"23";"24";"25";"26";"27";"28";"29";"30";"31"} & "!I:I")))} -> 0 | K72: =ROUND(SUM(C72,E72,G72,I72)/DAY(TODAY()),0) -> 0 | L72: =SUM(D72,F72,H72,J72)/DAY(TODAY()) -> 0 | M72: =K72*7 -> 0 | N72: =L72*7 -> 0 | O72: =ROUND(K72*30,0) -> 0 | P72: =L72*30 -> 0 | S72: =EXACT(B72,Total!B72) -> TRUE | T72: =SUM(D72+F72+H72+J72) -> 0 | W72: FOGON DE PETROLEO
A73: U | B73: FOGON DE GAS DE CRISTAL | C73: =SUM(SUMIF(INDIRECT({"01";"02";"03";"04";"05";"06";"07"} & "!B:G"),$B73,INDIRECT({"01";"02";"03";"04";"05";"06";"07"} & "!G:G"))) -> 0 | D73: =SUM(SUMIF(INDIRECT({"01";"02";"03";"04";"05";"06";"07"} & "!B:I"),$B73,INDIRECT({"01";"02";"03";"04";"05";"06";"07"} & "!I:I"))) -> 0 | E73: {=SUM(SUMIF(INDIRECT({"08";"09";"10";"11";"12";"13";"14"} & "!B:G"),$B73,INDIRECT({"08";"09";"10";"11";"12";"13";"14"} & "!G:G")))} -> 0 | F73: {=SUM(SUMIF(INDIRECT({"08";"09";"10";"11";"12";"13";"14"} & "!B:I"),$B73,INDIRECT({"08";"09";"10";"11";"12";"13";"14"} & "!I:I")))} -> 0 | G73: {=SUM(SUMIF(INDIRECT({"15";"16";"17";"18";"19";"20";"21"} & "!B:G"),$B73,INDIRECT({"15";"16";"17";"18";"19";"20";"21"} & "!G:G")))} -> 0 | H73: {=SUM(SUMIF(INDIRECT({"15";"16";"17";"18";"19";"20";"21"} & "!B:I"),$B73,INDIRECT({"15";"16";"17";"18";"19";"20";"21"} & "!I:I")))} -> 0 | I73: {=SUM(SUMIF(INDIRECT({"22";"23";"24";"25";"26";"27";"28";"29";"30";"31"} & "!B:G"),$B73,INDIRECT({"22";"23";"24";"25";"26";"27";"28";"29";"30";"31"} & "!G:G")))} -> 0 | J73: {=SUM(SUMIF(INDIRECT({"22";"23";"24";"25";"26";"27";"28";"29";"30";"31"} & "!B:I"),$B73,INDIRECT({"22";"23";"24";"25";"26";"27";"28";"29";"30";"31"} & "!I:I")))} -> 0 | K73: =ROUND(SUM(C73,E73,G73,I73)/DAY(TODAY()),0) -> 0 | L73: =SUM(D73,F73,H73,J73)/DAY(TODAY()) -> 0 | M73: =K73*7 -> 0 | N73: =L73*7 -> 0 | O73: =ROUND(K73*30,0) -> 0 | P73: =L73*30 -> 0 | S73: =EXACT(B73,Total!B73) -> TRUE | T73: =SUM(D73+F73+H73+J73) -> 0 | W73: FOGON DE GAS DE CRISTAL
B74: FOGON DE GAS SENCILLO | C74: =SUM(SUMIF(INDIRECT({"01";"02";"03";"04";"05";"06";"07"} & "!B:G"),$B74,INDIRECT({"01";"02";"03";"04";"05";"06";"07"} & "!G:G"))) -> 0 | D74: =SUM(SUMIF(INDIRECT({"01";"02";"03";"04";"05";"06";"07"} & "!B:I"),$B74,INDIRECT({"01";"02";"03";"04";"05";"06";"07"} & "!I:I"))) -> 0 | E74: {=SUM(SUMIF(INDIRECT({"08";"09";"10";"11";"12";"13";"14"} & "!B:G"),$B74,INDIRECT({"08";"09";"10";"11";"12";"13";"14"} & "!G:G")))} -> 0 | F74: {=SUM(SUMIF(INDIRECT({"08";"09";"10";"11";"12";"13";"14"} & "!B:I"),$B74,INDIRECT({"08";"09";"10";"11";"12";"13";"14"} & "!I:I")))} -> 0 | G74: {=SUM(SUMIF(INDIRECT({"15";"16";"17";"18";"19";"20";"21"} & "!B:G"),$B74,INDIRECT({"15";"16";"17";"18";"19";"20";"21"} & "!G:G")))} -> 0 | H74: {=SUM(SUMIF(INDIRECT({"15";"16";"17";"18";"19";"20";"21"} & "!B:I"),$B74,INDIRECT({"15";"16";"17";"18";"19";"20";"21"} & "!I:I")))} -> 0 | I74: {=SUM(SUMIF(INDIRECT({"22";"23";"24";"25";"26";"27";"28";"29";"30";"31"} & "!B:G"),$B74,INDIRECT({"22";"23";"24";"25";"26";"27";"28";"29";"30";"31"} & "!G:G")))} -> 0 | J74: {=SUM(SUMIF(INDIRECT({"22";"23";"24";"25";"26";"27";"28";"29";"30";"31"} & "!B:I"),$B74,INDIRECT({"22";"23";"24";"25";"26";"27";"28";"29";"30";"31"} & "!I:I")))} -> 0 | K74: =ROUND(SUM(C74,E74,G74,I74)/DAY(TODAY()),0) -> 0 | L74: =SUM(D74,F74,H74,J74)/DAY(TODAY()) -> 0 | M74: =K74*7 -> 0 | N74: =L74*7 -> 0 | O74: =ROUND(K74*30,0) -> 0 | P74: =L74*30 -> 0 | S74: =EXACT(B74,Total!B74) -> TRUE | T74: =SUM(D74+F74+H74+J74) -> 0 | W74: FOGON DE GAS SENCILLO
B75: FOGON DE GAS 2 QUEMADORES CRISTAL | C75: =SUM(SUMIF(INDIRECT({"01";"02";"03";"04";"05";"06";"07"} & "!B:G"),$B75,INDIRECT({"01";"02";"03";"04";"05";"06";"07"} & "!G:G"))) -> 0 | D75: =SUM(SUMIF(INDIRECT({"01";"02";"03";"04";"05";"06";"07"} & "!B:I"),$B75,INDIRECT({"01";"02";"03";"04";"05";"06";"07"} & "!I:I"))) -> 0 | E75: {=SUM(SUMIF(INDIRECT({"08";"09";"10";"11";"12";"13";"14"} & "!B:G"),$B75,INDIRECT({"08";"09";"10";"11";"12";"13";"14"} & "!G:G")))} -> 0 | F75: {=SUM(SUMIF(INDIRECT({"08";"09";"10";"11";"12";"13";"14"} & "!B:I"),$B75,INDIRECT({"08";"09";"10";"11";"12";"13";"14"} & "!I:I")))} -> 0 | G75: {=SUM(SUMIF(INDIRECT({"15";"16";"17";"18";"19";"20";"21"} & "!B:G"),$B75,INDIRECT({"15";"16";"17";"18";"19";"20";"21"} & "!G:G")))} -> 0 | H75: {=SUM(SUMIF(INDIRECT({"15";"16";"17";"18";"19";"20";"21"} & "!B:I"),$B75,INDIRECT({"15";"16";"17";"18";"19";"20";"21"} & "!I:I")))} -> 0 | I75: {=SUM(SUMIF(INDIRECT({"22";"23";"24";"25";"26";"27";"28";"29";"30";"31"} & "!B:G"),$B75,INDIRECT({"22";"23";"24";"25";"26";"27";"28";"29";"30";"31"} & "!G:G")))} -> 0 | J75: {=SUM(SUMIF(INDIRECT({"22";"23";"24";"25";"26";"27";"28";"29";"30";"31"} & "!B:I"),$B75,INDIRECT({"22";"23";"24";"25";"26";"27";"28";"29";"30";"31"} & "!I:I")))} -> 0 | K75: =ROUND(SUM(C75,E75,G75,I75)/DAY(TODAY()),0) -> 0 | L75: =SUM(D75,F75,H75,J75)/DAY(TODAY()) -> 0 | M75: =K75*7 -> 0 | N75: =L75*7 -> 0 | O75: =ROUND(K75*30,0) -> 0 | P75: =L75*30 -> 0 | S75: =EXACT(B75,Total!B75) -> TRUE | T75: =SUM(D75+F75+H75+J75) -> 0 | W75: FOGON DE GAS 2 QUEMADORES CRISTAL
A76: U | B76: FOGON DE GAS 3 QUEMADORES | C76: =SUM(SUMIF(INDIRECT({"01";"02";"03";"04";"05";"06";"07"} & "!B:G"),$B76,INDIRECT({"01";"02";"03";"04";"05";"06";"07"} & "!G:G"))) -> 0 | D76: =SUM(SUMIF(INDIRECT({"01";"02";"03";"04";"05";"06";"07"} & "!B:I"),$B76,INDIRECT({"01";"02";"03";"04";"05";"06";"07"} & "!I:I"))) -> 0 | E76: {=SUM(SUMIF(INDIRECT({"08";"09";"10";"11";"12";"13";"14"} & "!B:G"),$B76,INDIRECT({"08";"09";"10";"11";"12";"13";"14"} & "!G:G")))} -> 0 | F76: {=SUM(SUMIF(INDIRECT({"08";"09";"10";"11";"12";"13";"14"} & "!B:I"),$B76,INDIRECT({"08";"09";"10";"11";"12";"13";"14"} & "!I:I")))} -> 0 | G76: {=SUM(SUMIF(INDIRECT({"15";"16";"17";"18";"19";"20";"21"} & "!B:G"),$B76,INDIRECT({"15";"16";"17";"18";"19";"20";"21"} & "!G:G")))} -> 0 | H76: {=SUM(SUMIF(INDIRECT({"15";"16";"17";"18";"19";"20";"21"} & "!B:I"),$B76,INDIRECT({"15";"16";"17";"18";"19";"20";"21"} & "!I:I")))} -> 0 | I76: {=SUM(SUMIF(INDIRECT({"22";"23";"24";"25";"26";"27";"28";"29";"30";"31"} & "!B:G"),$B76,INDIRECT({"22";"23";"24";"25";"26";"27";"28";"29";"30";"31"} & "!G:G")))} -> 1 | J76: {=SUM(SUMIF(INDIRECT({"22";"23";"24";"25";"26";"27";"28";"29";"30";"31"} & "!B:I"),$B76,INDIRECT({"22";"23";"24";"25";"26";"27";"28";"29";"30";"31"} & "!I:I")))} -> 35 | K76: =ROUND(SUM(C76,E76,G76,I76)/DAY(TODAY()),0) -> 1 | L76: =SUM(D76,F76,H76,J76)/DAY(TODAY()) -> 35 | M76: =K76*7 -> 7 | N76: =L76*7 -> 245 | O76: =ROUND(K76*30,0) -> 30 | P76: =L76*30 -> 1050 | S76: =EXACT(B76,Total!B76) -> TRUE | T76: =SUM(D76+F76+H76+J76) -> 35 | W76: FOGON DE GAS 3 QUEMADORES
A77: U | B77: FOGON INDUCCION MILEXUS 1200 W | C77: =SUM(SUMIF(INDIRECT({"01";"02";"03";"04";"05";"06";"07"} & "!B:G"),$B77,INDIRECT({"01";"02";"03";"04";"05";"06";"07"} & "!G:G"))) -> 0 | D77: =SUM(SUMIF(INDIRECT({"01";"02";"03";"04";"05";"06";"07"} & "!B:I"),$B77,INDIRECT({"01";"02";"03";"04";"05";"06";"07"} & "!I:I"))) -> 0 | E77: {=SUM(SUMIF(INDIRECT({"08";"09";"10";"11";"12";"13";"14"} & "!B:G"),$B77,INDIRECT({"08";"09";"10";"11";"12";"13";"14"} & "!G:G")))} -> 0 | F77: {=SUM(SUMIF(INDIRECT({"08";"09";"10";"11";"12";"13";"14"} & "!B:I"),$B77,INDIRECT({"08";"09";"10";"11";"12";"13";"14"} & "!I:I")))} -> 0 | G77: {=SUM(SUMIF(INDIRECT({"15";"16";"17";"18";"19";"20";"21"} & "!B:G"),$B77,INDIRECT({"15";"16";"17";"18";"19";"20";"21"} & "!G:G")))} -> 0 | H77: {=SUM(SUMIF(INDIRECT({"15";"16";"17";"18";"19";"20";"21"} & "!B:I"),$B77,INDIRECT({"15";"16";"17";"18";"19";"20";"21"} & "!I:I")))} -> 0 | I77: {=SUM(SUMIF(INDIRECT({"22";"23";"24";"25";"26";"27";"28";"29";"30";"31"} & "!B:G"),$B77,INDIRECT({"22";"23";"24";"25";"26";"27";"28";"29";"30";"31"} & "!G:G")))} -> 0 | J77: {=SUM(SUMIF(INDIRECT({"22";"23";"24";"25";"26";"27";"28";"29";"30";"31"} & "!B:I"),$B77,INDIRECT({"22";"23";"24";"25";"26";"27";"28";"29";"30";"31"} & "!I:I")))} -> 0 | K77: =ROUND(SUM(C77,E77,G77,I77)/DAY(TODAY()),0) -> 0 | L77: =SUM(D77,F77,H77,J77)/DAY(TODAY()) -> 0 | M77: =K77*7 -> 0 | N77: =L77*7 -> 0 | O77: =ROUND(K77*30,0) -> 0 | P77: =L77*30 -> 0 | S77: =EXACT(B77,Total!B77) -> TRUE | T77: =SUM(D77+F77+H77+J77) -> 0 | W77: FOGON INDUCCION MILEXUS 1200 W
A78: U | B78: FOGON INFRARROJO MAF 2000 W | C78: =SUM(SUMIF(INDIRECT({"01";"02";"03";"04";"05";"06";"07"} & "!B:G"),$B78,INDIRECT({"01";"02";"03";"04";"05";"06";"07"} & "!G:G"))) -> 0 | D78: =SUM(SUMIF(INDIRECT({"01";"02";"03";"04";"05";"06";"07"} & "!B:I"),$B78,INDIRECT({"01";"02";"03";"04";"05";"06";"07"} & "!I:I"))) -> 0 | E78: {=SUM(SUMIF(INDIRECT({"08";"09";"10";"11";"12";"13";"14"} & "!B:G"),$B78,INDIRECT({"08";"09";"10";"11";"12";"13";"14"} & "!G:G")))} -> 0 | F78: {=SUM(SUMIF(INDIRECT({"08";"09";"10";"11";"12";"13";"14"} & "!B:I"),$B78,INDIRECT({"08";"09";"10";"11";"12";"13";"14"} & "!I:I")))} -> 0 | G78: {=SUM(SUMIF(INDIRECT({"15";"16";"17";"18";"19";"20";"21"} & "!B:G"),$B78,INDIRECT({"15";"16";"17";"18";"19";"20";"21"} & "!G:G")))} -> 0 | H78: {=SUM(SUMIF(INDIRECT({"15";"16";"17";"18";"19";"20";"21"} & "!B:I"),$B78,INDIRECT({"15";"16";"17";"18";"19";"20";"21"} & "!I:I")))} -> 0 | I78: {=SUM(SUMIF(INDIRECT({"22";"23";"24";"25";"26";"27";"28";"29";"30";"31"} & "!B:G"),$B78,INDIRECT({"22";"23";"24";"25";"26";"27";"28";"29";"30";"31"} & "!G:G")))} -> 0 | J78: {=SUM(SUMIF(INDIRECT({"22";"23";"24";"25";"26";"27";"28";"29";"30";"31"} & "!B:I"),$B78,INDIRECT({"22";"23";"24";"25";"26";"27";"28";"29";"30";"31"} & "!I:I")))} -> 0 | K78: =ROUND(SUM(C78,E78,G78,I78)/DAY(TODAY()),0) -> 0 | L78: =SUM(D78,F78,H78,J78)/DAY(TODAY()) -> 0 | M78: =K78*7 -> 0 | N78: =L78*7 -> 0 | O78: =ROUND(K78*30,0) -> 0 | P78: =L78*30 -> 0 | S78: =EXACT(B78,Total!B78) -> TRUE | T78: =SUM(D78+F78+H78+J78) -> 0 | W78: FOGON INFRARROJO MAF 2000 W
B79: FOGON INFRARROJO ROYAL 1500 W | C79: =SUM(SUMIF(INDIRECT({"01";"02";"03";"04";"05";"06";"07"} & "!B:G"),$B79,INDIRECT({"01";"02";"03";"04";"05";"06";"07"} & "!G:G"))) -> 0 | D79: =SUM(SUMIF(INDIRECT({"01";"02";"03";"04";"05";"06";"07"} & "!B:I"),$B79,INDIRECT({"01";"02";"03";"04";"05";"06";"07"} & "!I:I"))) -> 0 | E79: {=SUM(SUMIF(INDIRECT({"08";"09";"10";"11";"12";"13";"14"} & "!B:G"),$B79,INDIRECT({"08";"09";"10";"11";"12";"13";"14"} & "!G:G")))} -> 0 | F79: {=SUM(SUMIF(INDIRECT({"08";"09";"10";"11";"12";"13";"14"} & "!B:I"),$B79,INDIRECT({"08";"09";"10";"11";"12";"13";"14"} & "!I:I")))} -> 0 | G79: {=SUM(SUMIF(INDIRECT({"15";"16";"17";"18";"19";"20";"21"} & "!B:G"),$B79,INDIRECT({"15";"16";"17";"18";"19";"20";"21"} & "!G:G")))} -> 0 | H79: {=SUM(SUMIF(INDIRECT({"15";"16";"17";"18";"19";"20";"21"} & "!B:I"),$B79,INDIRECT({"15";"16";"17";"18";"19";"20";"21"} & "!I:I")))} -> 0 | I79: {=SUM(SUMIF(INDIRECT({"22";"23";"24";"25";"26";"27";"28";"29";"30";"31"} & "!B:G"),$B79,INDIRECT({"22";"23";"24";"25";"26";"27";"28";"29";"30";"31"} & "!G:G")))} -> 0 | J79: {=SUM(SUMIF(INDIRECT({"22";"23";"24";"25";"26";"27";"28";"29";"30";"31"} & "!B:I"),$B79,INDIRECT({"22";"23";"24";"25";"26";"27";"28";"29";"30";"31"} & "!I:I")))} -> 0 | K79: =ROUND(SUM(C79,E79,G79,I79)/DAY(TODAY()),0) -> 0 | L79: =SUM(D79,F79,H79,J79)/DAY(TODAY()) -> 0 | M79: =K79*7 -> 0 | N79: =L79*7 -> 0 | O79: =ROUND(K79*30,0) -> 0 | P79: =L79*30 -> 0 | S79: =EXACT(B79,Total!B79) -> TRUE | T79: =SUM(D79+F79+H79+J79) -> 0 | W79: FOGON INFRARROJO ROYAL 1500 W
A80: U | B80: FOGON INFRARROJO EKO 1500 W | C80: =SUM(SUMIF(INDIRECT({"01";"02";"03";"04";"05";"06";"07"} & "!B:G"),$B80,INDIRECT({"01";"02";"03";"04";"05";"06";"07"} & "!G:G"))) -> 0 | D80: =SUM(SUMIF(INDIRECT({"01";"02";"03";"04";"05";"06";"07"} & "!B:I"),$B80,INDIRECT({"01";"02";"03";"04";"05";"06";"07"} & "!I:I"))) -> 0 | E80: {=SUM(SUMIF(INDIRECT({"08";"09";"10";"11";"12";"13";"14"} & "!B:G"),$B80,INDIRECT({"08";"09";"10";"11";"12";"13";"14"} & "!G:G")))} -> 0 | F80: {=SUM(SUMIF(INDIRECT({"08";"09";"10";"11";"12";"13";"14"} & "!B:I"),$B80,INDIRECT({"08";"09";"10";"11";"12";"13";"14"} & "!I:I")))} -> 0 | G80: {=SUM(SUMIF(INDIRECT({"15";"16";"17";"18";"19";"20";"21"} & "!B:G"),$B80,INDIRECT({"15";"16";"17";"18";"19";"20";"21"} & "!G:G")))} -> 0 | H80: {=SUM(SUMIF(INDIRECT({"15";"16";"17";"18";"19";"20";"21"} & "!B:I"),$B80,INDIRECT({"15";"16";"17";"18";"19";"20";"21"} & "!I:I")))} -> 0 | I80: {=SUM(SUMIF(INDIRECT({"22";"23";"24";"25";"26";"27";"28";"29";"30";"31"} & "!B:G"),$B80,INDIRECT({"22";"23";"24";"25";"26";"27";"28";"29";"30";"31"} & "!G:G")))} -> 0 | J80: {=SUM(SUMIF(INDIRECT({"22";"23";"24";"25";"26";"27";"28";"29";"30";"31"} & "!B:I"),$B80,INDIRECT({"22";"23";"24";"25";"26";"27";"28";"29";"30";"31"} & "!I:I")))} -> 0 | K80: =ROUND(SUM(C80,E80,G80,I80)/DAY(TODAY()),0) -> 0 | L80: =SUM(D80,F80,H80,J80)/DAY(TODAY()) -> 0 | M80: =K80*7 -> 0 | N80: =L80*7 -> 0 | O80: =ROUND(K80*30,0) -> 0 | P80: =L80*30 -> 0 | S80: =EXACT(B80,Total!B80) -> TRUE | T80: =SUM(D80+F80+H80+J80) -> 0 | W80: FOGON INFRARROJO EKO 1500 W
A81: U | B81: FILTRO DE AGUA | C81: =SUM(SUMIF(INDIRECT({"01";"02";"03";"04";"05";"06";"07"} & "!B:G"),$B81,INDIRECT({"01";"02";"03";"04";"05";"06";"07"} & "!G:G"))) -> 0 | D81: =SUM(SUMIF(INDIRECT({"01";"02";"03";"04";"05";"06";"07"} & "!B:I"),$B81,INDIRECT({"01";"02";"03";"04";"05";"06";"07"} & "!I:I"))) -> 0 | E81: {=SUM(SUMIF(INDIRECT({"08";"09";"10";"11";"12";"13";"14"} & "!B:G"),$B81,INDIRECT({"08";"09";"10";"11";"12";"13";"14"} & "!G:G")))} -> 0 | F81: {=SUM(SUMIF(INDIRECT({"08";"09";"10";"11";"12";"13";"14"} & "!B:I"),$B81,INDIRECT({"08";"09";"10";"11";"12";"13";"14"} & "!I:I")))} -> 0 | G81: {=SUM(SUMIF(INDIRECT({"15";"16";"17";"18";"19";"20";"21"} & "!B:G"),$B81,INDIRECT({"15";"16";"17";"18";"19";"20";"21"} & "!G:G")))} -> 0 | H81: {=SUM(SUMIF(INDIRECT({"15";"16";"17";"18";"19";"20";"21"} & "!B:I"),$B81,INDIRECT({"15";"16";"17";"18";"19";"20";"21"} & "!I:I")))} -> 0 | I81: {=SUM(SUMIF(INDIRECT({"22";"23";"24";"25";"26";"27";"28";"29";"30";"31"} & "!B:G"),$B81,INDIRECT({"22";"23";"24";"25";"26";"27";"28";"29";"30";"31"} & "!G:G")))} -> 0 | J81: {=SUM(SUMIF(INDIRECT({"22";"23";"24";"25";"26";"27";"28";"29";"30";"31"} & "!B:I"),$B81,INDIRECT({"22";"23";"24";"25";"26";"27";"28";"29";"30";"31"} & "!I:I")))} -> 0 | K81: =ROUND(SUM(C81,E81,G81,I81)/DAY(TODAY()),0) -> 0 | L81: =SUM(D81,F81,H81,J81)/DAY(TODAY()) -> 0 | M81: =K81*7 -> 0 | N81: =L81*7 -> 0 | O81: =ROUND(K81*30,0) -> 0 | P81: =L81*30 -> 0 | S81: =EXACT(B81,Total!B81) -> TRUE | T81: =SUM(D81+F81+H81+J81) -> 0 | W81: FILTRO DE AGUA
A82: U | B82: FREIDORA DE AIRE JMD 4 L | C82: =SUM(SUMIF(INDIRECT({"01";"02";"03";"04";"05";"06";"07"} & "!B:G"),$B82,INDIRECT({"01";"02";"03";"04";"05";"06";"07"} & "!G:G"))) -> 0 | D82: =SUM(SUMIF(INDIRECT({"01";"02";"03";"04";"05";"06";"07"} & "!B:I"),$B82,INDIRECT({"01";"02";"03";"04";"05";"06";"07"} & "!I:I"))) -> 0 | E82: {=SUM(SUMIF(INDIRECT({"08";"09";"10";"11";"12";"13";"14"} & "!B:G"),$B82,INDIRECT({"08";"09";"10";"11";"12";"13";"14"} & "!G:G")))} -> 0 | F82: {=SUM(SUMIF(INDIRECT({"08";"09";"10";"11";"12";"13";"14"} & "!B:I"),$B82,INDIRECT({"08";"09";"10";"11";"12";"13";"14"} & "!I:I")))} -> 0 | G82: {=SUM(SUMIF(INDIRECT({"15";"16";"17";"18";"19";"20";"21"} & "!B:G"),$B82,INDIRECT({"15";"16";"17";"18";"19";"20";"21"} & "!G:G")))} -> 0 | H82: {=SUM(SUMIF(INDIRECT({"15";"16";"17";"18";"19";"20";"21"} & "!B:I"),$B82,INDIRECT({"15";"16";"17";"18";"19";"20";"21"} & "!I:I")))} -> 0 | I82: {=SUM(SUMIF(INDIRECT({"22";"23";"24";"25";"26";"27";"28";"29";"30";"31"} & "!B:G"),$B82,INDIRECT({"22";"23";"24";"25";"26";"27";"28";"29";"30";"31"} & "!G:G")))} -> 0 | J82: {=SUM(SUMIF(INDIRECT({"22";"23";"24";"25";"26";"27";"28";"29";"30";"31"} & "!B:I"),$B82,INDIRECT({"22";"23";"24";"25";"26";"27";"28";"29";"30";"31"} & "!I:I")))} -> 0 | K82: =ROUND(SUM(C82,E82,G82,I82)/DAY(TODAY()),0) -> 0 | L82: =SUM(D82,F82,H82,J82)/DAY(TODAY()) -> 0 | M82: =K82*7 -> 0 | N82: =L82*7 -> 0 | O82: =ROUND(K82*30,0) -> 0 | P82: =L82*30 -> 0 | S82: =EXACT(B82,Total!B82) -> TRUE | T82: =SUM(D82+F82+H82+J82) -> 0 | W82: FREIDORA DE AIRE JMD 4 L
A83: U | B83: FREIDORA DE AIRE MILEXUS NEGRA 4.2L | C83: =SUM(SUMIF(INDIRECT({"01";"02";"03";"04";"05";"06";"07"} & "!B:G"),$B83,INDIRECT({"01";"02";"03";"04";"05";"06";"07"} & "!G:G"))) -> 0 | D83: =SUM(SUMIF(INDIRECT({"01";"02";"03";"04";"05";"06";"07"} & "!B:I"),$B83,INDIRECT({"01";"02";"03";"04";"05";"06";"07"} & "!I:I"))) -> 0 | E83: {=SUM(SUMIF(INDIRECT({"08";"09";"10";"11";"12";"13";"14"} & "!B:G"),$B83,INDIRECT({"08";"09";"10";"11";"12";"13";"14"} & "!G:G")))} -> 0 | F83: {=SUM(SUMIF(INDIRECT({"08";"09";"10";"11";"12";"13";"14"} & "!B:I"),$B83,INDIRECT({"08";"09";"10";"11";"12";"13";"14"} & "!I:I")))} -> 0 | G83: {=SUM(SUMIF(INDIRECT({"15";"16";"17";"18";"19";"20";"21"} & "!B:G"),$B83,INDIRECT({"15";"16";"17";"18";"19";"20";"21"} & "!G:G")))} -> 0 | H83: {=SUM(SUMIF(INDIRECT({"15";"16";"17";"18";"19";"20";"21"} & "!B:I"),$B83,INDIRECT({"15";"16";"17";"18";"19";"20";"21"} & "!I:I")))} -> 0 | I83: {=SUM(SUMIF(INDIRECT({"22";"23";"24";"25";"26";"27";"28";"29";"30";"31"} & "!B:G"),$B83,INDIRECT({"22";"23";"24";"25";"26";"27";"28";"29";"30";"31"} & "!G:G")))} -> 0 | J83: {=SUM(SUMIF(INDIRECT({"22";"23";"24";"25";"26";"27";"28";"29";"30";"31"} & "!B:I"),$B83,INDIRECT({"22";"23";"24";"25";"26";"27";"28";"29";"30";"31"} & "!I:I")))} -> 0 | K83: =ROUND(SUM(C83,E83,G83,I83)/DAY(TODAY()),0) -> 0 | L83: =SUM(D83,F83,H83,J83)/DAY(TODAY()) -> 0 | M83: =K83*7 -> 0 | N83: =L83*7 -> 0 | O83: =ROUND(K83*30,0) -> 0 | P83: =L83*30 -> 0 | S83: =EXACT(B83,Total!B83) -> TRUE | T83: =SUM(D83+F83+H83+J83) -> 0 | W83: FREIDORA DE AIRE MILEXUS NEGRA 4.2L
B84: INVERSOR 4K | C84: =SUM(SUMIF(INDIRECT({"01";"02";"03";"04";"05";"06";"07"} & "!B:G"),$B84,INDIRECT({"01";"02";"03";"04";"05";"06";"07"} & "!G:G"))) -> 2 | D84: =SUM(SUMIF(INDIRECT({"01";"02";"03";"04";"05";"06";"07"} & "!B:I"),$B84,INDIRECT({"01";"02";"03";"04";"05";"06";"07"} & "!I:I"))) -> 1550 | E84: {=SUM(SUMIF(INDIRECT({"08";"09";"10";"11";"12";"13";"14"} & "!B:G"),$B84,INDIRECT({"08";"09";"10";"11";"12";"13";"14"} & "!G:G")))} -> 0 | F84: {=SUM(SUMIF(INDIRECT({"08";"09";"10";"11";"12";"13";"14"} & "!B:I"),$B84,INDIRECT({"08";"09";"10";"11";"12";"13";"14"} & "!I:I")))} -> 0 | G84: {=SUM(SUMIF(INDIRECT({"15";"16";"17";"18";"19";"20";"21"} & "!B:G"),$B84,INDIRECT({"15";"16";"17";"18";"19";"20";"21"} & "!G:G")))} -> 0 | H84: {=SUM(SUMIF(INDIRECT({"15";"16";"17";"18";"19";"20";"21"} & "!B:I"),$B84,INDIRECT({"15";"16";"17";"18";"19";"20";"21"} & "!I:I")))} -> 0 | I84: {=SUM(SUMIF(INDIRECT({"22";"23";"24";"25";"26";"27";"28";"29";"30";"31"} & "!B:G"),$B84,INDIRECT({"22";"23";"24";"25";"26";"27";"28";"29";"30";"31"} & "!G:G")))} -> 0 | J84: {=SUM(SUMIF(INDIRECT({"22";"23";"24";"25";"26";"27";"28";"29";"30";"31"} & "!B:I"),$B84,INDIRECT({"22";"23";"24";"25";"26";"27";"28";"29";"30";"31"} & "!I:I")))} -> 0 | K84: =ROUND(SUM(C84,E84,G84,I84)/DAY(TODAY()),0) -> 2 | L84: =SUM(D84,F84,H84,J84)/DAY(TODAY()) -> 1550 | M84: =K84*7 -> 14 | N84: =L84*7 -> 10850 | O84: =ROUND(K84*30,0) -> 60 | P84: =L84*30 -> 46500 | S84: =EXACT(B84,Total!B84) -> TRUE | T84: =SUM(D84+F84+H84+J84) -> 1550 | W84: INVERSOR 4K
A85: U | B85: INVERSOR 4K SUMRY | C85: =SUM(SUMIF(INDIRECT({"01";"02";"03";"04";"05";"06";"07"} & "!B:G"),$B85,INDIRECT({"01";"02";"03";"04";"05";"06";"07"} & "!G:G"))) -> 0 | D85: =SUM(SUMIF(INDIRECT({"01";"02";"03";"04";"05";"06";"07"} & "!B:I"),$B85,INDIRECT({"01";"02";"03";"04";"05";"06";"07"} & "!I:I"))) -> 0 | E85: {=SUM(SUMIF(INDIRECT({"08";"09";"10";"11";"12";"13";"14"} & "!B:G"),$B85,INDIRECT({"08";"09";"10";"11";"12";"13";"14"} & "!G:G")))} -> 0 | F85: {=SUM(SUMIF(INDIRECT({"08";"09";"10";"11";"12";"13";"14"} & "!B:I"),$B85,INDIRECT({"08";"09";"10";"11";"12";"13";"14"} & "!I:I")))} -> 0 | G85: {=SUM(SUMIF(INDIRECT({"15";"16";"17";"18";"19";"20";"21"} & "!B:G"),$B85,INDIRECT({"15";"16";"17";"18";"19";"20";"21"} & "!G:G")))} -> 0 | H85: {=SUM(SUMIF(INDIRECT({"15";"16";"17";"18";"19";"20";"21"} & "!B:I"),$B85,INDIRECT({"15";"16";"17";"18";"19";"20";"21"} & "!I:I")))} -> 0 | I85: {=SUM(SUMIF(INDIRECT({"22";"23";"24";"25";"26";"27";"28";"29";"30";"31"} & "!B:G"),$B85,INDIRECT({"22";"23";"24";"25";"26";"27";"28";"29";"30";"31"} & "!G:G")))} -> 0 | J85: {=SUM(SUMIF(INDIRECT({"22";"23";"24";"25";"26";"27";"28";"29";"30";"31"} & "!B:I"),$B85,INDIRECT({"22";"23";"24";"25";"26";"27";"28";"29";"30";"31"} & "!I:I")))} -> 0 | K85: =ROUND(SUM(C85,E85,G85,I85)/DAY(TODAY()),0) -> 0 | L85: =SUM(D85,F85,H85,J85)/DAY(TODAY()) -> 0 | M85: =K85*7 -> 0 | N85: =L85*7 -> 0 | O85: =ROUND(K85*30,0) -> 0 | P85: =L85*30 -> 0 | S85: =EXACT(B85,Total!B85) -> TRUE | T85: =SUM(D85+F85+H85+J85) -> 0 | W85: INVERSOR 4K SUMRY
A86: U | B86: INVERSOR DE 10 K SUNPAL | C86: =SUM(SUMIF(INDIRECT({"01";"02";"03";"04";"05";"06";"07"} & "!B:G"),$B86,INDIRECT({"01";"02";"03";"04";"05";"06";"07"} & "!G:G"))) -> 0 | D86: =SUM(SUMIF(INDIRECT({"01";"02";"03";"04";"05";"06";"07"} & "!B:I"),$B86,INDIRECT({"01";"02";"03";"04";"05";"06";"07"} & "!I:I"))) -> 0 | E86: {=SUM(SUMIF(INDIRECT({"08";"09";"10";"11";"12";"13";"14"} & "!B:G"),$B86,INDIRECT({"08";"09";"10";"11";"12";"13";"14"} & "!G:G")))} -> 0 | F86: {=SUM(SUMIF(INDIRECT({"08";"09";"10";"11";"12";"13";"14"} & "!B:I"),$B86,INDIRECT({"08";"09";"10";"11";"12";"13";"14"} & "!I:I")))} -> 0 | G86: {=SUM(SUMIF(INDIRECT({"15";"16";"17";"18";"19";"20";"21"} & "!B:G"),$B86,INDIRECT({"15";"16";"17";"18";"19";"20";"21"} & "!G:G")))} -> 0 | H86: {=SUM(SUMIF(INDIRECT({"15";"16";"17";"18";"19";"20";"21"} & "!B:I"),$B86,INDIRECT({"15";"16";"17";"18";"19";"20";"21"} & "!I:I")))} -> 0 | I86: {=SUM(SUMIF(INDIRECT({"22";"23";"24";"25";"26";"27";"28";"29";"30";"31"} & "!B:G"),$B86,INDIRECT({"22";"23";"24";"25";"26";"27";"28";"29";"30";"31"} & "!G:G")))} -> 0 | J86: {=SUM(SUMIF(INDIRECT({"22";"23";"24";"25";"26";"27";"28";"29";"30";"31"} & "!B:I"),$B86,INDIRECT({"22";"23";"24";"25";"26";"27";"28";"29";"30";"31"} & "!I:I")))} -> 0 | K86: =ROUND(SUM(C86,E86,G86,I86)/DAY(TODAY()),0) -> 0 | L86: =SUM(D86,F86,H86,J86)/DAY(TODAY()) -> 0 | M86: =K86*7 -> 0 | N86: =L86*7 -> 0 | O86: =ROUND(K86*30,0) -> 0 | P86: =L86*30 -> 0 | S86: =EXACT(B86,Total!B86) -> TRUE | T86: =SUM(D86+F86+H86+J86) -> 0 | W86: INVERSOR DE 10 K SUNPAL
B87: INVERSOR 12K SACO | C87: =SUM(SUMIF(INDIRECT({"01";"02";"03";"04";"05";"06";"07"} & "!B:G"),$B87,INDIRECT({"01";"02";"03";"04";"05";"06";"07"} & "!G:G"))) -> 0 | D87: =SUM(SUMIF(INDIRECT({"01";"02";"03";"04";"05";"06";"07"} & "!B:I"),$B87,INDIRECT({"01";"02";"03";"04";"05";"06";"07"} & "!I:I"))) -> 0 | E87: {=SUM(SUMIF(INDIRECT({"08";"09";"10";"11";"12";"13";"14"} & "!B:G"),$B87,INDIRECT({"08";"09";"10";"11";"12";"13";"14"} & "!G:G")))} -> 0 | F87: {=SUM(SUMIF(INDIRECT({"08";"09";"10";"11";"12";"13";"14"} & "!B:I"),$B87,INDIRECT({"08";"09";"10";"11";"12";"13";"14"} & "!I:I")))} -> 0 | G87: {=SUM(SUMIF(INDIRECT({"15";"16";"17";"18";"19";"20";"21"} & "!B:G"),$B87,INDIRECT({"15";"16";"17";"18";"19";"20";"21"} & "!G:G")))} -> 0 | H87: {=SUM(SUMIF(INDIRECT({"15";"16";"17";"18";"19";"20";"21"} & "!B:I"),$B87,INDIRECT({"15";"16";"17";"18";"19";"20";"21"} & "!I:I")))} -> 0 | I87: {=SUM(SUMIF(INDIRECT({"22";"23";"24";"25";"26";"27";"28";"29";"30";"31"} & "!B:G"),$B87,INDIRECT({"22";"23";"24";"25";"26";"27";"28";"29";"30";"31"} & "!G:G")))} -> 0 | J87: {=SUM(SUMIF(INDIRECT({"22";"23";"24";"25";"26";"27";"28";"29";"30";"31"} & "!B:I"),$B87,INDIRECT({"22";"23";"24";"25";"26";"27";"28";"29";"30";"31"} & "!I:I")))} -> 0 | K87: =ROUND(SUM(C87,E87,G87,I87)/DAY(TODAY()),0) -> 0 | L87: =SUM(D87,F87,H87,J87)/DAY(TODAY()) -> 0 | M87: =K87*7 -> 0 | N87: =L87*7 -> 0 | O87: =ROUND(K87*30,0) -> 0 | P87: =L87*30 -> 0 | S87: =EXACT(B87,Total!B87) -> TRUE | T87: =SUM(D87+F87+H87+J87) -> 0 | W87: INVERSOR 12K SACO
A88: U | B88: INVERSOR 12K MUST | C88: =SUM(SUMIF(INDIRECT({"01";"02";"03";"04";"05";"06";"07"} & "!B:G"),$B88,INDIRECT({"01";"02";"03";"04";"05";"06";"07"} & "!G:G"))) -> 0 | D88: =SUM(SUMIF(INDIRECT({"01";"02";"03";"04";"05";"06";"07"} & "!B:I"),$B88,INDIRECT({"01";"02";"03";"04";"05";"06";"07"} & "!I:I"))) -> 0 | E88: {=SUM(SUMIF(INDIRECT({"08";"09";"10";"11";"12";"13";"14"} & "!B:G"),$B88,INDIRECT({"08";"09";"10";"11";"12";"13";"14"} & "!G:G")))} -> 0 | F88: {=SUM(SUMIF(INDIRECT({"08";"09";"10";"11";"12";"13";"14"} & "!B:I"),$B88,INDIRECT({"08";"09";"10";"11";"12";"13";"14"} & "!I:I")))} -> 0 | G88: {=SUM(SUMIF(INDIRECT({"15";"16";"17";"18";"19";"20";"21"} & "!B:G"),$B88,INDIRECT({"15";"16";"17";"18";"19";"20";"21"} & "!G:G")))} -> 0 | H88: {=SUM(SUMIF(INDIRECT({"15";"16";"17";"18";"19";"20";"21"} & "!B:I"),$B88,INDIRECT({"15";"16";"17";"18";"19";"20";"21"} & "!I:I")))} -> 0 | I88: {=SUM(SUMIF(INDIRECT({"22";"23";"24";"25";"26";"27";"28";"29";"30";"31"} & "!B:G"),$B88,INDIRECT({"22";"23";"24";"25";"26";"27";"28";"29";"30";"31"} & "!G:G")))} -> 0 | J88: {=SUM(SUMIF(INDIRECT({"22";"23";"24";"25";"26";"27";"28";"29";"30";"31"} & "!B:I"),$B88,INDIRECT({"22";"23";"24";"25";"26";"27";"28";"29";"30";"31"} & "!I:I")))} -> 0 | K88: =ROUND(SUM(C88,E88,G88,I88)/DAY(TODAY()),0) -> 0 | L88: =SUM(D88,F88,H88,J88)/DAY(TODAY()) -> 0 | M88: =K88*7 -> 0 | N88: =L88*7 -> 0 | O88: =ROUND(K88*30,0) -> 0 | P88: =L88*30 -> 0 | S88: =EXACT(B88,Total!B88) -> TRUE | T88: =SUM(D88+F88+H88+J88) -> 0 | W88: INVERSOR 12K MUST
A89: U | B89: INVERSOR MUST 3000 W | C89: =SUM(SUMIF(INDIRECT({"01";"02";"03";"04";"05";"06";"07"} & "!B:G"),$B89,INDIRECT({"01";"02";"03";"04";"05";"06";"07"} & "!G:G"))) -> 0 | D89: =SUM(SUMIF(INDIRECT({"01";"02";"03";"04";"05";"06";"07"} & "!B:I"),$B89,INDIRECT({"01";"02";"03";"04";"05";"06";"07"} & "!I:I"))) -> 0 | E89: {=SUM(SUMIF(INDIRECT({"08";"09";"10";"11";"12";"13";"14"} & "!B:G"),$B89,INDIRECT({"08";"09";"10";"11";"12";"13";"14"} & "!G:G")))} -> 0 | F89: {=SUM(SUMIF(INDIRECT({"08";"09";"10";"11";"12";"13";"14"} & "!B:I"),$B89,INDIRECT({"08";"09";"10";"11";"12";"13";"14"} & "!I:I")))} -> 0 | G89: {=SUM(SUMIF(INDIRECT({"15";"16";"17";"18";"19";"20";"21"} & "!B:G"),$B89,INDIRECT({"15";"16";"17";"18";"19";"20";"21"} & "!G:G")))} -> 0 | H89: {=SUM(SUMIF(INDIRECT({"15";"16";"17";"18";"19";"20";"21"} & "!B:I"),$B89,INDIRECT({"15";"16";"17";"18";"19";"20";"21"} & "!I:I")))} -> 0 | I89: {=SUM(SUMIF(INDIRECT({"22";"23";"24";"25";"26";"27";"28";"29";"30";"31"} & "!B:G"),$B89,INDIRECT({"22";"23";"24";"25";"26";"27";"28";"29";"30";"31"} & "!G:G")))} -> 0 | J89: {=SUM(SUMIF(INDIRECT({"22";"23";"24";"25";"26";"27";"28";"29";"30";"31"} & "!B:I"),$B89,INDIRECT({"22";"23";"24";"25";"26";"27";"28";"29";"30";"31"} & "!I:I")))} -> 0 | K89: =ROUND(SUM(C89,E89,G89,I89)/DAY(TODAY()),0) -> 0 | L89: =SUM(D89,F89,H89,J89)/DAY(TODAY()) -> 0 | M89: =K89*7 -> 0 | N89: =L89*7 -> 0 | O89: =ROUND(K89*30,0) -> 0 | P89: =L89*30 -> 0 | S89: =EXACT(B89,Total!B89) -> TRUE | T89: =SUM(D89+F89+H89+J89) -> 0 | W89: INVERSOR MUST 3000 W
B90: INVERSOR 6K MUST | C90: =SUM(SUMIF(INDIRECT({"01";"02";"03";"04";"05";"06";"07"} & "!B:G"),$B90,INDIRECT({"01";"02";"03";"04";"05";"06";"07"} & "!G:G"))) -> 0 | D90: =SUM(SUMIF(INDIRECT({"01";"02";"03";"04";"05";"06";"07"} & "!B:I"),$B90,INDIRECT({"01";"02";"03";"04";"05";"06";"07"} & "!I:I"))) -> 0 | E90: {=SUM(SUMIF(INDIRECT({"08";"09";"10";"11";"12";"13";"14"} & "!B:G"),$B90,INDIRECT({"08";"09";"10";"11";"12";"13";"14"} & "!G:G")))} -> 0 | F90: {=SUM(SUMIF(INDIRECT({"08";"09";"10";"11";"12";"13";"14"} & "!B:I"),$B90,INDIRECT({"08";"09";"10";"11";"12";"13";"14"} & "!I:I")))} -> 0 | G90: {=SUM(SUMIF(INDIRECT({"15";"16";"17";"18";"19";"20";"21"} & "!B:G"),$B90,INDIRECT({"15";"16";"17";"18";"19";"20";"21"} & "!G:G")))} -> 0 | H90: {=SUM(SUMIF(INDIRECT({"15";"16";"17";"18";"19";"20";"21"} & "!B:I"),$B90,INDIRECT({"15";"16";"17";"18";"19";"20";"21"} & "!I:I")))} -> 0 | I90: {=SUM(SUMIF(INDIRECT({"22";"23";"24";"25";"26";"27";"28";"29";"30";"31"} & "!B:G"),$B90,INDIRECT({"22";"23";"24";"25";"26";"27";"28";"29";"30";"31"} & "!G:G")))} -> 0 | J90: {=SUM(SUMIF(INDIRECT({"22";"23";"24";"25";"26";"27";"28";"29";"30";"31"} & "!B:I"),$B90,INDIRECT({"22";"23";"24";"25";"26";"27";"28";"29";"30";"31"} & "!I:I")))} -> 0 | K90: =ROUND(SUM(C90,E90,G90,I90)/DAY(TODAY()),0) -> 0 | L90: =SUM(D90,F90,H90,J90)/DAY(TODAY()) -> 0 | M90: =K90*7 -> 0 | N90: =L90*7 -> 0 | O90: =ROUND(K90*30,0) -> 0 | P90: =L90*30 -> 0 | S90: =EXACT(B90,Total!B90) -> TRUE | T90: =SUM(D90+F90+H90+J90) -> 0 | W90: INVERSOR 6K MUST
A91: U | B91: LAMPARA RECARGABLE DE 50 CM | C91: =SUM(SUMIF(INDIRECT({"01";"02";"03";"04";"05";"06";"07"} & "!B:G"),$B91,INDIRECT({"01";"02";"03";"04";"05";"06";"07"} & "!G:G"))) -> 0 | D91: =SUM(SUMIF(INDIRECT({"01";"02";"03";"04";"05";"06";"07"} & "!B:I"),$B91,INDIRECT({"01";"02";"03";"04";"05";"06";"07"} & "!I:I"))) -> 0 | E91: {=SUM(SUMIF(INDIRECT({"08";"09";"10";"11";"12";"13";"14"} & "!B:G"),$B91,INDIRECT({"08";"09";"10";"11";"12";"13";"14"} & "!G:G")))} -> 0 | F91: {=SUM(SUMIF(INDIRECT({"08";"09";"10";"11";"12";"13";"14"} & "!B:I"),$B91,INDIRECT({"08";"09";"10";"11";"12";"13";"14"} & "!I:I")))} -> 0 | G91: {=SUM(SUMIF(INDIRECT({"15";"16";"17";"18";"19";"20";"21"} & "!B:G"),$B91,INDIRECT({"15";"16";"17";"18";"19";"20";"21"} & "!G:G")))} -> 0 | H91: {=SUM(SUMIF(INDIRECT({"15";"16";"17";"18";"19";"20";"21"} & "!B:I"),$B91,INDIRECT({"15";"16";"17";"18";"19";"20";"21"} & "!I:I")))} -> 0 | I91: {=SUM(SUMIF(INDIRECT({"22";"23";"24";"25";"26";"27";"28";"29";"30";"31"} & "!B:G"),$B91,INDIRECT({"22";"23";"24";"25";"26";"27";"28";"29";"30";"31"} & "!G:G")))} -> 1 | J91: {=SUM(SUMIF(INDIRECT({"22";"23";"24";"25";"26";"27";"28";"29";"30";"31"} & "!B:I"),$B91,INDIRECT({"22";"23";"24";"25";"26";"27";"28";"29";"30";"31"} & "!I:I")))} -> 10 | K91: =ROUND(SUM(C91,E91,G91,I91)/DAY(TODAY()),0) -> 1 | L91: =SUM(D91,F91,H91,J91)/DAY(TODAY()) -> 10 | M91: =K91*7 -> 7 | N91: =L91*7 -> 70 | O91: =ROUND(K91*30,0) -> 30 | P91: =L91*30 -> 300 | S91: =EXACT(B91,Total!B91) -> TRUE | T91: =SUM(D91+F91+H91+J91) -> 10 | W91: LAMPARA RECARGABLE DE 50 CM
A92: U | B92: LAMPARA SOLAR 800W | C92: =SUM(SUMIF(INDIRECT({"01";"02";"03";"04";"05";"06";"07"} & "!B:G"),$B92,INDIRECT({"01";"02";"03";"04";"05";"06";"07"} & "!G:G"))) -> 0 | D92: =SUM(SUMIF(INDIRECT({"01";"02";"03";"04";"05";"06";"07"} & "!B:I"),$B92,INDIRECT({"01";"02";"03";"04";"05";"06";"07"} & "!I:I"))) -> 0 | E92: {=SUM(SUMIF(INDIRECT({"08";"09";"10";"11";"12";"13";"14"} & "!B:G"),$B92,INDIRECT({"08";"09";"10";"11";"12";"13";"14"} & "!G:G")))} -> 0 | F92: {=SUM(SUMIF(INDIRECT({"08";"09";"10";"11";"12";"13";"14"} & "!B:I"),$B92,INDIRECT({"08";"09";"10";"11";"12";"13";"14"} & "!I:I")))} -> 0 | G92: {=SUM(SUMIF(INDIRECT({"15";"16";"17";"18";"19";"20";"21"} & "!B:G"),$B92,INDIRECT({"15";"16";"17";"18";"19";"20";"21"} & "!G:G")))} -> 0 | H92: {=SUM(SUMIF(INDIRECT({"15";"16";"17";"18";"19";"20";"21"} & "!B:I"),$B92,INDIRECT({"15";"16";"17";"18";"19";"20";"21"} & "!I:I")))} -> 0 | I92: {=SUM(SUMIF(INDIRECT({"22";"23";"24";"25";"26";"27";"28";"29";"30";"31"} & "!B:G"),$B92,INDIRECT({"22";"23";"24";"25";"26";"27";"28";"29";"30";"31"} & "!G:G")))} -> 0 | J92: {=SUM(SUMIF(INDIRECT({"22";"23";"24";"25";"26";"27";"28";"29";"30";"31"} & "!B:I"),$B92,INDIRECT({"22";"23";"24";"25";"26";"27";"28";"29";"30";"31"} & "!I:I")))} -> 0 | K92: =ROUND(SUM(C92,E92,G92,I92)/DAY(TODAY()),0) -> 0 | L92: =SUM(D92,F92,H92,J92)/DAY(TODAY()) -> 0 | M92: =K92*7 -> 0 | N92: =L92*7 -> 0 | O92: =ROUND(K92*30,0) -> 0 | P92: =L92*30 -> 0 | S92: =EXACT(B92,Total!B92) -> TRUE | T92: =SUM(D92+F92+H92+J92) -> 0 | W92: LAMPARA SOLAR 800W
A93: U | B93: LAMPARA SOLAR 1000W | C93: =SUM(SUMIF(INDIRECT({"01";"02";"03";"04";"05";"06";"07"} & "!B:G"),$B93,INDIRECT({"01";"02";"03";"04";"05";"06";"07"} & "!G:G"))) -> 0 | D93: =SUM(SUMIF(INDIRECT({"01";"02";"03";"04";"05";"06";"07"} & "!B:I"),$B93,INDIRECT({"01";"02";"03";"04";"05";"06";"07"} & "!I:I"))) -> 0 | E93: {=SUM(SUMIF(INDIRECT({"08";"09";"10";"11";"12";"13";"14"} & "!B:G"),$B93,INDIRECT({"08";"09";"10";"11";"12";"13";"14"} & "!G:G")))} -> 0 | F93: {=SUM(SUMIF(INDIRECT({"08";"09";"10";"11";"12";"13";"14"} & "!B:I"),$B93,INDIRECT({"08";"09";"10";"11";"12";"13";"14"} & "!I:I")))} -> 0 | G93: {=SUM(SUMIF(INDIRECT({"15";"16";"17";"18";"19";"20";"21"} & "!B:G"),$B93,INDIRECT({"15";"16";"17";"18";"19";"20";"21"} & "!G:G")))} -> 0 | H93: {=SUM(SUMIF(INDIRECT({"15";"16";"17";"18";"19";"20";"21"} & "!B:I"),$B93,INDIRECT({"15";"16";"17";"18";"19";"20";"21"} & "!I:I")))} -> 0 | I93: {=SUM(SUMIF(INDIRECT({"22";"23";"24";"25";"26";"27";"28";"29";"30";"31"} & "!B:G"),$B93,INDIRECT({"22";"23";"24";"25";"26";"27";"28";"29";"30";"31"} & "!G:G")))} -> 0 | J93: {=SUM(SUMIF(INDIRECT({"22";"23";"24";"25";"26";"27";"28";"29";"30";"31"} & "!B:I"),$B93,INDIRECT({"22";"23";"24";"25";"26";"27";"28";"29";"30";"31"} & "!I:I")))} -> 0 | K93: =ROUND(SUM(C93,E93,G93,I93)/DAY(TODAY()),0) -> 0 | L93: =SUM(D93,F93,H93,J93)/DAY(TODAY()) -> 0 | M93: =K93*7 -> 0 | N93: =L93*7 -> 0 | O93: =ROUND(K93*30,0) -> 0 | P93: =L93*30 -> 0 | S93: =EXACT(B93,Total!B93) -> TRUE | T93: =SUM(D93+F93+H93+J93) -> 0 | W93: LAMPARA SOLAR 1000W
A94: U | B94: LAMPARA DE 100W CON PANEL | C94: =SUM(SUMIF(INDIRECT({"01";"02";"03";"04";"05";"06";"07"} & "!B:G"),$B94,INDIRECT({"01";"02";"03";"04";"05";"06";"07"} & "!G:G"))) -> 0 | D94: =SUM(SUMIF(INDIRECT({"01";"02";"03";"04";"05";"06";"07"} & "!B:I"),$B94,INDIRECT({"01";"02";"03";"04";"05";"06";"07"} & "!I:I"))) -> 0 | E94: {=SUM(SUMIF(INDIRECT({"08";"09";"10";"11";"12";"13";"14"} & "!B:G"),$B94,INDIRECT({"08";"09";"10";"11";"12";"13";"14"} & "!G:G")))} -> 0 | F94: {=SUM(SUMIF(INDIRECT({"08";"09";"10";"11";"12";"13";"14"} & "!B:I"),$B94,INDIRECT({"08";"09";"10";"11";"12";"13";"14"} & "!I:I")))} -> 0 | G94: {=SUM(SUMIF(INDIRECT({"15";"16";"17";"18";"19";"20";"21"} & "!B:G"),$B94,INDIRECT({"15";"16";"17";"18";"19";"20";"21"} & "!G:G")))} -> 0 | H94: {=SUM(SUMIF(INDIRECT({"15";"16";"17";"18";"19";"20";"21"} & "!B:I"),$B94,INDIRECT({"15";"16";"17";"18";"19";"20";"21"} & "!I:I")))} -> 0 | I94: {=SUM(SUMIF(INDIRECT({"22";"23";"24";"25";"26";"27";"28";"29";"30";"31"} & "!B:G"),$B94,INDIRECT({"22";"23";"24";"25";"26";"27";"28";"29";"30";"31"} & "!G:G")))} -> 0 | J94: {=SUM(SUMIF(INDIRECT({"22";"23";"24";"25";"26";"27";"28";"29";"30";"31"} & "!B:I"),$B94,INDIRECT({"22";"23";"24";"25";"26";"27";"28";"29";"30";"31"} & "!I:I")))} -> 0 | K94: =ROUND(SUM(C94,E94,G94,I94)/DAY(TODAY()),0) -> 0 | L94: =SUM(D94,F94,H94,J94)/DAY(TODAY()) -> 0 | M94: =K94*7 -> 0 | N94: =L94*7 -> 0 | O94: =ROUND(K94*30,0) -> 0 | P94: =L94*30 -> 0 | S94: =EXACT(B94,Total!B94) -> TRUE | T94: =SUM(D94+F94+H94+J94) -> 0 | W94: LAMPARA DE 100W CON PANEL
A95: U | B95: LAMPARA DE 360 W CON PANEL INTEGRADO | C95: =SUM(SUMIF(INDIRECT({"01";"02";"03";"04";"05";"06";"07"} & "!B:G"),$B95,INDIRECT({"01";"02";"03";"04";"05";"06";"07"} & "!G:G"))) -> 0 | D95: =SUM(SUMIF(INDIRECT({"01";"02";"03";"04";"05";"06";"07"} & "!B:I"),$B95,INDIRECT({"01";"02";"03";"04";"05";"06";"07"} & "!I:I"))) -> 0 | E95: {=SUM(SUMIF(INDIRECT({"08";"09";"10";"11";"12";"13";"14"} & "!B:G"),$B95,INDIRECT({"08";"09";"10";"11";"12";"13";"14"} & "!G:G")))} -> 0 | F95: {=SUM(SUMIF(INDIRECT({"08";"09";"10";"11";"12";"13";"14"} & "!B:I"),$B95,INDIRECT({"08";"09";"10";"11";"12";"13";"14"} & "!I:I")))} -> 0 | G95: {=SUM(SUMIF(INDIRECT({"15";"16";"17";"18";"19";"20";"21"} & "!B:G"),$B95,INDIRECT({"15";"16";"17";"18";"19";"20";"21"} & "!G:G")))} -> 0 | H95: {=SUM(SUMIF(INDIRECT({"15";"16";"17";"18";"19";"20";"21"} & "!B:I"),$B95,INDIRECT({"15";"16";"17";"18";"19";"20";"21"} & "!I:I")))} -> 0 | I95: {=SUM(SUMIF(INDIRECT({"22";"23";"24";"25";"26";"27";"28";"29";"30";"31"} & "!B:G"),$B95,INDIRECT({"22";"23";"24";"25";"26";"27";"28";"29";"30";"31"} & "!G:G")))} -> 0 | J95: {=SUM(SUMIF(INDIRECT({"22";"23";"24";"25";"26";"27";"28";"29";"30";"31"} & "!B:I"),$B95,INDIRECT({"22";"23";"24";"25";"26";"27";"28";"29";"30";"31"} & "!I:I")))} -> 0 | K95: =ROUND(SUM(C95,E95,G95,I95)/DAY(TODAY()),0) -> 0 | L95: =SUM(D95,F95,H95,J95)/DAY(TODAY()) -> 0 | M95: =K95*7 -> 0 | N95: =L95*7 -> 0 | O95: =ROUND(K95*30,0) -> 0 | P95: =L95*30 -> 0 | S95: =EXACT(B95,Total!B95) -> TRUE | T95: =SUM(D95+F95+H95+J95) -> 0 | W95: LAMPARA DE 360 W CON PANEL INTEGRADO
A96: U | B96: LAMPARA DE 300 W CON PANEL INTEGRADO | C96: =SUM(SUMIF(INDIRECT({"01";"02";"03";"04";"05";"06";"07"} & "!B:G"),$B96,INDIRECT({"01";"02";"03";"04";"05";"06";"07"} & "!G:G"))) -> 0 | D96: =SUM(SUMIF(INDIRECT({"01";"02";"03";"04";"05";"06";"07"} & "!B:I"),$B96,INDIRECT({"01";"02";"03";"04";"05";"06";"07"} & "!I:I"))) -> 0 | E96: {=SUM(SUMIF(INDIRECT({"08";"09";"10";"11";"12";"13";"14"} & "!B:G"),$B96,INDIRECT({"08";"09";"10";"11";"12";"13";"14"} & "!G:G")))} -> 0 | F96: {=SUM(SUMIF(INDIRECT({"08";"09";"10";"11";"12";"13";"14"} & "!B:I"),$B96,INDIRECT({"08";"09";"10";"11";"12";"13";"14"} & "!I:I")))} -> 0 | G96: {=SUM(SUMIF(INDIRECT({"15";"16";"17";"18";"19";"20";"21"} & "!B:G"),$B96,INDIRECT({"15";"16";"17";"18";"19";"20";"21"} & "!G:G")))} -> 0 | H96: {=SUM(SUMIF(INDIRECT({"15";"16";"17";"18";"19";"20";"21"} & "!B:I"),$B96,INDIRECT({"15";"16";"17";"18";"19";"20";"21"} & "!I:I")))} -> 0 | I96: {=SUM(SUMIF(INDIRECT({"22";"23";"24";"25";"26";"27";"28";"29";"30";"31"} & "!B:G"),$B96,INDIRECT({"22";"23";"24";"25";"26";"27";"28";"29";"30";"31"} & "!G:G")))} -> 0 | J96: {=SUM(SUMIF(INDIRECT({"22";"23";"24";"25";"26";"27";"28";"29";"30";"31"} & "!B:I"),$B96,INDIRECT({"22";"23";"24";"25";"26";"27";"28";"29";"30";"31"} & "!I:I")))} -> 0 | K96: =ROUND(SUM(C96,E96,G96,I96)/DAY(TODAY()),0) -> 0 | L96: =SUM(D96,F96,H96,J96)/DAY(TODAY()) -> 0 | M96: =K96*7 -> 0 | N96: =L96*7 -> 0 | O96: =ROUND(K96*30,0) -> 0 | P96: =L96*30 -> 0 | S96: =EXACT(B96,Total!B96) -> TRUE | T96: =SUM(D96+F96+H96+J96) -> 0 | W96: LAMPARA DE 300 W CON PANEL INTEGRADO
A97: U | B97: LAMPARA DE 200 W CON PANEL INDEPENDIENTE | C97: =SUM(SUMIF(INDIRECT({"01";"02";"03";"04";"05";"06";"07"} & "!B:G"),$B97,INDIRECT({"01";"02";"03";"04";"05";"06";"07"} & "!G:G"))) -> 0 | D97: =SUM(SUMIF(INDIRECT({"01";"02";"03";"04";"05";"06";"07"} & "!B:I"),$B97,INDIRECT({"01";"02";"03";"04";"05";"06";"07"} & "!I:I"))) -> 0 | E97: {=SUM(SUMIF(INDIRECT({"08";"09";"10";"11";"12";"13";"14"} & "!B:G"),$B97,INDIRECT({"08";"09";"10";"11";"12";"13";"14"} & "!G:G")))} -> 0 | F97: {=SUM(SUMIF(INDIRECT({"08";"09";"10";"11";"12";"13";"14"} & "!B:I"),$B97,INDIRECT({"08";"09";"10";"11";"12";"13";"14"} & "!I:I")))} -> 0 | G97: {=SUM(SUMIF(INDIRECT({"15";"16";"17";"18";"19";"20";"21"} & "!B:G"),$B97,INDIRECT({"15";"16";"17";"18";"19";"20";"21"} & "!G:G")))} -> 0 | H97: {=SUM(SUMIF(INDIRECT({"15";"16";"17";"18";"19";"20";"21"} & "!B:I"),$B97,INDIRECT({"15";"16";"17";"18";"19";"20";"21"} & "!I:I")))} -> 0 | I97: {=SUM(SUMIF(INDIRECT({"22";"23";"24";"25";"26";"27";"28";"29";"30";"31"} & "!B:G"),$B97,INDIRECT({"22";"23";"24";"25";"26";"27";"28";"29";"30";"31"} & "!G:G")))} -> 0 | J97: {=SUM(SUMIF(INDIRECT({"22";"23";"24";"25";"26";"27";"28";"29";"30";"31"} & "!B:I"),$B97,INDIRECT({"22";"23";"24";"25";"26";"27";"28";"29";"30";"31"} & "!I:I")))} -> 0 | K97: =ROUND(SUM(C97,E97,G97,I97)/DAY(TODAY()),0) -> 0 | L97: =SUM(D97,F97,H97,J97)/DAY(TODAY()) -> 0 | M97: =K97*7 -> 0 | N97: =L97*7 -> 0 | O97: =ROUND(K97*30,0) -> 0 | P97: =L97*30 -> 0 | S97: =EXACT(B97,Total!B97) -> TRUE | T97: =SUM(D97+F97+H97+J97) -> 0 | W97: LAMPARA DE 200 W CON PANEL INDEPENDIENTE
B98: LAMPARA DE 300 W CON PANEL INDEPENDIENTE | C98: =SUM(SUMIF(INDIRECT({"01";"02";"03";"04";"05";"06";"07"} & "!B:G"),$B98,INDIRECT({"01";"02";"03";"04";"05";"06";"07"} & "!G:G"))) -> 0 | D98: =SUM(SUMIF(INDIRECT({"01";"02";"03";"04";"05";"06";"07"} & "!B:I"),$B98,INDIRECT({"01";"02";"03";"04";"05";"06";"07"} & "!I:I"))) -> 0 | E98: {=SUM(SUMIF(INDIRECT({"08";"09";"10";"11";"12";"13";"14"} & "!B:G"),$B98,INDIRECT({"08";"09";"10";"11";"12";"13";"14"} & "!G:G")))} -> 0 | F98: {=SUM(SUMIF(INDIRECT({"08";"09";"10";"11";"12";"13";"14"} & "!B:I"),$B98,INDIRECT({"08";"09";"10";"11";"12";"13";"14"} & "!I:I")))} -> 0 | G98: {=SUM(SUMIF(INDIRECT({"15";"16";"17";"18";"19";"20";"21"} & "!B:G"),$B98,INDIRECT({"15";"16";"17";"18";"19";"20";"21"} & "!G:G")))} -> 0 | H98: {=SUM(SUMIF(INDIRECT({"15";"16";"17";"18";"19";"20";"21"} & "!B:I"),$B98,INDIRECT({"15";"16";"17";"18";"19";"20";"21"} & "!I:I")))} -> 0 | I98: {=SUM(SUMIF(INDIRECT({"22";"23";"24";"25";"26";"27";"28";"29";"30";"31"} & "!B:G"),$B98,INDIRECT({"22";"23";"24";"25";"26";"27";"28";"29";"30";"31"} & "!G:G")))} -> 0 | J98: {=SUM(SUMIF(INDIRECT({"22";"23";"24";"25";"26";"27";"28";"29";"30";"31"} & "!B:I"),$B98,INDIRECT({"22";"23";"24";"25";"26";"27";"28";"29";"30";"31"} & "!I:I")))} -> 0 | K98: =ROUND(SUM(C98,E98,G98,I98)/DAY(TODAY()),0) -> 0 | L98: =SUM(D98,F98,H98,J98)/DAY(TODAY()) -> 0 | M98: =K98*7 -> 0 | N98: =L98*7 -> 0 | O98: =ROUND(K98*30,0) -> 0 | P98: =L98*30 -> 0 | S98: =EXACT(B98,Total!B98) -> TRUE | T98: =SUM(D98+F98+H98+J98) -> 0 | W98: LAMPARA DE 300 W CON PANEL INDEPENDIENTE
A99: U | B99: LAVADORA SECADORA AUTOMÁTICA MILEXUS 10 KG | C99: =SUM(SUMIF(INDIRECT({"01";"02";"03";"04";"05";"06";"07"} & "!B:G"),$B99,INDIRECT({"01";"02";"03";"04";"05";"06";"07"} & "!G:G"))) -> 0 | D99: =SUM(SUMIF(INDIRECT({"01";"02";"03";"04";"05";"06";"07"} & "!B:I"),$B99,INDIRECT({"01";"02";"03";"04";"05";"06";"07"} & "!I:I"))) -> 0 | E99: {=SUM(SUMIF(INDIRECT({"08";"09";"10";"11";"12";"13";"14"} & "!B:G"),$B99,INDIRECT({"08";"09";"10";"11";"12";"13";"14"} & "!G:G")))} -> 0 | F99: {=SUM(SUMIF(INDIRECT({"08";"09";"10";"11";"12";"13";"14"} & "!B:I"),$B99,INDIRECT({"08";"09";"10";"11";"12";"13";"14"} & "!I:I")))} -> 0 | G99: {=SUM(SUMIF(INDIRECT({"15";"16";"17";"18";"19";"20";"21"} & "!B:G"),$B99,INDIRECT({"15";"16";"17";"18";"19";"20";"21"} & "!G:G")))} -> 0 | H99: {=SUM(SUMIF(INDIRECT({"15";"16";"17";"18";"19";"20";"21"} & "!B:I"),$B99,INDIRECT({"15";"16";"17";"18";"19";"20";"21"} & "!I:I")))} -> 0 | I99: {=SUM(SUMIF(INDIRECT({"22";"23";"24";"25";"26";"27";"28";"29";"30";"31"} & "!B:G"),$B99,INDIRECT({"22";"23";"24";"25";"26";"27";"28";"29";"30";"31"} & "!G:G")))} -> 0 | J99: {=SUM(SUMIF(INDIRECT({"22";"23";"24";"25";"26";"27";"28";"29";"30";"31"} & "!B:I"),$B99,INDIRECT({"22";"23";"24";"25";"26";"27";"28";"29";"30";"31"} & "!I:I")))} -> 0 | K99: =ROUND(SUM(C99,E99,G99,I99)/DAY(TODAY()),0) -> 0 | L99: =SUM(D99,F99,H99,J99)/DAY(TODAY()) -> 0 | M99: =K99*7 -> 0 | N99: =L99*7 -> 0 | O99: =ROUND(K99*30,0) -> 0 | P99: =L99*30 -> 0 | S99: =EXACT(B99,Total!B99) -> TRUE | T99: =SUM(D99+F99+H99+J99) -> 0 | W99: LAVADORA SECADORA AUTOMÁTICA MILEXUS 10 KG
A100: U | B100: LAVADORA PREMIER AUTOMÁTICA 11 KG | C100: =SUM(SUMIF(INDIRECT({"01";"02";"03";"04";"05";"06";"07"} & "!B:G"),$B100,INDIRECT({"01";"02";"03";"04";"05";"06";"07"} & "!G:G"))) -> 0 | D100: =SUM(SUMIF(INDIRECT({"01";"02";"03";"04";"05";"06";"07"} & "!B:I"),$B100,INDIRECT({"01";"02";"03";"04";"05";"06";"07"} & "!I:I"))) -> 0 | E100: {=SUM(SUMIF(INDIRECT({"08";"09";"10";"11";"12";"13";"14"} & "!B:G"),$B100,INDIRECT({"08";"09";"10";"11";"12";"13";"14"} & "!G:G")))} -> 0 | F100: {=SUM(SUMIF(INDIRECT({"08";"09";"10";"11";"12";"13";"14"} & "!B:I"),$B100,INDIRECT({"08";"09";"10";"11";"12";"13";"14"} & "!I:I")))} -> 0 | G100: {=SUM(SUMIF(INDIRECT({"15";"16";"17";"18";"19";"20";"21"} & "!B:G"),$B100,INDIRECT({"15";"16";"17";"18";"19";"20";"21"} & "!G:G")))} -> 0 | H100: {=SUM(SUMIF(INDIRECT({"15";"16";"17";"18";"19";"20";"21"} & "!B:I"),$B100,INDIRECT({"15";"16";"17";"18";"19";"20";"21"} & "!I:I")))} -> 0 | I100: {=SUM(SUMIF(INDIRECT({"22";"23";"24";"25";"26";"27";"28";"29";"30";"31"} & "!B:G"),$B100,INDIRECT({"22";"23";"24";"25";"26";"27";"28";"29";"30";"31"} & "!G:G")))} -> 0 | J100: {=SUM(SUMIF(INDIRECT({"22";"23";"24";"25";"26";"27";"28";"29";"30";"31"} & "!B:I"),$B100,INDIRECT({"22";"23";"24";"25";"26";"27";"28";"29";"30";"31"} & "!I:I")))} -> 0 | K100: =ROUND(SUM(C100,E100,G100,I100)/DAY(TODAY()),0) -> 0 | L100: =SUM(D100,F100,H100,J100)/DAY(TODAY()) -> 0 | M100: =K100*7 -> 0 | N100: =L100*7 -> 0 | O100: =ROUND(K100*30,0) -> 0 | P100: =L100*30 -> 0 | S100: =EXACT(B100,Total!B100) -> TRUE | T100: =SUM(D100+F100+H100+J100) -> 0 | W100: LAVADORA PREMIER AUTOMÁTICA 11 KG
A101: U | B101: LAVADORA ENERLIFE 7 KG SEMI | C101: =SUM(SUMIF(INDIRECT({"01";"02";"03";"04";"05";"06";"07"} & "!B:G"),$B101,INDIRECT({"01";"02";"03";"04";"05";"06";"07"} & "!G:G"))) -> 0 | D101: =SUM(SUMIF(INDIRECT({"01";"02";"03";"04";"05";"06";"07"} & "!B:I"),$B101,INDIRECT({"01";"02";"03";"04";"05";"06";"07"} & "!I:I"))) -> 0 | E101: {=SUM(SUMIF(INDIRECT({"08";"09";"10";"11";"12";"13";"14"} & "!B:G"),$B101,INDIRECT({"08";"09";"10";"11";"12";"13";"14"} & "!G:G")))} -> 0 | F101: {=SUM(SUMIF(INDIRECT({"08";"09";"10";"11";"12";"13";"14"} & "!B:I"),$B101,INDIRECT({"08";"09";"10";"11";"12";"13";"14"} & "!I:I")))} -> 0 | G101: {=SUM(SUMIF(INDIRECT({"15";"16";"17";"18";"19";"20";"21"} & "!B:G"),$B101,INDIRECT({"15";"16";"17";"18";"19";"20";"21"} & "!G:G")))} -> 0 | H101: {=SUM(SUMIF(INDIRECT({"15";"16";"17";"18";"19";"20";"21"} & "!B:I"),$B101,INDIRECT({"15";"16";"17";"18";"19";"20";"21"} & "!I:I")))} -> 0 | I101: {=SUM(SUMIF(INDIRECT({"22";"23";"24";"25";"26";"27";"28";"29";"30";"31"} & "!B:G"),$B101,INDIRECT({"22";"23";"24";"25";"26";"27";"28";"29";"30";"31"} & "!G:G")))} -> 0 | J101: {=SUM(SUMIF(INDIRECT({"22";"23";"24";"25";"26";"27";"28";"29";"30";"31"} & "!B:I"),$B101,INDIRECT({"22";"23";"24";"25";"26";"27";"28";"29";"30";"31"} & "!I:I")))} -> 0 | K101: =ROUND(SUM(C101,E101,G101,I101)/DAY(TODAY()),0) -> 0 | L101: =SUM(D101,F101,H101,J101)/DAY(TODAY()) -> 0 | M101: =K101*7 -> 0 | N101: =L101*7 -> 0 | O101: =ROUND(K101*30,0) -> 0 | P101: =L101*30 -> 0 | S101: =EXACT(B101,Total!B101) -> TRUE | T101: =SUM(D101+F101+H101+J101) -> 0 | W101: LAVADORA ENERLIFE 7 KG SEMI
B102: LAVADORA 7 KG MILEXUS SEMI. | C102: =SUM(SUMIF(INDIRECT({"01";"02";"03";"04";"05";"06";"07"} & "!B:G"),$B102,INDIRECT({"01";"02";"03";"04";"05";"06";"07"} & "!G:G"))) -> 1 | D102: =SUM(SUMIF(INDIRECT({"01";"02";"03";"04";"05";"06";"07"} & "!B:I"),$B102,INDIRECT({"01";"02";"03";"04";"05";"06";"07"} & "!I:I"))) -> 180 | E102: {=SUM(SUMIF(INDIRECT({"08";"09";"10";"11";"12";"13";"14"} & "!B:G"),$B102,INDIRECT({"08";"09";"10";"11";"12";"13";"14"} & "!G:G")))} -> 0 | F102: {=SUM(SUMIF(INDIRECT({"08";"09";"10";"11";"12";"13";"14"} & "!B:I"),$B102,INDIRECT({"08";"09";"10";"11";"12";"13";"14"} & "!I:I")))} -> 0 | G102: {=SUM(SUMIF(INDIRECT({"15";"16";"17";"18";"19";"20";"21"} & "!B:G"),$B102,INDIRECT({"15";"16";"17";"18";"19";"20";"21"} & "!G:G")))} -> 0 | H102: {=SUM(SUMIF(INDIRECT({"15";"16";"17";"18";"19";"20";"21"} & "!B:I"),$B102,INDIRECT({"15";"16";"17";"18";"19";"20";"21"} & "!I:I")))} -> 0 | I102: {=SUM(SUMIF(INDIRECT({"22";"23";"24";"25";"26";"27";"28";"29";"30";"31"} & "!B:G"),$B102,INDIRECT({"22";"23";"24";"25";"26";"27";"28";"29";"30";"31"} & "!G:G")))} -> 0 | J102: {=SUM(SUMIF(INDIRECT({"22";"23";"24";"25";"26";"27";"28";"29";"30";"31"} & "!B:I"),$B102,INDIRECT({"22";"23";"24";"25";"26";"27";"28";"29";"30";"31"} & "!I:I")))} -> 0 | K102: =ROUND(SUM(C102,E102,G102,I102)/DAY(TODAY()),0) -> 1 | L102: =SUM(D102,F102,H102,J102)/DAY(TODAY()) -> 180 | M102: =K102*7 -> 7 | N102: =L102*7 -> 1260 | O102: =ROUND(K102*30,0) -> 30 | P102: =L102*30 -> 5400 | S102: =EXACT(B102,Total!B102) -> TRUE | T102: =SUM(D102+F102+H102+J102) -> 180 | W102: LAVADORA 7 KG MILEXUS SEMI.
...

Sheet Total
B3: CONTROL DE INVENTARIO | F3: ÁREA: | G3: NOVA
B4: A PRECIO DE VENTA
F5: No.
J6: =SUBTOTAL(9,J9:J396) -> 930
A7: UM | B7: DETALLE | C7: EXISTENCIA INICIAL | D7: ENTRADA | E7: TRANSFERENCIA | F7: A LA VENTA | G7: VENDIDO | H7: PRECIO USD VENTA | I7: IMPORTE | J7: EXISTENCIA FINAL | K7: PRECIO DE COSTO | L7: IMPORTE | M7: UTILIDAD EN VENTA
A8: A | B8: B | C8: C | D8: D | E8: E | F8: F=C+D-3 | G8: G | H8: H | I8: I=G*H | J8: J=F-G
A9: U | B9: BOLSA DE CEMENTO BLANCO | C9: =VLOOKUP(B9,'01'!$B$9:$C$412,2,0) -> 0 | D9: {=SUM(SUMIF(INDIRECT(HOJASDIASDELMES & "!B:D"),$B9,INDIRECT(HOJASDIASDELMES & "!D:D")))} -> 0 | E9: {=SUM(SUMIF(INDIRECT(HOJASDIASDELMES & "!B:E"),$B9,INDIRECT(HOJASDIASDELMES & "!E:E")))} -> 0 | F9: =C9+D9-E9 -> 0 | G9: {=SUM(SUMIF(INDIRECT(HOJASDIASDELMES & "!B:G"),$B9,INDIRECT(HOJASDIASDELMES & "!G:G")))} -> 0 | H9: 2.86 | I9: {=SUM(SUMIF(INDIRECT(HOJASDIASDELMES & "!B:I"),$B9,INDIRECT(HOJASDIASDELMES & "!I:I")))} -> 0 | J9: =F9-G9 -> 0 | K9: =IFERROR(L9/G9,0) -> 0 | L9: {=SUM(SUMIF(INDIRECT(HOJASDIASDELMES & "!B:L"),$B9,INDIRECT(HOJASDIASDELMES & "!L:L")))} -> 0 | M9: =I9-L9 -> 0 | N9: =EXACT(B9,Total!B9) -> TRUE
A10: U | B10: SACO DE CEMENTO GRIS P350 | C10: =VLOOKUP(B10,'01'!$B$9:$C$412,2,0) -> 193 | D10: {=SUM(SUMIF(INDIRECT(HOJASDIASDELMES & "!B:D"),$B10,INDIRECT(HOJASDIASDELMES & "!D:D")))} -> 0 | E10: {=SUM(SUMIF(INDIRECT(HOJASDIASDELMES & "!B:E"),$B10,INDIRECT(HOJASDIASDELMES & "!E:E")))} -> 163 | F10: =C10+D10-E10 -> 30 | G10: {=SUM(SUMIF(INDIRECT(HOJASDIASDELMES & "!B:G"),$B10,INDIRECT(HOJASDIASDELMES & "!G:G")))} -> 5 | H10: 27.61 | I10: {=SUM(SUMIF(INDIRECT(HOJASDIASDELMES & "!B:I"),$B10,INDIRECT(HOJASDIASDELMES & "!I:I")))} -> 150 | J10: =F10-G10 -> 25 | K10: =IFERROR(L10/G10,0) -> 22 | L10: {=SUM(SUMIF(INDIRECT(HOJASDIASDELMES & "!B:L"),$B10,INDIRECT(HOJASDIASDELMES & "!L:L")))} -> 110 | M10: =I10-L10 -> 40 | N10: =EXACT(B10,Total!B10) -> TRUE
A11: U | B11: BATERIA 5K MUST | C11: =VLOOKUP(B11,'01'!$B$9:$C$412,2,0) -> 2 | D11: {=SUM(SUMIF(INDIRECT(HOJASDIASDELMES & "!B:D"),$B11,INDIRECT(HOJASDIASDELMES & "!D:D")))} -> 0 | E11: {=SUM(SUMIF(INDIRECT(HOJASDIASDELMES & "!B:E"),$B11,INDIRECT(HOJASDIASDELMES & "!E:E")))} -> 0 | F11: =C11+D11-E11 -> 2 | G11: {=SUM(SUMIF(INDIRECT(HOJASDIASDELMES & "!B:G"),$B11,INDIRECT(HOJASDIASDELMES & "!G:G")))} -> 2 | H11: 1500 | I11: {=SUM(SUMIF(INDIRECT(HOJASDIASDELMES & "!B:I"),$B11,INDIRECT(HOJASDIASDELMES & "!I:I")))} -> 3200 | J11: =F11-G11 -> 0 | K11: =IFERROR(L11/G11,0) -> 1230 | L11: {=SUM(SUMIF(INDIRECT(HOJASDIASDELMES & "!B:L"),$B11,INDIRECT(HOJASDIASDELMES & "!L:L")))} -> 2460 | M11: =I11-L11 -> 740 | N11: =EXACT(B11,Total!B11) -> TRUE
A12: U | B12: BATERIA HUMSIENK 24V 200AMP | C12: =VLOOKUP(B12,'01'!$B$9:$C$412,2,0) -> 1 | D12: {=SUM(SUMIF(INDIRECT(HOJASDIASDELMES & "!B:D"),$B12,INDIRECT(HOJASDIASDELMES & "!D:D")))} -> 0 | E12: {=SUM(SUMIF(INDIRECT(HOJASDIASDELMES & "!B:E"),$B12,INDIRECT(HOJASDIASDELMES & "!E:E")))} -> 0 | F12: =C12+D12-E12 -> 1 | G12: {=SUM(SUMIF(INDIRECT(HOJASDIASDELMES & "!B:G"),$B12,INDIRECT(HOJASDIASDELMES & "!G:G")))} -> 0 | H12: 780 | I12: {=SUM(SUMIF(INDIRECT(HOJASDIASDELMES & "!B:I"),$B12,INDIRECT(HOJASDIASDELMES & "!I:I")))} -> 0 | J12: =F12-G12 -> 1 | K12: =IFERROR(L12/G12,0) -> 0 | L12: {=SUM(SUMIF(INDIRECT(HOJASDIASDELMES & "!B:L"),$B12,INDIRECT(HOJASDIASDELMES & "!L:L")))} -> 0 | M12: =I12-L12 -> 0 | N12: =EXACT(B12,Total!B12) -> TRUE
A13: U | B13: BATERIA DE 12V 100A JMD | C13: =VLOOKUP(B13,'01'!$B$9:$C$412,2,0) -> 4 | D13: {=SUM(SUMIF(INDIRECT(HOJASDIASDELMES & "!B:D"),$B13,INDIRECT(HOJASDIASDELMES & "!D:D")))} -> 0 | E13: {=SUM(SUMIF(INDIRECT(HOJASDIASDELMES & "!B:E"),$B13,INDIRECT(HOJASDIASDELMES & "!E:E")))} -> 0 | F13: =C13+D13-E13 -> 4 | G13: {=SUM(SUMIF(INDIRECT(HOJASDIASDELMES & "!B:G"),$B13,INDIRECT(HOJASDIASDELMES & "!G:G")))} -> 0 | H13: 350 | I13: {=SUM(SUMIF(INDIRECT(HOJASDIASDELMES & "!B:I"),$B13,INDIRECT(HOJASDIASDELMES & "!I:I")))} -> 0 | J13: =F13-G13 -> 4 | K13: =IFERROR(L13/G13,0) -> 0 | L13: {=SUM(SUMIF(INDIRECT(HOJASDIASDELMES & "!B:L"),$B13,INDIRECT(HOJASDIASDELMES & "!L:L")))} -> 0 | M13: =I13-L13 -> 0 | N13: =EXACT(B13,Total!B13) -> TRUE
A14: U | B14: BATERIA DE 12V 150A SACO | C14: =VLOOKUP(B14,'01'!$B$9:$C$412,2,0) -> 2 | D14: {=SUM(SUMIF(INDIRECT(HOJASDIASDELMES & "!B:D"),$B14,INDIRECT(HOJASDIASDELMES & "!D:D")))} -> 0 | E14: {=SUM(SUMIF(INDIRECT(HOJASDIASDELMES & "!B:E"),$B14,INDIRECT(HOJASDIASDELMES & "!E:E")))} -> 0 | F14: =C14+D14-E14 -> 2 | G14: {=SUM(SUMIF(INDIRECT(HOJASDIASDELMES & "!B:G"),$B14,INDIRECT(HOJASDIASDELMES & "!G:G")))} -> 1 | H14: 300 | I14: {=SUM(SUMIF(INDIRECT(HOJASDIASDELMES & "!B:I"),$B14,INDIRECT(HOJASDIASDELMES & "!I:I")))} -> 500 | J14: =F14-G14 -> 1 | K14: =IFERROR(L14/G14,0) -> 350 | L14: {=SUM(SUMIF(INDIRECT(HOJASDIASDELMES & "!B:L"),$B14,INDIRECT(HOJASDIASDELMES & "!L:L")))} -> 350 | M14: =I14-L14 -> 150 | N14: =EXACT(B14,Total!B14) -> TRUE
A15: U | B15: BATERIA EXTRA 16K SACO | C15: =VLOOKUP(B15,'01'!$B$9:$C$412,2,0) -> 1 | D15: {=SUM(SUMIF(INDIRECT(HOJASDIASDELMES & "!B:D"),$B15,INDIRECT(HOJASDIASDELMES & "!D:D")))} -> 0 | E15: {=SUM(SUMIF(INDIRECT(HOJASDIASDELMES & "!B:E"),$B15,INDIRECT(HOJASDIASDELMES & "!E:E")))} -> 0 | F15: =C15+D15-E15 -> 1 | G15: {=SUM(SUMIF(INDIRECT(HOJASDIASDELMES & "!B:G"),$B15,INDIRECT(HOJASDIASDELMES & "!G:G")))} -> 0 | H15: 1300 | I15: {=SUM(SUMIF(INDIRECT(HOJASDIASDELMES & "!B:I"),$B15,INDIRECT(HOJASDIASDELMES & "!I:I")))} -> 0 | J15: =F15-G15 -> 1 | K15: =IFERROR(L15/G15,0) -> 0 | L15: {=SUM(SUMIF(INDIRECT(HOJASDIASDELMES & "!B:L"),$B15,INDIRECT(HOJASDIASDELMES & "!L:L")))} -> 0 | M15: =I15-L15 -> 0 | N15: =EXACT(B15,Total!B15) -> TRUE
A16: U | B16: BASE PARA PANELES GRANDES | C16: =VLOOKUP(B16,'01'!$B$9:$C$412,2,0) -> 3 | D16: {=SUM(SUMIF(INDIRECT(HOJASDIASDELMES & "!B:D"),$B16,INDIRECT(HOJASDIASDELMES & "!D:D")))} -> 0 | E16: {=SUM(SUMIF(INDIRECT(HOJASDIASDELMES & "!B:E"),$B16,INDIRECT(HOJASDIASDELMES & "!E:E")))} -> 3 | F16: =C16+D16-E16 -> 0 | G16: {=SUM(SUMIF(INDIRECT(HOJASDIASDELMES & "!B:G"),$B16,INDIRECT(HOJASDIASDELMES & "!G:G")))} -> 0 | H16: 100 | I16: {=SUM(SUMIF(INDIRECT(HOJASDIASDELMES & "!B:I"),$B16,INDIRECT(HOJASDIASDELMES & "!I:I")))} -> 0 | J16: =F16-G16 -> 0 | K16: =IFERROR(L16/G16,0) -> 0 | L16: {=SUM(SUMIF(INDIRECT(HOJASDIASDELMES & "!B:L"),$B16,INDIRECT(HOJASDIASDELMES & "!L:L")))} -> 0 | M16: =I16-L16 -> 0 | N16: =EXACT(B16,Total!B16) -> TRUE
A17: U | B17: BASE PARA PANELES | C17: =VLOOKUP(B17,'01'!$B$9:$C$412,2,0) -> 0 | D17: {=SUM(SUMIF(INDIRECT(HOJASDIASDELMES & "!B:D"),$B17,INDIRECT(HOJASDIASDELMES & "!D:D")))} -> 8 | E17: {=SUM(SUMIF(INDIRECT(HOJASDIASDELMES & "!B:E"),$B17,INDIRECT(HOJASDIASDELMES & "!E:E")))} -> 0 | F17: =C17+D17-E17 -> 8 | G17: {=SUM(SUMIF(INDIRECT(HOJASDIASDELMES & "!B:G"),$B17,INDIRECT(HOJASDIASDELMES & "!G:G")))} -> 0 | H17: 50 | I17: {=SUM(SUMIF(INDIRECT(HOJASDIASDELMES & "!B:I"),$B17,INDIRECT(HOJASDIASDELMES & "!I:I")))} -> 0 | J17: =F17-G17 -> 8 | K17: =IFERROR(L17/G17,0) -> 0 | L17: {=SUM(SUMIF(INDIRECT(HOJASDIASDELMES & "!B:L"),$B17,INDIRECT(HOJASDIASDELMES & "!L:L")))} -> 0 | M17: =I17-L17 -> 0 | N17: =EXACT(B17,Total!B17) -> TRUE
A18: U | B18: BASE FIJA PARA TV 32'' - 86'' | C18: =VLOOKUP(B18,'01'!$B$9:$C$412,2,0) -> 1 | D18: {=SUM(SUMIF(INDIRECT(HOJASDIASDELMES & "!B:D"),$B18,INDIRECT(HOJASDIASDELMES & "!D:D")))} -> 0 | E18: {=SUM(SUMIF(INDIRECT(HOJASDIASDELMES & "!B:E"),$B18,INDIRECT(HOJASDIASDELMES & "!E:E")))} -> 0 | F18: =C18+D18-E18 -> 1 | G18: {=SUM(SUMIF(INDIRECT(HOJASDIASDELMES & "!B:G"),$B18,INDIRECT(HOJASDIASDELMES & "!G:G")))} -> 1 | H18: 20 | I18: {=SUM(SUMIF(INDIRECT(HOJASDIASDELMES & "!B:I"),$B18,INDIRECT(HOJASDIASDELMES & "!I:I")))} -> 20 | J18: =F18-G18 -> 0 | K18: =IFERROR(L18/G18,0) -> 7 | L18: {=SUM(SUMIF(INDIRECT(HOJASDIASDELMES & "!B:L"),$B18,INDIRECT(HOJASDIASDELMES & "!L:L")))} -> 7 | M18: =I18-L18 -> 13 | N18: =EXACT(B18,Total!B18) -> TRUE
A19: U | B19: BASE GIRATORIA | C19: =VLOOKUP(B19,'01'!$B$9:$C$412,2,0) -> 0 | D19: {=SUM(SUMIF(INDIRECT(HOJASDIASDELMES & "!B:D"),$B19,INDIRECT(HOJASDIASDELMES & "!D:D")))} -> 0 | E19: {=SUM(SUMIF(INDIRECT(HOJASDIASDELMES & "!B:E"),$B19,INDIRECT(HOJASDIASDELMES & "!E:E")))} -> 0 | F19: =C19+D19-E19 -> 0 | G19: {=SUM(SUMIF(INDIRECT(HOJASDIASDELMES & "!B:G"),$B19,INDIRECT(HOJASDIASDELMES & "!G:G")))} -> 0 | H19: 25 | I19: {=SUM(SUMIF(INDIRECT(HOJASDIASDELMES & "!B:I"),$B19,INDIRECT(HOJASDIASDELMES & "!I:I")))} -> 0 | J19: =F19-G19 -> 0 | K19: =IFERROR(L19/G19,0) -> 0 | L19: {=SUM(SUMIF(INDIRECT(HOJASDIASDELMES & "!B:L"),$B19,INDIRECT(HOJASDIASDELMES & "!L:L")))} -> 0 | M19: =I19-L19 -> 0 | N19: =EXACT(B19,Total!B19) -> TRUE
A20: U | B20: BASE PARA SPLIT | C20: =VLOOKUP(B20,'01'!$B$9:$C$412,2,0) -> 0 | D20: {=SUM(SUMIF(INDIRECT(HOJASDIASDELMES & "!B:D"),$B20,INDIRECT(HOJASDIASDELMES & "!D:D")))} -> 0 | E20: {=SUM(SUMIF(INDIRECT(HOJASDIASDELMES & "!B:E"),$B20,INDIRECT(HOJASDIASDELMES & "!E:E")))} -> 0 | F20: =C20+D20-E20 -> 0 | G20: {=SUM(SUMIF(INDIRECT(HOJASDIASDELMES & "!B:G"),$B20,INDIRECT(HOJASDIASDELMES & "!G:G")))} -> 0 | H20: 20 | I20: {=SUM(SUMIF(INDIRECT(HOJASDIASDELMES & "!B:I"),$B20,INDIRECT(HOJASDIASDELMES & "!I:I")))} -> 0 | J20: =F20-G20 -> 0 | K20: =IFERROR(L20/G20,0) -> 0 | L20: {=SUM(SUMIF(INDIRECT(HOJASDIASDELMES & "!B:L"),$B20,INDIRECT(HOJASDIASDELMES & "!L:L")))} -> 0 | M20: =I20-L20 -> 0 | N20: =EXACT(B20,Total!B20) -> TRUE
... A23: U | B23: BATERIA MUST 10.25 KW | C23: =VLOOKUP(B23,'01'!$B$9:$C$412,2,0) -> 1 | D23: {=SUM(SUMIF(INDIRECT(HOJASDIASDELMES & "!B:D"),$B23,INDIRECT(HOJASDIASDELMES & "!D:D")))} -> 0 | E23: {=SUM(SUMIF(INDIRECT(HOJASDIASDELMES & "!B:E"),$B23,INDIRECT(HOJASDIASDELMES & "!E:E")))} -> 0 | F23: =C23+D23-E23 -> 1 | G23: {=SUM(SUMIF(INDIRECT(HOJASDIASDELMES & "!B:G"),$B23,INDIRECT(HOJASDIASDELMES & "!G:G")))} -> 1 | H23: 2600 | I23: {=SUM(SUMIF(INDIRECT(HOJASDIASDELMES & "!B:I"),$B23,INDIRECT(HOJASDIASDELMES & "!I:I")))} -> 2600 | J23: =F23-G23 -> 0 | K23: =IFERROR(L23/G23,0) -> 1980 | L23: {=SUM(SUMIF(INDIRECT(HOJASDIASDELMES & "!B:L"),$B23,INDIRECT(HOJASDIASDELMES & "!L:L")))} -> 1980 | M23: =I23-L23 -> 620 | N23: =EXACT(B23,Total!B23) -> TRUE
A24: U | B24: BREKE 63A DOBLE TIR | C24: =VLOOKUP(B24,'01'!$B$9:$C$412,2,0) -> 0 | D24: {=SUM(SUMIF(INDIRECT(HOJASDIASDELMES & "!B:D"),$B24,INDIRECT(HOJASDIASDELMES & "!D:D")))} -> 0 | E24: {=SUM(SUMIF(INDIRECT(HOJASDIASDELMES & "!B:E"),$B24,INDIRECT(HOJASDIASDELMES & "!E:E")))} -> 0 | F24: =C24+D24-E24 -> 0 | G24: {=SUM(SUMIF(INDIRECT(HOJASDIASDELMES & "!B:G"),$B24,INDIRECT(HOJASDIASDELMES & "!G:G")))} -> 0 | I24: {=SUM(SUMIF(INDIRECT(HOJASDIASDELMES & "!B:I"),$B24,INDIRECT(HOJASDIASDELMES & "!I:I")))} -> 0 | J24: =F24-G24 -> 0 | K24: =IFERROR(L24/G24,0) -> 0 | L24: {=SUM(SUMIF(INDIRECT(HOJASDIASDELMES & "!B:L"),$B24,INDIRECT(HOJASDIASDELMES & "!L:L")))} -> 0 | M24: =I24-L24 -> 0 | N24: =EXACT(B24,Total!B24) -> TRUE
A25: U | B25: BREKE 32A DOBLE | C25: =VLOOKUP(B25,'01'!$B$9:$C$412,2,0) -> 0 | D25: {=SUM(SUMIF(INDIRECT(HOJASDIASDELMES & "!B:D"),$B25,INDIRECT(HOJASDIASDELMES & "!D:D")))} -> 0 | E25: {=SUM(SUMIF(INDIRECT(HOJASDIASDELMES & "!B:E"),$B25,INDIRECT(HOJASDIASDELMES & "!E:E")))} -> 0 | F25: =C25+D25-E25 -> 0 | G25: {=SUM(SUMIF(INDIRECT(HOJASDIASDELMES & "!B:G"),$B25,INDIRECT(HOJASDIASDELMES & "!G:G")))} -> 0 | I25: {=SUM(SUMIF(INDIRECT(HOJASDIASDELMES & "!B:I"),$B25,INDIRECT(HOJASDIASDELMES & "!I:I")))} -> 0 | J25: =F25-G25 -> 0 | K25: =IFERROR(L25/G25,0) -> 0 | L25: {=SUM(SUMIF(INDIRECT(HOJASDIASDELMES & "!B:L"),$B25,INDIRECT(HOJASDIASDELMES & "!L:L")))} -> 0 | M25: =I25-L25 -> 0 | N25: =EXACT(B25,Total!B25) -> TRUE
A26: U | B26: BOCINA BOOM 8 PULGADAS | C26: =VLOOKUP(B26,'01'!$B$9:$C$412,2,0) -> 0 | D26: {=SUM(SUMIF(INDIRECT(HOJASDIASDELMES & "!B:D"),$B26,INDIRECT(HOJASDIASDELMES & "!D:D")))} -> 0 | E26: {=SUM(SUMIF(INDIRECT(HOJASDIASDELMES & "!B:E"),$B26,INDIRECT(HOJASDIASDELMES & "!E:E")))} -> 0 | F26: =C26+D26-E26 -> 0 | G26: {=SUM(SUMIF(INDIRECT(HOJASDIASDELMES & "!B:G"),$B26,INDIRECT(HOJASDIASDELMES & "!G:G")))} -> 0 | H26: 35 | I26: {=SUM(SUMIF(INDIRECT(HOJASDIASDELMES & "!B:I"),$B26,INDIRECT(HOJASDIASDELMES & "!I:I")))} -> 0 | J26: =F26-G26 -> 0 | K26: =IFERROR(L26/G26,0) -> 0 | L26: {=SUM(SUMIF(INDIRECT(HOJASDIASDELMES & "!B:L"),$B26,INDIRECT(HOJASDIASDELMES & "!L:L")))} -> 0 | M26: =I26-L26 -> 0 | N26: =EXACT(B26,Total!B26) -> TRUE
A27: U | B27: BOCINA MILEXUS 8 PULGADAS | C27: =VLOOKUP(B27,'01'!$B$9:$C$412,2,0) -> 3 | D27: {=SUM(SUMIF(INDIRECT(HOJASDIASDELMES & "!B:D"),$B27,INDIRECT(HOJASDIASDELMES & "!D:D")))} -> 0 | E27: {=SUM(SUMIF(INDIRECT(HOJASDIASDELMES & "!B:E"),$B27,INDIRECT(HOJASDIASDELMES & "!E:E")))} -> 0 | F27: =C27+D27-E27 -> 3 | G27: {=SUM(SUMIF(INDIRECT(HOJASDIASDELMES & "!B:G"),$B27,INDIRECT(HOJASDIASDELMES & "!G:G")))} -> 2 | H27: 85 | I27: {=SUM(SUMIF(INDIRECT(HOJASDIASDELMES & "!B:I"),$B27,INDIRECT(HOJASDIASDELMES & "!I:I")))} -> 360 | J27: =F27-G27 -> 1 | K27: =IFERROR(L27/G27,0) -> 20 | L27: {=SUM(SUMIF(INDIRECT(HOJASDIASDELMES & "!B:L"),$B27,INDIRECT(HOJASDIASDELMES & "!L:L")))} -> 40 | M27: =I27-L27 -> 320 | N27: =EXACT(B27,Total!B27) -> TRUE
A28: U | B28: BOCINA MILEXUS 6 DUAL | C28: =VLOOKUP(B28,'01'!$B$9:$C$412,2,0) -> 2 | D28: {=SUM(SUMIF(INDIRECT(HOJASDIASDELMES & "!B:D"),$B28,INDIRECT(HOJASDIASDELMES & "!D:D")))} -> 0 | E28: {=SUM(SUMIF(INDIRECT(HOJASDIASDELMES & "!B:E"),$B28,INDIRECT(HOJASDIASDELMES & "!E:E")))} -> 0 | F28: =C28+D28-E28 -> 2 | G28: {=SUM(SUMIF(INDIRECT(HOJASDIASDELMES & "!B:G"),$B28,INDIRECT(HOJASDIASDELMES & "!G:G")))} -> 0 | H28: 190 | I28: {=SUM(SUMIF(INDIRECT(HOJASDIASDELMES & "!B:I"),$B28,INDIRECT(HOJASDIASDELMES & "!I:I")))} -> 0 | J28: =F28-G28 -> 2 | K28: =IFERROR(L28/G28,0) -> 0 | L28: {=SUM(SUMIF(INDIRECT(HOJASDIASDELMES & "!B:L"),$B28,INDIRECT(HOJASDIASDELMES & "!L:L")))} -> 0 | M28: =I28-L28 -> 0 | N28: =EXACT(B28,Total!B28) -> TRUE
A29: U | B29: BOMBA DE AGUA SILVER POINT 1 HP | C29: =VLOOKUP(B29,'01'!$B$9:$C$412,2,0) -> 1 | D29: {=SUM(SUMIF(INDIRECT(HOJASDIASDELMES & "!B:D"),$B29,INDIRECT(HOJASDIASDELMES & "!D:D")))} -> 0 | E29: {=SUM(SUMIF(INDIRECT(HOJASDIASDELMES & "!B:E"),$B29,INDIRECT(HOJASDIASDELMES & "!E:E")))} -> 1 | F29: =C29+D29-E29 -> 0 | G29: {=SUM(SUMIF(INDIRECT(HOJASDIASDELMES & "!B:G"),$B29,INDIRECT(HOJASDIASDELMES & "!G:G")))} -> 0 | H29: 60 | I29: {=SUM(SUMIF(INDIRECT(HOJASDIASDELMES & "!B:I"),$B29,INDIRECT(HOJASDIASDELMES & "!I:I")))} -> 0 | J29: =F29-G29 -> 0 | K29: =IFERROR(L29/G29,0) -> 0 | L29: {=SUM(SUMIF(INDIRECT(HOJASDIASDELMES & "!B:L"),$B29,INDIRECT(HOJASDIASDELMES & "!L:L")))} -> 0 | M29: =I29-L29 -> 0 | N29: =EXACT(B29,Total!B29) -> TRUE
A30: U | B30: BOMBA DE AGUA SILVER POINT 1X1/2 | C30: =VLOOKUP(B30,'01'!$B$9:$C$412,2,0) -> 3 | D30: {=SUM(SUMIF(INDIRECT(HOJASDIASDELMES & "!B:D"),$B30,INDIRECT(HOJASDIASDELMES & "!D:D")))} -> 0 | E30: {=SUM(SUMIF(INDIRECT(HOJASDIASDELMES & "!B:E"),$B30,INDIRECT(HOJASDIASDELMES & "!E:E")))} -> 1 | F30: =C30+D30-E30 -> 2 | G30: {=SUM(SUMIF(INDIRECT(HOJASDIASDELMES & "!B:G"),$B30,INDIRECT(HOJASDIASDELMES & "!G:G")))} -> 1 | H30: 45 | I30: {=SUM(SUMIF(INDIRECT(HOJASDIASDELMES & "!B:I"),$B30,INDIRECT(HOJASDIASDELMES & "!I:I")))} -> 45 | J30: =F30-G30 -> 1 | K30: =IFERROR(L30/G30,0) -> 30 | L30: {=SUM(SUMIF(INDIRECT(HOJASDIASDELMES & "!B:L"),$B30,INDIRECT(HOJASDIASDELMES & "!L:L")))} -> 30 | M30: =I30-L30 -> 15 | N30: =EXACT(B30,Total!B30) -> TRUE
A31: U | B31: BICICLETA INFANTIL | C31: =VLOOKUP(B31,'01'!$B$9:$C$412,2,0) -> 0 | D31: {=SUM(SUMIF(INDIRECT(HOJASDIASDELMES & "!B:D"),$B31,INDIRECT(HOJASDIASDELMES & "!D:D")))} -> 0 | E31: {=SUM(SUMIF(INDIRECT(HOJASDIASDELMES & "!B:E"),$B31,INDIRECT(HOJASDIASDELMES & "!E:E")))} -> 0 | F31: =C31+D31-E31 -> 0 | G31: {=SUM(SUMIF(INDIRECT(HOJASDIASDELMES & "!B:G"),$B31,INDIRECT(HOJASDIASDELMES & "!G:G")))} -> 0 | H31: 130 | I31: {=SUM(SUMIF(INDIRECT(HOJASDIASDELMES & "!B:I"),$B31,INDIRECT(HOJASDIASDELMES & "!I:I")))} -> 0 | J31: =F31-G31 -> 0 | K31: =IFERROR(L31/G31,0) -> 0 | L31: {=SUM(SUMIF(INDIRECT(HOJASDIASDELMES & "!B:L"),$B31,INDIRECT(HOJASDIASDELMES & "!L:L")))} -> 0 | M31: =I31-L31 -> 0 | N31: =EXACT(B31,Total!B31) -> TRUE
A32: U | B32: BICICLETA INFANTIL 20 TZ002 | C32: =VLOOKUP(B32,'01'!$B$9:$C$412,2,0) -> 6 | D32: {=SUM(SUMIF(INDIRECT(HOJASDIASDELMES & "!B:D"),$B32,INDIRECT(HOJASDIASDELMES & "!D:D")))} -> 3 | E32: {=SUM(SUMIF(INDIRECT(HOJASDIASDELMES & "!B:E"),$B32,INDIRECT(HOJASDIASDELMES & "!E:E")))} -> 2 | F32: =C32+D32-E32 -> 7 | G32: {=SUM(SUMIF(INDIRECT(HOJASDIASDELMES & "!B:G"),$B32,INDIRECT(HOJASDIASDELMES & "!G:G")))} -> 1 | H32: 130 | I32: {=SUM(SUMIF(INDIRECT(HOJASDIASDELMES & "!B:I"),$B32,INDIRECT(HOJASDIASDELMES & "!I:I")))} -> 130 | J32: =F32-G32 -> 6 | K32: =IFERROR(L32/G32,0) -> 90 | L32: {=SUM(SUMIF(INDIRECT(HOJASDIASDELMES & "!B:L"),$B32,INDIRECT(HOJASDIASDELMES & "!L:L")))} -> 90 | M32: =I32-L32 -> 40 | N32: =EXACT(B32,Total!B32) -> TRUE
A33: U | B33: BICICLETA 26 008-5 | C33: =VLOOKUP(B33,'01'!$B$9:$C$412,2,0) -> 2 | D33: {=SUM(SUMIF(INDIRECT(HOJASDIASDELMES & "!B:D"),$B33,INDIRECT(HOJASDIASDELMES & "!D:D")))} -> 3 | E33: {=SUM(SUMIF(INDIRECT(HOJASDIASDELMES & "!B:E"),$B33,INDIRECT(HOJASDIASDELMES & "!E:E")))} -> 0 | F33: =C33+D33-E33 -> 5 | G33: {=SUM(SUMIF(INDIRECT(HOJASDIASDELMES & "!B:G"),$B33,INDIRECT(HOJASDIASDELMES & "!G:G")))} -> 0 | H33: 180 | I33: {=SUM(SUMIF(INDIRECT(HOJASDIASDELMES & "!B:I"),$B33,INDIRECT(HOJASDIASDELMES & "!I:I")))} -> 0 | J33: =F33-G33 -> 5 | K33: =IFERROR(L33/G33,0) -> 0 | L33: {=SUM(SUMIF(INDIRECT(HOJASDIASDELMES & "!B:L"),$B33,INDIRECT(HOJASDIASDELMES & "!L:L")))} -> 0 | M33: =I33-L33 -> 0 | N33: =EXACT(B33,Total!B33) -> TRUE
A34: U | B34: BICICLETA 26 012 | C34: =VLOOKUP(B34,'01'!$B$9:$C$412,2,0) -> 2 | D34: {=SUM(SUMIF(INDIRECT(HOJASDIASDELMES & "!B:D"),$B34,INDIRECT(HOJASDIASDELMES & "!D:D")))} -> 3 | E34: {=SUM(SUMIF(INDIRECT(HOJASDIASDELMES & "!B:E"),$B34,INDIRECT(HOJASDIASDELMES & "!E:E")))} -> 0 | F34: =C34+D34-E34 -> 5 | G34: {=SUM(SUMIF(INDIRECT(HOJASDIASDELMES & "!B:G"),$B34,INDIRECT(HOJASDIASDELMES & "!G:G")))} -> 0 | I34: {=SUM(SUMIF(INDIRECT(HOJASDIASDELMES & "!B:I"),$B34,INDIRECT(HOJASDIASDELMES & "!I:I")))} -> 0 | J34: =F34-G34 -> 5 | K34: =IFERROR(L34/G34,0) -> 0 | L34: {=SUM(SUMIF(INDIRECT(HOJASDIASDELMES & "!B:L"),$B34,INDIRECT(HOJASDIASDELMES & "!L:L")))} -> 0 | M34: =I34-L34 -> 0 | N34: =EXACT(B34,Total!B34) -> TRUE
A35: U | B35: BICICLETA 26 003-4 | C35: =VLOOKUP(B35,'01'!$B$9:$C$412,2,0) -> 1 | D35: {=SUM(SUMIF(INDIRECT(HOJASDIASDELMES & "!B:D"),$B35,INDIRECT(HOJASDIASDELMES & "!D:D")))} -> 3 | E35: {=SUM(SUMIF(INDIRECT(HOJASDIASDELMES & "!B:E"),$B35,INDIRECT(HOJASDIASDELMES & "!E:E")))} -> 1 | F35: =C35+D35-E35 -> 3 | G35: {=SUM(SUMIF(INDIRECT(HOJASDIASDELMES & "!B:G"),$B35,INDIRECT(HOJASDIASDELMES & "!G:G")))} -> 1 | I35: {=SUM(SUMIF(INDIRECT(HOJASDIASDELMES & "!B:I"),$B35,INDIRECT(HOJASDIASDELMES & "!I:I")))} -> 185 | J35: =F35-G35 -> 2 | K35: =IFERROR(L35/G35,0) -> 143 | L35: {=SUM(SUMIF(INDIRECT(HOJASDIASDELMES & "!B:L"),$B35,INDIRECT(HOJASDIASDELMES & "!L:L")))} -> 143 | M35: =I35-L35 -> 42 | N35: =EXACT(B35,Total!B35) -> TRUE
A36: U | B36: BICICLETA 16 023 | C36: =VLOOKUP(B36,'01'!$B$9:$C$412,2,0) -> 2 | D36: {=SUM(SUMIF(INDIRECT(HOJASDIASDELMES & "!B:D"),$B36,INDIRECT(HOJASDIASDELMES & "!D:D")))} -> 2 | E36: {=SUM(SUMIF(INDIRECT(HOJASDIASDELMES & "!B:E"),$B36,INDIRECT(HOJASDIASDELMES & "!E:E")))} -> 0 | F36: =C36+D36-E36 -> 4 | G36: {=SUM(SUMIF(INDIRECT(HOJASDIASDELMES & "!B:G"),$B36,INDIRECT(HOJASDIASDELMES & "!G:G")))} -> 0 | I36: {=SUM(SUMIF(INDIRECT(HOJASDIASDELMES & "!B:I"),$B36,INDIRECT(HOJASDIASDELMES & "!I:I")))} -> 0 | J36: =F36-G36 -> 4 | K36: =IFERROR(L36/G36,0) -> 0 | L36: {=SUM(SUMIF(INDIRECT(HOJASDIASDELMES & "!B:L"),$B36,INDIRECT(HOJASDIASDELMES & "!L:L")))} -> 0 | M36: =I36-L36 -> 0 | N36: =EXACT(B36,Total!B36) -> TRUE
A37: U | B37: BICICLETA ELECTRICA | C37: =VLOOKUP(B37,'01'!$B$9:$C$412,2,0) -> 1 | D37: {=SUM(SUMIF(INDIRECT(HOJASDIASDELMES & "!B:D"),$B37,INDIRECT(HOJASDIASDELMES & "!D:D")))} -> 0 | E37: {=SUM(SUMIF(INDIRECT(HOJASDIASDELMES & "!B:E"),$B37,INDIRECT(HOJASDIASDELMES & "!E:E")))} -> 1 | F37: =C37+D37-E37 -> 0 | G37: {=SUM(SUMIF(INDIRECT(HOJASDIASDELMES & "!B:G"),$B37,INDIRECT(HOJASDIASDELMES & "!G:G")))} -> 0 | H37: 600 | I37: {=SUM(SUMIF(INDIRECT(HOJASDIASDELMES & "!B:I"),$B37,INDIRECT(HOJASDIASDELMES & "!I:I")))} -> 0 | J37: =F37-G37 -> 0 | K37: =IFERROR(L37/G37,0) -> 0 | L37: {=SUM(SUMIF(INDIRECT(HOJASDIASDELMES & "!B:L"),$B37,INDIRECT(HOJASDIASDELMES & "!L:L")))} -> 0 | M37: =I37-L37 -> 0 | N37: =EXACT(B37,Total!B37) -> TRUE
A38: U | B38: CONECTORES MC4 | C38: =VLOOKUP(B38,'01'!$B$9:$C$412,2,0) -> 1 | D38: {=SUM(SUMIF(INDIRECT(HOJASDIASDELMES & "!B:D"),$B38,INDIRECT(HOJASDIASDELMES & "!D:D")))} -> 0 | E38: {=SUM(SUMIF(INDIRECT(HOJASDIASDELMES & "!B:E"),$B38,INDIRECT(HOJASDIASDELMES & "!E:E")))} -> 0 | F38: =C38+D38-E38 -> 1 | G38: {=SUM(SUMIF(INDIRECT(HOJASDIASDELMES & "!B:G"),$B38,INDIRECT(HOJASDIASDELMES & "!G:G")))} -> 0 | I38: {=SUM(SUMIF(INDIRECT(HOJASDIASDELMES & "!B:I"),$B38,INDIRECT(HOJASDIASDELMES & "!I:I")))} -> 0 | J38: =F38-G38 -> 1 | K38: =IFERROR(L38/G38,0) -> 0 | L38: {=SUM(SUMIF(INDIRECT(HOJASDIASDELMES & "!B:L"),$B38,INDIRECT(HOJASDIASDELMES & "!L:L")))} -> 0 | M38: =I38-L38 -> 0 | N38: =EXACT(B38,Total!B38) -> TRUE
A39: U | B39: CAJITA DECODIFICADORA ATEC | C39: =VLOOKUP(B39,'01'!$B$9:$C$412,2,0) -> 10 | D39: {=SUM(SUMIF(INDIRECT(HOJASDIASDELMES & "!B:D"),$B39,INDIRECT(HOJASDIASDELMES & "!D:D")))} -> 0 | E39: {=SUM(SUMIF(INDIRECT(HOJASDIASDELMES & "!B:E"),$B39,INDIRECT(HOJASDIASDELMES & "!E:E")))} -> 1 | F39: =C39+D39-E39 -> 9 | G39: {=SUM(SUMIF(INDIRECT(HOJASDIASDELMES & "!B:G"),$B39,INDIRECT(HOJASDIASDELMES & "!G:G")))} -> 4 | H39: 45 | I39: {=SUM(SUMIF(INDIRECT(HOJASDIASDELMES & "!B:I"),$B39,INDIRECT(HOJASDIASDELMES & "!I:I")))} -> 150 | J39: =F39-G39 -> 5 | K39: =IFERROR(L39/G39,0) -> 24 | L39: {=SUM(SUMIF(INDIRECT(HOJASDIASDELMES & "!B:L"),$B39,INDIRECT(HOJASDIASDELMES & "!L:L")))} -> 96 | M39: =I39-L39 -> 54 | N39: =EXACT(B39,Total!B39) -> TRUE
A40: U | B40: CAJA DE DISTRIBUCION DE 8 VIAS | C40: =VLOOKUP(B40,'01'!$B$9:$C$412,2,0) -> 3 | D40: {=SUM(SUMIF(INDIRECT(HOJASDIASDELMES & "!B:D"),$B40,INDIRECT(HOJASDIASDELMES & "!D:D")))} -> 0 | E40: {=SUM(SUMIF(INDIRECT(HOJASDIASDELMES & "!B:E"),$B40,INDIRECT(HOJASDIASDELMES & "!E:E")))} -> 0 | F40: =C40+D40-E40 -> 3 | G40: {=SUM(SUMIF(INDIRECT(HOJASDIASDELMES & "!B:G"),$B40,INDIRECT(HOJASDIASDELMES & "!G:G")))} -> 0 | I40: {=SUM(SUMIF(INDIRECT(HOJASDIASDELMES & "!B:I"),$B40,INDIRECT(HOJASDIASDELMES & "!I:I")))} -> 0 | J40: =F40-G40 -> 3 | K40: =IFERROR(L40/G40,0) -> 0 | L40: {=SUM(SUMIF(INDIRECT(HOJASDIASDELMES & "!B:L"),$B40,INDIRECT(HOJASDIASDELMES & "!L:L")))} -> 0 | M40: =I40-L40 -> 0 | N40: =EXACT(B40,Total!B40) -> TRUE
A41: U | B41: CAJA DE DISTRIBUCION DE 12 VIAS | C41: =VLOOKUP(B41,'01'!$B$9:$C$412,2,0) -> 0 | D41: {=SUM(SUMIF(INDIRECT(HOJASDIASDELMES & "!B:D"),$B41,INDIRECT(HOJASDIASDELMES & "!D:D")))} -> 0 | E41: {=SUM(SUMIF(INDIRECT(HOJASDIASDELMES & "!B:E"),$B41,INDIRECT(HOJASDIASDELMES & "!E:E")))} -> 0 | F41: =C41+D41-E41 -> 0 | G41: {=SUM(SUMIF(INDIRECT(HOJASDIASDELMES & "!B:G"),$B41,INDIRECT(HOJASDIASDELMES & "!G:G")))} -> 0 | H41: 15 | I41: {=SUM(SUMIF(INDIRECT(HOJASDIASDELMES & "!B:I"),$B41,INDIRECT(HOJASDIASDELMES & "!I:I")))} -> 0 | J41: =F41-G41 -> 0 | K41: =IFERROR(L41/G41,0) -> 0 | L41: {=SUM(SUMIF(INDIRECT(HOJASDIASDELMES & "!B:L"),$B41,INDIRECT(HOJASDIASDELMES & "!L:L")))} -> 0 | M41: =I41-L41 -> 0 | N41: =EXACT(B41,Total!B41) -> TRUE
A42: U | B42: CAJA DE HERRAMIENTAS 13PCS | C42: =VLOOKUP(B42,'01'!$B$9:$C$412,2,0) -> 12 | D42: {=SUM(SUMIF(INDIRECT(HOJASDIASDELMES & "!B:D"),$B42,INDIRECT(HOJASDIASDELMES & "!D:D")))} -> 0 | E42: {=SUM(SUMIF(INDIRECT(HOJASDIASDELMES & "!B:E"),$B42,INDIRECT(HOJASDIASDELMES & "!E:E")))} -> 0 | F42: =C42+D42-E42 -> 12 | G42: {=SUM(SUMIF(INDIRECT(HOJASDIASDELMES & "!B:G"),$B42,INDIRECT(HOJASDIASDELMES & "!G:G")))} -> 2 | H42: 20 | I42: {=SUM(SUMIF(INDIRECT(HOJASDIASDELMES & "!B:I"),$B42,INDIRECT(HOJASDIASDELMES & "!I:I")))} -> 40 | J42: =F42-G42 -> 10 | K42: =IFERROR(L42/G42,0) -> 13 | L42: {=SUM(SUMIF(INDIRECT(HOJASDIASDELMES & "!B:L"),$B42,INDIRECT(HOJASDIASDELMES & "!L:L")))} -> 26 | M42: =I42-L42 -> 14 | N42: =EXACT(B42,Total!B42) -> TRUE
A43: U | B43: COLCHON PERSONAL | C43: =VLOOKUP(B43,'01'!$B$9:$C$412,2,0) -> 0 | D43: {=SUM(SUMIF(INDIRECT(HOJASDIASDELMES & "!B:D"),$B43,INDIRECT(HOJASDIASDELMES & "!D:D")))} -> 0 | E43: {=SUM(SUMIF(INDIRECT(HOJASDIASDELMES & "!B:E"),$B43,INDIRECT(HOJASDIASDELMES & "!E:E")))} -> 0 | F43: =C43+D43-E43 -> 0 | G43: {=SUM(SUMIF(INDIRECT(HOJASDIASDELMES & "!B:G"),$B43,INDIRECT(HOJASDIASDELMES & "!G:G")))} -> 0 | H43: 160 | I43: {=SUM(SUMIF(INDIRECT(HOJASDIASDELMES & "!B:I"),$B43,INDIRECT(HOJASDIASDELMES & "!I:I")))} -> 0 | J43: =F43-G43 -> 0 | K43: =IFERROR(L43/G43,0) -> 0 | L43: {=SUM(SUMIF(INDIRECT(HOJASDIASDELMES & "!B:L"),$B43,INDIRECT(HOJASDIASDELMES & "!L:L")))} -> 0 | M43: =I43-L43 -> 0 | N43: =EXACT(B43,Total!B43) -> TRUE
A44: U | B44: COLCHON EKO | C44: =VLOOKUP(B44,'01'!$B$9:$C$412,2,0) -> 3 | D44: {=SUM(SUMIF(INDIRECT(HOJASDIASDELMES & "!B:D"),$B44,INDIRECT(HOJASDIASDELMES & "!D:D")))} -> 1 | E44: {=SUM(SUMIF(INDIRECT(HOJASDIASDELMES & "!B:E"),$B44,INDIRECT(HOJASDIASDELMES & "!E:E")))} -> 2 | F44: =C44+D44-E44 -> 2 | G44: {=SUM(SUMIF(INDIRECT(HOJASDIASDELMES & "!B:G"),$B44,INDIRECT(HOJASDIASDELMES & "!G:G")))} -> 1 | H44: 190 | I44: {=SUM(SUMIF(INDIRECT(HOJASDIASDELMES & "!B:I"),$B44,INDIRECT(HOJASDIASDELMES & "!I:I")))} -> 330 | J44: =F44-G44 -> 1 | K44: =IFERROR(L44/G44,0) -> 0 | L44: {=SUM(SUMIF(INDIRECT(HOJASDIASDELMES & "!B:L"),$B44,INDIRECT(HOJASDIASDELMES & "!L:L")))} -> 0 | M44: =I44-L44 -> 330 | N44: =EXACT(B44,Total!B44) -> TRUE
A45: U | B45: CAJAS DE AZULEJOS 44X44 2.5 M | C45: =VLOOKUP(B45,'01'!$B$9:$C$412,2,0) -> 2 | D45: {=SUM(SUMIF(INDIRECT(HOJASDIASDELMES & "!B:D"),$B45,INDIRECT(HOJASDIASDELMES & "!D:D")))} -> 0 | E45: {=SUM(SUMIF(INDIRECT(HOJASDIASDELMES & "!B:E"),$B45,INDIRECT(HOJASDIASDELMES & "!E:E")))} -> 0 | F45: =C45+D45-E45 -> 2 | G45: {=SUM(SUMIF(INDIRECT(HOJASDIASDELMES & "!B:G"),$B45,INDIRECT(HOJASDIASDELMES & "!G:G")))} -> 0 | H45: 36.41 | I45: {=SUM(SUMIF(INDIRECT(HOJASDIASDELMES & "!B:I"),$B45,INDIRECT(HOJASDIASDELMES & "!I:I")))} -> 0 | J45: =F45-G45 -> 2 | K45: =IFERROR(L45/G45,0) -> 0 | L45: {=SUM(SUMIF(INDIRECT(HOJASDIASDELMES & "!B:L"),$B45,INDIRECT(HOJASDIASDELMES & "!L:L")))} -> 0 | M45: =I45-L45 -> 0 | N45: =EXACT(B45,Total!B45) -> TRUE
A46: U | B46: CAFETERA 3 TASAS | C46: =VLOOKUP(B46,'01'!$B$9:$C$412,2,0) -> 1 | D46: {=SUM(SUMIF(INDIRECT(HOJASDIASDELMES & "!B:D"),$B46,INDIRECT(HOJASDIASDELMES & "!D:D")))} -> 0 | E46: {=SUM(SUMIF(INDIRECT(HOJASDIASDELMES & "!B:E"),$B46,INDIRECT(HOJASDIASDELMES & "!E:E")))} -> 0 | F46: =C46+D46-E46 -> 1 | G46: {=SUM(SUMIF(INDIRECT(HOJASDIASDELMES & "!B:G"),$B46,INDIRECT(HOJASDIASDELMES & "!G:G")))} -> 0 | H46: 15 | I46: {=SUM(SUMIF(INDIRECT(HOJASDIASDELMES & "!B:I"),$B46,INDIRECT(HOJASDIASDELMES & "!I:I")))} -> 0 | J46: =F46-G46 -> 1 | K46: =IFERROR(L46/G46,0) -> 0 | L46: {=SUM(SUMIF(INDIRECT(HOJASDIASDELMES & "!B:L"),$B46,INDIRECT(HOJASDIASDELMES & "!L:L")))} -> 0 | M46: =I46-L46 -> 0 | N46: =EXACT(B46,Total!B46) -> TRUE
A47: U | B47: CAFETERA ELECTRICA ESPRESO 800W | C47: =VLOOKUP(B47,'01'!$B$9:$C$412,2,0) -> 5 | D47: {=SUM(SUMIF(INDIRECT(HOJASDIASDELMES & "!B:D"),$B47,INDIRECT(HOJASDIASDELMES & "!D:D")))} -> 0 | E47: {=SUM(SUMIF(INDIRECT(HOJASDIASDELMES & "!B:E"),$B47,INDIRECT(HOJASDIASDELMES & "!E:E")))} -> 0 | F47: =C47+D47-E47 -> 5 | G47: {=SUM(SUMIF(INDIRECT(HOJASDIASDELMES & "!B:G"),$B47,INDIRECT(HOJASDIASDELMES & "!G:G")))} -> 1 | H47: 70 | I47: {=SUM(SUMIF(INDIRECT(HOJASDIASDELMES & "!B:I"),$B47,INDIRECT(HOJASDIASDELMES & "!I:I")))} -> 70 | J47: =F47-G47 -> 4 | K47: =IFERROR(L47/G47,0) -> 38 | L47: {=SUM(SUMIF(INDIRECT(HOJASDIASDELMES & "!B:L"),$B47,INDIRECT(HOJASDIASDELMES & "!L:L")))} -> 38 | M47: =I47-L47 -> 32 | N47: =EXACT(B47,Total!B47) -> TRUE
A48: U | B48: CAFETERA ELECTRICA RUDENKOV | C48: =VLOOKUP(B48,'01'!$B$9:$C$412,2,0) -> 7 | D48: {=SUM(SUMIF(INDIRECT(HOJASDIASDELMES & "!B:D"),$B48,INDIRECT(HOJASDIASDELMES & "!D:D")))} -> 0 | E48: {=SUM(SUMIF(INDIRECT(HOJASDIASDELMES & "!B:E"),$B48,INDIRECT(HOJASDIASDELMES & "!E:E")))} -> 6 | F48: =C48+D48-E48 -> 1 | G48: {=SUM(SUMIF(INDIRECT(HOJASDIASDELMES & "!B:G"),$B48,INDIRECT(HOJASDIASDELMES & "!G:G")))} -> 1 | H48: 40 | I48: {=SUM(SUMIF(INDIRECT(HOJASDIASDELMES & "!B:I"),$B48,INDIRECT(HOJASDIASDELMES & "!I:I")))} -> 40 | J48: =F48-G48 -> 0 | K48: =IFERROR(L48/G48,0) -> 20 | L48: {=SUM(SUMIF(INDIRECT(HOJASDIASDELMES & "!B:L"),$B48,INDIRECT(HOJASDIASDELMES & "!L:L")))} -> 20 | M48: =I48-L48 -> 20 | N48: =EXACT(B48,Total!B48) -> TRUE
A49: U | B49: CALENTADOR 80 L | C49: =VLOOKUP(B49,'01'!$B$9:$C$412,2,0) -> 5 | D49: {=SUM(SUMIF(INDIRECT(HOJASDIASDELMES & "!B:D"),$B49,INDIRECT(HOJASDIASDELMES & "!D:D")))} -> 0 | E49: {=SUM(SUMIF(INDIRECT(HOJASDIASDELMES & "!B:E"),$B49,INDIRECT(HOJASDIASDELMES & "!E:E")))} -> 0 | F49: =C49+D49-E49 -> 5 | G49: {=SUM(SUMIF(INDIRECT(HOJASDIASDELMES & "!B:G"),$B49,INDIRECT(HOJASDIASDELMES & "!G:G")))} -> 1 | H49: 230 | I49: {=SUM(SUMIF(INDIRECT(HOJASDIASDELMES & "!B:I"),$B49,INDIRECT(HOJASDIASDELMES & "!I:I")))} -> 200 | J49: =F49-G49 -> 4 | K49: =IFERROR(L49/G49,0) -> 170 | L49: {=SUM(SUMIF(INDIRECT(HOJASDIASDELMES & "!B:L"),$B49,INDIRECT(HOJASDIASDELMES & "!L:L")))} -> 170 | M49: =I49-L49 -> 30 | N49: =EXACT(B49,Total!B49) -> TRUE
A50: U | B50: CALENTADOR 50 L | C50: =VLOOKUP(B50,'01'!$B$9:$C$412,2,0) -> 0 | D50: {=SUM(SUMIF(INDIRECT(HOJASDIASDELMES & "!B:D"),$B50,INDIRECT(HOJASDIASDELMES & "!D:D")))} -> 0 | E50: {=SUM(SUMIF(INDIRECT(HOJASDIASDELMES & "!B:E"),$B50,INDIRECT(HOJASDIASDELMES & "!E:E")))} -> 0 | F50: =C50+D50-E50 -> 0 | G50: {=SUM(SUMIF(INDIRECT(HOJASDIASDELMES & "!B:G"),$B50,INDIRECT(HOJASDIASDELMES & "!G:G")))} -> 0 | H50: 180 | I50: {=SUM(SUMIF(INDIRECT(HOJASDIASDELMES & "!B:I"),$B50,INDIRECT(HOJASDIASDELMES & "!I:I")))} -> 0 | J50: =F50-G50 -> 0 | K50: =IFERROR(L50/G50,0) -> 0 | L50: {=SUM(SUMIF(INDIRECT(HOJASDIASDELMES & "!B:L"),$B50,INDIRECT(HOJASDIASDELMES & "!L:L")))} -> 0 | M50: =I50-L50 -> 0 | N50: =EXACT(B50,Total!B50) -> TRUE
A51: U | B51: DISPENSSDOR DE AGUA ROYAL | C51: =VLOOKUP(B51,'01'!$B$9:$C$412,2,0) -> 0 | D51: {=SUM(SUMIF(INDIRECT(HOJASDIASDELMES & "!B:D"),$B51,INDIRECT(HOJASDIASDELMES & "!D:D")))} -> 0 | E51: {=SUM(SUMIF(INDIRECT(HOJASDIASDELMES & "!B:E"),$B51,INDIRECT(HOJASDIASDELMES & "!E:E")))} -> 0 | F51: =C51+D51-E51 -> 0 | G51: {=SUM(SUMIF(INDIRECT(HOJASDIASDELMES & "!B:G"),$B51,INDIRECT(HOJASDIASDELMES & "!G:G")))} -> 0 | H51: 160 | I51: {=SUM(SUMIF(INDIRECT(HOJASDIASDELMES & "!B:I"),$B51,INDIRECT(HOJASDIASDELMES & "!I:I")))} -> 0 | J51: =F51-G51 -> 0 | K51: =IFERROR(L51/G51,0) -> 0 | L51: {=SUM(SUMIF(INDIRECT(HOJASDIASDELMES & "!B:L"),$B51,INDIRECT(HOJASDIASDELMES & "!L:L")))} -> 0 | M51: =I51-L51 -> 0 | N51: =EXACT(B51,Total!B51) -> TRUE
A52: U | B52: ESTACION ENERGIA 6000 W | C52: =VLOOKUP(B52,'01'!$B$9:$C$412,2,0) -> 0 | D52: {=SUM(SUMIF(INDIRECT(HOJASDIASDELMES & "!B:D"),$B52,INDIRECT(HOJASDIASDELMES & "!D:D")))} -> 0 | E52: {=SUM(SUMIF(INDIRECT(HOJASDIASDELMES & "!B:E"),$B52,INDIRECT(HOJASDIASDELMES & "!E:E")))} -> 0 | F52: =C52+D52-E52 -> 0 | G52: {=SUM(SUMIF(INDIRECT(HOJASDIASDELMES & "!B:G"),$B52,INDIRECT(HOJASDIASDELMES & "!G:G")))} -> 0 | H52: 760 | I52: {=SUM(SUMIF(INDIRECT(HOJASDIASDELMES & "!B:I"),$B52,INDIRECT(HOJASDIASDELMES & "!I:I")))} -> 0 | J52: =F52-G52 -> 0 | K52: =IFERROR(L52/G52,0) -> 0 | L52: {=SUM(SUMIF(INDIRECT(HOJASDIASDELMES & "!B:L"),$B52,INDIRECT(HOJASDIASDELMES & "!L:L")))} -> 0 | M52: =I52-L52 -> 0 | N52: =EXACT(B52,Total!B52) -> TRUE
... A55: U | B55: ESTACION ENERGIA ECOFLOW DELTA 3 | C55: =VLOOKUP(B55,'01'!$B$9:$C$412,2,0) -> 3 | D55: {=SUM(SUMIF(INDIRECT(HOJASDIASDELMES & "!B:D"),$B55,INDIRECT(HOJASDIASDELMES & "!D:D")))} -> 0 | E55: {=SUM(SUMIF(INDIRECT(HOJASDIASDELMES & "!B:E"),$B55,INDIRECT(HOJASDIASDELMES & "!E:E")))} -> 0 | F55: =C55+D55-E55 -> 3 | G55: {=SUM(SUMIF(INDIRECT(HOJASDIASDELMES & "!B:G"),$B55,INDIRECT(HOJASDIASDELMES & "!G:G")))} -> 0 | H55: 820 | I55: {=SUM(SUMIF(INDIRECT(HOJASDIASDELMES & "!B:I"),$B55,INDIRECT(HOJASDIASDELMES & "!I:I")))} -> 0 | J55: =F55-G55 -> 3 | K55: =IFERROR(L55/G55,0) -> 0 | L55: {=SUM(SUMIF(INDIRECT(HOJASDIASDELMES & "!B:L"),$B55,INDIRECT(HOJASDIASDELMES & "!L:L")))} -> 0 | M55: =I55-L55 -> 0 | N55: =EXACT(B55,Total!B55) -> TRUE
A56: U | B56: ESTACION MUST 6000 W | C56: =VLOOKUP(B56,'01'!$B$9:$C$412,2,0) -> 0 | D56: {=SUM(SUMIF(INDIRECT(HOJASDIASDELMES & "!B:D"),$B56,INDIRECT(HOJASDIASDELMES & "!D:D")))} -> 0 | E56: {=SUM(SUMIF(INDIRECT(HOJASDIASDELMES & "!B:E"),$B56,INDIRECT(HOJASDIASDELMES & "!E:E")))} -> 0 | F56: =C56+D56-E56 -> 0 | G56: {=SUM(SUMIF(INDIRECT(HOJASDIASDELMES & "!B:G"),$B56,INDIRECT(HOJASDIASDELMES & "!G:G")))} -> 0 | I56: {=SUM(SUMIF(INDIRECT(HOJASDIASDELMES & "!B:I"),$B56,INDIRECT(HOJASDIASDELMES & "!I:I")))} -> 0 | J56: =F56-G56 -> 0 | K56: =IFERROR(L56/G56,0) -> 0 | L56: {=SUM(SUMIF(INDIRECT(HOJASDIASDELMES & "!B:L"),$B56,INDIRECT(HOJASDIASDELMES & "!L:L")))} -> 0 | M56: =I56-L56 -> 0 | N56: =EXACT(B56,Total!B56) -> TRUE
A57: U | B57: ESTACION MUST 2K CON 2.7K | C57: =VLOOKUP(B57,'01'!$B$9:$C$412,2,0) -> 1 | D57: {=SUM(SUMIF(INDIRECT(HOJASDIASDELMES & "!B:D"),$B57,INDIRECT(HOJASDIASDELMES & "!D:D")))} -> 0 | E57: {=SUM(SUMIF(INDIRECT(HOJASDIASDELMES & "!B:E"),$B57,INDIRECT(HOJASDIASDELMES & "!E:E")))} -> 0 | F57: =C57+D57-E57 -> 1 | G57: {=SUM(SUMIF(INDIRECT(HOJASDIASDELMES & "!B:G"),$B57,INDIRECT(HOJASDIASDELMES & "!G:G")))} -> 1 | H57: 1300 | I57: {=SUM(SUMIF(INDIRECT(HOJASDIASDELMES & "!B:I"),$B57,INDIRECT(HOJASDIASDELMES & "!I:I")))} -> 1300 | J57: =F57-G57 -> 0 | K57: =IFERROR(L57/G57,0) -> 800 | L57: {=SUM(SUMIF(INDIRECT(HOJASDIASDELMES & "!B:L"),$B57,INDIRECT(HOJASDIASDELMES & "!L:L")))} -> 800 | M57: =I57-L57 -> 500 | N57: =EXACT(B57,Total!B57) -> TRUE
A58: U | B58: ESCRITORIO | C58: =VLOOKUP(B58,'01'!$B$9:$C$412,2,0) -> 2 | D58: {=SUM(SUMIF(INDIRECT(HOJASDIASDELMES & "!B:D"),$B58,INDIRECT(HOJASDIASDELMES & "!D:D")))} -> 0 | E58: {=SUM(SUMIF(INDIRECT(HOJASDIASDELMES & "!B:E"),$B58,INDIRECT(HOJASDIASDELMES & "!E:E")))} -> 2 | F58: =C58+D58-E58 -> 0 | G58: {=SUM(SUMIF(INDIRECT(HOJASDIASDELMES & "!B:G"),$B58,INDIRECT(HOJASDIASDELMES & "!G:G")))} -> 0 | H58: 230 | I58: {=SUM(SUMIF(INDIRECT(HOJASDIASDELMES & "!B:I"),$B58,INDIRECT(HOJASDIASDELMES & "!I:I")))} -> 0 | J58: =F58-G58 -> 0 | K58: =IFERROR(L58/G58,0) -> 0 | L58: {=SUM(SUMIF(INDIRECT(HOJASDIASDELMES & "!B:L"),$B58,INDIRECT(HOJASDIASDELMES & "!L:L")))} -> 0 | M58: =I58-L58 -> 0 | N58: =EXACT(B58,Total!B58) -> TRUE
A59: U | B59: ESTACION ECOFLOW DELTA 2 1800W | C59: =VLOOKUP(B59,'01'!$B$9:$C$412,2,0) -> 0 | D59: {=SUM(SUMIF(INDIRECT(HOJASDIASDELMES & "!B:D"),$B59,INDIRECT(HOJASDIASDELMES & "!D:D")))} -> 0 | E59: {=SUM(SUMIF(INDIRECT(HOJASDIASDELMES & "!B:E"),$B59,INDIRECT(HOJASDIASDELMES & "!E:E")))} -> 0 | F59: =C59+D59-E59 -> 0 | G59: {=SUM(SUMIF(INDIRECT(HOJASDIASDELMES & "!B:G"),$B59,INDIRECT(HOJASDIASDELMES & "!G:G")))} -> 0 | H59: 800 | I59: {=SUM(SUMIF(INDIRECT(HOJASDIASDELMES & "!B:I"),$B59,INDIRECT(HOJASDIASDELMES & "!I:I")))} -> 0 | J59: =F59-G59 -> 0 | K59: =IFERROR(L59/G59,0) -> 0 | L59: {=SUM(SUMIF(INDIRECT(HOJASDIASDELMES & "!B:L"),$B59,INDIRECT(HOJASDIASDELMES & "!L:L")))} -> 0 | M59: =I59-L59 -> 0 | N59: =EXACT(B59,Total!B59) -> TRUE
A60: U | B60: KIT DE INSTALACION | C60: =VLOOKUP(B60,'01'!$B$9:$C$412,2,0) -> 0 | D60: {=SUM(SUMIF(INDIRECT(HOJASDIASDELMES & "!B:D"),$B60,INDIRECT(HOJASDIASDELMES & "!D:D")))} -> 0 | E60: {=SUM(SUMIF(INDIRECT(HOJASDIASDELMES & "!B:E"),$B60,INDIRECT(HOJASDIASDELMES & "!E:E")))} -> 0 | F60: =C60+D60-E60 -> 0 | G60: {=SUM(SUMIF(INDIRECT(HOJASDIASDELMES & "!B:G"),$B60,INDIRECT(HOJASDIASDELMES & "!G:G")))} -> 0 | H60: 120 | I60: {=SUM(SUMIF(INDIRECT(HOJASDIASDELMES & "!B:I"),$B60,INDIRECT(HOJASDIASDELMES & "!I:I")))} -> 0 | J60: =F60-G60 -> 0 | K60: =IFERROR(L60/G60,0) -> 0 | L60: {=SUM(SUMIF(INDIRECT(HOJASDIASDELMES & "!B:L"),$B60,INDIRECT(HOJASDIASDELMES & "!L:L")))} -> 0 | M60: =I60-L60 -> 0 | N60: =EXACT(B60,Total!B60) -> TRUE
A61: U | B61: EXHIBIDOR HORIZONTAL 13P | C61: =VLOOKUP(B61,'01'!$B$9:$C$412,2,0) -> 0 | D61: {=SUM(SUMIF(INDIRECT(HOJASDIASDELMES & "!B:D"),$B61,INDIRECT(HOJASDIASDELMES & "!D:D")))} -> 0 | E61: {=SUM(SUMIF(INDIRECT(HOJASDIASDELMES & "!B:E"),$B61,INDIRECT(HOJASDIASDELMES & "!E:E")))} -> 0 | F61: =C61+D61-E61 -> 0 | G61: {=SUM(SUMIF(INDIRECT(HOJASDIASDELMES & "!B:G"),$B61,INDIRECT(HOJASDIASDELMES & "!G:G")))} -> 0 | H61: 650 | I61: {=SUM(SUMIF(INDIRECT(HOJASDIASDELMES & "!B:I"),$B61,INDIRECT(HOJASDIASDELMES & "!I:I")))} -> 0 | J61: =F61-G61 -> 0 | K61: =IFERROR(L61/G61,0) -> 0 | L61: {=SUM(SUMIF(INDIRECT(HOJASDIASDELMES & "!B:L"),$B61,INDIRECT(HOJASDIASDELMES & "!L:L")))} -> 0 | M61: =I61-L61 -> 0 | N61: =EXACT(B61,Total!B61) -> TRUE
A62: U | B62: EXHIBIDOR VERTICAL SANKEY 8P | C62: =VLOOKUP(B62,'01'!$B$9:$C$412,2,0) -> 0 | D62: {=SUM(SUMIF(INDIRECT(HOJASDIASDELMES & "!B:D"),$B62,INDIRECT(HOJASDIASDELMES & "!D:D")))} -> 0 | E62: {=SUM(SUMIF(INDIRECT(HOJASDIASDELMES & "!B:E"),$B62,INDIRECT(HOJASDIASDELMES & "!E:E")))} -> 0 | F62: =C62+D62-E62 -> 0 | G62: {=SUM(SUMIF(INDIRECT(HOJASDIASDELMES & "!B:G"),$B62,INDIRECT(HOJASDIASDELMES & "!G:G")))} -> 0 | H62: 500 | I62: {=SUM(SUMIF(INDIRECT(HOJASDIASDELMES & "!B:I"),$B62,INDIRECT(HOJASDIASDELMES & "!I:I")))} -> 0 | J62: =F62-G62 -> 0 | K62: =IFERROR(L62/G62,0) -> 0 | L62: {=SUM(SUMIF(INDIRECT(HOJASDIASDELMES & "!B:L"),$B62,INDIRECT(HOJASDIASDELMES & "!L:L")))} -> 0 | M62: =I62-L62 -> 0 | N62: =EXACT(B62,Total!B62) -> TRUE
A63: U | B63: EXHIBIDOR MILEXUS 390 L 14PIES | C63: =VLOOKUP(B63,'01'!$B$9:$C$412,2,0) -> 0 | D63: {=SUM(SUMIF(INDIRECT(HOJASDIASDELMES & "!B:D"),$B63,INDIRECT(HOJASDIASDELMES & "!D:D")))} -> 0 | E63: {=SUM(SUMIF(INDIRECT(HOJASDIASDELMES & "!B:E"),$B63,INDIRECT(HOJASDIASDELMES & "!E:E")))} -> 0 | F63: =C63+D63-E63 -> 0 | G63: {=SUM(SUMIF(INDIRECT(HOJASDIASDELMES & "!B:G"),$B63,INDIRECT(HOJASDIASDELMES & "!G:G")))} -> 0 | H63: 630 | I63: {=SUM(SUMIF(INDIRECT(HOJASDIASDELMES & "!B:I"),$B63,INDIRECT(HOJASDIASDELMES & "!I:I")))} -> 0 | J63: =F63-G63 -> 0 | K63: =IFERROR(L63/G63,0) -> 0 | L63: {=SUM(SUMIF(INDIRECT(HOJASDIASDELMES & "!B:L"),$B63,INDIRECT(HOJASDIASDELMES & "!L:L")))} -> 0 | M63: =I63-L63 -> 0 | N63: =EXACT(B63,Total!B63) -> TRUE
A64: U | B64: EXHIBIDOR DOBLE MILEXUS 560 LITROS | C64: =VLOOKUP(B64,'01'!$B$9:$C$412,2,0) -> 1 | D64: {=SUM(SUMIF(INDIRECT(HOJASDIASDELMES & "!B:D"),$B64,INDIRECT(HOJASDIASDELMES & "!D:D")))} -> 0 | E64: {=SUM(SUMIF(INDIRECT(HOJASDIASDELMES & "!B:E"),$B64,INDIRECT(HOJASDIASDELMES & "!E:E")))} -> 1 | F64: =C64+D64-E64 -> 0 | G64: {=SUM(SUMIF(INDIRECT(HOJASDIASDELMES & "!B:G"),$B64,INDIRECT(HOJASDIASDELMES & "!G:G")))} -> 0 | H64: 900 | I64: {=SUM(SUMIF(INDIRECT(HOJASDIASDELMES & "!B:I"),$B64,INDIRECT(HOJASDIASDELMES & "!I:I")))} -> 0 | J64: =F64-G64 -> 0 | K64: =IFERROR(L64/G64,0) -> 0 | L64: {=SUM(SUMIF(INDIRECT(HOJASDIASDELMES & "!B:L"),$B64,INDIRECT(HOJASDIASDELMES & "!L:L")))} -> 0 | M64: =I64-L64 -> 0 | N64: =EXACT(B64,Total!B64) -> TRUE
A65: U | B65: ENFRIADOR DE AIRE ALL NOVU | C65: =VLOOKUP(B65,'01'!$B$9:$C$412,2,0) -> 0 | D65: {=SUM(SUMIF(INDIRECT(HOJASDIASDELMES & "!B:D"),$B65,INDIRECT(HOJASDIASDELMES & "!D:D")))} -> 0 | E65: {=SUM(SUMIF(INDIRECT(HOJASDIASDELMES & "!B:E"),$B65,INDIRECT(HOJASDIASDELMES & "!E:E")))} -> 0 | F65: =C65+D65-E65 -> 0 | G65: {=SUM(SUMIF(INDIRECT(HOJASDIASDELMES & "!B:G"),$B65,INDIRECT(HOJASDIASDELMES & "!G:G")))} -> 0 | H65: 65 | I65: {=SUM(SUMIF(INDIRECT(HOJASDIASDELMES & "!B:I"),$B65,INDIRECT(HOJASDIASDELMES & "!I:I")))} -> 0 | J65: =F65-G65 -> 0 | K65: =IFERROR(L65/G65,0) -> 0 | L65: {=SUM(SUMIF(INDIRECT(HOJASDIASDELMES & "!B:L"),$B65,INDIRECT(HOJASDIASDELMES & "!L:L")))} -> 0 | M65: =I65-L65 -> 0 | N65: =EXACT(B65,Total!B65) -> TRUE
A66: U | B66: ENFRIADOR DE AIRE ALL NOVU DOBLE | C66: =VLOOKUP(B66,'01'!$B$9:$C$412,2,0) -> 0 | D66: {=SUM(SUMIF(INDIRECT(HOJASDIASDELMES & "!B:D"),$B66,INDIRECT(HOJASDIASDELMES & "!D:D")))} -> 0 | E66: {=SUM(SUMIF(INDIRECT(HOJASDIASDELMES & "!B:E"),$B66,INDIRECT(HOJASDIASDELMES & "!E:E")))} -> 0 | F66: =C66+D66-E66 -> 0 | G66: {=SUM(SUMIF(INDIRECT(HOJASDIASDELMES & "!B:G"),$B66,INDIRECT(HOJASDIASDELMES & "!G:G")))} -> 0 | H66: 170 | I66: {=SUM(SUMIF(INDIRECT(HOJASDIASDELMES & "!B:I"),$B66,INDIRECT(HOJASDIASDELMES & "!I:I")))} -> 0 | J66: =F66-G66 -> 0 | K66: =IFERROR(L66/G66,0) -> 0 | L66: {=SUM(SUMIF(INDIRECT(HOJASDIASDELMES & "!B:L"),$B66,INDIRECT(HOJASDIASDELMES & "!L:L")))} -> 0 | M66: =I66-L66 -> 0 | N66: =EXACT(B66,Total!B66) -> TRUE
A67: U | B67: EQUIPO DE MUSICA LG | C67: =VLOOKUP(B67,'01'!$B$9:$C$412,2,0) -> 0 | D67: {=SUM(SUMIF(INDIRECT(HOJASDIASDELMES & "!B:D"),$B67,INDIRECT(HOJASDIASDELMES & "!D:D")))} -> 0 | E67: {=SUM(SUMIF(INDIRECT(HOJASDIASDELMES & "!B:E"),$B67,INDIRECT(HOJASDIASDELMES & "!E:E")))} -> 0 | F67: =C67+D67-E67 -> 0 | G67: {=SUM(SUMIF(INDIRECT(HOJASDIASDELMES & "!B:G"),$B67,INDIRECT(HOJASDIASDELMES & "!G:G")))} -> 0 | H67: 180 | I67: {=SUM(SUMIF(INDIRECT(HOJASDIASDELMES & "!B:I"),$B67,INDIRECT(HOJASDIASDELMES & "!I:I")))} -> 0 | J67: =F67-G67 -> 0 | K67: =IFERROR(L67/G67,0) -> 0 | L67: {=SUM(SUMIF(INDIRECT(HOJASDIASDELMES & "!B:L"),$B67,INDIRECT(HOJASDIASDELMES & "!L:L")))} -> 0 | M67: =I67-L67 -> 0 | N67: =EXACT(B67,Total!B67) -> TRUE
A68: U | B68: EQUIPO DE MUSICA LG GRANDE | C68: =VLOOKUP(B68,'01'!$B$9:$C$412,2,0) -> 1 | D68: {=SUM(SUMIF(INDIRECT(HOJASDIASDELMES & "!B:D"),$B68,INDIRECT(HOJASDIASDELMES & "!D:D")))} -> 0 | E68: {=SUM(SUMIF(INDIRECT(HOJASDIASDELMES & "!B:E"),$B68,INDIRECT(HOJASDIASDELMES & "!E:E")))} -> 0 | F68: =C68+D68-E68 -> 1 | G68: {=SUM(SUMIF(INDIRECT(HOJASDIASDELMES & "!B:G"),$B68,INDIRECT(HOJASDIASDELMES & "!G:G")))} -> 0 | H68: 235 | I68: {=SUM(SUMIF(INDIRECT(HOJASDIASDELMES & "!B:I"),$B68,INDIRECT(HOJASDIASDELMES & "!I:I")))} -> 0 | J68: =F68-G68 -> 1 | K68: =IFERROR(L68/G68,0) -> 0 | L68: {=SUM(SUMIF(INDIRECT(HOJASDIASDELMES & "!B:L"),$B68,INDIRECT(HOJASDIASDELMES & "!L:L")))} -> 0 | M68: =I68-L68 -> 0 | N68: =EXACT(B68,Total!B68) -> TRUE
... A163: U | B163: PRESURIZADOR 6 L DAWANG | C163: =VLOOKUP(B163,'01'!$B$9:$C$412,2,0) -> 3 | D163: {=SUM(SUMIF(INDIRECT(HOJASDIASDELMES & "!B:D"),$B163,INDIRECT(HOJASDIASDELMES & "!D:D")))} -> 0 | E163: {=SUM(SUMIF(INDIRECT(HOJASDIASDELMES & "!B:E"),$B163,INDIRECT(HOJASDIASDELMES & "!E:E")))} -> 0 | F163: =C163+D163-E163 -> 3 | G163: {=SUM(SUMIF(INDIRECT(HOJASDIASDELMES & "!B:G"),$B163,INDIRECT(HOJASDIASDELMES & "!G:G")))} -> 2 | H163: 60 | I163: {=SUM(SUMIF(INDIRECT(HOJASDIASDELMES & "!B:I"),$B163,INDIRECT(HOJASDIASDELMES & "!I:I")))} -> 120 | J163: =F163-G163 -> 1 | K163: =IFERROR(L163/G163,0) -> 35 | L163: {=SUM(SUMIF(INDIRECT(HOJASDIASDELMES & "!B:L"),$B163,INDIRECT(HOJASDIASDELMES & "!L:L")))} -> 70 | M163: =I163-L163 -> 50 | N163: =EXACT(B163,Total!B163) -> TRUE
A164: U | B164: PROTECTOR DE LINEA 110V | C164: =VLOOKUP(B164,'01'!$B$9:$C$412,2,0) -> 4 | D164: {=SUM(SUMIF(INDIRECT(HOJASDIASDELMES & "!B:D"),$B164,INDIRECT(HOJASDIASDELMES & "!D:D")))} -> 1 | E164: {=SUM(SUMIF(INDIRECT(HOJASDIASDELMES & "!B:E"),$B164,INDIRECT(HOJASDIASDELMES & "!E:E")))} -> 0 | F164: =C164+D164-E164 -> 5 | G164: {=SUM(SUMIF(INDIRECT(HOJASDIASDELMES & "!B:G"),$B164,INDIRECT(HOJASDIASDELMES & "!G:G")))} -> 1 | I164: {=SUM(SUMIF(INDIRECT(HOJASDIASDELMES & "!B:I"),$B164,INDIRECT(HOJASDIASDELMES & "!I:I")))} -> 0 | J164: =F164-G164 -> 4 | K164: =IFERROR(L164/G164,0) -> 0 | L164: {=SUM(SUMIF(INDIRECT(HOJASDIASDELMES & "!B:L"),$B164,INDIRECT(HOJASDIASDELMES & "!L:L")))} -> 0 | M164: =I164-L164 -> 0 | N164: =EXACT(B164,Total!B164) -> TRUE
A165: U | B165: PROTECTOR DE LINEA 220V | C165: =VLOOKUP(B165,'01'!$B$9:$C$412,2,0) -> 4 | D165: {=SUM(SUMIF(INDIRECT(HOJASDIASDELMES & "!B:D"),$B165,INDIRECT(HOJASDIASDELMES & "!D:D")))} -> 1 | E165: {=SUM(SUMIF(INDIRECT(HOJASDIASDELMES & "!B:E"),$B165,INDIRECT(HOJASDIASDELMES & "!E:E")))} -> 0 | F165: =C165+D165-E165 -> 5 | G165: {=SUM(SUMIF(INDIRECT(HOJASDIASDELMES & "!B:G"),$B165,INDIRECT(HOJASDIASDELMES & "!G:G")))} -> 0 | I165: {=SUM(SUMIF(INDIRECT(HOJASDIASDELMES & "!B:I"),$B165,INDIRECT(HOJASDIASDELMES & "!I:I")))} -> 0 | J165: =F165-G165 -> 5 | K165: =IFERROR(L165/G165,0) -> 0 | L165: {=SUM(SUMIF(INDIRECT(HOJASDIASDELMES & "!B:L"),$B165,INDIRECT(HOJASDIASDELMES & "!L:L")))} -> 0 | M165: =I165-L165 -> 0 | N165: =EXACT(B165,Total!B165) -> TRUE
A166: U | B166: PROTECTOR DE VOLTAJE 120V/15A | C166: =VLOOKUP(B166,'01'!$B$9:$C$412,2,0) -> 6 | D166: {=SUM(SUMIF(INDIRECT(HOJASDIASDELMES & "!B:D"),$B166,INDIRECT(HOJASDIASDELMES & "!D:D")))} -> 0 | E166: {=SUM(SUMIF(INDIRECT(HOJASDIASDELMES & "!B:E"),$B166,INDIRECT(HOJASDIASDELMES & "!E:E")))} -> 1 | F166: =C166+D166-E166 -> 5 | G166: {=SUM(SUMIF(INDIRECT(HOJASDIASDELMES & "!B:G"),$B166,INDIRECT(HOJASDIASDELMES & "!G:G")))} -> 0 | I166: {=SUM(SUMIF(INDIRECT(HOJASDIASDELMES & "!B:I"),$B166,INDIRECT(HOJASDIASDELMES & "!I:I")))} -> 0 | J166: =F166-G166 -> 5 | K166: =IFERROR(L166/G166,0) -> 0 | L166: {=SUM(SUMIF(INDIRECT(HOJASDIASDELMES & "!B:L"),$B166,INDIRECT(HOJASDIASDELMES & "!L:L")))} -> 0 | M166: =I166-L166 -> 0 | N166: =EXACT(B166,Total!B166) -> TRUE
A167: U | B167: PANELES 490 W | C167: =VLOOKUP(B167,'01'!$B$9:$C$412,2,0) -> 1 | D167: {=SUM(SUMIF(INDIRECT(HOJASDIASDELMES & "!B:D"),$B167,INDIRECT(HOJASDIASDELMES & "!D:D")))} -> 0 | E167: {=SUM(SUMIF(INDIRECT(HOJASDIASDELMES & "!B:E"),$B167,INDIRECT(HOJASDIASDELMES & "!E:E")))} -> 1 | F167: =C167+D167-E167 -> 0 | G167: {=SUM(SUMIF(INDIRECT(HOJASDIASDELMES & "!B:G"),$B167,INDIRECT(HOJASDIASDELMES & "!G:G")))} -> 0 | H167: 210 | I167: {=SUM(SUMIF(INDIRECT(HOJASDIASDELMES & "!B:I"),$B167,INDIRECT(HOJASDIASDELMES & "!I:I")))} -> 0 | J167: =F167-G167 -> 0 | K167: =IFERROR(L167/G167,0) -> 0 | L167: {=SUM(SUMIF(INDIRECT(HOJASDIASDELMES & "!B:L"),$B167,INDIRECT(HOJASDIASDELMES & "!L:L")))} -> 0 | M167: =I167-L167 -> 0 | N167: =EXACT(B167,Total!B167) -> TRUE
A168: U | B168: PANELES 620 W | C168: =VLOOKUP(B168,'01'!$B$9:$C$412,2,0) -> 0 | D168: {=SUM(SUMIF(INDIRECT(HOJASDIASDELMES & "!B:D"),$B168,INDIRECT(HOJASDIASDELMES & "!D:D")))} -> 0 | E168: {=SUM(SUMIF(INDIRECT(HOJASDIASDELMES & "!B:E"),$B168,INDIRECT(HOJASDIASDELMES & "!E:E")))} -> 0 | F168: =C168+D168-E168 -> 0 | G168: {=SUM(SUMIF(INDIRECT(HOJASDIASDELMES & "!B:G"),$B168,INDIRECT(HOJASDIASDELMES & "!G:G")))} -> 0 | H168: 300 | I168: {=SUM(SUMIF(INDIRECT(HOJASDIASDELMES & "!B:I"),$B168,INDIRECT(HOJASDIASDELMES & "!I:I")))} -> 0 | J168: =F168-G168 -> 0 | K168: =IFERROR(L168/G168,0) -> 0 | L168: {=SUM(SUMIF(INDIRECT(HOJASDIASDELMES & "!B:L"),$B168,INDIRECT(HOJASDIASDELMES & "!L:L")))} -> 0 | M168: =I168-L168 -> 0 | N168: =EXACT(B168,Total!B168) -> TRUE
A169: U | B169: PANELES 615 W | C169: =VLOOKUP(B169,'01'!$B$9:$C$412,2,0) -> 24 | D169: {=SUM(SUMIF(INDIRECT(HOJASDIASDELMES & "!B:D"),$B169,INDIRECT(HOJASDIASDELMES & "!D:D")))} -> 0 | E169: {=SUM(SUMIF(INDIRECT(HOJASDIASDELMES & "!B:E"),$B169,INDIRECT(HOJASDIASDELMES & "!E:E")))} -> 1 | F169: =C169+D169-E169 -> 23 | G169: {=SUM(SUMIF(INDIRECT(HOJASDIASDELMES & "!B:G"),$B169,INDIRECT(HOJASDIASDELMES & "!G:G")))} -> 11 | H169: 280 | I169: {=SUM(SUMIF(INDIRECT(HOJASDIASDELMES & "!B:I"),$B169,INDIRECT(HOJASDIASDELMES & "!I:I")))} -> 3060 | J169: =F169-G169 -> 12 | K169: =IFERROR(L169/G169,0) -> 250 | L169: {=SUM(SUMIF(INDIRECT(HOJASDIASDELMES & "!B:L"),$B169,INDIRECT(HOJASDIASDELMES & "!L:L")))} -> 2750 | M169: =I169-L169 -> 310 | N169: =EXACT(B169,Total!B169) -> TRUE
